{
  "type": "Feature",
  "properties": {
    "iso:country":"IN",
    "sg:address":"A.c. Guards",
    "sg:city":"Hyderabad",
    "sg:phone":"+91 40 5650 3166",
    "sg:postcode":"500004",
    "sg:province":"Andhra Pradesh",
    "sg:website":"http://www.reliablecorp.com",
    "wof:name":"Reliable Web Solutions Pvt Ltd",
    "wof:placetype":"venue"
},
  "geometry": {"coordinates":[78.457787,17.404873],"type":"Point"}
}