{
  "type": "Feature",
  "properties": {
    "iso:country":"IN",
    "sg:address":"12, Richmond Road",
    "sg:city":"Bangalore",
    "sg:phone":"+91 802998216",
    "sg:postcode":"560025",
    "sg:province":"Karnataka",
    "sg:website":"http://www.answerpal.com",
    "wof:name":"Answerpal Pvt Ltd",
    "wof:placetype":"venue"
},
  "geometry": {"coordinates":[77.605919,12.966026],"type":"Point"}
}