{
  "type": "Feature",
  "properties": {
    "iso:country":"IN",
    "sg:address":"Angappa Naicken Street",
    "sg:city":"Chennai",
    "sg:phone":"+91 44 2533 1010",
    "sg:postcode":"600001",
    "sg:province":"Tamil Nadu",
    "wof:name":"Tata Nyk Transport Systems Ltd",
    "wof:placetype":"venue"
},
  "geometry": {"coordinates":[80.289886,13.091798],"type":"Point"}
}