{
  "type": "Feature",
  "properties": {
    "iso:country":"IN",
    "sg:address":"L.b.s. Marg, Bhandup (west),",
    "sg:city":"Mumbai",
    "sg:classifiers":[
        {
            "category":"Manufacturing",
            "subcategory":"Tools & Machinery",
            "type":"Manufacturing & Wholesale Goods"
        }
    ],
    "sg:phone":"+91 22 2561 2566",
    "sg:postcode":"400078",
    "sg:tags":[
        "cutter",
        "cutting",
        "tools",
        "broach"
    ],
    "sg:website":"http://www.adorwelding.com",
    "wof:name":"Ador Welding Limited",
    "wof:placetype":"venue"
},
  "geometry": {"coordinates":[72.928932,19.135406],"type":"Point"}
}