{
  "type": "Feature",
  "properties": {
    "iso:country":"IN",
    "sg:address":"12, 1st Floor, New Cloth Market,",
    "sg:city":"Ahmedabad",
    "sg:classifiers":[
        {
            "category":"Manufacturing",
            "subcategory":"Chemicals & Compounds",
            "type":"Manufacturing & Wholesale Goods"
        }
    ],
    "sg:phone":"+91 79 2216 0446",
    "sg:postcode":"380002",
    "sg:tags":[
        "sulphur"
    ],
    "sg:website":"http://",
    "wof:name":"Shalibhadra Dyechem Pvt. Ltd.",
    "wof:placetype":"venue"
},
  "geometry": {"coordinates":[72.59996,23.017845],"type":"Point"}
}