{
  "type": "Feature",
  "properties": {
    "iso:country":"IN",
    "sg:address":"Vadgadi, Masjid Bunder (west),",
    "sg:city":"Mumbai",
    "sg:classifiers":[
        {
            "category":"Manufacturing",
            "subcategory":"Rubber & Plastics",
            "type":"Manufacturing & Wholesale Goods"
        }
    ],
    "sg:phone":"+91 22 2341 2908",
    "sg:postcode":"400003",
    "sg:tags":[
        "product"
    ],
    "sg:website":"http://www.keswanigroup.com",
    "wof:name":"Auto Steels & Rubber Ind. Pvt. Ltd.",
    "wof:placetype":"venue"
},
  "geometry": {"coordinates":[72.83715100000001,18.951572],"type":"Point"}
}