{
  "type": "Feature",
  "properties": {
    "iso:country":"IN",
    "sg:address":"B.k.paul Avenue",
    "sg:city":"Kolkata",
    "sg:phone":"+91 33 2231 6301",
    "sg:postcode":"700005",
    "sg:province":"West Bengal",
    "wof:name":"Lion Pictures & Frames India Ltd",
    "wof:placetype":"venue"
},
  "geometry": {"coordinates":[88.360252,22.595108],"type":"Point"}
}