{
  "type": "Feature",
  "properties": {
    "iso:country":"IN",
    "sg:address":"B 144, Road No.9, Vishwakarma Industrial Area,",
    "sg:city":"Jaipur",
    "sg:classifiers":[
        {
            "category":"Manufacturing",
            "subcategory":"Chemicals & Compounds",
            "type":"Manufacturing & Wholesale Goods"
        }
    ],
    "sg:phone":"+91 141 233 1559",
    "sg:postcode":"302013",
    "sg:tags":[
        "supply"
    ],
    "sg:website":"http://www.guptachemicals.com",
    "wof:name":"Gupta Chemicals Pvt. Ltd.",
    "wof:placetype":"venue"
},
  "geometry": {"coordinates":[77.191551,28.650553],"type":"Point"}
}