{
  "type": "Feature",
  "properties": {
    "iso:country":"IN",
    "sg:address":"P.b.no.7126, 15, Bvk Iyengar Road,",
    "sg:city":"Bangalore",
    "sg:orig_category":"Pvc & Hdpe Pipes",
    "sg:phone":"+91 80 2226 3499",
    "sg:postcode":"560053",
    "wof:name":"Macoplast",
    "wof:placetype":"venue"
},
  "geometry": {"coordinates":[77.577499,12.973182],"type":"Point"}
}