{
  "type": "Feature",
  "properties": {
    "iso:country":"IN",
    "sg:address":"No. 248, 3rd Cross, 8th Main Peenya Industrial Area, Phase-iii,",
    "sg:city":"Bangalore",
    "sg:classifiers":[
        {
            "category":"Manufacturing",
            "subcategory":"Paper Products",
            "type":"Manufacturing & Wholesale Goods"
        }
    ],
    "sg:phone":"+91 80 2839 4259",
    "sg:postcode":"560058",
    "sg:tags":[
        "equipment",
        "solar"
    ],
    "sg:website":"http://www.anusolar.com",
    "wof:name":"Anu Solar Power Pvt. Ltd.",
    "wof:placetype":"venue"
},
  "geometry": {"coordinates":[77.523338,13.024735],"type":"Point"}
}