{
  "type": "Feature",
  "properties": {
    "iso:country":"IN",
    "sg:address":"D/66, Street No. 4, Bhajanpura,",
    "sg:city":"Delhi",
    "sg:classifiers":[
        {
            "category":"Manufacturing",
            "subcategory":"Rubber & Plastics",
            "type":"Manufacturing & Wholesale Goods"
        }
    ],
    "sg:phone":"+91 11 2256 3718",
    "sg:postcode":"110053",
    "sg:tags":[
        "product"
    ],
    "wof:name":"Sigmaa Rubber Inc.",
    "wof:placetype":"venue"
},
  "geometry": {"coordinates":[77.27314800000001,28.707514],"type":"Point"}
}