{
  "type": "Feature",
  "properties": {
    "iso:country":"IN",
    "sg:address":"18-b, Lake Road,",
    "sg:city":"Kolkata",
    "sg:classifiers":[
        {
            "category":"Manufacturing",
            "subcategory":"Petroleum Products",
            "type":"Manufacturing & Wholesale Goods"
        }
    ],
    "sg:phone":"+91 33 2466 3865",
    "sg:postcode":"700029",
    "sg:tags":[
        "wax"
    ],
    "wof:name":"Chem Impex Corporation Private Limited",
    "wof:placetype":"venue"
},
  "geometry": {"coordinates":[76.683052,11.402356],"type":"Point"}
}