{
  "type": "Feature",
  "properties": {
    "iso:country":"IN",
    "sg:address":"125, Netaji Subhas Road, 5th Floor, R. No.-55,",
    "sg:city":"Kolkata",
    "sg:classifiers":[
        {
            "category":"Manufacturing",
            "subcategory":"Chemicals & Compounds",
            "type":"Manufacturing & Wholesale Goods"
        }
    ],
    "sg:phone":"+91 33 3090 3326",
    "sg:postcode":"700001",
    "sg:tags":[
        "supply"
    ],
    "wof:name":"Rungta Chemicals Pvt. Ltd.",
    "wof:placetype":"venue"
},
  "geometry": {"coordinates":[88.348991,22.576496],"type":"Point"}
}