{
  "type": "Feature",
  "properties": {
    "iso:country":"IN",
    "sg:address":"21/5, A.m. Road, Kalasipalayam New Extn.,",
    "sg:city":"Bangalore",
    "sg:classifiers":[
        {
            "category":"Manufacturing",
            "subcategory":"Tools & Machinery",
            "type":"Manufacturing & Wholesale Goods"
        }
    ],
    "sg:phone":"+91 91802127459",
    "sg:postcode":"560002",
    "sg:tags":[
        "component",
        "auto",
        "part",
        "turned",
        "precision"
    ],
    "wof:name":"M. N. Radiators",
    "wof:placetype":"venue"
},
  "geometry": {"coordinates":[77.570427,12.957186],"type":"Point"}
}