{
  "type": "Feature",
  "properties": {
    "iso:country":"IN",
    "sg:address":"10th Floor, Bajaj Bhavan, Nariman Point,",
    "sg:city":"Mumbai",
    "sg:classifiers":[
        {
            "category":"Banks & Credit Unions",
            "subcategory":"Investment Brokerage",
            "type":"Services"
        }
    ],
    "sg:phone":"+91 22 2288 2250",
    "sg:postcode":"400021",
    "sg:tags":[
        "agro",
        "product",
        "based",
        "commodity"
    ],
    "wof:name":"Hk Group Of Companies",
    "wof:placetype":"venue"
},
  "geometry": {"coordinates":[72.822403,18.925873],"type":"Point"}
}