{
  "type": "Feature",
  "properties": {
    "iso:country":"IN",
    "sg:address":"#600, Koramangal Village, Kormangla,",
    "sg:city":"Bangalore",
    "sg:orig_category":"Readymade Garments",
    "sg:phone":"+91 80 2571 0705",
    "sg:postcode":"560061",
    "wof:name":"Rokhein International Pvt. Ltd.",
    "wof:placetype":"venue"
},
  "geometry": {"coordinates":[77.622559,12.930661],"type":"Point"}
}