{
  "type": "Feature",
  "properties": {
    "iso:country":"IN",
    "sg:address":"412-a, City Centre, 570, M.g.road,",
    "sg:city":"Indore",
    "sg:classifiers":[
        {
            "category":"Wholesale",
            "subcategory":"Chemicals & Plastics",
            "type":"Manufacturing & Wholesale Goods"
        }
    ],
    "sg:phone":"+91 731 253 5587",
    "sg:postcode":"452008",
    "sg:tags":[
        "dye"
    ],
    "wof:name":"M. N. Capital Pvt. Ltd.",
    "wof:placetype":"venue"
},
  "geometry": {"coordinates":[77.158218,28.70295],"type":"Point"}
}