{
  "type": "Feature",
  "properties": {
    "iso:country":"IN",
    "sg:address":"Bhopal Bhopal",
    "sg:city":"Bhopal",
    "sg:classifiers":[
        {
            "category":"Professional",
            "subcategory":"Computer Services",
            "type":"Services"
        }
    ],
    "sg:postcode":"462021",
    "sg:tags":[
        "web-development-company"
    ],
    "sg:website":"http://www.hariomtechnologies.com",
    "wof:name":"HariOmTechnologies",
    "wof:placetype":"venue"
},
  "geometry": {"coordinates":[77.458903,23.27711],"type":"Point"}
}