{
  "type": "Feature",
  "properties": {
    "iso:country":"IN",
    "sg:address":"40, Phears Lane,",
    "sg:city":"Kolkata",
    "sg:classifiers":[
        {
            "category":"Manufacturing",
            "subcategory":"Textiles",
            "type":"Manufacturing & Wholesale Goods"
        }
    ],
    "sg:postcode":"700073",
    "sg:tags":[
        "chemical"
    ],
    "wof:name":"Vohra Enterprise",
    "wof:placetype":"venue"
},
  "geometry": {"coordinates":[88.357758,22.574474],"type":"Point"}
}