{
  "type": "Feature",
  "properties": {
    "iso:country":"IN",
    "sg:address":"50, Princess Street, 4th Floor,",
    "sg:city":"Mumbai",
    "sg:classifiers":[
        {
            "category":"Home & Garden",
            "subcategory":"Carpets & Floor Coverings",
            "type":"Retail Goods"
        }
    ],
    "sg:phone":"+91 22 2203 6108",
    "sg:postcode":"400002",
    "sg:tags":[
        "bedspread"
    ],
    "wof:name":"Dhan Tex",
    "wof:placetype":"venue"
},
  "geometry": {"coordinates":[72.830635,18.947435],"type":"Point"}
}