{
  "type": "Feature",
  "properties": {
    "iso:country":"IN",
    "sg:address":"Bhandup Ind. Estate, A-wing, Unit No.1037, L.b.s.marg, Pannalal Compound, Bhandup (w),",
    "sg:city":"Mumbai",
    "sg:classifiers":[
        {
            "category":"Utilities",
            "subcategory":"Fuel Oil & Lpg",
            "type":"Services"
        }
    ],
    "sg:phone":"+91 22 5599 3015",
    "sg:postcode":"400078",
    "sg:tags":[
        "aromatics",
        "essential"
    ],
    "wof:name":"Abhisek Aromatics",
    "wof:placetype":"venue"
},
  "geometry": {"coordinates":[72.93129,19.150547],"type":"Point"}
}