{
  "type": "Feature",
  "properties": {
    "iso:country":"IN",
    "sg:address":"5, Shreeji Bhuvan, 70, Lohar Chawl,",
    "sg:city":"Mumbai",
    "sg:classifiers":[
        {
            "category":"Communications",
            "subcategory":"Film & Video Production",
            "type":"Services"
        }
    ],
    "sg:phone":"+91 22 2206 1738",
    "sg:postcode":"400002",
    "sg:tags":[
        "lighting",
        "product",
        "electrical",
        "component",
        "/"
    ],
    "wof:name":"Parimal Electric Corporation",
    "wof:placetype":"venue"
},
  "geometry": {"coordinates":[72.83193199999999,18.947191],"type":"Point"}
}