{
  "type": "Feature",
  "properties": {
    "iso:country":"IN",
    "sg:address":"42 Gidc Makarpura,",
    "sg:city":"Vadodara",
    "sg:classifiers":[
        {
            "category":"Building & Trades",
            "subcategory":"Pest Control",
            "type":"Services"
        }
    ],
    "sg:phone":"+91 265 264 2790",
    "sg:postcode":"390010",
    "sg:tags":[
        "fastener"
    ],
    "wof:name":"R. M. Fasteners",
    "wof:placetype":"venue"
},
  "geometry": {"coordinates":[72.65799,23.076591],"type":"Point"}
}