{
  "type": "Feature",
  "properties": {
    "iso:country":"IN",
    "sg:address":"A#13/8, 1st Main Cross, Brindavan Nagar, Thavarekere Main Road,",
    "sg:city":"Bangalore",
    "sg:classifiers":[
        {
            "category":"Home & Garden",
            "subcategory":"Building Materials",
            "type":"Retail Goods"
        }
    ],
    "sg:phone":"+91 80 2552 2731",
    "sg:postcode":"560081",
    "sg:tags":[
        "textile",
        "silk"
    ],
    "wof:name":"Padma Trading Company",
    "wof:placetype":"venue"
},
  "geometry": {"coordinates":[77.611351,12.921551],"type":"Point"}
}