{
  "type": "Feature",
  "properties": {
    "iso:country":"IN",
    "sg:address":"48, Millers Tank Bund Road,",
    "sg:city":"Bangalore",
    "sg:classifiers":[
        {
            "category":"Shopping",
            "subcategory":"Clothing, Apparel, & Fashions",
            "type":"Retail Goods"
        }
    ],
    "sg:phone":"+91 80 2235 0905",
    "sg:postcode":"560052",
    "sg:tags":[
        "t-shirt"
    ],
    "wof:name":"J. R. Trading Pvt. Ltd.",
    "wof:placetype":"venue"
},
  "geometry": {"coordinates":[77.59493999999999,12.992598],"type":"Point"}
}