{
  "type": "Feature",
  "properties": {
    "iso:country":"IN",
    "sg:address":"473, Sector - 11,",
    "sg:city":"Udaipur",
    "sg:classifiers":[
        {
            "category":"Shopping",
            "subcategory":"Used Merchandise",
            "type":"Retail Goods"
        }
    ],
    "sg:phone":"+91 294 258 4171",
    "sg:postcode":"313001",
    "sg:tags":[
        "merchant",
        "exporter"
    ],
    "wof:name":"Dave Exports",
    "wof:placetype":"venue"
},
  "geometry": {"coordinates":[76.850471,30.686115],"type":"Point"}
}