{
  "type": "Feature",
  "properties": {
    "iso:country":"IN",
    "sg:address":"I B Patel Road, Goregaon (e)",
    "sg:city":"Mumbai",
    "sg:phone":"+91 22 2876 9133",
    "sg:postcode":"400063",
    "sg:province":"Maharashtra",
    "sg:website":"http://www.eandcpower.com",
    "wof:name":"Electronics & Controls Power Systems Pvt Ltd",
    "wof:placetype":"venue"
},
  "geometry": {"coordinates":[72.85504899999999,19.161362],"type":"Point"}
}