{
  "type": "Feature",
  "properties": {
    "iso:country":"IN",
    "sg:address":"Phase 1, Mayur Vihar",
    "sg:city":"Delhi",
    "sg:phone":"+91 11 2275 6184",
    "sg:postcode":"110091",
    "sg:province":"Delhi",
    "sg:website":"http://www.callinacare.com",
    "wof:name":"Callina Care Overseas Pvt Ltd",
    "wof:placetype":"venue"
},
  "geometry": {"coordinates":[77.30085,28.605492],"type":"Point"}
}