{
  "type": "Feature",
  "properties": {
    "iso:country":"IN",
    "sg:address":"435/436, Kaliandas Udyog Bhavan, Near Century Bazar, Prabhadevi,",
    "sg:city":"Mumbai",
    "sg:classifiers":[
        {
            "category":"Wholesale",
            "subcategory":"Machinery & Supplies",
            "type":"Manufacturing & Wholesale Goods"
        }
    ],
    "sg:phone":"+91 22 2430 3032",
    "sg:postcode":"400025",
    "sg:tags":[
        "air-compressing",
        "air-separation"
    ],
    "wof:name":"Pneumech Compressor Co.",
    "wof:placetype":"venue"
},
  "geometry": {"coordinates":[72.824333,19.011509],"type":"Point"}
}