{
  "type": "Feature",
  "properties": {
    "iso:country":"IN",
    "sg:address":"2136, Tilak Bazar, Khari Badli,",
    "sg:city":"Delhi",
    "sg:classifiers":[
        {
            "category":"Wholesale",
            "subcategory":"Chemicals & Plastics",
            "type":"Manufacturing & Wholesale Goods"
        }
    ],
    "sg:phone":"+91 11 2396 4522",
    "sg:postcode":"110006",
    "sg:tags":[
        "dyestuff"
    ],
    "wof:name":"Jay Kay Dyes & Chemicals",
    "wof:placetype":"venue"
},
  "geometry": {"coordinates":[77.220764,28.658045],"type":"Point"}
}