{
  "type": "Feature",
  "properties": {
    "iso:country":"IN",
    "sg:address":"6th  Floor",
    "sg:city":"Bangalore",
    "sg:phone":"+91 80 2221 2143",
    "sg:postcode":"560025",
    "sg:province":"Karnataka",
    "wof:name":"Minigranites Ltd",
    "wof:placetype":"venue"
},
  "geometry": {"coordinates":[77.656998,12.968318],"type":"Point"}
}