{
  "type": "Feature",
  "properties": {
    "iso:country":"IN",
    "sg:address":"211, Dalamal Chambers, New Marine Lines,",
    "sg:city":"Mumbai",
    "sg:classifiers":[
        {
            "category":"Personal",
            "subcategory":"Hair Removal",
            "type":"Services"
        }
    ],
    "sg:phone":"+91 22 2200 1993",
    "sg:postcode":"400020",
    "sg:tags":[
        "cosmetic",
        "accessory"
    ],
    "sg:website":"http://www.dewherbalcosmetics.com",
    "wof:name":"Dew Cosmetics",
    "wof:placetype":"venue"
},
  "geometry": {"coordinates":[72.82862900000001,18.939135],"type":"Point"}
}