{
  "type": "Feature",
  "properties": {
    "iso:country":"IN",
    "sg:address":"252-l, Sant Nagar, East Of Kailash,",
    "sg:city":"New Delhi",
    "sg:classifiers":[
        {
            "category":"Farming",
            "subcategory":"Fish & Marine Products",
            "type":"Manufacturing & Wholesale Goods"
        }
    ],
    "sg:phone":"+91 11 2628 2059",
    "sg:postcode":"110065",
    "sg:tags":[
        "silicon"
    ],
    "wof:name":"Sumna Jewellers",
    "wof:placetype":"venue"
},
  "geometry": {"coordinates":[77.249855,28.554041],"type":"Point"}
}