{
  "type": "Feature",
  "properties": {
    "iso:country":"IN",
    "sg:address":"Metro House, 2nd Floor, Mahatma Gandhi Road,",
    "sg:city":"Mumbai",
    "sg:classifiers":[
        {
            "category":"Shopping",
            "subcategory":"Jewelry",
            "type":"Retail Goods"
        }
    ],
    "sg:phone":"+91 22 2208 5092",
    "sg:postcode":"400020",
    "sg:tags":[
        "diamond"
    ],
    "wof:name":"Top Diamonds Ltd.",
    "wof:placetype":"venue"
},
  "geometry": {"coordinates":[77.248802,28.619921],"type":"Point"}
}