{
  "type": "Feature",
  "properties": {
    "iso:country":"IN",
    "sg:address":"8, Camac Street, shantiniketan, 5th Floor, Room No.7,",
    "sg:city":"Kolkata",
    "sg:classifiers":[
        {
            "category":"Manufacturing",
            "subcategory":"Chemicals & Compounds",
            "type":"Manufacturing & Wholesale Goods"
        }
    ],
    "sg:phone":"+91 33 2282 7101",
    "sg:postcode":"700017",
    "sg:tags":[
        "industrial"
    ],
    "wof:name":"Chemetall-rai",
    "wof:placetype":"venue"
},
  "geometry": {"coordinates":[88.35202,22.543602],"type":"Point"}
}