{
  "type": "Feature",
  "properties": {
    "iso:country":"IN",
    "sg:address":"Plot No 2428, G.i.d.c, Surat,",
    "sg:city":"Sachin",
    "sg:classifiers":[
        {
            "category":"Manufacturing",
            "subcategory":"Chemicals & Compounds",
            "type":"Manufacturing & Wholesale Goods"
        }
    ],
    "sg:phone":"+91 261 559 3354",
    "sg:postcode":"394230",
    "sg:tags":[
        "dye",
        "intermediate"
    ],
    "sg:website":"http://www.nutandyechem.com",
    "wof:name":"Nutan Dye Chem",
    "wof:placetype":"venue"
},
  "geometry": {"coordinates":[72.82392900000001,21.181299],"type":"Point"}
}