{
  "type": "Feature",
  "properties": {
    "iso:country":"IN",
    "sg:address":"51, Avenue Road, 2nd Floor, P.s. Buildings,",
    "sg:city":"Bangalore",
    "sg:orig_category":"Pvc Products",
    "sg:phone":"+91 80 2221 6567",
    "sg:postcode":"560002",
    "wof:name":"Dipika Plastic Industries",
    "wof:placetype":"venue"
},
  "geometry": {"coordinates":[72.844032,19.010548],"type":"Point"}
}