{
  "type": "Feature",
  "properties": {
    "iso:country":"IN",
    "sg:address":"142, M.g.d. Atish Market,",
    "sg:city":"Jaipur",
    "sg:classifiers":[
        {
            "category":"Manufacturing",
            "subcategory":"Chemicals & Compounds",
            "type":"Manufacturing & Wholesale Goods"
        }
    ],
    "sg:phone":"+91 141 231 2866",
    "sg:postcode":"302002",
    "sg:tags":[
        "supply"
    ],
    "wof:name":"International Traders (india)",
    "wof:placetype":"venue"
},
  "geometry": {"coordinates":[75.820892,26.924782],"type":"Point"}
}