{
  "type": "Feature",
  "properties": {
    "iso:country":"IN",
    "sg:address":"5110, Bhandup Industrial Estate, Bhandup(w),",
    "sg:city":"Mumbai",
    "sg:classifiers":[
        {
            "category":"Wholesale",
            "subcategory":"Drugs",
            "type":"Manufacturing & Wholesale Goods"
        }
    ],
    "sg:phone":"+91 22 2569 1735",
    "sg:postcode":"400078",
    "sg:tags":[
        "bulk"
    ],
    "sg:website":"http://www.synergybropharma.com",
    "wof:name":"Synergy Biopharma Pvt. Ltd.",
    "wof:placetype":"venue"
},
  "geometry": {"coordinates":[72.937935,19.154734],"type":"Point"}
}