{
  "type": "Feature",
  "properties": {
    "iso:country":"IN",
    "sg:address":"D-134, Sector-7,",
    "sg:city":"Noida",
    "sg:classifiers":[
        {
            "category":"Manufacturing",
            "subcategory":"Petroleum Products",
            "type":"Manufacturing & Wholesale Goods"
        }
    ],
    "sg:phone":"+91 120 652 3455",
    "sg:postcode":"201301",
    "sg:tags":[
        "wax"
    ],
    "wof:name":"Universal Thermoplas",
    "wof:placetype":"venue"
},
  "geometry": {"coordinates":[77.011826,28.467407],"type":"Point"}
}