{
  "type": "Feature",
  "properties": {
    "iso:country":"IN",
    "sg:address":"32 - 33, Nehru Place",
    "sg:city":"New Delhi",
    "sg:phone":"+91 11 2643 1903",
    "sg:postcode":"110019",
    "sg:province":"Delhi",
    "sg:website":"http://www.bkconsimpex.com",
    "wof:name":"B K Consimpex",
    "wof:placetype":"venue"
},
  "geometry": {"coordinates":[77.253448,28.550797],"type":"Point"}
}