{
  "type": "Feature",
  "properties": {
    "iso:country":"IN",
    "sg:address":"634, G.i.d.c., Waghodia,",
    "sg:city":"Vadodara",
    "sg:classifiers":[
        {
            "category":"Ice Cream",
            "type":"Food & Drink"
        }
    ],
    "sg:phone":"+91 265 243 9931",
    "sg:postcode":"390001",
    "sg:tags":[
        "bottle"
    ],
    "wof:name":"Sjr Plast",
    "wof:placetype":"venue"
},
  "geometry": {"coordinates":[73.233536,22.286194],"type":"Point"}
}