{
  "type": "Feature",
  "properties": {
    "iso:country":"IN",
    "sg:address":"Plot No. L-15/1, Taloja Midc,",
    "sg:city":"Mumbai",
    "sg:orig_category":"Building Glass",
    "sg:phone":"+91 22 2741 0992",
    "sg:postcode":"410208",
    "sg:website":"http://www.fgglasscom",
    "wof:name":"Fg Glass Industries Pvt. Ltd.",
    "wof:placetype":"venue"
},
  "geometry": {"coordinates":[73.121002,19.063381],"type":"Point"}
}