{
  "type": "Feature",
  "properties": {
    "iso:country":"IN",
    "sg:address":"No.-77/1, M.m. Road, Fraser Town,",
    "sg:city":"Bangalore",
    "sg:classifiers":[
        {
            "category":"Shopping",
            "subcategory":"Stationery & Office Supplies",
            "type":"Retail Goods"
        }
    ],
    "sg:phone":"+91 80 2548 8407",
    "sg:postcode":"560005",
    "sg:tags":[
        "ups",
        "power"
    ],
    "sg:website":"http://www.teamtronix.in",
    "wof:name":"Teamtronix India Pvt. Ltd.",
    "wof:placetype":"venue"
},
  "geometry": {"coordinates":[77.616066,13.000596],"type":"Point"}
}