{
  "type": "Feature",
  "properties": {
    "iso:country":"IN",
    "sg:address":"X/974/30, 2nd Floor, Bhima Building, South Bazar,",
    "sg:city":"Thrissur",
    "sg:classifiers":[
        {
            "category":"Shopping",
            "subcategory":"Jewelry",
            "type":"Retail Goods"
        }
    ],
    "sg:phone":"+91 4882 427 739",
    "sg:postcode":"680001",
    "wof:name":"Super Stone Diamonds",
    "wof:placetype":"venue"
},
  "geometry": {"coordinates":[78.495064,17.434727],"type":"Point"}
}