{
  "type": "Feature",
  "properties": {
    "iso:country":"IN",
    "sg:address":"Shahpur Jat",
    "sg:city":"New Delhi",
    "sg:phone":"+91 11 2649 4439",
    "sg:postcode":"110049",
    "sg:province":"Delhi",
    "sg:website":"http://www.eisalifts.com",
    "wof:name":"Eisa Lifts Pvt Ltd",
    "wof:placetype":"venue"
},
  "geometry": {"coordinates":[77.213928,28.549189],"type":"Point"}
}