{
  "type": "Feature",
  "properties": {
    "iso:country":"IN",
    "sg:address":"W/78, Phase-2, Opp. H.m.v., Midc,",
    "sg:city":"Dombivili",
    "sg:classifiers":[
        {
            "category":"Manufacturing",
            "subcategory":"Chemicals & Compounds",
            "type":"Manufacturing & Wholesale Goods"
        }
    ],
    "sg:phone":"+91 251 287 1078",
    "sg:postcode":"421203",
    "sg:tags":[
        "supply"
    ],
    "wof:name":"Pliogrip Resins & Chemicals Pvt. Ltd.",
    "wof:placetype":"venue"
},
  "geometry": {"coordinates":[77.034859,20.684992],"type":"Point"}
}