{
  "type": "Feature",
  "properties": {
    "iso:country":"IN",
    "sg:address":"10/119, Sahakar Nagar-1, Chembur,",
    "sg:city":"Mumbai",
    "sg:classifiers":[
        {
            "category":"Banks & Credit Unions",
            "subcategory":"Financial Services",
            "type":"Services"
        }
    ],
    "sg:phone":"+91 22 2522 2384",
    "sg:postcode":"400071",
    "sg:tags":[
        "banking",
        "product",
        "automation"
    ],
    "wof:name":"Spg Enterprises",
    "wof:placetype":"venue"
},
  "geometry": {"coordinates":[72.891792,19.06307],"type":"Point"}
}