{
  "type": "Feature",
  "properties": {
    "iso:country":"IN",
    "sg:address":"Rachana Industrial Estate, Gala No.3 & 4, A-wing, Valiv Phata, Sativali Road, Vasai (e),",
    "sg:city":"Mumbai",
    "sg:classifiers":[
        {
            "category":"Manufacturing",
            "subcategory":"Rubber & Plastics",
            "type":"Manufacturing & Wholesale Goods"
        }
    ],
    "sg:phone":"+91 250 248 0032",
    "sg:tags":[
        "product"
    ],
    "wof:name":"Shreenath Rubber Industries",
    "wof:placetype":"venue"
},
  "geometry": {"coordinates":[72.863365,19.394211],"type":"Point"}
}