{
  "type": "Feature",
  "properties": {
    "iso:country":"IN",
    "sg:address":"176, Anand Indl. Estate, Mohan Nagar,",
    "sg:city":"Ghaziabad",
    "sg:classifiers":[
        {
            "category":"Manufacturing",
            "subcategory":"Chemicals & Compounds",
            "type":"Manufacturing & Wholesale Goods"
        }
    ],
    "sg:phone":"+91 120 265 7157",
    "sg:postcode":"201007",
    "sg:tags":[
        "coatings-powder",
        "coating"
    ],
    "wof:name":"Wel Cast Engineers (p) Ltd.",
    "wof:placetype":"venue"
},
  "geometry": {"coordinates":[77.37694500000001,28.680077],"type":"Point"}
}