{
  "type": "Feature",
  "properties": {
    "iso:country":"IN",
    "sg:address":"B-42, Iii Stage, Peenya,",
    "sg:city":"Bangalore",
    "sg:classifiers":[
        {
            "category":"Manufacturing",
            "subcategory":"Chemicals & Compounds",
            "type":"Manufacturing & Wholesale Goods"
        }
    ],
    "sg:phone":"+91 80 2836 1176",
    "sg:postcode":"560058",
    "sg:tags":[
        "supply"
    ],
    "wof:name":"Colloids Impex Pvt. Ltd.",
    "wof:placetype":"venue"
},
  "geometry": {"coordinates":[77.52253,13.030821],"type":"Point"}
}