{
  "type": "Feature",
  "properties": {
    "iso:country":"IN",
    "sg:address":"Govindpura",
    "sg:city":"Bhopal",
    "sg:phone":"+91 755586800",
    "sg:postcode":"462023",
    "sg:province":"Madhya Pradesh",
    "wof:name":"Eastern Air Products Pvt Ltd",
    "wof:placetype":"venue"
},
  "geometry": {"coordinates":[77.447777,23.209444],"type":"Point"}
}