{
  "type": "Feature",
  "properties": {
    "iso:country":"IN",
    "sg:address":"Industrial Area",
    "sg:city":"Yamuna Nagar",
    "sg:phone":"+91 171 375 0601",
    "sg:postcode":"135001",
    "sg:province":"Haryana",
    "wof:name":"Pragati Silicones Ltd",
    "wof:placetype":"venue"
},
  "geometry": {"coordinates":[76.954224,29.402643],"type":"Point"}
}