{
  "type": "Feature",
  "properties": {
    "iso:country":"IN",
    "sg:address":"G-53, Dawa Bazar,",
    "sg:city":"Indore",
    "sg:classifiers":[
        {
            "category":"Real Estate",
            "subcategory":"Surveying",
            "type":"Services"
        }
    ],
    "sg:phone":"+91 731 404 0025",
    "sg:postcode":"452001",
    "sg:tags":[
        "pharmaceutical",
        "material",
        "raw"
    ],
    "sg:website":"http://www.djlabs.com",
    "wof:name":"D. J. Laborrtories Pvt. Ltd.",
    "wof:placetype":"venue"
},
  "geometry": {"coordinates":[77.00655399999999,20.710428],"type":"Point"}
}