{
  "type": "Feature",
  "properties": {
    "iso:country":"IN",
    "sg:address":"30, Unique Industrial Estate, Dr. R.p. Road, Mulund West,",
    "sg:city":"Mumbai",
    "sg:classifiers":[
        {
            "category":"Manufacturing",
            "subcategory":"Rubber & Plastics",
            "type":"Manufacturing & Wholesale Goods"
        }
    ],
    "sg:phone":"+91 22 2593 0940",
    "sg:tags":[
        "product"
    ],
    "sg:website":"http://www.kkthelittlegiant.com",
    "wof:name":"Technovinyl Polymers India Limited",
    "wof:placetype":"venue"
},
  "geometry": {"coordinates":[72.943108,19.174673],"type":"Point"}
}