{
  "type": "Feature",
  "properties": {
    "iso:country":"IN",
    "sg:address":"167, Khadilkar Road, 2nd Floor, Zaveri Bazar,",
    "sg:city":"Mumbai",
    "sg:classifiers":[
        {
            "category":"Shopping",
            "subcategory":"Stationery & Office Supplies",
            "type":"Retail Goods"
        }
    ],
    "sg:phone":"+91 22 2385 3121",
    "sg:postcode":"400004",
    "sg:tags":[
        "calendar",
        "diary"
    ],
    "wof:name":"Mangalam Cards & Arts",
    "wof:placetype":"venue"
},
  "geometry": {"coordinates":[72.82357,18.954981],"type":"Point"}
}