{
  "type": "Feature",
  "properties": {
    "iso:country":"IN",
    "sg:address":"Plot No.3709/4, Gidc,",
    "sg:city":"Ankleshwar",
    "sg:classifiers":[
        {
            "category":"Home & Garden",
            "subcategory":"Mobile Homes",
            "type":"Retail Goods"
        }
    ],
    "sg:phone":"+91 2646 221 825",
    "sg:postcode":"393002",
    "sg:tags":[
        "acid"
    ],
    "wof:name":"Elam Pharma Pvt. Ltd.",
    "wof:placetype":"venue"
},
  "geometry": {"coordinates":[70.826859,22.280378],"type":"Point"}
}