{
  "type": "Feature",
  "properties": {
    "iso:country":"IN",
    "sg:address":"Abid Road",
    "sg:city":"Hyderabad",
    "sg:phone":"+91 40 2475 8222",
    "sg:postcode":"500001",
    "sg:province":"Andhra Pradesh",
    "wof:name":"Taj Mahal Hotel",
    "wof:placetype":"venue"
},
  "geometry": {"coordinates":[78.46991,17.374405],"type":"Point"}
}