{
  "type": "Feature",
  "properties": {
    "iso:country":"IN",
    "sg:address":"7-8, Mahalaxmi Bridge,",
    "sg:city":"Mumbai",
    "sg:classifiers":[
        {
            "category":"Government",
            "subcategory":"Fire Station",
            "type":"Public Place"
        }
    ],
    "sg:phone":"+91 22 2307 4183",
    "sg:postcode":"400011",
    "sg:tags":[
        "burners/industrial",
        "burner",
        "incinerator"
    ],
    "wof:name":"United Works Private Limited",
    "wof:placetype":"venue"
},
  "geometry": {"coordinates":[72.81446800000001,18.971123],"type":"Point"}
}