{
  "type": "Feature",
  "properties": {
    "iso:country":"IN",
    "sg:address":"401-1, 1st Crs., 1st Mn., M. Pura,",
    "sg:city":"Bangalore",
    "sg:classifiers":[
        {
            "category":"Manufacturing",
            "subcategory":"Rubber & Plastics",
            "type":"Manufacturing & Wholesale Goods"
        }
    ],
    "sg:phone":"+91 80 57 682738",
    "sg:postcode":"48",
    "sg:tags":[
        "product"
    ],
    "wof:name":"Saastha Plastics (india) Pvt. Ltd.",
    "wof:placetype":"venue"
},
  "geometry": {"coordinates":[77.562218,13.080066],"type":"Point"}
}