{
  "type": "Feature",
  "properties": {
    "iso:country":"IN",
    "sg:address":"120, Udyog Kshetra, Goregaon Link Road, Mulund (w),",
    "sg:city":"Mumbai",
    "sg:classifiers":[
        {
            "category":"Manufacturing",
            "subcategory":"Chemicals & Compounds",
            "type":"Manufacturing & Wholesale Goods"
        }
    ],
    "sg:phone":"+91 22 5621 3741",
    "sg:postcode":"400080",
    "sg:tags":[
        "supply"
    ],
    "wof:name":"Hem Chem Corporation",
    "wof:placetype":"venue"
},
  "geometry": {"coordinates":[72.939064,19.164045],"type":"Point"}
}