{
  "type": "Feature",
  "properties": {
    "iso:country":"IN",
    "sg:address":"Sco 164-165, Sector 9-c,",
    "sg:city":"Chandigarh",
    "sg:classifiers":[
        {
            "category":"Real Estate",
            "subcategory":"Surveying",
            "type":"Services"
        }
    ],
    "sg:phone":"+91 172 500 5000",
    "sg:postcode":"160009",
    "sg:tags":[
        "pharmaceutical",
        "material",
        "raw"
    ],
    "sg:website":"http://www.suryapharma.com",
    "wof:name":"Surya Pharmaceutical Limited",
    "wof:placetype":"venue"
},
  "geometry": {"coordinates":[77.008804,28.473675],"type":"Point"}
}