{
  "type": "Feature",
  "properties": {
    "iso:country":"IN",
    "sg:address":"D-39a, Yadav Nagar,",
    "sg:city":"New Delhi",
    "sg:classifiers":[
        {
            "category":"Military Area",
            "subcategory":"Air Force Base",
            "type":"Public Place"
        }
    ],
    "sg:postcode":"110042",
    "sg:tags":[
        "silica",
        "gel"
    ],
    "wof:name":"Organic Chemicals",
    "wof:placetype":"venue"
},
  "geometry": {"coordinates":[77.139168,28.749847],"type":"Point"}
}