{
  "type": "Feature",
  "properties": {
    "iso:country":"IN",
    "sg:address":"2011, 2nd Floor, Bhandup Industrial Estate, Lbs Marg, Bhandup (west),",
    "sg:city":"Mumbai",
    "sg:classifiers":[
        {
            "category":"Manufacturing",
            "subcategory":"Motor Vehicles & Parts",
            "type":"Manufacturing & Wholesale Goods"
        }
    ],
    "sg:phone":"+91 22 2567 8072",
    "sg:tags":[
        "component",
        "product",
        "electronic"
    ],
    "wof:name":"Sonit Electronics Co.",
    "wof:placetype":"venue"
},
  "geometry": {"coordinates":[72.937935,19.154734],"type":"Point"}
}