{
  "type": "Feature",
  "properties": {
    "iso:country":"IN",
    "sg:address":"Off. Dr. E. Moses Road, Worli Naka",
    "sg:city":"Mumbai",
    "sg:phone":"+91 22 2497 0186",
    "sg:postcode":"400018",
    "sg:province":"Maharashtra",
    "wof:name":"Lactose (i) Ltd",
    "wof:placetype":"venue"
},
  "geometry": {"coordinates":[72.817482,18.998594],"type":"Point"}
}