{
  "type": "Feature",
  "properties": {
    "iso:country":"IN",
    "sg:address":"193/3, N.s. Palya, Bannerghatta Road,",
    "sg:city":"Bangalore",
    "sg:classifiers":[
        {
            "category":"Banks & Credit Unions",
            "subcategory":"Investment Brokerage",
            "type":"Services"
        }
    ],
    "sg:phone":"+91 80 2668 6451",
    "sg:postcode":"560076",
    "sg:tags":[
        "wires/cables",
        "accessory"
    ],
    "wof:name":"Karnataka Engineering Works",
    "wof:placetype":"venue"
},
  "geometry": {"coordinates":[77.60020400000001,12.914347],"type":"Point"}
}