{
  "type": "Feature",
  "properties": {
    "iso:country":"IN",
    "sg:address":"S-553, Greater Kailash-ii,",
    "sg:city":"New Delhi",
    "sg:classifiers":[
        {
            "category":"Real Estate",
            "subcategory":"Surveying",
            "type":"Services"
        }
    ],
    "sg:phone":"+91 11 2922 2188",
    "sg:postcode":"110048",
    "sg:tags":[
        "pharmaceutical",
        "material",
        "raw"
    ],
    "wof:name":"Emerald Industries",
    "wof:placetype":"venue"
},
  "geometry": {"coordinates":[77.249138,28.531738],"type":"Point"}
}