{
  "type": "Feature",
  "properties": {
    "iso:country":"IN",
    "sg:address":"C/2, Near Dena Bank, Lower Parel,",
    "sg:city":"Mumbai",
    "sg:classifiers":[
        {
            "category":"Manufacturing",
            "subcategory":"Tools & Machinery",
            "type":"Manufacturing & Wholesale Goods"
        }
    ],
    "sg:phone":"+91 22 2492 9103",
    "sg:postcode":"400013",
    "sg:tags":[
        "equipment",
        "moving",
        "earth"
    ],
    "wof:name":"Dalip Manufacturers & Co.",
    "wof:placetype":"venue"
},
  "geometry": {"coordinates":[72.82872,19.016768],"type":"Point"}
}