{
  "type": "Feature",
  "properties": {
    "iso:country":"IN",
    "sg:address":"B-88/45, 5th Main Road, Industrial Estate, Rajajinagar,",
    "sg:city":"Bangalore",
    "sg:classifiers":[
        {
            "category":"Wholesale",
            "subcategory":"Auto Parts",
            "type":"Manufacturing & Wholesale Goods"
        }
    ],
    "sg:phone":"+91 80 2338 7847",
    "sg:postcode":"560044",
    "sg:tags":[
        "component",
        "pressed"
    ],
    "wof:name":"Sri Satish Press Tools",
    "wof:placetype":"venue"
},
  "geometry": {"coordinates":[77.542755,13.014302],"type":"Point"}
}