{
  "type": "Feature",
  "properties": {
    "iso:country":"IN",
    "sg:address":"Nyniappa Naicken Street",
    "sg:city":"Chennai",
    "sg:phone":"+91 44 2535 4965",
    "sg:postcode":"600003",
    "sg:province":"Tamil Nadu",
    "wof:name":"Shantilal & Co",
    "wof:placetype":"venue"
},
  "geometry": {"coordinates":[80.279053,13.085027],"type":"Point"}
}