{
  "type": "Feature",
  "properties": {
    "iso:country":"IN",
    "sg:address":"#26/3, Indl. Suburb, Rajaji Nagar,",
    "sg:city":"Bangalore",
    "sg:classifiers":[
        {
            "category":"Personal",
            "subcategory":"Shoe Repair & Shine",
            "type":"Services"
        }
    ],
    "sg:phone":"+91 80 2337 8918",
    "sg:postcode":"560055",
    "sg:tags":[
        "polishing",
        "polish",
        "material/machinery"
    ],
    "sg:website":"http://www.parijatha.com",
    "wof:name":"Sree Parijatha Machinery Works",
    "wof:placetype":"venue"
},
  "geometry": {"coordinates":[77.539429,13.009407],"type":"Point"}
}