{
  "type": "Feature",
  "properties": {
    "iso:country":"IN",
    "sg:address":"nirmal, 3rd Floor, Nariman Point,",
    "sg:city":"Mumbai",
    "sg:classifiers":[
        {
            "category":"Manufacturing",
            "subcategory":"Chemicals & Compounds",
            "type":"Manufacturing & Wholesale Goods"
        }
    ],
    "sg:phone":"+91 22 2287 1914",
    "sg:postcode":"400021",
    "sg:tags":[
        "supply"
    ],
    "sg:website":"http://www.dcwltd.com",
    "wof:name":"Dcw Limited",
    "wof:placetype":"venue"
},
  "geometry": {"coordinates":[72.822281,18.927454],"type":"Point"}
}