{
  "type": "Feature",
  "properties": {
    "iso:country":"IN",
    "sg:address":"Sydenhams Road",
    "sg:city":"Chennai",
    "sg:phone":"+91 44 2532 1022",
    "sg:postcode":"600112",
    "sg:province":"Tamil Nadu",
    "sg:website":"http://www.business.com/btply",
    "wof:name":"Balaji Timber Supplying Co",
    "wof:placetype":"venue"
},
  "geometry": {"coordinates":[80.270256,13.086504],"type":"Point"}
}