{
  "type": "Feature",
  "properties": {
    "iso:country":"IN",
    "sg:address":"D-27, Sector-10,",
    "sg:city":"Noida",
    "sg:orig_category":"Pvc Profiles",
    "sg:phone":"+91 120 433 7634",
    "sg:postcode":"201301",
    "wof:name":"Rajshri Plastic Door & Mod. Kitchen",
    "wof:placetype":"venue"
},
  "geometry": {"coordinates":[81.331688,21.183992],"type":"Point"}
}