{
  "type": "Feature",
  "properties": {
    "iso:country":"IN",
    "sg:address":"# 41, 1st Floor, Kanakapura Road, Basavanagudi,",
    "sg:city":"Bangalore",
    "sg:orig_category":"Plasticizer",
    "sg:phone":"+91 80 2676 6064",
    "sg:postcode":"560004",
    "wof:name":"Saba Chemie",
    "wof:placetype":"venue"
},
  "geometry": {"coordinates":[77.576614,12.923839],"type":"Point"}
}