{
  "type": "Feature",
  "properties": {
    "iso:country":"IN",
    "sg:address":"75, Church Road, Kalina,",
    "sg:city":"Mumbai",
    "sg:classifiers":[
        {
            "category":"Utilities",
            "subcategory":"Refuse",
            "type":"Services"
        }
    ],
    "sg:phone":"+91 22 2666 8626",
    "sg:postcode":"400029",
    "sg:tags":[
        "equipment",
        "air-conditioning"
    ],
    "wof:name":"Saitech Hvac Projects Pvt. Ltd.",
    "wof:placetype":"venue"
},
  "geometry": {"coordinates":[72.86834,19.078382],"type":"Point"}
}