{
  "type": "Feature",
  "properties": {
    "iso:country":"IN",
    "sg:address":"Lg-1, 4/62, Punjabi Bagh (west),",
    "sg:city":"New Delhi",
    "sg:classifiers":[
        {
            "category":"Manufacturing",
            "subcategory":"Chemicals & Compounds",
            "type":"Manufacturing & Wholesale Goods"
        }
    ],
    "sg:phone":"+91 11 6544 4905",
    "sg:postcode":"110026",
    "sg:tags":[
        "salt"
    ],
    "sg:website":"http://www.lopan.co.in",
    "wof:name":"Lopan Kemicals",
    "wof:placetype":"venue"
},
  "geometry": {"coordinates":[77.18225099999999,28.650148],"type":"Point"}
}