{
  "type": "Feature",
  "properties": {
    "iso:country":"IN",
    "sg:address":"3/110, Lalita Park, Laxmi Nagar,",
    "sg:city":"Delhi",
    "sg:classifiers":[
        {
            "category":"Manufacturing",
            "subcategory":"Chemicals & Compounds",
            "type":"Manufacturing & Wholesale Goods"
        }
    ],
    "sg:phone":"+91 11 2254 6048",
    "sg:postcode":"110092",
    "sg:tags":[
        "supply"
    ],
    "sg:website":"http://www.bansgroup.com",
    "wof:name":"Bans Aerosol Pvt. Ltd.",
    "wof:placetype":"venue"
},
  "geometry": {"coordinates":[77.274277,28.630932],"type":"Point"}
}