{
  "type": "Feature",
  "properties": {
    "iso:country":"IN",
    "sg:address":"169 - Bryant Nagar,",
    "sg:city":"Madurai",
    "sg:classifiers":[
        {
            "category":"Manufacturing",
            "subcategory":"Chemicals & Compounds",
            "type":"Manufacturing & Wholesale Goods"
        }
    ],
    "sg:phone":"+91 461 234 0591",
    "sg:postcode":"628002",
    "sg:tags":[
        "supply"
    ],
    "wof:name":"Sterlite Industries",
    "wof:placetype":"venue"
},
  "geometry": {"coordinates":[78.130714,8.792871],"type":"Point"}
}