{
  "type": "Feature",
  "properties": {
    "iso:country":"IN",
    "sg:address":"3804, G.i.d.c. Industrial Estate,",
    "sg:city":"Ankleshwar",
    "sg:classifiers":[
        {
            "category":"Manufacturing",
            "subcategory":"Chemicals & Compounds",
            "type":"Manufacturing & Wholesale Goods"
        }
    ],
    "sg:phone":"+91 2646 221 421",
    "sg:postcode":"393002",
    "sg:tags":[
        "supply"
    ],
    "sg:website":"http://www.shreevardayini.com",
    "wof:name":"Shree Vardayini Chemicals Industries Pvt. Ltd.",
    "wof:placetype":"venue"
},
  "geometry": {"coordinates":[80.306335,26.455313],"type":"Point"}
}