{
  "type": "Feature",
  "properties": {
    "iso:country":"IN",
    "sg:address":"13th Cross, Malleswaram",
    "sg:city":"Bangalore",
    "sg:phone":"+91 803341997",
    "sg:postcode":"560003",
    "sg:province":"Karnataka",
    "wof:name":"Seshadri & Co Pvt Ltd",
    "wof:placetype":"venue"
},
  "geometry": {"coordinates":[77.566025,13.003681],"type":"Point"}
}