{
  "type": "Feature",
  "properties": {
    "iso:country":"IN",
    "sg:address":"Near Natraj Cinema, Moti Nagar",
    "sg:city":"New Delhi",
    "sg:phone":"+91 11 2545 9640",
    "sg:postcode":"110015",
    "sg:province":"Delhi",
    "sg:website":"http://www.dustovent.com",
    "wof:name":"Dust O Vent Equipments India Pvt Ltd",
    "wof:placetype":"venue"
},
  "geometry": {"coordinates":[77.138451,28.663107],"type":"Point"}
}