{
  "type": "Feature",
  "properties": {
    "iso:country":"IN",
    "sg:address":"204 George Road,",
    "sg:city":"Tuticorin",
    "sg:classifiers":[
        {
            "category":"Banks & Credit Unions",
            "subcategory":"Investment Brokerage",
            "type":"Services"
        }
    ],
    "sg:phone":"+91 461 232 1276",
    "sg:postcode":"628002",
    "sg:tags":[
        "agro",
        "product",
        "based",
        "commodity"
    ],
    "wof:name":"Rajarajan & Company",
    "wof:placetype":"venue"
},
  "geometry": {"coordinates":[72.837219,18.939556],"type":"Point"}
}