{
  "type": "Feature",
  "properties": {
    "iso:country":"IN",
    "sg:address":"7, Chittarnjan Ave.,",
    "sg:city":"Kolkata",
    "sg:classifiers":[
        {
            "category":"Manufacturing",
            "subcategory":"Chemicals & Compounds",
            "type":"Manufacturing & Wholesale Goods"
        }
    ],
    "sg:phone":"+91 33 2237 0116",
    "sg:postcode":"700072",
    "sg:tags":[
        "supply"
    ],
    "sg:website":"http://www.wirefabrik.com",
    "wof:name":"Wires & Fabriks (s.a.) Ltd.",
    "wof:placetype":"venue"
},
  "geometry": {"coordinates":[88.360397,22.577614],"type":"Point"}
}