{
  "type": "Feature",
  "properties": {
    "iso:country":"IN",
    "sg:address":"M G Road",
    "sg:city":"Mumbai",
    "sg:phone":"+91 22 2509 3519",
    "sg:postcode":"400086",
    "sg:province":"Maharashtra",
    "sg:website":"www.acegasanalysers.com",
    "wof:name":"Ace Gas Analysers Pvt Ltd",
    "wof:placetype":"venue"
},
  "geometry": {"coordinates":[74.45098900000001,17.290974],"type":"Point"}
}