{
  "type": "Feature",
  "properties": {
    "iso:country":"IN",
    "sg:address":"15, Galaxy Apart., B.p. Road, Bhayander E,",
    "sg:city":"Mumbai",
    "sg:classifiers":[
        {
            "category":"Parking",
            "subcategory":"Garage",
            "type":"Transportation"
        }
    ],
    "sg:phone":"+91 22 2819 0522",
    "sg:postcode":"400105",
    "sg:tags":[
        "cookware"
    ],
    "wof:name":"Shreepal Overseas",
    "wof:placetype":"venue"
},
  "geometry": {"coordinates":[72.863632,19.254427],"type":"Point"}
}