{
  "type": "Feature",
  "properties": {
    "iso:country":"IN",
    "sg:address":"First Cross Street",
    "sg:city":"Chennai",
    "sg:phone":"+91 44 2493 7310",
    "sg:postcode":"600028",
    "sg:province":"Tamil Nadu",
    "sg:website":"http://www.webindia.com/aandf",
    "wof:name":"A&f Overseas Trade Ltd",
    "wof:placetype":"venue"
},
  "geometry": {"coordinates":[80.254616,13.004293],"type":"Point"}
}