{
  "type": "Feature",
  "properties": {
    "iso:country":"IN",
    "sg:address":"331/a-1/9, Gidc, Makarpura,",
    "sg:city":"Vadodara",
    "sg:classifiers":[
        {
            "category":"Manufacturing",
            "subcategory":"Tools & Machinery",
            "type":"Manufacturing & Wholesale Goods"
        }
    ],
    "sg:phone":"+91 265 263 1678",
    "sg:postcode":"390010",
    "sg:tags":[
        "processing",
        "plastic"
    ],
    "sg:website":"http://www.dudhaiyaindustries.com",
    "wof:name":"Dudhaiya Industries",
    "wof:placetype":"venue"
},
  "geometry": {"coordinates":[72.65799,23.076591],"type":"Point"}
}