{
  "type": "Feature",
  "properties": {
    "iso:country":"IN",
    "sg:address":"Ndse Part I",
    "sg:city":"New Delhi",
    "sg:phone":"+91 11 2462 2546",
    "sg:postcode":"110049",
    "sg:province":"Delhi",
    "wof:name":"Century Pulp & Paper Ltd",
    "wof:placetype":"venue"
},
  "geometry": {"coordinates":[77.321495,28.602245],"type":"Point"}
}