{
  "type": "Feature",
  "properties": {
    "iso:country":"IN",
    "sg:address":"Dr R N Mukherjee Road",
    "sg:city":"Kolkata",
    "sg:phone":"+91 33 2248 7651",
    "sg:postcode":"700001",
    "sg:province":"West Bengal",
    "sg:website":"http://www.emamigroup.com",
    "wof:name":"Emami Ltd",
    "wof:placetype":"venue"
},
  "geometry": {"coordinates":[88.351257,22.570007],"type":"Point"}
}