{
  "type": "Feature",
  "properties": {
    "iso:country":"IN",
    "sg:address":"16, Vithaldas Road, Devkaran Mansion, No. 6, Lohar Chawl,",
    "sg:city":"Mumbai",
    "sg:classifiers":[
        {
            "category":"Wholesale",
            "subcategory":"Machinery & Supplies",
            "type":"Manufacturing & Wholesale Goods"
        }
    ],
    "sg:phone":"+91 22 2200 3555",
    "sg:postcode":"400002",
    "sg:tags":[
        "equipment",
        "goods",
        "electrical"
    ],
    "wof:name":"J. B. Electricals",
    "wof:placetype":"venue"
},
  "geometry": {"coordinates":[72.831146,18.947405],"type":"Point"}
}