{
  "type": "Feature",
  "properties": {
    "iso:country":"IN",
    "sg:address":"Rishikesh",
    "sg:city":"Uttaranchal",
    "sg:phone":"+91 135431658",
    "sg:postcode":"249201",
    "sg:province":"Uttar Pradesh",
    "sg:website":"http://www.yogaindia.com",
    "wof:name":"Hotel Ganga Kinare",
    "wof:placetype":"venue"
},
  "geometry": {"coordinates":[80.934647,26.932421],"type":"Point"}
}