{
  "type": "Feature",
  "properties": {
    "iso:country":"IN",
    "sg:address":"Maneshwara Industrial Estae, Tumkur Road, Peenya,",
    "sg:city":"Bangalore",
    "sg:classifiers":[
        {
            "category":"Government",
            "subcategory":"Fire Station",
            "type":"Public Place"
        }
    ],
    "sg:phone":"+91 80 51 170092",
    "sg:tags":[
        "steel",
        "stainless",
        "product",
        "component"
    ],
    "sg:website":"http://www.beekaysteel.com",
    "wof:name":"Radice Ispat (india) Ltd.",
    "wof:placetype":"venue"
},
  "geometry": {"coordinates":[77.527306,13.035222],"type":"Point"}
}