{
  "type": "Feature",
  "properties": {
    "iso:country":"IN",
    "sg:address":"Gulab Bagh,",
    "sg:city":"Udaipur",
    "sg:classifiers":[
        {
            "category":"Retail",
            "subcategory":"Repair Shop",
            "type":"Services"
        }
    ],
    "sg:phone":"+91 294 242 1922",
    "sg:postcode":"313001",
    "sg:tags":[
        "handicraft"
    ],
    "sg:website":"http://www.shilpgram.com",
    "wof:name":"Shilp Gramodhyog Sales Complex",
    "wof:placetype":"venue"
},
  "geometry": {"coordinates":[73.692757,24.575169],"type":"Point"}
}