{
  "type": "Feature",
  "properties": {
    "iso:country":"IN",
    "sg:address":"#88 P, 1st Flr, Epip Indl Area, Whitefield,",
    "sg:city":"Bangalore",
    "sg:classifiers":[
        {
            "category":"Banks & Credit Unions",
            "subcategory":"Atm",
            "type":"Services"
        }
    ],
    "sg:phone":"+91 80 4011 8000",
    "sg:postcode":"560048",
    "sg:tags":[
        "product",
        "allied",
        "switchgear"
    ],
    "wof:name":"Schneider India",
    "wof:placetype":"venue"
},
  "geometry": {"coordinates":[77.709404,12.982682],"type":"Point"}
}