{
  "type": "Feature",
  "properties": {
    "iso:country":"IN",
    "sg:address":"Bommanahalli",
    "sg:city":"Bangalore",
    "sg:phone":"+91 805732333",
    "sg:postcode":"560068",
    "sg:province":"Karnataka",
    "wof:name":"Crystal Vision Pvt Ltd",
    "wof:placetype":"venue"
},
  "geometry": {"coordinates":[77.623543,12.905025],"type":"Point"}
}