{
  "type": "Feature",
  "properties": {
    "iso:country":"IN",
    "sg:address":"5-5-156, 1st Floor, Opp. Lala Temple, Ranigunj,",
    "sg:city":"Secunderabad",
    "sg:classifiers":[
        {
            "category":"Home & Garden",
            "subcategory":"Mobile Homes",
            "type":"Retail Goods"
        }
    ],
    "sg:phone":"+91 40 2771 4695",
    "sg:postcode":"500003",
    "sg:tags":[
        "acid"
    ],
    "wof:name":"Comet Chemicals",
    "wof:placetype":"venue"
},
  "geometry": {"coordinates":[78.490532,17.434963],"type":"Point"}
}