{
  "type": "Feature",
  "properties": {
    "iso:country":"IN",
    "sg:address":"Opp. Harni Water Tank, Halol Road, Harni,",
    "sg:city":"Vadodara",
    "sg:classifiers":[
        {
            "category":"Real Estate",
            "subcategory":"Architect",
            "type":"Services"
        }
    ],
    "sg:phone":"+91 265 559 1010",
    "sg:tags":[
        "marble"
    ],
    "wof:name":"Kalpesh Marble",
    "wof:placetype":"venue"
},
  "geometry": {"coordinates":[73.210182,22.332172],"type":"Point"}
}