{
  "type": "Feature",
  "properties": {
    "iso:country":"IN",
    "sg:address":"Nagdevi Cross Lane,63",
    "sg:city":"Mumbai",
    "sg:classifiers":[
        {
            "category":"Wholesale",
            "subcategory":"Hardware",
            "type":"Manufacturing & Wholesale Goods"
        }
    ],
    "sg:phone":"+91 22 2343 7723",
    "sg:postcode":"400003",
    "sg:tags":[
        "bearing"
    ],
    "wof:name":"Trade Linkers",
    "wof:placetype":"venue"
},
  "geometry": {"coordinates":[72.83399199999999,18.950926],"type":"Point"}
}