{
  "type": "Feature",
  "properties": {
    "iso:country":"IN",
    "sg:address":"Trichy,",
    "sg:city":"Thiruchirapalli",
    "sg:classifiers":[
        {
            "category":"Manufacturing",
            "subcategory":"Leather Goods",
            "type":"Manufacturing & Wholesale Goods"
        }
    ],
    "sg:phone":"+91 431 241 4863",
    "sg:postcode":"620001",
    "sg:tags":[
        "finished"
    ],
    "wof:name":"Ahmed Leathers",
    "wof:placetype":"venue"
},
  "geometry": {"coordinates":[77.568275,11.000287],"type":"Point"}
}