{
  "type": "Feature",
  "properties": {
    "iso:country":"IN",
    "sg:address":"C-64, Lajpat Nagar, Part-i,",
    "sg:city":"New Delhi",
    "sg:classifiers":[
        {
            "category":"Real Estate",
            "subcategory":"Surveying",
            "type":"Services"
        }
    ],
    "sg:phone":"+91 11 2981 0424",
    "sg:postcode":"110024",
    "sg:tags":[
        "pharmaceutical",
        "material",
        "raw"
    ],
    "wof:name":"Brawn Laboratories Ltd.",
    "wof:placetype":"venue"
},
  "geometry": {"coordinates":[80.30877700000001,26.471178],"type":"Point"}
}