{
  "type": "Feature",
  "properties": {
    "iso:country":"IN",
    "sg:address":"910, Budhwar Peth,",
    "sg:city":"Pune",
    "sg:classifiers":[
        {
            "category":"Manufacturing",
            "subcategory":"Rubber & Plastics",
            "type":"Manufacturing & Wholesale Goods"
        }
    ],
    "sg:phone":"+91 20 3290 0670",
    "sg:postcode":"411002",
    "sg:tags":[
        "product"
    ],
    "wof:name":"Classic Rubber & Engineering Stores",
    "wof:placetype":"venue"
},
  "geometry": {"coordinates":[73.85881000000001,18.517784],"type":"Point"}
}