{
  "type": "Feature",
  "properties": {
    "iso:country":"IN",
    "sg:address":"1/1, Cheran Nagar,",
    "sg:city":"Thiruporur",
    "sg:classifiers":[
        {
            "category":"Shopping",
            "subcategory":"Crafts & Fabrics",
            "type":"Retail Goods"
        }
    ],
    "sg:phone":"+91 421 435 5956",
    "sg:postcode":"641606",
    "sg:tags":[
        "knitted",
        "knitwear"
    ],
    "wof:name":"The Natural Impex",
    "wof:placetype":"venue"
},
  "geometry": {"coordinates":[76.943962,11.05149],"type":"Point"}
}