{
  "type": "Feature",
  "properties": {
    "iso:country":"IN",
    "sg:address":"S.j.p. Road Cross",
    "sg:city":"Bangalore",
    "sg:phone":"+91 802278825",
    "sg:postcode":"560002",
    "sg:province":"Karnataka",
    "sg:website":"http://www.eurekapumps.com",
    "wof:name":"Eureka Pumps",
    "wof:placetype":"venue"
},
  "geometry": {"coordinates":[77.578209,12.967132],"type":"Point"}
}