{
  "type": "Feature",
  "properties": {
    "iso:country":"IN",
    "sg:address":"Kodimatha,",
    "sg:city":"Kottayam",
    "sg:classifiers":[
        {
            "category":"Manufacturing",
            "subcategory":"Rubber & Plastics",
            "type":"Manufacturing & Wholesale Goods"
        }
    ],
    "sg:phone":"+91 481 256 5687",
    "sg:postcode":"686039",
    "sg:tags":[
        "natural",
        "-"
    ],
    "sg:website":"http://www.indiannaturalrubber.com",
    "wof:name":"Oswal Entarprises",
    "wof:placetype":"venue"
},
  "geometry": {"coordinates":[76.519821,9.577624],"type":"Point"}
}