{
  "type": "Feature",
  "properties": {
    "iso:country":"IN",
    "sg:address":"Gateway Building, Apollo Bunder,",
    "sg:city":"Mumbai",
    "sg:classifiers":[
        {
            "category":"Utilities",
            "subcategory":"Cable",
            "type":"Services"
        }
    ],
    "sg:phone":"+91 22 2202 1031",
    "sg:postcode":"400001",
    "sg:tags":[
        "cables/cable",
        "conductor",
        "accessory"
    ],
    "sg:website":"http://www.mecpltd.com",
    "wof:name":"Mahindra Engineering & Chemical Products Ltd.",
    "wof:placetype":"venue"
},
  "geometry": {"coordinates":[72.834328,18.922504],"type":"Point"}
}