{
  "type": "Feature",
  "properties": {
    "iso:country":"IN",
    "sg:address":"386 , Phase-2, Urban Estate, Dugri,",
    "sg:city":"Ludhiana",
    "sg:classifiers":[
        {
            "category":"Manufacturing",
            "subcategory":"Chemicals & Compounds",
            "type":"Manufacturing & Wholesale Goods"
        }
    ],
    "sg:postcode":"141002",
    "sg:tags":[
        "supply"
    ],
    "wof:name":"Star Enterprises",
    "wof:placetype":"venue"
},
  "geometry": {"coordinates":[75.83886699999999,30.869669],"type":"Point"}
}