{
  "type": "Feature",
  "properties": {
    "iso:country":"IN",
    "sg:address":"531-532, Udyog Vihar, Phase-v,",
    "sg:city":"Gurgaon",
    "sg:classifiers":[
        {
            "category":"Home & Garden",
            "subcategory":"Building Materials",
            "type":"Retail Goods"
        }
    ],
    "sg:phone":"+91 124 234 7373",
    "sg:postcode":"122019",
    "sg:tags":[
        "sealant",
        "adhesive"
    ],
    "sg:website":"http://www.threebond.co.jp",
    "wof:name":"Three Bond (i) Pvt. Ltd.",
    "wof:placetype":"venue"
},
  "geometry": {"coordinates":[77.08091,28.50275],"type":"Point"}
}