{
  "type": "Feature",
  "properties": {
    "iso:country":"IN",
    "sg:address":"A/14 Vishwa Villa, Ramchandra Lane, Malad (west),",
    "sg:city":"Mumbai",
    "sg:orig_category":"Carpets, Rugs, Mats & Durries",
    "sg:phone":"+91 22 2880 8855",
    "sg:website":"http://www.rungtex.com",
    "wof:name":"Rung International",
    "wof:placetype":"venue"
},
  "geometry": {"coordinates":[72.840469,19.18988],"type":"Point"}
}