{
  "type": "Feature",
  "properties": {
    "iso:country":"IN",
    "sg:address":"137/a, Parvati,",
    "sg:city":"Pune",
    "sg:classifiers":[
        {
            "category":"Manufacturing",
            "subcategory":"Rubber & Plastics",
            "type":"Manufacturing & Wholesale Goods"
        }
    ],
    "sg:phone":"+91 20 2444 4079",
    "sg:postcode":"411009",
    "sg:tags":[
        "product"
    ],
    "wof:name":"Standard Rubber Products",
    "wof:placetype":"venue"
},
  "geometry": {"coordinates":[73.89630099999999,18.560659],"type":"Point"}
}