{
  "type": "Feature",
  "properties": {
    "iso:country":"IN",
    "sg:address":"No. 33/63, E.v.k. Sampath Road, Vepery,",
    "sg:city":"Chennai",
    "sg:classifiers":[
        {
            "category":"Manufacturing",
            "subcategory":"Leather Goods",
            "type":"Manufacturing & Wholesale Goods"
        }
    ],
    "sg:phone":"+91 44 2561 2627",
    "sg:postcode":"600003",
    "wof:name":"Meridian Specialities Pvt. Ltd.",
    "wof:placetype":"venue"
},
  "geometry": {"coordinates":[80.26245900000001,13.08414],"type":"Point"}
}