{
  "type": "Feature",
  "properties": {
    "iso:country":"IN",
    "sg:address":"Plot No. 16, Sector-6,",
    "sg:city":"Faridabad",
    "sg:orig_category":"Foam,rexine & P.u.products",
    "sg:phone":"+91 129 224 1111",
    "sg:postcode":"121006",
    "sg:website":"http://www.nilcoindia.com",
    "wof:name":"Northern India Leather Cloth Mfg. Co. Ltd.",
    "wof:placetype":"venue"
},
  "geometry": {"coordinates":[84.859398,22.243811],"type":"Point"}
}