{
  "type": "Feature",
  "properties": {
    "iso:country":"IN",
    "sg:address":"206, Samuel Street, 2nd Floor, Masjid,",
    "sg:city":"Mumbai",
    "sg:classifiers":[
        {
            "category":"Shopping",
            "subcategory":"Luggage & Leather Goods",
            "type":"Retail Goods"
        }
    ],
    "sg:phone":"+91 22 2343 3198",
    "sg:postcode":"400003",
    "sg:tags":[
        "bag",
        "-",
        "cotton/canvas/synthetic"
    ],
    "sg:website":"http://www.hifliers.com",
    "wof:name":"Better Deals",
    "wof:placetype":"venue"
},
  "geometry": {"coordinates":[72.836662,18.951439],"type":"Point"}
}