{
  "type": "Feature",
  "properties": {
    "iso:country":"IN",
    "sg:address":"# 4025-4026, K.r.main Road, 7th Block, Jayanagar West,",
    "sg:city":"Bangalore",
    "sg:classifiers":[
        {
            "category":"Coffee & Tea",
            "type":"Food & Drink"
        }
    ],
    "sg:phone":"+91 80 4014 1050",
    "sg:postcode":"560082",
    "sg:website":"http://www.vedicelements.com",
    "wof:name":"Vedic Elements Pvt. Ltd.",
    "wof:placetype":"venue"
},
  "geometry": {"coordinates":[77.58200100000001,12.92389],"type":"Point"}
}