{
  "type": "Feature",
  "properties": {
    "iso:country":"IN",
    "sg:address":"F-6, K K Manor, Ambattur Industrial Estate,",
    "sg:city":"Chennai",
    "sg:classifiers":[
        {
            "category":"Manufacturing",
            "subcategory":"Chemicals & Compounds",
            "type":"Manufacturing & Wholesale Goods"
        }
    ],
    "sg:phone":"+91 44 2625 0904",
    "sg:postcode":"600058",
    "sg:tags":[
        "chemicals-additives"
    ],
    "sg:website":"http://www.kkpolycolor.com",
    "wof:name":"K. K. Polycolor India Ltd.",
    "wof:placetype":"venue"
},
  "geometry": {"coordinates":[80.162392,13.086576],"type":"Point"}
}