{
  "type": "Feature",
  "properties": {
    "iso:country":"IN",
    "sg:address":"No. 25/1, 3rd Main, 1st Stage, 2nd Phase,",
    "sg:city":"Bangalore",
    "sg:classifiers":[
        {
            "category":"Shopping",
            "subcategory":"Computers & Home Electronics",
            "type":"Retail Goods"
        }
    ],
    "sg:phone":"+91 80 2337 4227",
    "sg:postcode":"560054",
    "sg:tags":[
        "power",
        "supply"
    ],
    "wof:name":"Gallant Electronic Controls",
    "wof:placetype":"venue"
},
  "geometry": {"coordinates":[77.556061,12.925956],"type":"Point"}
}