{
  "type": "Feature",
  "properties": {
    "iso:country":"IN",
    "sg:address":"288, 3a Cross, 2nd Block, 3rd Stage, West Of Chord Road,",
    "sg:city":"Bangalore",
    "sg:classifiers":[
        {
            "category":"Wholesale",
            "subcategory":"Electrical",
            "type":"Manufacturing & Wholesale Goods"
        }
    ],
    "sg:phone":"+91 80 2322 0859",
    "sg:postcode":"560079",
    "sg:tags":[
        "voltage",
        "stabilizer"
    ],
    "sg:website":"http://www.adigaindia.com",
    "wof:name":"Adiga Transformers & Coils Pvt. Ltd.",
    "wof:placetype":"venue"
},
  "geometry": {"coordinates":[77.538445,12.989657],"type":"Point"}
}