{
  "type": "Feature",
  "properties": {
    "iso:country":"IN",
    "sg:address":"1b, 1st. Floor, No. 9, New Tank Street, Nungambakkam,",
    "sg:city":"Chennai",
    "sg:classifiers":[
        {
            "category":"Manufacturing",
            "subcategory":"Chemicals & Compounds",
            "type":"Manufacturing & Wholesale Goods"
        }
    ],
    "sg:phone":"+91 44 2827 6733",
    "sg:postcode":"600034",
    "sg:tags":[
        "industrial"
    ],
    "sg:website":"http://www.guardianchemicals.com",
    "wof:name":"Guardian Anti-corrosives Pvt. Ltd.",
    "wof:placetype":"venue"
},
  "geometry": {"coordinates":[80.243896,13.055696],"type":"Point"}
}