{
  "type": "Feature",
  "properties": {
    "iso:country":"IN",
    "sg:address":"W-102d, Midc, Khairne,",
    "sg:city":"Thane",
    "sg:classifiers":[
        {
            "category":"Manufacturing",
            "subcategory":"Rubber & Plastics",
            "type":"Manufacturing & Wholesale Goods"
        }
    ],
    "sg:phone":"+91 22 5590 1770",
    "sg:postcode":"400705",
    "sg:tags":[
        "product"
    ],
    "wof:name":"Polyrub Extrusions (india)",
    "wof:placetype":"venue"
},
  "geometry": {"coordinates":[73.023567,19.070747],"type":"Point"}
}