{
  "type": "Feature",
  "properties": {
    "iso:country":"IN",
    "sg:address":"No.43, 7th Main, Srirampuram,",
    "sg:city":"Bangalore",
    "sg:classifiers":[
        {
            "category":"Wholesale",
            "subcategory":"Auto Parts",
            "type":"Manufacturing & Wholesale Goods"
        }
    ],
    "sg:phone":"+91 80 2332 4486",
    "sg:postcode":"560021",
    "sg:tags":[
        "component",
        "pressed"
    ],
    "wof:name":"Miracel Tech",
    "wof:placetype":"venue"
},
  "geometry": {"coordinates":[77.566498,12.991776],"type":"Point"}
}