{
  "type": "Feature",
  "properties": {
    "iso:country":"IN",
    "sg:address":"L.b.s. Road, Vikhroli (w)",
    "sg:city":"Mumbai",
    "sg:phone":"+91 2255969501559",
    "sg:postcode":"400083",
    "sg:province":"Maharashtra",
    "sg:website":"http://www.mdeel.com",
    "wof:name":"Monsanto Dmcc Enviro-tech & Engineering Ltd",
    "wof:placetype":"venue"
},
  "geometry": {"coordinates":[72.928047,19.107029],"type":"Point"}
}