{
  "type": "Feature",
  "properties": {
    "iso:country":"IN",
    "sg:address":"No. 103, 1st Main Road, Khb Colony, Basaveshwaranagar,",
    "sg:city":"Bangalore",
    "sg:classifiers":[
        {
            "category":"Wholesale",
            "subcategory":"Electrical",
            "type":"Manufacturing & Wholesale Goods"
        }
    ],
    "sg:phone":"+91 80 2348 9853",
    "sg:postcode":"560079",
    "sg:tags":[
        "voltage",
        "stabilizer"
    ],
    "wof:name":"Tektronics Power System & Controls",
    "wof:placetype":"venue"
},
  "geometry": {"coordinates":[77.539154,12.987318],"type":"Point"}
}