{
  "type": "Feature",
  "properties": {
    "iso:country":"IN",
    "sg:address":"11, Mosque Road, Frazer Town",
    "sg:city":"Bangalore",
    "sg:phone":"+91 805495334",
    "sg:postcode":"560005",
    "sg:province":"Karnataka",
    "sg:website":"http://www.quasarit.com",
    "wof:name":"Quasar Infotech & Telecommunication Pvt Ltd",
    "wof:placetype":"venue"
},
  "geometry": {"coordinates":[77.615021,12.998038],"type":"Point"}
}