{
  "type": "Feature",
  "properties": {
    "iso:country":"IN",
    "sg:address":"R-53, 5th Floor, Glodern Enclave,",
    "sg:city":"Bangalore",
    "sg:classifiers":[
        {
            "category":"Professional",
            "subcategory":"Computer Services",
            "type":"Services"
        }
    ],
    "sg:phone":"+91 80 2507 5927",
    "sg:postcode":"560017",
    "sg:tags":[
        "software"
    ],
    "wof:name":"Maxal Consulting Service Inc.",
    "wof:placetype":"venue"
},
  "geometry": {"coordinates":[77.651604,12.958296],"type":"Point"}
}