{
  "type": "Feature",
  "properties": {
    "iso:country":"IN",
    "sg:address":"A-7/1/16, South Side Of G.t. Road,",
    "sg:city":"Ghaziabad",
    "sg:classifiers":[
        {
            "category":"Professional",
            "subcategory":"Detective & Security Services",
            "type":"Services"
        }
    ],
    "sg:phone":"+91 120 325 1255",
    "sg:tags":[
        "material",
        "protection",
        "corrosion"
    ],
    "wof:name":"Plasma Enterprises (india) Pvt. Ltd.",
    "wof:placetype":"venue"
},
  "geometry": {"coordinates":[72.171219,21.387884],"type":"Point"}
}