{
  "type": "Feature",
  "properties": {
    "iso:country":"IN",
    "sg:address":"23/p/13, A.k. Mukherjee Road,",
    "sg:city":"Kolkata",
    "sg:orig_category":"Foam,rexine & P.u.products",
    "sg:phone":"+91 33 2216 2974",
    "sg:postcode":"700090",
    "wof:name":"Dolphin Foam Industries (p) Ltd.",
    "wof:placetype":"venue"
},
  "geometry": {"coordinates":[88.34671,22.52548],"type":"Point"}
}