{
  "type": "Feature",
  "properties": {
    "iso:country":"IN",
    "sg:address":"Elgi House, 1789, Trichy Road,",
    "sg:city":"Coimbatore",
    "sg:classifiers":[
        {
            "category":"Manufacturing",
            "subcategory":"Rubber & Plastics",
            "type":"Manufacturing & Wholesale Goods"
        }
    ],
    "sg:phone":"+91 422 231 9909",
    "sg:postcode":"641045",
    "sg:tags":[
        "product"
    ],
    "wof:name":"Elgi Rubber Products Ltd.",
    "wof:placetype":"venue"
},
  "geometry": {"coordinates":[77.02475699999999,10.99927],"type":"Point"}
}