{
  "type": "Feature",
  "properties": {
    "iso:country":"IN",
    "sg:address":"A/4,n.pujari Nagar,    \nA.g.khan Rd.",
    "sg:city":"Mumbai",
    "sg:classifiers":[
        {
            "category":"Manufacturing",
            "subcategory":"Petroleum Products",
            "type":"Manufacturing & Wholesale Goods"
        }
    ],
    "sg:phone":"+91 22 2492 3972",
    "sg:postcode":"400018",
    "sg:tags":[
        "oil",
        "edible"
    ],
    "wof:name":"Pragji Gopalji & Sons",
    "wof:placetype":"venue"
},
  "geometry": {"coordinates":[72.811646,18.999083],"type":"Point"}
}