{
  "type": "Feature",
  "properties": {
    "iso:country":"IN",
    "sg:address":"121, 3rd Cross, 2nd Main, Prakashnagar,",
    "sg:city":"Bangalore",
    "sg:classifiers":[
        {
            "category":"Wholesale",
            "subcategory":"Metals & Minerals",
            "type":"Manufacturing & Wholesale Goods"
        }
    ],
    "sg:phone":"+91 80 2352 6548",
    "sg:postcode":"560021",
    "sg:tags":[
        "tin",
        "container"
    ],
    "wof:name":"Gopal Packing",
    "wof:placetype":"venue"
},
  "geometry": {"coordinates":[78.763603,10.790658],"type":"Point"}
}