{
  "type": "Feature",
  "properties": {
    "iso:country":"IN",
    "sg:address":"11 Gold Mist, Vakola Pipeline Road, Santacruz (east),",
    "sg:city":"Mumbai",
    "sg:classifiers":[
        {
            "category":"Professional",
            "subcategory":"Engineering",
            "type":"Services"
        }
    ],
    "sg:phone":"+91 22 2668 5856",
    "sg:postcode":"400055",
    "sg:tags":[
        "equipment",
        "good"
    ],
    "wof:name":"Rohan Exports",
    "wof:placetype":"venue"
},
  "geometry": {"coordinates":[72.853058,19.081835],"type":"Point"}
}