{
  "type": "Feature",
  "properties": {
    "iso:country":"IN",
    "sg:address":"100 Feet Ring Road, J. P. Nagar, 4th Phase",
    "sg:city":"Bangalore",
    "sg:phone":"+91 806585401",
    "sg:postcode":"560078",
    "sg:province":"Karnataka",
    "wof:name":"Duckworth Elavours (india) Pvt Ltd",
    "wof:placetype":"venue"
},
  "geometry": {"coordinates":[77.56199599999999,12.921033],"type":"Point"}
}