{
  "type": "Feature",
  "properties": {
    "iso:country":"IN",
    "sg:address":"No. 87, Jumma Masjid Road, 1st Floor, Avenue Road Cross,",
    "sg:city":"Bangalore",
    "sg:orig_category":"Sarees",
    "sg:phone":"+91 80 2221 6235",
    "sg:postcode":"560002",
    "wof:name":"Madan Traders",
    "wof:placetype":"venue"
},
  "geometry": {"coordinates":[77.579666,12.969664],"type":"Point"}
}