{
  "type": "Feature",
  "properties": {
    "iso:country":"IN",
    "sg:address":"P-250, C.i.t. Road,",
    "sg:city":"Kolkata",
    "sg:classifiers":[
        {
            "category":"Home & Garden",
            "subcategory":"Mobile Homes",
            "type":"Retail Goods"
        }
    ],
    "sg:phone":"+91 33 2320 9161",
    "sg:postcode":"700054",
    "sg:tags":[
        "acid"
    ],
    "sg:website":"http://www.easternmicropor.com",
    "wof:name":"Eastern Micropor Pvt. Limited",
    "wof:placetype":"venue"
},
  "geometry": {"coordinates":[74.450989,17.290974],"type":"Point"}
}