{
  "type": "Feature",
  "properties": {
    "iso:country":"IN",
    "sg:address":"beml Soudha, 23/1, 4th Main, S.r. Nagar,",
    "sg:city":"Bangalore",
    "sg:classifiers":[
        {
            "category":"Autos & Motor Vehicles",
            "subcategory":"Fuel & Gas Station",
            "type":"Retail Goods"
        }
    ],
    "sg:phone":"+91 80 2296 3167",
    "sg:postcode":"560027",
    "sg:tags":[
        "trolley",
        "trailer"
    ],
    "sg:website":"http://www.bemlindia.com",
    "wof:name":"Bharat Earth Movers Ltd.",
    "wof:placetype":"venue"
},
  "geometry": {"coordinates":[77.591743,12.965208],"type":"Point"}
}