{
  "type": "Feature",
  "properties": {
    "iso:country":"IN",
    "sg:address":"C-35, Iii Main Road, Industrial Estate, Rajajinagar,",
    "sg:city":"Bangalore",
    "sg:classifiers":[
        {
            "category":"Manufacturing",
            "subcategory":"Tools & Machinery",
            "type":"Manufacturing & Wholesale Goods"
        }
    ],
    "sg:phone":"+91 80 2335 5913",
    "sg:postcode":"560044",
    "sg:tags":[
        "product",
        "pneumatic"
    ],
    "sg:website":"http://www.esbeeprecisionindustries.com",
    "wof:name":"Esbee Precision Industries",
    "wof:placetype":"venue"
},
  "geometry": {"coordinates":[80.204575,13.114305],"type":"Point"}
}