{
  "type": "Feature",
  "properties": {
    "iso:country":"IN",
    "sg:address":"8/35, 1st Floor, Hennur Main Road, Lingarajapuram,",
    "sg:city":"Bangalore",
    "sg:classifiers":[
        {
            "category":"Wholesale",
            "subcategory":"Auto Parts",
            "type":"Manufacturing & Wholesale Goods"
        }
    ],
    "sg:phone":"+91 80 2546 5724",
    "sg:postcode":"560084",
    "sg:tags":[
        "component",
        "pressed"
    ],
    "wof:name":"Singh Engineering Works",
    "wof:placetype":"venue"
},
  "geometry": {"coordinates":[77.624115,13.010252],"type":"Point"}
}