{
  "type": "Feature",
  "properties": {
    "iso:country":"IN",
    "sg:address":"60, 2nd Floor, 8th Main, 18th Cross, Malleswaram,",
    "sg:city":"Bangalore",
    "sg:classifiers":[
        {
            "category":"Professional",
            "subcategory":"Computer Services",
            "type":"Services"
        }
    ],
    "sg:phone":"+91 80 2331 8942",
    "sg:postcode":"560003",
    "sg:tags":[
        "software"
    ],
    "wof:name":"K-corp Services",
    "wof:placetype":"venue"
},
  "geometry": {"coordinates":[77.563179,13.00893],"type":"Point"}
}