{
  "type": "Feature",
  "properties": {
    "iso:country":"IN",
    "sg:address":"Plot No. 2408, Near Asian Paints, G.i.d.c.,",
    "sg:city":"Ankleshwar",
    "sg:classifiers":[
        {
            "category":"Shopping",
            "subcategory":"Crafts & Fabrics",
            "type":"Retail Goods"
        }
    ],
    "sg:phone":"+91 2646 221 322",
    "sg:postcode":"393002",
    "sg:tags":[
        "pigment"
    ],
    "wof:name":"West Coast Pigment Corporation",
    "wof:placetype":"venue"
},
  "geometry": {"coordinates":[78.115768,9.914664],"type":"Point"}
}