{
  "type": "Feature",
  "properties": {
    "iso:country":"IN",
    "sg:address":"No: 33, Flowers Road, Kilpauk,",
    "sg:city":"Chennai",
    "sg:classifiers":[
        {
            "category":"Manufacturing",
            "subcategory":"Chemicals & Compounds",
            "type":"Manufacturing & Wholesale Goods"
        }
    ],
    "sg:postcode":"600010",
    "sg:tags":[
        "supply"
    ],
    "sg:website":"http://www.pinnacleinternational.net",
    "wof:name":"Pinnacle International",
    "wof:placetype":"venue"
},
  "geometry": {"coordinates":[80.250031,13.080589],"type":"Point"}
}