{
  "type": "Feature",
  "properties": {
    "iso:country":"IN",
    "sg:address":"Whitefield Road, Mahadevapura,",
    "sg:city":"Bangalore",
    "sg:classifiers":[
        {
            "category":"Utilities",
            "subcategory":"Natural Gas",
            "type":"Services"
        }
    ],
    "sg:phone":"+91 80 2852 4239",
    "sg:postcode":"560048",
    "sg:tags":[
        "industrial"
    ],
    "sg:website":"http://www.bhorukagases.com",
    "wof:name":"Bhoruka Gases Ltd.",
    "wof:placetype":"venue"
},
  "geometry": {"coordinates":[77.68714900000001,12.999802],"type":"Point"}
}