{
  "type": "Feature",
  "properties": {
    "iso:country":"IN",
    "sg:address":"Lalghat",
    "sg:city":"Udaipur",
    "sg:phone":"+91 294 252 1252",
    "sg:postcode":"313001",
    "sg:province":"Rajasthan",
    "wof:name":"Hotel Caravan Serai",
    "wof:placetype":"venue"
},
  "geometry": {"coordinates":[88.351517,22.581482],"type":"Point"}
}