{
  "type": "Feature",
  "properties": {
    "iso:country":"IN",
    "sg:address":"13-75-77, Bhuleshwar Road,",
    "sg:city":"Mumbai",
    "sg:classifiers":[
        {
            "category":"Shopping",
            "subcategory":"Crafts & Fabrics",
            "type":"Retail Goods"
        }
    ],
    "sg:phone":"+91 22 2241 6253",
    "sg:postcode":"400002",
    "sg:website":"http://www.dresswala.com",
    "wof:name":"Maganlal Dresswala",
    "wof:placetype":"venue"
},
  "geometry": {"coordinates":[72.827568,18.953436],"type":"Point"}
}