{
  "type": "Feature",
  "properties": {
    "iso:country":"IN",
    "sg:address":"2988, Ganj Bazar",
    "sg:city":"Ahmednagar",
    "sg:phone":"+91 241341372",
    "sg:postcode":"414001",
    "sg:province":"Maharashtra",
    "wof:name":"Jaymoti Aluminium Company Pvt Ltd",
    "wof:placetype":"venue"
},
  "geometry": {"coordinates":[80.190468,21.454573],"type":"Point"}
}