{
  "type": "Feature",
  "properties": {
    "iso:country":"IN",
    "sg:address":"Sector 21-b",
    "sg:city":"Chandigarh",
    "sg:phone":"+91 172703226",
    "sg:postcode":"160022",
    "sg:province":"Chandigarh",
    "wof:name":"Cooper Gaskets Pvt Ltd",
    "wof:placetype":"venue"
},
  "geometry": {"coordinates":[76.77549,30.726391],"type":"Point"}
}