{
  "type": "Feature",
  "properties": {
    "iso:country":"IN",
    "sg:address":"5, Mali Colony,",
    "sg:city":"Udaipur",
    "sg:classifiers":[
        {
            "category":"Wholesale",
            "subcategory":"Plants",
            "type":"Manufacturing & Wholesale Goods"
        }
    ],
    "sg:phone":"+91 294 248 7017",
    "sg:postcode":"313001",
    "sg:tags":[
        "flower",
        "dried"
    ],
    "wof:name":"Chaudhary Herbal Farm House",
    "wof:placetype":"venue"
},
  "geometry": {"coordinates":[77.229088,28.654163],"type":"Point"}
}