{
  "type": "Feature",
  "properties": {
    "iso:country":"IN",
    "sg:address":"75, Jariwala Bldg., 3rd Flr., R.no 115, S.v.p Road,",
    "sg:city":"Mumbai",
    "sg:classifiers":[
        {
            "category":"Manufacturing",
            "subcategory":"Rubber & Plastics",
            "type":"Manufacturing & Wholesale Goods"
        }
    ],
    "sg:phone":"+91 22 2346 5125",
    "sg:postcode":"400003",
    "sg:tags":[
        "product"
    ],
    "wof:name":"Hutaib Rubber Products",
    "wof:placetype":"venue"
},
  "geometry": {"coordinates":[77.192795,28.649347],"type":"Point"}
}