{
  "type": "Feature",
  "properties": {
    "iso:country":"IN",
    "sg:address":"492, 493, Bharat Chowk,",
    "sg:city":"Ulhasnagar",
    "sg:classifiers":[
        {
            "category":"Professional",
            "subcategory":"Credit Reporting & Collection",
            "type":"Services"
        }
    ],
    "sg:phone":"+91 251 254 5797",
    "sg:postcode":"421001",
    "sg:tags":[
        "seasoning",
        "spice"
    ],
    "sg:website":"http://www.papadking.com",
    "wof:name":"Shree Satyanarayan Masala",
    "wof:placetype":"venue"
},
  "geometry": {"coordinates":[78.759079,23.833054],"type":"Point"}
}