{
  "type": "Feature",
  "properties": {
    "iso:country":"IN",
    "sg:address":"Senapati Bapat Marg, Dadar (w)",
    "sg:city":"Mumbai",
    "sg:phone":"+91 22 2422 7964",
    "sg:postcode":"400028",
    "sg:province":"Maharashtra",
    "wof:name":"Trans World Traders",
    "wof:placetype":"venue"
},
  "geometry": {"coordinates":[72.847725,19.034321],"type":"Point"}
}