{
  "type": "Feature",
  "properties": {
    "iso:country":"IN",
    "sg:address":"Wadia Street, Tardeo",
    "sg:city":"Mumbai",
    "sg:phone":"+91 22 2494 2026",
    "sg:postcode":"400034",
    "sg:province":"Maharashtra",
    "wof:name":"Icon Infotech Pvt Ltd",
    "wof:placetype":"venue"
},
  "geometry": {"coordinates":[72.815468,18.970507],"type":"Point"}
}