{
  "type": "Feature",
  "properties": {
    "iso:country":"IN",
    "sg:address":"51-53, Dhanji Street,",
    "sg:city":"Mumbai",
    "sg:classifiers":[
        {
            "category":"Manufacturing",
            "subcategory":"Tools & Machinery",
            "type":"Manufacturing & Wholesale Goods"
        }
    ],
    "sg:phone":"+91 22 2342 2175",
    "sg:postcode":"400003",
    "sg:tags":[
        "machine",
        "cutting",
        "diamond"
    ],
    "sg:website":"http://www.aventools.com",
    "wof:name":"Aven Tools Centre",
    "wof:placetype":"venue"
},
  "geometry": {"coordinates":[72.831863,18.951458],"type":"Point"}
}