{
  "type": "Feature",
  "properties": {
    "iso:country":"IN",
    "sg:address":"#539,16th cross Indiranagar 2nd stage",
    "sg:city":"Bangalore",
    "sg:classifiers":[
        {
            "category":"Professional",
            "subcategory":"Computer Services",
            "type":"Services"
        }
    ],
    "sg:postcode":"560038",
    "sg:tags":[
        "sales-facilitation",
        "buyer-seller-interaction",
        "sales-mediation"
    ],
    "sg:website":"http://www.buyerraja.com",
    "wof:name":"BuyerRaja",
    "wof:placetype":"venue"
},
  "geometry": {"coordinates":[77.578768,13.033353],"type":"Point"}
}