{
  "type": "Feature",
  "properties": {
    "iso:country":"IN",
    "sg:address":"52, Tagore Park, Model Town,",
    "sg:city":"Delhi",
    "sg:classifiers":[
        {
            "category":"Manufacturing",
            "subcategory":"Textiles",
            "type":"Manufacturing & Wholesale Goods"
        }
    ],
    "sg:phone":"+91 11 2744 4281",
    "sg:postcode":"110009",
    "sg:tags":[
        "chemical"
    ],
    "wof:name":"Cooperation Overseas Private Limited",
    "wof:placetype":"venue"
},
  "geometry": {"coordinates":[77.193085,28.705605],"type":"Point"}
}