{
  "type": "Feature",
  "properties": {
    "iso:country":"IN",
    "sg:address":"128, Mangalam Road,",
    "sg:city":"Tirupur",
    "sg:classifiers":[
        {
            "category":"Shopping",
            "subcategory":"Clothing, Apparel, & Fashions",
            "type":"Retail Goods"
        }
    ],
    "sg:phone":"+91 421 224 9936",
    "sg:postcode":"641604",
    "sg:tags":[
        "woman",
        "wear"
    ],
    "sg:website":"http://www.indiamart.com/aravalliiknitting/about-us.html#contact",
    "wof:name":"Aravallii Knitting Mills Pvt. Ltd.",
    "wof:placetype":"venue"
},
  "geometry": {"coordinates":[77.29735599999999,28.649111],"type":"Point"}
}