{
  "type": "Feature",
  "properties": {
    "iso:country":"IN",
    "sg:address":"Purasawallam",
    "sg:city":"Chennai",
    "sg:phone":"+91 44 2641 7025",
    "sg:postcode":"600007",
    "sg:province":"Tamil Nadu",
    "sg:website":"http://www.naturalgranite.com",
    "wof:name":"Natural Granite",
    "wof:placetype":"venue"
},
  "geometry": {"coordinates":[80.24929,13.0861],"type":"Point"}
}