{
  "type": "Feature",
  "properties": {
    "iso:country":"IN",
    "sg:address":"Bg-7 East, Shalimar Bagh,",
    "sg:city":"Delhi",
    "sg:classifiers":[
        {
            "category":"Manufacturing",
            "subcategory":"Rubber & Plastics",
            "type":"Manufacturing & Wholesale Goods"
        }
    ],
    "sg:phone":"+91 11 2749 4536",
    "sg:postcode":"110088",
    "sg:tags":[
        "product"
    ],
    "wof:name":"Kwality Rubber Products Co.",
    "wof:placetype":"venue"
},
  "geometry": {"coordinates":[77.222298,28.659807],"type":"Point"}
}