{
  "type": "Feature",
  "properties": {
    "iso:country":"IN",
    "sg:address":"Malaypore",
    "sg:city":"Chennai",
    "sg:phone":"+91 44 2499 2680",
    "sg:postcode":"600004",
    "sg:province":"Tamil Nadu",
    "wof:name":"Baron Power Ltd",
    "wof:placetype":"venue"
},
  "geometry": {"coordinates":[80.268372,13.039339],"type":"Point"}
}