{
  "type": "Feature",
  "properties": {
    "iso:country":"IN",
    "sg:address":"Station Road,",
    "sg:city":"Moradabad",
    "sg:classifiers":[
        {
            "category":"Manufacturing",
            "subcategory":"Petroleum Products",
            "type":"Manufacturing & Wholesale Goods"
        }
    ],
    "sg:phone":"+91 591 232 6596",
    "sg:postcode":"244001",
    "sg:tags":[
        "wax"
    ],
    "wof:name":"Mayur International",
    "wof:placetype":"venue"
},
  "geometry": {"coordinates":[80.934517,26.837732],"type":"Point"}
}