{
  "type": "Feature",
  "properties": {
    "iso:country":"IN",
    "sg:address":"Mathura Road",
    "sg:city":"Faridabad",
    "sg:phone":"+91 129 227 5411",
    "sg:postcode":"121003",
    "sg:province":"Haryana",
    "sg:website":"www.superseal.com",
    "wof:name":"Super Seals India Ltd",
    "wof:placetype":"venue"
},
  "geometry": {"coordinates":[77.311653,28.406626],"type":"Point"}
}