{
  "type": "Feature",
  "properties": {
    "iso:country":"IN",
    "sg:address":"F.c.road",
    "sg:city":"Pune",
    "sg:phone":"+91 205531511",
    "sg:postcode":"411004",
    "sg:province":"Maharashtra",
    "wof:name":"Hotel Parichay",
    "wof:placetype":"venue"
},
  "geometry": {"coordinates":[74.450989,17.290974],"type":"Point"}
}