{
  "type": "Feature",
  "properties": {
    "iso:country":"IN",
    "sg:address":"G-12 Midc, Andheri East,",
    "sg:city":"Mumbai",
    "sg:classifiers":[
        {
            "category":"Shopping",
            "subcategory":"Luggage & Leather Goods",
            "type":"Retail Goods"
        }
    ],
    "sg:phone":"+91 22 2620 2218",
    "sg:postcode":"400093",
    "sg:tags":[
        "bag",
        "-",
        "cotton/canvas/synthetic"
    ],
    "wof:name":"Indo Impex",
    "wof:placetype":"venue"
},
  "geometry": {"coordinates":[72.86913300000001,19.12438],"type":"Point"}
}