{
  "type": "Feature",
  "properties": {
    "iso:country":"IN",
    "sg:address":"3x/95, Mariyamman Koil Street, M.g.r.nagar,",
    "sg:city":"Thuthipattu",
    "sg:classifiers":[
        {
            "category":"Manufacturing",
            "subcategory":"Leather Goods",
            "type":"Manufacturing & Wholesale Goods"
        }
    ],
    "sg:phone":"+91 44 2224 1086",
    "sg:postcode":"635811",
    "sg:tags":[
        "finished"
    ],
    "wof:name":"Winytan Leather Exports",
    "wof:placetype":"venue"
},
  "geometry": {"coordinates":[80.191254,13.039797],"type":"Point"}
}