{
  "type": "Feature",
  "properties": {
    "iso:country":"IN",
    "sg:address":"Errabalu Street",
    "sg:city":"Chennai",
    "sg:phone":"+91 44 2522 4938",
    "sg:postcode":"600001",
    "sg:province":"Tamil Nadu",
    "wof:name":"Mill Stores (madras) Pvt Ltd",
    "wof:placetype":"venue"
},
  "geometry": {"coordinates":[80.287247,13.091187],"type":"Point"}
}