{
  "type": "Feature",
  "properties": {
    "iso:country":"IN",
    "sg:address":"18/32, Street No. 5, Anand Parbat Industrial Area,",
    "sg:city":"New Delhi",
    "sg:classifiers":[
        {
            "category":"Manufacturing",
            "subcategory":"Chemicals & Compounds",
            "type":"Manufacturing & Wholesale Goods"
        }
    ],
    "sg:phone":"+91 11 2871 7124",
    "sg:postcode":"110005",
    "sg:tags":[
        "plant",
        "processing"
    ],
    "wof:name":"Lall Iron Works",
    "wof:placetype":"venue"
},
  "geometry": {"coordinates":[77.177589,28.663069],"type":"Point"}
}