{
  "type": "Feature",
  "properties": {
    "iso:country":"IN",
    "sg:address":"501, 4th Floor, Oxford Towers, 139, Airport Road,",
    "sg:city":"Bangalore",
    "sg:classifiers":[
        {
            "category":"Shopping",
            "subcategory":"Clothing, Apparel, & Fashions",
            "type":"Retail Goods"
        }
    ],
    "sg:phone":"+91 80 2221 4447",
    "sg:postcode":"560008",
    "sg:tags":[
        "woman",
        "wear"
    ],
    "wof:name":"Frontline Ventures",
    "wof:placetype":"venue"
},
  "geometry": {"coordinates":[77.647057,12.95889],"type":"Point"}
}