{
  "type": "Feature",
  "properties": {
    "iso:country":"IN",
    "sg:address":"25, Deven Industrial Estate, I.b. Patel Road, Goregaon (e),",
    "sg:city":"Mumbai",
    "sg:classifiers":[
        {
            "category":"Farming",
            "subcategory":"Fish & Marine Products",
            "type":"Manufacturing & Wholesale Goods"
        }
    ],
    "sg:phone":"+91 22 2685 9713",
    "sg:postcode":"400063",
    "sg:tags":[
        "silicon"
    ],
    "wof:name":"Spreco Corporation",
    "wof:placetype":"venue"
},
  "geometry": {"coordinates":[72.853951,19.16082],"type":"Point"}
}