{
  "type": "Feature",
  "properties": {
    "iso:country":"IN",
    "sg:address":"108/17, Gandhi Nagar,",
    "sg:city":"Kanpur",
    "sg:classifiers":[
        {
            "category":"Manufacturing",
            "subcategory":"Chemicals & Compounds",
            "type":"Manufacturing & Wholesale Goods"
        }
    ],
    "sg:phone":"+91 512 254 2314",
    "sg:postcode":"208012",
    "sg:tags":[
        "supply"
    ],
    "wof:name":"Atom Industries",
    "wof:placetype":"venue"
},
  "geometry": {"coordinates":[76.297867,9.977374],"type":"Point"}
}