{
  "type": "Feature",
  "properties": {
    "iso:country":"IN",
    "sg:address":"A 14 Sector 7",
    "sg:city":"Noida",
    "sg:classifiers":[
        {
            "category":"Professional",
            "subcategory":"Computer Services",
            "type":"Services"
        }
    ],
    "sg:postcode":"201301",
    "sg:tags":[
        "seo-india",
        "seo-company-india",
        "seo-services-india",
        "search-marketing--india",
        "ppc-services-india",
        "search-consultants",
        "seo-firms-india"
    ],
    "sg:website":"http://www.mosaic-service.com",
    "wof:name":"Mosaic ITES Services",
    "wof:placetype":"venue"
},
  "geometry": {"coordinates":[77.30731299999999,28.586741],"type":"Point"}
}