{
  "type": "Feature",
  "properties": {
    "iso:country":"IN",
    "sg:address":"No-75/2, 4th N-block, Rajajinagar,",
    "sg:city":"Bangalore",
    "sg:classifiers":[
        {
            "category":"Home & Garden",
            "subcategory":"Garden Supply",
            "type":"Retail Goods"
        }
    ],
    "sg:phone":"+91 80 2342 0806",
    "sg:postcode":"560010",
    "sg:tags":[
        "fertilizer"
    ],
    "wof:name":"Sigma Projects And Concepts",
    "wof:placetype":"venue"
},
  "geometry": {"coordinates":[77.56083700000001,12.983385],"type":"Point"}
}