{
  "type": "Feature",
  "properties": {
    "iso:country":"IN",
    "sg:address":"Commercial Complex",
    "sg:city":"New Delhi",
    "sg:phone":"+91 11 2570 1678",
    "sg:postcode":"110008",
    "sg:province":"Delhi",
    "wof:name":"Trans Air Logicstics Services",
    "wof:placetype":"venue"
},
  "geometry": {"coordinates":[77.289635,28.532372],"type":"Point"}
}