{
  "type": "Feature",
  "properties": {
    "iso:country":"IN",
    "sg:address":"Plot No. 184, G.i.d.c. Estate,",
    "sg:city":"Nandesari",
    "sg:classifiers":[
        {
            "category":"Manufacturing",
            "subcategory":"Chemicals & Compounds",
            "type":"Manufacturing & Wholesale Goods"
        }
    ],
    "sg:phone":"+91 265 309 0808",
    "sg:postcode":"391340",
    "sg:tags":[
        "dye",
        "intermediate"
    ],
    "sg:website":"http://www.bromofine.com",
    "wof:name":"Bromofine Chem Pvt. Ltd.",
    "wof:placetype":"venue"
},
  "geometry": {"coordinates":[77.614281,12.97456],"type":"Point"}
}