{
  "type": "Feature",
  "properties": {
    "iso:country":"IN",
    "sg:address":"46/47, Electronics City, Phase 2, Hosur Road,",
    "sg:city":"Bangalore",
    "sg:classifiers":[
        {
            "category":"Wholesale",
            "subcategory":"Electrical",
            "type":"Manufacturing & Wholesale Goods"
        }
    ],
    "sg:phone":"+91 80 2852 1489",
    "sg:postcode":"560100",
    "sg:tags":[
        "voltage",
        "stabilizer"
    ],
    "wof:name":"Hical Mangetics Pvt. Ltd.",
    "wof:placetype":"venue"
},
  "geometry": {"coordinates":[77.647598,12.877272],"type":"Point"}
}