{
  "type": "Feature",
  "properties": {
    "iso:country":"IN",
    "sg:address":"Navsari Building, 3rd Floor, 240, Dr. D.n Road,",
    "sg:city":"Mumbai",
    "sg:classifiers":[
        {
            "category":"Manufacturing",
            "subcategory":"Chemicals & Compounds",
            "type":"Manufacturing & Wholesale Goods"
        }
    ],
    "sg:phone":"+91 22 2207 1961",
    "sg:postcode":"400001",
    "sg:tags":[
        "supply"
    ],
    "sg:website":"http://www.sued-chemie-india.com",
    "wof:name":"S\u00fcd-chemie India Pvt. Ltd",
    "wof:placetype":"venue"
},
  "geometry": {"coordinates":[72.921463,20.951851],"type":"Point"}
}