{
  "type": "Feature",
  "properties": {
    "iso:country":"IN",
    "sg:address":"75-a, Chandra Villa, Gadhia House, Vile Parle (e),",
    "sg:city":"Mumbai",
    "sg:classifiers":[
        {
            "category":"Manufacturing",
            "subcategory":"Pet Food",
            "type":"Manufacturing & Wholesale Goods"
        }
    ],
    "sg:tags":[
        "additive",
        "flavour"
    ],
    "wof:name":"Y Corporation",
    "wof:placetype":"venue"
},
  "geometry": {"coordinates":[72.860413,19.092056],"type":"Point"}
}