{
  "type": "Feature",
  "properties": {
    "iso:country":"IN",
    "sg:address":"West Street, Thiruthangal",
    "sg:city":"Sivakasi",
    "sg:phone":"+91 4562 276 248",
    "sg:postcode":"626123",
    "sg:province":"Tamil Nadu",
    "sg:website":"http://www.sonyfireworks.com",
    "wof:name":"Sony Fire Works Pvt Ltd",
    "wof:placetype":"venue"
},
  "geometry": {"coordinates":[77.813332,9.471413],"type":"Point"}
}