{
  "type": "Feature",
  "properties": {
    "iso:country":"IN",
    "sg:address":"193/270, Bombay Talkies Compound, Malad,",
    "sg:city":"Mumbai",
    "sg:classifiers":[
        {
            "category":"Building & Trades",
            "subcategory":"Construction",
            "type":"Services"
        }
    ],
    "sg:phone":"+91 22 2882 8899",
    "sg:postcode":"400064",
    "sg:tags":[
        "hardware",
        "builder"
    ],
    "wof:name":"Jani Products",
    "wof:placetype":"venue"
},
  "geometry": {"coordinates":[72.843079,19.179806],"type":"Point"}
}