{
  "type": "Feature",
  "properties": {
    "iso:country":"IN",
    "sg:address":"46c, Chowringhee Road",
    "sg:city":"Kolkata",
    "sg:phone":"+91 332881066",
    "sg:postcode":"700071",
    "sg:province":"West Bengal",
    "sg:website":"http://www.narayancoirs.com",
    "wof:name":"Narayan Coirs Ltd",
    "wof:placetype":"venue"
},
  "geometry": {"coordinates":[88.346992,22.540216],"type":"Point"}
}