{
  "type": "Feature",
  "properties": {
    "iso:country":"IN",
    "sg:address":"Old Mahabalipuram Road",
    "sg:city":"Chennai",
    "sg:phone":"+91 44 2496 3707",
    "sg:postcode":"600096",
    "sg:province":"Tamil Nadu",
    "wof:name":"Asvini Fisheries Ltd",
    "wof:placetype":"venue"
},
  "geometry": {"coordinates":[80.226608,12.847635],"type":"Point"}
}