{
  "type": "Feature",
  "properties": {
    "iso:country":"IN",
    "sg:address":"7/22, Tardeo A/c Market, Tardeo,",
    "sg:city":"Mumbai",
    "sg:orig_category":"Antiques, Collectables & Antique Handicrafts",
    "sg:phone":"+91 22 2351 0777",
    "sg:postcode":"400034",
    "wof:name":"Motafram Exports",
    "wof:placetype":"venue"
},
  "geometry": {"coordinates":[72.81409499999999,18.97249],"type":"Point"}
}