{
  "type": "Feature",
  "properties": {
    "iso:country":"IN",
    "sg:address":"82/84, Clare Road, Nagpada,",
    "sg:city":"Mumbai",
    "sg:classifiers":[
        {
            "category":"Personal",
            "subcategory":"Hair Removal",
            "type":"Services"
        }
    ],
    "sg:phone":"+91 22 2308 6252",
    "sg:postcode":"400008",
    "sg:tags":[
        "cosmetic",
        "accessory"
    ],
    "wof:name":"A. A. Attarwala & Co. Pvt. Ltd.",
    "wof:placetype":"venue"
},
  "geometry": {"coordinates":[72.829842,18.969574],"type":"Point"}
}