{
  "type": "Feature",
  "properties": {
    "iso:country":"IN",
    "sg:address":"8/54, Ram Street, Vishwas Nagar, Shahdara,",
    "sg:city":"Delhi",
    "sg:classifiers":[
        {
            "category":"Manufacturing",
            "subcategory":"Chemicals & Compounds",
            "type":"Manufacturing & Wholesale Goods"
        }
    ],
    "sg:phone":"+91 11 2238 1441",
    "sg:postcode":"110032",
    "sg:tags":[
        "dye",
        "intermediate"
    ],
    "wof:name":"Corona Switch Gears Pvt. Ltd.",
    "wof:placetype":"venue"
},
  "geometry": {"coordinates":[77.296555,28.666365],"type":"Point"}
}