{
  "type": "Feature",
  "properties": {
    "iso:country":"IN",
    "sg:address":"Plot No.442, Office No.2, Sector-1/a,",
    "sg:city":"Gandhidham",
    "sg:classifiers":[
        {
            "category":"Autos & Motor Vehicles",
            "subcategory":"Fuel & Gas Station",
            "type":"Retail Goods"
        }
    ],
    "sg:phone":"+91 2836 232 325",
    "sg:postcode":"370201",
    "sg:tags":[
        "explosive"
    ],
    "sg:website":"http://www.panchshil.net",
    "wof:name":"Samay Impex Pvt. Ltd.",
    "wof:placetype":"venue"
},
  "geometry": {"coordinates":[76.956383,30.838766],"type":"Point"}
}