{
  "type": "Feature",
  "properties": {
    "iso:country":"IN",
    "sg:address":"Desh Bandhu Gupta Road, Karol Bagh",
    "sg:city":"New Delhi",
    "sg:phone":"+91 115785836",
    "sg:postcode":"110005",
    "sg:province":"Delhi",
    "sg:website":"http://www.dindradigital.com,  http://www.delhibazaaronline.com/photo/bindra",
    "wof:name":"Bindra Color Lab Pvt Ltd",
    "wof:placetype":"venue"
},
  "geometry": {"coordinates":[77.18514999999999,28.656862],"type":"Point"}
}