{
  "type": "Feature",
  "properties": {
    "iso:country":"IN",
    "sg:address":"Plot No. 24b/1, Ida, Phase-i,",
    "sg:city":"Patancheru",
    "sg:classifiers":[
        {
            "category":"Manufacturing",
            "subcategory":"Chemicals & Compounds",
            "type":"Manufacturing & Wholesale Goods"
        }
    ],
    "sg:phone":"+91 8455 241 148",
    "sg:postcode":"502319",
    "sg:tags":[
        "pharmaceutical"
    ],
    "sg:website":"http://www.srdrugs.in",
    "wof:name":"S. R. Drugs & Intermediates Pvt. Ltd.",
    "wof:placetype":"venue"
},
  "geometry": {"coordinates":[78.39737700000001,17.483984],"type":"Point"}
}