{
  "type": "Feature",
  "properties": {
    "iso:country":"IN",
    "sg:address":"B-184, 2nd Stage, Peenya Industrial Estate,",
    "sg:city":"Bangalore",
    "sg:classifiers":[
        {
            "category":"Building & Trades",
            "subcategory":"Construction",
            "type":"Services"
        }
    ],
    "sg:phone":"+91 80 2836 2487",
    "sg:postcode":"560058",
    "sg:tags":[
        "repair",
        "material",
        "retreading",
        "tyre",
        "machinery"
    ],
    "sg:website":"http://www.hydroproducts.net",
    "wof:name":"Hydro Products",
    "wof:placetype":"venue"
},
  "geometry": {"coordinates":[77.515373,13.030847],"type":"Point"}
}