{
  "type": "Feature",
  "properties": {
    "iso:country":"IN",
    "sg:address":"267, Biren Roy Road (e),",
    "sg:city":"Kolkata",
    "sg:classifiers":[
        {
            "category":"Manufacturing",
            "subcategory":"Chemicals & Compounds",
            "type":"Manufacturing & Wholesale Goods"
        }
    ],
    "sg:phone":"+91 33 2402 5975",
    "sg:postcode":"700041",
    "sg:tags":[
        "paint",
        "product",
        "allied"
    ],
    "wof:name":"Crs Paints & Resins Pvt. Ltd.",
    "wof:placetype":"venue"
},
  "geometry": {"coordinates":[88.305305,22.483757],"type":"Point"}
}