{
  "type": "Feature",
  "properties": {
    "iso:country":"IN",
    "sg:address":"Banergatta Road, Adugodi",
    "sg:city":"Bangalore",
    "sg:phone":"+91 802232758",
    "sg:postcode":"560030",
    "sg:province":"Karnataka",
    "wof:name":"Load Controls India Pvt Ltd",
    "wof:placetype":"venue"
},
  "geometry": {"coordinates":[77.602341,12.939114],"type":"Point"}
}