{
  "type": "Feature",
  "properties": {
    "iso:country":"IN",
    "sg:address":"50, Sarang Street, 1st Floor, Masjid Bunder,",
    "sg:city":"Mumbai",
    "sg:classifiers":[
        {
            "category":"Manufacturing",
            "subcategory":"Tools & Machinery",
            "type":"Manufacturing & Wholesale Goods"
        }
    ],
    "sg:phone":"+91 22 2342 5845",
    "sg:postcode":"400003",
    "sg:tags":[
        "electric",
        "power"
    ],
    "wof:name":"Y. A. & Co.",
    "wof:placetype":"venue"
},
  "geometry": {"coordinates":[72.83395400000001,18.94875],"type":"Point"}
}