{
  "type": "Feature",
  "properties": {
    "iso:country":"IN",
    "sg:address":"328/330, Samuel Street., R. No. 404/a, 4th Floor, Vadgadi,",
    "sg:city":"Mumbai",
    "sg:classifiers":[
        {
            "category":"Manufacturing",
            "subcategory":"Chemicals & Compounds",
            "type":"Manufacturing & Wholesale Goods"
        }
    ],
    "sg:phone":"+91 22 2344 2315",
    "sg:postcode":"400003",
    "sg:tags":[
        "supply"
    ],
    "wof:name":"Rahul Dye Chem.",
    "wof:placetype":"venue"
},
  "geometry": {"coordinates":[72.836662,18.951439],"type":"Point"}
}