{
  "type": "Feature",
  "properties": {
    "iso:country":"IN",
    "sg:address":"Victoria Layout",
    "sg:city":"Bangalore",
    "sg:phone":"+91 805514471",
    "sg:postcode":"560047",
    "sg:province":"Karnataka",
    "wof:name":"Aci Infocom Ltd",
    "wof:placetype":"venue"
},
  "geometry": {"coordinates":[77.61494399999999,12.963933],"type":"Point"}
}