{
  "type": "Feature",
  "properties": {
    "iso:country":"IN",
    "sg:address":"Middleton Street",
    "sg:city":"Kolkata",
    "sg:phone":"+91 33 2247 3950",
    "sg:postcode":"700071",
    "sg:province":"West Bengal",
    "wof:name":"Eveready Energizer Miniatures Ltd",
    "wof:placetype":"venue"
},
  "geometry": {"coordinates":[88.35076100000001,22.54908],"type":"Point"}
}