{
  "type": "Feature",
  "properties": {
    "iso:country":"IN",
    "sg:address":"Opp. Worli, Bdd Chawl No.114, Worli,",
    "sg:city":"Mumbai",
    "sg:orig_category":"Dvd, Vcd,vcr",
    "sg:phone":"+91 22 2492 7154",
    "sg:postcode":"400013",
    "sg:website":"http://www.krcd.com",
    "wof:name":"Krcd (india) Pvt. Ltd.",
    "wof:placetype":"venue"
},
  "geometry": {"coordinates":[72.818382,19.002281],"type":"Point"}
}