{
  "type": "Feature",
  "properties": {
    "iso:country":"IN",
    "sg:address":"31, Sahyadri, Aarey Road, Goregaon (east),",
    "sg:city":"Mumbai",
    "sg:classifiers":[
        {
            "category":"Shopping",
            "subcategory":"Crafts & Fabrics",
            "type":"Retail Goods"
        }
    ],
    "sg:phone":"+91 22 2686 0417",
    "sg:postcode":"400063",
    "wof:name":"Indutex Industrial Fabrics P. Ltd.",
    "wof:placetype":"venue"
},
  "geometry": {"coordinates":[72.85423299999999,19.166391],"type":"Point"}
}