{
  "type": "Feature",
  "properties": {
    "iso:country":"IN",
    "sg:address":"20, Bharat Udyog Nagar, Ind. Estate, Off Aarey Road, Goregaon (e),",
    "sg:city":"Mumbai",
    "sg:classifiers":[
        {
            "category":"Utilities",
            "subcategory":"Natural Gas",
            "type":"Services"
        }
    ],
    "sg:phone":"+91 22 2874 2645",
    "sg:postcode":"400063",
    "sg:tags":[
        "mould",
        "dy"
    ],
    "wof:name":"Deelu Moulds (dm)",
    "wof:placetype":"venue"
},
  "geometry": {"coordinates":[72.851006,19.166361],"type":"Point"}
}