{
  "type": "Feature",
  "properties": {
    "iso:country":"IN",
    "sg:address":"B-69/70, Sector-5,",
    "sg:city":"Noida",
    "sg:orig_category":"Pvc Profiles",
    "sg:phone":"+91 120 242 0336",
    "sg:postcode":"201301",
    "sg:website":"http://www.marutirubber.com",
    "wof:name":"Maruti Techno Rubber Pvt. Ltd.",
    "wof:placetype":"venue"
},
  "geometry": {"coordinates":[76.856239,30.698002],"type":"Point"}
}