{
  "type": "Feature",
  "properties": {
    "iso:country":"IN",
    "sg:address":"Connaught Road",
    "sg:city":"Pune",
    "sg:phone":"+91 206128585",
    "sg:postcode":"411001",
    "sg:province":"Maharashtra",
    "wof:name":"Hotel Ashirwad",
    "wof:placetype":"venue"
},
  "geometry": {"coordinates":[72.835892,18.988861],"type":"Point"}
}