{
  "type": "Feature",
  "properties": {
    "iso:country":"IN",
    "sg:address":"2, Vipul, 28, Ridge Road, Walkeshwar,",
    "sg:city":"Mumbai",
    "sg:classifiers":[
        {
            "category":"Shopping",
            "subcategory":"Jewelry",
            "type":"Retail Goods"
        }
    ],
    "sg:phone":"+91 22 2366 6715",
    "sg:postcode":"400006",
    "sg:tags":[
        "diamond"
    ],
    "wof:name":"C.d. Star",
    "wof:placetype":"venue"
},
  "geometry": {"coordinates":[72.800583,18.951189],"type":"Point"}
}