{
  "type": "Feature",
  "properties": {
    "iso:country":"IN",
    "sg:address":"174 Princess Street",
    "sg:city":"Mumbai",
    "sg:phone":"+91 22 2205 0268",
    "sg:postcode":"400002",
    "sg:province":"Maharashtra",
    "wof:name":"Khyati Advisory Services Ltd",
    "wof:placetype":"venue"
},
  "geometry": {"coordinates":[72.830635,18.947435],"type":"Point"}
}