{
  "type": "Feature",
  "properties": {
    "iso:country":"IN",
    "sg:address":"Liberty House, Town Hall,",
    "sg:city":"Udaipur",
    "sg:classifiers":[
        {
            "category":"Manufacturing",
            "subcategory":"Furniture",
            "type":"Manufacturing & Wholesale Goods"
        }
    ],
    "sg:phone":"+91 294 329 0233",
    "sg:postcode":"313001",
    "sg:tags":[
        "fitting",
        "fixture"
    ],
    "wof:name":"Lmm Pvt. Ltd.",
    "wof:placetype":"venue"
},
  "geometry": {"coordinates":[72.825485,18.972462],"type":"Point"}
}