{
  "type": "Feature",
  "properties": {
    "iso:country":"IN",
    "sg:address":"560 Avenue Rd., Chickpet,",
    "sg:city":"Bangalore",
    "sg:classifiers":[
        {
            "category":"Banks & Credit Unions",
            "subcategory":"Investment Brokerage",
            "type":"Services"
        }
    ],
    "sg:phone":"+91 80 2220 2939",
    "sg:postcode":"560027",
    "sg:tags":[
        "garment",
        "silk"
    ],
    "wof:name":"Sirigiri Silks",
    "wof:placetype":"venue"
},
  "geometry": {"coordinates":[77.579018,12.969014],"type":"Point"}
}