{
  "type": "Feature",
  "properties": {
    "iso:country":"IN",
    "sg:address":"Russel Street",
    "sg:city":"Kolkata",
    "sg:phone":"+91 33 2229 3531",
    "sg:postcode":"700071",
    "sg:province":"West Bengal",
    "wof:name":"Sutton & Sons (india) Pvt Ltd",
    "wof:placetype":"venue"
},
  "geometry": {"coordinates":[88.35090599999999,22.552536],"type":"Point"}
}