{
  "type": "Feature",
  "properties": {
    "iso:country":"IN",
    "sg:address":"15, Gopal House, I.b. Patel, Goregaon (e),",
    "sg:city":"Mumbai",
    "sg:classifiers":[
        {
            "category":"Retail",
            "subcategory":"Storage",
            "type":"Services"
        }
    ],
    "sg:phone":"+91 22 2686 5088",
    "sg:postcode":"400063",
    "sg:tags":[
        "box"
    ],
    "wof:name":"Bharat Enterprises",
    "wof:placetype":"venue"
},
  "geometry": {"coordinates":[72.850136,19.206161],"type":"Point"}
}