{
  "type": "Feature",
  "properties": {
    "iso:country":"IN",
    "sg:address":"38, 1st Floor, 1st Main, 'd' Street, Guddadahalli, Mysore Road,",
    "sg:city":"Bangalore",
    "sg:orig_category":"Soap/detergents",
    "sg:phone":"+91 80 2674 8702",
    "sg:postcode":"560026",
    "sg:website":"http://www.anokhaconcepts.com",
    "wof:name":"Anokha Concepts",
    "wof:placetype":"venue"
},
  "geometry": {"coordinates":[77.55231499999999,12.959064],"type":"Point"}
}