{
  "type": "Feature",
  "properties": {
    "iso:country":"IN",
    "sg:address":"67/1, 15th Cross, 8th Main, Malleswaram,",
    "sg:city":"Bangalore",
    "sg:classifiers":[
        {
            "category":"Building & Trades",
            "subcategory":"Construction",
            "type":"Services"
        }
    ],
    "sg:phone":"+91 80 2346 5570",
    "sg:postcode":"560003",
    "sg:tags":[
        "valve"
    ],
    "wof:name":"Reach Pneumatics",
    "wof:placetype":"venue"
},
  "geometry": {"coordinates":[77.565216,13.005623],"type":"Point"}
}