{
  "type": "Feature",
  "properties": {
    "iso:country":"IN",
    "sg:address":"496/1, Gidc, Makarpura,",
    "sg:city":"Vadodara",
    "sg:classifiers":[
        {
            "category":"Transit Center",
            "subcategory":"Freight",
            "type":"Transportation"
        }
    ],
    "sg:phone":"+91 265 263 6547",
    "sg:postcode":"390010",
    "sg:tags":[
        "pipe",
        "fitting"
    ],
    "sg:website":"http://www.pipefit.net",
    "wof:name":"Pipefit Engineers Pvt. Ltd.",
    "wof:placetype":"venue"
},
  "geometry": {"coordinates":[72.65799,23.076591],"type":"Point"}
}