{
  "type": "Feature",
  "properties": {
    "iso:country":"IN",
    "sg:address":"155/157 Samuel St., 305, 3rd Floor,",
    "sg:city":"Mumbai",
    "sg:classifiers":[
        {
            "category":"Manufacturing",
            "subcategory":"Chemicals & Compounds",
            "type":"Manufacturing & Wholesale Goods"
        }
    ],
    "sg:phone":"+91 22 5631 1933",
    "sg:postcode":"400009",
    "sg:tags":[
        "supply"
    ],
    "sg:website":"http://www.radiant-chemicals.com",
    "wof:name":"Radiant Chemicals",
    "wof:placetype":"venue"
},
  "geometry": {"coordinates":[72.836662,18.951439],"type":"Point"}
}