{
  "type": "Feature",
  "properties": {
    "iso:country":"IN",
    "sg:address":"A-16, Hmt Industrial Estate,",
    "sg:city":"Bangalore",
    "sg:classifiers":[
        {
            "category":"Retail",
            "subcategory":"Emissions Testing",
            "type":"Services"
        }
    ],
    "sg:phone":"+91 80 2838 9240",
    "sg:postcode":"560031",
    "sg:tags":[
        "measuring",
        "instrument"
    ],
    "sg:website":"http://www.purushothamengg.com",
    "wof:name":"Purushotham Engineering Industries",
    "wof:placetype":"venue"
},
  "geometry": {"coordinates":[77.536148,13.046322],"type":"Point"}
}