{
  "type": "Feature",
  "properties": {
    "iso:country":"IN",
    "sg:address":"No. 40, 2nd Block, Koramangala,",
    "sg:city":"Bangalore",
    "sg:classifiers":[
        {
            "category":"Food & Beverages",
            "subcategory":"Specialty",
            "type":"Retail Goods"
        }
    ],
    "sg:phone":"+91 80 2552 2709",
    "sg:postcode":"560034",
    "sg:tags":[
        "solvent"
    ],
    "wof:name":"Chemical Palette",
    "wof:placetype":"venue"
},
  "geometry": {"coordinates":[77.61853,12.926673],"type":"Point"}
}