{
  "type": "Feature",
  "properties": {
    "iso:country":"IN",
    "sg:address":"C-33/1, Meerut Road, Industrial Area,",
    "sg:city":"Ghaziabad",
    "sg:classifiers":[
        {
            "category":"Manufacturing",
            "subcategory":"Chemicals & Compounds",
            "type":"Manufacturing & Wholesale Goods"
        }
    ],
    "sg:phone":"+91 120 271 2296",
    "sg:postcode":"201003",
    "sg:tags":[
        "supply"
    ],
    "sg:website":"http://www.bludip.com",
    "wof:name":"Bludip Paints & Chemicals",
    "wof:placetype":"venue"
},
  "geometry": {"coordinates":[77.434341,28.685476],"type":"Point"}
}