{
  "type": "Feature",
  "properties": {
    "iso:country":"IN",
    "sg:address":"No.-6/6, Begur Road, Bommanahalli,",
    "sg:city":"Bangalore",
    "sg:classifiers":[
        {
            "category":"Manufacturing",
            "subcategory":"Tools & Machinery",
            "type":"Manufacturing & Wholesale Goods"
        }
    ],
    "sg:phone":"+91 80 3096 9064",
    "sg:postcode":"560068",
    "sg:tags":[
        "component",
        "auto",
        "part",
        "turned",
        "precision"
    ],
    "wof:name":"Indus Technologies",
    "wof:placetype":"venue"
},
  "geometry": {"coordinates":[77.627831,12.905565],"type":"Point"}
}