{
  "type": "Feature",
  "properties": {
    "iso:country":"IN",
    "sg:address":"1958, Mie, Part-b,",
    "sg:city":"Bahadurgarh",
    "sg:classifiers":[
        {
            "category":"Manufacturing",
            "subcategory":"Rubber & Plastics",
            "type":"Manufacturing & Wholesale Goods"
        }
    ],
    "sg:phone":"+91 1276 268 222",
    "sg:tags":[
        "product"
    ],
    "wof:name":"Vastas Hose Division (p) Ltd.",
    "wof:placetype":"venue"
},
  "geometry": {"coordinates":[80.260666,13.061556],"type":"Point"}
}