{
  "type": "Feature",
  "properties": {
    "iso:country":"IN",
    "sg:address":"Baroda-jambusar, N.h. Road, At & Po. Dabhasa, Tal Padra,",
    "sg:city":"Vadodara",
    "sg:classifiers":[
        {
            "category":"Shopping",
            "subcategory":"Beauty & Cosmetics",
            "type":"Retail Goods"
        }
    ],
    "sg:phone":"+91 2662 222 783",
    "sg:postcode":"391440",
    "wof:name":"Royal Dutch Cosmetics Pvt. Ltd.",
    "wof:placetype":"venue"
},
  "geometry": {"coordinates":[73.187576,22.306549],"type":"Point"}
}