{
  "type": "Feature",
  "properties": {
    "iso:country":"IN",
    "sg:address":"208, G.i.d.c., Waghodia,",
    "sg:city":"Vadodara",
    "sg:orig_category":"Pourers / Pouring Spouts & Cones",
    "sg:phone":"+91 2668 262 107",
    "sg:postcode":"391760",
    "sg:website":"http://www.compack.in",
    "wof:name":"Compack Private Limited",
    "wof:placetype":"venue"
},
  "geometry": {"coordinates":[73.233536,22.286194],"type":"Point"}
}