{
  "type": "Feature",
  "properties": {
    "iso:country":"IN",
    "sg:address":"H Siddaiah Road",
    "sg:city":"Bangalore",
    "sg:phone":"+91 805269968",
    "sg:postcode":"560002",
    "sg:province":"Karnataka",
    "sg:website":"http://www.stellarubber.com",
    "wof:name":"Stella Rubber Works",
    "wof:placetype":"venue"
},
  "geometry": {"coordinates":[77.595169,12.951335],"type":"Point"}
}