{
  "type": "Feature",
  "properties": {
    "iso:country":"IN",
    "sg:address":"Peenya Indl Area,",
    "sg:city":"Bangalore",
    "sg:classifiers":[
        {
            "category":"Home & Garden",
            "subcategory":"Garden Supply",
            "type":"Retail Goods"
        }
    ],
    "sg:phone":"+91 80 2372 0635",
    "sg:postcode":"560052",
    "sg:tags":[
        "fertilizer"
    ],
    "wof:name":"Rallis India Limited",
    "wof:placetype":"venue"
},
  "geometry": {"coordinates":[77.499596,13.008512],"type":"Point"}
}