{
  "type": "Feature",
  "properties": {
    "iso:country":"IN",
    "sg:address":"24-4-12, Harbour Road,",
    "sg:city":"Vishakapattanam",
    "sg:classifiers":[
        {
            "category":"Manufacturing",
            "subcategory":"Chemicals & Compounds",
            "type":"Manufacturing & Wholesale Goods"
        }
    ],
    "sg:phone":"+91 891 256 2227",
    "sg:postcode":"530001",
    "sg:tags":[
        "supply"
    ],
    "wof:name":"Shm Ship Care",
    "wof:placetype":"venue"
},
  "geometry": {"coordinates":[88.245689,22.298937],"type":"Point"}
}