{
  "type": "Feature",
  "properties": {
    "iso:country":"IN",
    "sg:address":"112/208, c, Swaroop Nagar,",
    "sg:city":"Kanpur",
    "sg:classifiers":[
        {
            "category":"Manufacturing",
            "subcategory":"Chemicals & Compounds",
            "type":"Manufacturing & Wholesale Goods"
        }
    ],
    "sg:phone":"+91 512 254 4345",
    "sg:postcode":"208002",
    "sg:tags":[
        "plant",
        "processing"
    ],
    "wof:name":"D.tech Paper Machines Pvt. Ltd",
    "wof:placetype":"venue"
},
  "geometry": {"coordinates":[80.316437,26.484112],"type":"Point"}
}