{
  "type": "Feature",
  "properties": {
    "iso:country":"IN",
    "sg:address":"Greams Road",
    "sg:city":"Chennai",
    "sg:phone":"+91 44 2829 2166",
    "sg:postcode":"600006",
    "sg:province":"Tamil Nadu",
    "wof:name":"Tulsyan Nec Ltd",
    "wof:placetype":"venue"
},
  "geometry": {"coordinates":[80.254509,13.061238],"type":"Point"}
}