{
  "type": "Feature",
  "properties": {
    "iso:country":"IN",
    "sg:address":"501, Vishal Appt, Brivali-w, T. P. S Road,",
    "sg:city":"Mumbai",
    "sg:classifiers":[
        {
            "category":"Shopping",
            "subcategory":"Jewelry",
            "type":"Retail Goods"
        }
    ],
    "sg:phone":"+91 22 2899 4635",
    "sg:postcode":"400092",
    "sg:tags":[
        "diamond"
    ],
    "wof:name":"Naresh Gems And Jewellery",
    "wof:placetype":"venue"
},
  "geometry": {"coordinates":[72.863518,19.250887],"type":"Point"}
}