{
  "type": "Feature",
  "properties": {
    "iso:country":"IN",
    "sg:address":"Dr. Ranga Road",
    "sg:city":"Chennai",
    "sg:phone":"+91 44 2499 6422",
    "sg:postcode":"600018",
    "sg:province":"Tamil Nadu",
    "sg:website":"http://www.gclsite.com",
    "wof:name":"Gemini Communication Ltd",
    "wof:placetype":"venue"
},
  "geometry": {"coordinates":[80.259377,13.033338],"type":"Point"}
}