{
  "type": "Feature",
  "properties": {
    "iso:country":"IN",
    "sg:address":"265-b, Abdul Rehman Street,",
    "sg:city":"Mumbai",
    "sg:orig_category":"Ayurvedic Products",
    "sg:phone":"+91 22 2342 7093",
    "sg:postcode":"400003",
    "sg:website":"http://www.seekandsource.com/mgshahani",
    "wof:name":"M. G. Shahani & Co. (bombay) Pvt. Ltd.",
    "wof:placetype":"venue"
},
  "geometry": {"coordinates":[72.832787,18.950718],"type":"Point"}
}