{
  "type": "Feature",
  "properties": {
    "iso:country":"IN",
    "sg:address":"7, 3rd Cross, 4th Main, Industrial Town, Rajaji Nagar,",
    "sg:city":"Bangalore",
    "sg:classifiers":[
        {
            "category":"Wholesale",
            "subcategory":"Auto Parts",
            "type":"Manufacturing & Wholesale Goods"
        }
    ],
    "sg:phone":"+91 80 4128 7206",
    "sg:postcode":"560044",
    "sg:tags":[
        "component",
        "pressed"
    ],
    "sg:website":"http://www.ragaprecisions.com",
    "wof:name":"Raga Precisions",
    "wof:placetype":"venue"
},
  "geometry": {"coordinates":[77.544014,12.971944],"type":"Point"}
}