{
  "type": "Feature",
  "properties": {
    "iso:country":"IN",
    "sg:address":"C-26, Indl. Estate, Rajaji Nagar,",
    "sg:city":"Bangalore",
    "sg:classifiers":[
        {
            "category":"Manufacturing",
            "subcategory":"Rubber & Plastics",
            "type":"Manufacturing & Wholesale Goods"
        }
    ],
    "sg:phone":"+91 80 2330 4396",
    "sg:postcode":"560044",
    "sg:tags":[
        "product"
    ],
    "wof:name":"Bangalore Rubber Industries",
    "wof:placetype":"venue"
},
  "geometry": {"coordinates":[80.21051799999999,13.111913],"type":"Point"}
}