{
  "type": "Feature",
  "properties": {
    "iso:country":"IN",
    "sg:address":"42/44, Bazar Gate Street, Fort,",
    "sg:city":"Mumbai",
    "sg:classifiers":[
        {
            "category":"Manufacturing",
            "subcategory":"Chemicals & Compounds",
            "type":"Manufacturing & Wholesale Goods"
        }
    ],
    "sg:phone":"+91 22 6637 6330",
    "sg:postcode":"400001",
    "sg:tags":[
        "supply"
    ],
    "wof:name":"Vibha Industries",
    "wof:placetype":"venue"
},
  "geometry": {"coordinates":[72.835823,18.936329],"type":"Point"}
}