{
  "type": "Feature",
  "properties": {
    "iso:country":"IN",
    "sg:address":"2e/9, Jhandewalan Extn.,",
    "sg:city":"New Delhi",
    "sg:classifiers":[
        {
            "category":"Manufacturing",
            "subcategory":"Rubber & Plastics",
            "type":"Manufacturing & Wholesale Goods"
        }
    ],
    "sg:phone":"+91 11 2368 1016",
    "sg:postcode":"110055",
    "sg:tags":[
        "polymer"
    ],
    "wof:name":"V. M. I. Polymers",
    "wof:placetype":"venue"
},
  "geometry": {"coordinates":[77.200996,28.645454],"type":"Point"}
}