{
  "type": "Feature",
  "properties": {
    "iso:country":"IN",
    "sg:address":"226, Samuel Street, 1st Floor, Masjid Bunder,",
    "sg:city":"Mumbai",
    "sg:classifiers":[
        {
            "category":"Home & Garden",
            "subcategory":"Mobile Homes",
            "type":"Retail Goods"
        }
    ],
    "sg:phone":"+91 22 6610 8144",
    "sg:postcode":"400003",
    "sg:tags":[
        "acid"
    ],
    "sg:website":"http://www.acidindia.in",
    "wof:name":"Acid India",
    "wof:placetype":"venue"
},
  "geometry": {"coordinates":[72.836662,18.951439],"type":"Point"}
}