{
  "type": "Feature",
  "properties": {
    "iso:country":"IN",
    "sg:address":"51-52, Free Press House, 215, Nariman Point,",
    "sg:city":"Mumbai",
    "sg:orig_category":"Denim Fabrics",
    "sg:phone":"+91 22 2283 3355",
    "sg:postcode":"400021",
    "sg:website":"http://www.rainbowdenims.com",
    "wof:name":"Rainbow Denim Limited",
    "wof:placetype":"venue"
},
  "geometry": {"coordinates":[72.823189,18.923292],"type":"Point"}
}