{
  "type": "Feature",
  "properties": {
    "iso:country":"IN",
    "sg:address":"B-154, Yojna Vihar,",
    "sg:city":"New Delhi",
    "sg:classifiers":[
        {
            "category":"Manufacturing",
            "subcategory":"Pet Food",
            "type":"Manufacturing & Wholesale Goods"
        }
    ],
    "sg:phone":"+91 11 2216 6054",
    "sg:postcode":"110092",
    "sg:tags":[
        "additive",
        "flavour"
    ],
    "sg:website":"http://www.culinar.se",
    "wof:name":"Culinar India Pvt. Ltd.",
    "wof:placetype":"venue"
},
  "geometry": {"coordinates":[77.315933,28.662125],"type":"Point"}
}