{
  "type": "Feature",
  "properties": {
    "iso:country":"IN",
    "sg:address":"Plot No. 19(b), Industrial Area,",
    "sg:city":"Chik Ballapur",
    "sg:classifiers":[
        {
            "category":"Manufacturing",
            "subcategory":"Rubber & Plastics",
            "type":"Manufacturing & Wholesale Goods"
        }
    ],
    "sg:phone":"+91 8156 263 045",
    "sg:postcode":"562101",
    "sg:tags":[
        "product"
    ],
    "wof:name":"S.v. Rubber Industries",
    "wof:placetype":"venue"
},
  "geometry": {"coordinates":[74.787102,13.334578],"type":"Point"}
}