{
  "type": "Feature",
  "properties": {
    "iso:country":"IN",
    "sg:address":"Off. Saki Vihar Road, Chandivali, Andheri (e)",
    "sg:city":"Mumbai",
    "sg:phone":"+91 22 2856 0555",
    "sg:postcode":"400072",
    "sg:province":"Maharashtra",
    "wof:name":"Saisons Communications Pvt Ltd",
    "wof:placetype":"venue"
},
  "geometry": {"coordinates":[72.889168,19.115517],"type":"Point"}
}