{
  "type": "Feature",
  "properties": {
    "iso:country":"IN",
    "sg:address":"Oliver Road, Mylapore",
    "sg:city":"Chennai",
    "sg:phone":"+91 44 2499 3820",
    "sg:postcode":"600004",
    "sg:province":"Tamil Nadu",
    "wof:name":"Vaigai Sanitation Pvt Ltd",
    "wof:placetype":"venue"
},
  "geometry": {"coordinates":[80.261948,13.039398],"type":"Point"}
}