{
  "type": "Feature",
  "properties": {
    "iso:country":"IN",
    "sg:address":"Mandhana",
    "sg:city":"Kanpur",
    "sg:phone":"+91 512210161",
    "sg:postcode":"208001",
    "sg:province":"Uttar Pradesh",
    "wof:name":"Alvin Cements Pvt Ltd",
    "wof:placetype":"venue"
},
  "geometry": {"coordinates":[80.222374,26.552853],"type":"Point"}
}