{
  "type": "Feature",
  "properties": {
    "iso:country":"IN",
    "sg:address":"Gidc Vatva",
    "sg:city":"Ahmedabad",
    "sg:phone":"+91 79835171",
    "sg:postcode":"382445",
    "sg:province":"Gujarat",
    "wof:name":"Rohan Dyes And Intermediates Ltd",
    "wof:placetype":"venue"
},
  "geometry": {"coordinates":[72.643204,22.974106],"type":"Point"}
}