{
  "type": "Feature",
  "properties": {
    "iso:country":"IN",
    "sg:address":"204, Nagdevi Street, 2nd Floor, P.o. Box 3074,",
    "sg:city":"Mumbai",
    "sg:orig_category":"Carpets, Rugs, Mats & Durries",
    "sg:phone":"+91 22 2344 5258",
    "sg:postcode":"400003",
    "wof:name":"Kausar Textiles",
    "wof:placetype":"venue"
},
  "geometry": {"coordinates":[72.833992,18.950926],"type":"Point"}
}