{
  "type": "Feature",
  "properties": {
    "iso:country":"IN",
    "sg:address":"B-17, Sangam Appt., Opposite Vijay Sales, S.v. Road, Santacruz (west),",
    "sg:city":"Mumbai",
    "sg:classifiers":[
        {
            "category":"Manufacturing",
            "subcategory":"Paper Products",
            "type":"Manufacturing & Wholesale Goods"
        }
    ],
    "sg:tags":[
        "equipment",
        "cast"
    ],
    "wof:name":"Pratik International",
    "wof:placetype":"venue"
},
  "geometry": {"coordinates":[72.83805099999999,19.084053],"type":"Point"}
}