{
  "type": "Feature",
  "properties": {
    "iso:country":"IN",
    "sg:address":"Trivandrum,",
    "sg:city":"Thiruvananthapuram",
    "sg:classifiers":[
        {
            "category":"Banks & Credit Unions",
            "subcategory":"Financial Services",
            "type":"Services"
        }
    ],
    "sg:phone":"+91 471 454 4119",
    "sg:tags":[
        "rough",
        "stone",
        "gem"
    ],
    "wof:name":"Aditya Impex",
    "wof:placetype":"venue"
},
  "geometry": {"coordinates":[76.952187,8.503696],"type":"Point"}
}