{
  "type": "Feature",
  "properties": {
    "iso:country":"IN",
    "sg:address":"46-d, Rafi Ahmed Kidwai Road,",
    "sg:city":"Kolkata",
    "sg:classifiers":[
        {
            "category":"Manufacturing",
            "subcategory":"Petroleum Products",
            "type":"Manufacturing & Wholesale Goods"
        }
    ],
    "sg:phone":"+91 33 2234 8285",
    "sg:postcode":"700016",
    "sg:tags":[
        "wax"
    ],
    "wof:name":"Shree Ram Industries",
    "wof:placetype":"venue"
},
  "geometry": {"coordinates":[88.357292,22.556393],"type":"Point"}
}