{
  "type": "Feature",
  "properties": {
    "iso:country":"IN",
    "sg:address":"179 G.i.d.c., Waghodia,",
    "sg:city":"Vadodara",
    "sg:classifiers":[
        {
            "category":"Shopping",
            "subcategory":"Crafts & Fabrics",
            "type":"Retail Goods"
        }
    ],
    "sg:phone":"+91 265 279 2122",
    "sg:postcode":"391760",
    "wof:name":"Spring Master Sleep Products (i) Pvt. Ltd.",
    "wof:placetype":"venue"
},
  "geometry": {"coordinates":[73.233536,22.286194],"type":"Point"}
}