{
  "type": "Feature",
  "properties": {
    "iso:country":"IN",
    "sg:address":"18/20, Indl. Area, Site-iv,",
    "sg:city":"Sahibabad",
    "sg:classifiers":[
        {
            "category":"Manufacturing",
            "subcategory":"Rubber & Plastics",
            "type":"Manufacturing & Wholesale Goods"
        }
    ],
    "sg:phone":"+91 120 551 5041",
    "sg:postcode":"201010",
    "sg:tags":[
        "polymer"
    ],
    "wof:name":"Systrans Polymers Pvt. Ltd.",
    "wof:placetype":"venue"
},
  "geometry": {"coordinates":[77.341057,28.660917],"type":"Point"}
}