{
  "type": "Feature",
  "properties": {
    "iso:country":"IN",
    "sg:address":"52/b, 100 Feet Road, 4th Block, Koramangala,",
    "sg:city":"Bangalore",
    "sg:classifiers":[
        {
            "category":"Manufacturing",
            "subcategory":"Textiles",
            "type":"Manufacturing & Wholesale Goods"
        }
    ],
    "sg:phone":"+91 80 56 694238",
    "sg:postcode":"560034",
    "sg:website":"http://www.mobiapps.com",
    "wof:name":"Mobi Apps",
    "wof:placetype":"venue"
},
  "geometry": {"coordinates":[77.623184,12.932578],"type":"Point"}
}