{
  "type": "Feature",
  "properties": {
    "iso:country":"IN",
    "sg:address":"F-17, National Plaza, Alkapuri,",
    "sg:city":"Vadodara",
    "sg:orig_category":"Papier Machie",
    "sg:phone":"+91 265 235 9510",
    "sg:postcode":"390007",
    "wof:name":"Kashmir Art Palace",
    "wof:placetype":"venue"
},
  "geometry": {"coordinates":[72.872398,22.6889],"type":"Point"}
}