{
  "type": "Feature",
  "properties": {
    "iso:country":"IN",
    "sg:address":"601, 6th Floor, Parshva Apt., Dr.ambedkar Road, Mulund-west,",
    "sg:city":"Mumbai",
    "sg:classifiers":[
        {
            "category":"Banks & Credit Unions",
            "subcategory":"Investment Brokerage",
            "type":"Services"
        }
    ],
    "sg:phone":"+91 22 5654 5359",
    "sg:postcode":"400080",
    "sg:tags":[
        "agro",
        "product",
        "based",
        "commodity"
    ],
    "wof:name":"Pdm Exports",
    "wof:placetype":"venue"
},
  "geometry": {"coordinates":[72.952934,19.17033],"type":"Point"}
}