{
  "type": "Feature",
  "properties": {
    "iso:country":"IN",
    "sg:address":"R-42, M.id.c., T.b. Road,",
    "sg:city":"Navi Mumbai",
    "sg:classifiers":[
        {
            "category":"Manufacturing",
            "subcategory":"Chemicals & Compounds",
            "type":"Manufacturing & Wholesale Goods"
        }
    ],
    "sg:phone":"+91 22 2769 1494",
    "sg:postcode":"400701",
    "sg:tags":[
        "supply"
    ],
    "wof:name":"Hebbar Chemicals Pvt. Ltd.",
    "wof:placetype":"venue"
},
  "geometry": {"coordinates":[72.857391,19.021835],"type":"Point"}
}