{
  "type": "Feature",
  "properties": {
    "iso:country":"IN",
    "sg:address":"2, Vardhman Complex, L.b.s. Marg, Vikhroli (west),",
    "sg:city":"Mumbai",
    "sg:classifiers":[
        {
            "category":"Manufacturing",
            "subcategory":"Rubber & Plastics",
            "type":"Manufacturing & Wholesale Goods"
        }
    ],
    "sg:phone":"+91 22 2578 5880",
    "sg:postcode":"400083",
    "sg:tags":[
        "chemical",
        "-"
    ],
    "wof:name":"Clark Rubbers Ltd.",
    "wof:placetype":"venue"
},
  "geometry": {"coordinates":[72.924553,19.119467],"type":"Point"}
}