{
  "type": "Feature",
  "properties": {
    "iso:country":"IN",
    "sg:address":"3-g-1, Court Chambers, 3rd Floor, New Marine Lines,",
    "sg:city":"Mumbai",
    "sg:classifiers":[
        {
            "category":"Manufacturing",
            "subcategory":"Chemicals & Compounds",
            "type":"Manufacturing & Wholesale Goods"
        }
    ],
    "sg:phone":"+91 22 2200 1134",
    "sg:postcode":"400020",
    "sg:tags":[
        "supply"
    ],
    "wof:name":"Pagel Concrete Technologies Pvt. Ltd.",
    "wof:placetype":"venue"
},
  "geometry": {"coordinates":[72.828903,18.938452],"type":"Point"}
}