{
  "type": "Feature",
  "properties": {
    "iso:country":"IN",
    "sg:address":"A-353 (b), 8th Main, Peenya 2nd Stage,",
    "sg:city":"Bangalore",
    "sg:classifiers":[
        {
            "category":"Manufacturing",
            "subcategory":"Chemicals & Compounds",
            "type":"Manufacturing & Wholesale Goods"
        }
    ],
    "sg:phone":"+91 80 4117 1331",
    "sg:postcode":"560058",
    "sg:tags":[
        "paint",
        "product",
        "allied"
    ],
    "wof:name":"Rasayana",
    "wof:placetype":"venue"
},
  "geometry": {"coordinates":[77.543488,13.010885],"type":"Point"}
}