{
  "type": "Feature",
  "properties": {
    "iso:country":"IN",
    "sg:address":"R.n.marg",
    "sg:city":"Indore",
    "sg:phone":"+91 731528866",
    "sg:postcode":"452001",
    "sg:province":"Madhya Pradesh",
    "wof:name":"Hotel President",
    "wof:placetype":"venue"
},
  "geometry": {"coordinates":[75.873611,22.716345],"type":"Point"}
}