{
  "type": "Feature",
  "properties": {
    "iso:country":"IN",
    "sg:address":"180, 1st Main Road, Mahalaxmi Layout, Extension,",
    "sg:city":"Bangalore",
    "sg:classifiers":[
        {
            "category":"Home & Garden",
            "subcategory":"Garden Supply",
            "type":"Retail Goods"
        }
    ],
    "sg:phone":"+91 80 2349 4406",
    "sg:postcode":"560086",
    "sg:tags":[
        "fertilizer"
    ],
    "sg:website":"http://www.multiplexgroup.net",
    "wof:name":"Karnataka Agro Chemicals Multiplex Fertilizers Pvt. Ltd.",
    "wof:placetype":"venue"
},
  "geometry": {"coordinates":[77.56117999999999,13.004516],"type":"Point"}
}