{
  "type": "Feature",
  "properties": {
    "iso:country":"IN",
    "sg:address":"87, Chowdeshwari Temple Street,",
    "sg:city":"Bangalore",
    "sg:orig_category":"Sarees",
    "sg:phone":"+91 80 2221 6698",
    "sg:postcode":"560002",
    "sg:website":"http://www.lalcoe.com",
    "wof:name":"Lalco Enterprises",
    "wof:placetype":"venue"
},
  "geometry": {"coordinates":[77.746193,12.939657],"type":"Point"}
}