{
  "type": "Feature",
  "properties": {
    "iso:country":"IN",
    "sg:address":"37, Strand Road, 1st Floor, R-19-a,",
    "sg:city":"Kolkata",
    "sg:classifiers":[
        {
            "category":"Manufacturing",
            "subcategory":"Chemicals & Compounds",
            "type":"Manufacturing & Wholesale Goods"
        }
    ],
    "sg:phone":"+91 33 2243 2143",
    "sg:postcode":"700001",
    "sg:tags":[
        "supply"
    ],
    "wof:name":"Kalpatana Corporation",
    "wof:placetype":"venue"
},
  "geometry": {"coordinates":[88.34532900000001,22.573307],"type":"Point"}
}