{
  "type": "Feature",
  "properties": {
    "iso:country":"IN",
    "sg:address":"A-802, Windsor Plaza, R.c. Dutt Road, Alkapuri,",
    "sg:city":"Vadodara",
    "sg:classifiers":[
        {
            "category":"Health Services",
            "subcategory":"Medical Lab",
            "type":"Services"
        }
    ],
    "sg:phone":"+91 265 235 2016",
    "sg:postcode":"390007",
    "sg:tags":[
        "medication",
        "drug"
    ],
    "sg:website":"http://www.siestapharmaceuticals.com",
    "wof:name":"Siesta Formulations Pvt. Ltd.",
    "wof:placetype":"venue"
},
  "geometry": {"coordinates":[73.170372,22.309984],"type":"Point"}
}