{
  "type": "Feature",
  "properties": {
    "iso:country":"IN",
    "sg:address":"301, Anand Plaza,",
    "sg:city":"Udaipur",
    "sg:classifiers":[
        {
            "category":"Home & Garden",
            "subcategory":"Garden Supply",
            "type":"Retail Goods"
        }
    ],
    "sg:postcode":"313001",
    "sg:tags":[
        "fertilizer"
    ],
    "sg:website":"http://www.bppl.net.in",
    "wof:name":"Bohra Pratisthan Pvt. Ltd.",
    "wof:placetype":"venue"
},
  "geometry": {"coordinates":[83.285316,27.096249],"type":"Point"}
}