{
  "type": "Feature",
  "properties": {
    "iso:country":"IN",
    "sg:address":"# V-3, 1st Main Road, 1st Stage, Peenya Industrial Estate,",
    "sg:city":"Bangalore",
    "sg:classifiers":[
        {
            "category":"Wholesale",
            "subcategory":"Vending Machines",
            "type":"Manufacturing & Wholesale Goods"
        }
    ],
    "sg:phone":"+91 80 2839 8497",
    "sg:postcode":"560013",
    "sg:tags":[
        "weighing"
    ],
    "sg:website":"http://www.wave-mechanics.com",
    "wof:name":"Wave Mechanics Pvt. Ltd.",
    "wof:placetype":"venue"
},
  "geometry": {"coordinates":[77.513054,13.035933],"type":"Point"}
}