{
  "type": "Feature",
  "properties": {
    "iso:country":"IN",
    "sg:address":"102, Adarsh Nagar, New Link Road, Oshiwara, Jogeshwari (west),",
    "sg:city":"Mumbai",
    "sg:orig_category":"Air Curtains",
    "sg:phone":"+91 22 5687 6897",
    "sg:postcode":"400102",
    "wof:name":"Shaullintiger",
    "wof:placetype":"venue"
},
  "geometry": {"coordinates":[72.832909,19.145893],"type":"Point"}
}