{
  "type": "Feature",
  "properties": {
    "iso:country":"IN",
    "sg:address":"C-18 & 19, Sec-2,",
    "sg:city":"Noida",
    "sg:classifiers":[
        {
            "category":"Home & Garden",
            "subcategory":"Building Materials",
            "type":"Retail Goods"
        }
    ],
    "sg:phone":"+91 120 306 7008",
    "sg:postcode":"201301",
    "sg:tags":[
        "sealant",
        "adhesive"
    ],
    "wof:name":"Pashupatinath Paper Convertor",
    "wof:placetype":"venue"
},
  "geometry": {"coordinates":[77.432274,28.669598],"type":"Point"}
}