{
  "type": "Feature",
  "properties": {
    "iso:country":"IN",
    "sg:address":"1104, Arcadia, 11th Floor, Nariman Point,",
    "sg:city":"Mumbai",
    "sg:classifiers":[
        {
            "category":"Shopping",
            "subcategory":"Photographic Equipment",
            "type":"Retail Goods"
        }
    ],
    "sg:phone":"+91 22 2288 1953",
    "sg:postcode":"400021",
    "sg:tags":[
        "camera"
    ],
    "sg:website":"http://www.ricohindia.com",
    "wof:name":"Ricoh India Limited",
    "wof:placetype":"venue"
},
  "geometry": {"coordinates":[72.820618,18.924555],"type":"Point"}
}