{
  "type": "Feature",
  "properties": {
    "iso:country":"IN",
    "sg:address":"Behind Building No. 3, Sai Baba Nagar, 90 Feet Road, Ghatkopar (east),",
    "sg:city":"Mumbai",
    "sg:classifiers":[
        {
            "category":"Shopping",
            "subcategory":"Clothing, Apparel, & Fashions",
            "type":"Retail Goods"
        }
    ],
    "sg:phone":"+91 22 2515 6271",
    "sg:postcode":"400075",
    "sg:tags":[
        "garment",
        "accessory"
    ],
    "wof:name":"Vasudha Engineering",
    "wof:placetype":"venue"
},
  "geometry": {"coordinates":[72.912056,19.081377],"type":"Point"}
}