{
  "type": "Feature",
  "properties": {
    "iso:country":"IN",
    "sg:address":"No. 348, Avenue Road,",
    "sg:city":"Bangalore",
    "sg:classifiers":[
        {
            "category":"Banks & Credit Unions",
            "subcategory":"Investment Brokerage",
            "type":"Services"
        }
    ],
    "sg:phone":"+91 80 2223 7188",
    "sg:postcode":"560002",
    "sg:tags":[
        "precious",
        "stone",
        "semi"
    ],
    "wof:name":"Vellachamy & Sons",
    "wof:placetype":"venue"
},
  "geometry": {"coordinates":[76.228737,10.512239],"type":"Point"}
}