{
  "type": "Feature",
  "properties": {
    "iso:country":"IN",
    "sg:address":"Plot No. 35, Sector G, Shastri Nagar,",
    "sg:city":"Jodhpur",
    "sg:classifiers":[
        {
            "category":"Manufacturing",
            "subcategory":"Chemicals & Compounds",
            "type":"Manufacturing & Wholesale Goods"
        }
    ],
    "sg:phone":"+91 291 243 3183",
    "sg:postcode":"342001",
    "sg:tags":[
        "supply"
    ],
    "wof:name":"Itex",
    "wof:placetype":"venue"
},
  "geometry": {"coordinates":[77.452629,28.691135],"type":"Point"}
}