{
  "type": "Feature",
  "properties": {
    "iso:country":"IN",
    "sg:address":"117, Bhola Bhagwan Industrial Estate, I.b. Patel Road, Goregaon (e),",
    "sg:city":"Mumbai",
    "sg:classifiers":[
        {
            "category":"Manufacturing",
            "subcategory":"Motor Vehicles & Parts",
            "type":"Manufacturing & Wholesale Goods"
        }
    ],
    "sg:phone":"+91 22 5621 8681",
    "sg:postcode":"400063",
    "sg:tags":[
        "engine",
        "electric"
    ],
    "sg:website":"http://www.eltekindia.com",
    "wof:name":"Elektrocraft (india) Pvt. Ltd.",
    "wof:placetype":"venue"
},
  "geometry": {"coordinates":[72.854469,19.161274],"type":"Point"}
}