{
  "type": "Feature",
  "properties": {
    "iso:country":"IN",
    "sg:address":"4th Block, Koramangala",
    "sg:city":"Bangalore",
    "sg:phone":"+91 805501055",
    "sg:postcode":"560034",
    "sg:province":"Karnataka",
    "sg:website":"http://www.ediumatics.com",
    "wof:name":"Educomp Datamatics Ltd",
    "wof:placetype":"venue"
},
  "geometry": {"coordinates":[77.629272,12.933542],"type":"Point"}
}