{
  "type": "Feature",
  "properties": {
    "iso:country":"IN",
    "sg:address":"204, Nagdevi Street,",
    "sg:city":"Mumbai",
    "sg:classifiers":[
        {
            "category":"Utilities",
            "subcategory":"Water",
            "type":"Services"
        }
    ],
    "sg:phone":"+91 22 2340 1568",
    "sg:postcode":"400003",
    "sg:tags":[
        "pulley",
        "coupling"
    ],
    "sg:website":"http://www.fairfieldengineers.com",
    "wof:name":"Fairfield Engineers",
    "wof:placetype":"venue"
},
  "geometry": {"coordinates":[72.833992,18.950926],"type":"Point"}
}