{
  "type": "Feature",
  "properties": {
    "iso:country":"IN",
    "sg:address":"Gandhi Gate",
    "sg:city":"Amritsar",
    "sg:phone":"+91 183292275",
    "sg:postcode":"143001",
    "sg:province":"Punjab",
    "sg:website":"http://www.choprachess.com",
    "wof:name":"Girdhari Lal Chopra (agents) Pvt Ltd",
    "wof:placetype":"venue"
},
  "geometry": {"coordinates":[74.874168,31.631344],"type":"Point"}
}