{
  "type": "Feature",
  "properties": {
    "iso:country":"IN",
    "sg:address":"137, Peters Road, P.b. No.661, Royapettah,",
    "sg:city":"Chennai",
    "sg:classifiers":[
        {
            "category":"Manufacturing",
            "subcategory":"Rubber & Plastics",
            "type":"Manufacturing & Wholesale Goods"
        }
    ],
    "sg:phone":"+91 44 2431 2450",
    "sg:postcode":"600014",
    "sg:tags":[
        "product"
    ],
    "sg:website":"http://www.fennerindia.com/mhs.html",
    "wof:name":"Fenner India Ltd.",
    "wof:placetype":"venue"
},
  "geometry": {"coordinates":[80.265221,13.053772],"type":"Point"}
}