{
  "type": "Feature",
  "properties": {
    "iso:country":"IN",
    "sg:address":"S. N. Banerjee Road",
    "sg:city":"Kolkata",
    "sg:phone":"+91 33 2228 3839",
    "sg:postcode":"700013",
    "sg:province":"West Bengal",
    "wof:name":"Electrical Components Manufacturers",
    "wof:placetype":"venue"
},
  "geometry": {"coordinates":[88.362617,22.560434],"type":"Point"}
}