{
  "type": "Feature",
  "properties": {
    "iso:country":"IN",
    "sg:address":"14/15, Tardeo Air-condition Market, Tardeo Road,",
    "sg:city":"Mumbai",
    "sg:classifiers":[
        {
            "category":"Shopping",
            "subcategory":"Stationery & Office Supplies",
            "type":"Retail Goods"
        }
    ],
    "sg:phone":"+91 22 2352 3559",
    "sg:postcode":"400034",
    "sg:tags":[
        "calendar",
        "diary"
    ],
    "sg:website":"http://www.calendarsfromindia.com",
    "wof:name":"Arun Art Printers Pvt. Ltd.",
    "wof:placetype":"venue"
},
  "geometry": {"coordinates":[72.813889,18.973789],"type":"Point"}
}