{
  "type": "Feature",
  "properties": {
    "iso:country":"IN",
    "sg:address":"84, Bhajipala Street, 1st Flr.,",
    "sg:city":"Mumbai",
    "sg:classifiers":[
        {
            "category":"Wholesale",
            "subcategory":"Machinery & Supplies",
            "type":"Manufacturing & Wholesale Goods"
        }
    ],
    "sg:phone":"+91 22 2344 3832",
    "sg:postcode":"400003",
    "sg:tags":[
        "equipment",
        "goods",
        "electrical"
    ],
    "wof:name":"Freez-air Enterprise",
    "wof:placetype":"venue"
},
  "geometry": {"coordinates":[72.83345,18.950758],"type":"Point"}
}