{
  "type": "Feature",
  "properties": {
    "iso:country":"IN",
    "sg:address":"4th `t' Block, Jayanagar",
    "sg:city":"Bangalore",
    "sg:phone":"+91 806344513",
    "sg:postcode":"560041",
    "sg:province":"Karnataka",
    "sg:website":"http://www.cp-india.com",
    "wof:name":"Chicago Pneumatic India Ltd",
    "wof:placetype":"venue"
},
  "geometry": {"coordinates":[77.584511,12.927514],"type":"Point"}
}