{
  "type": "Feature",
  "properties": {
    "iso:country":"IN",
    "sg:address":"No 47, V.k.r. Thottam, B.s.s. Road,",
    "sg:city":"Tirupur",
    "sg:classifiers":[
        {
            "category":"Banks & Credit Unions",
            "subcategory":"Investment Brokerage",
            "type":"Services"
        }
    ],
    "sg:phone":"+91 421 222 4437",
    "sg:postcode":"641601",
    "sg:tags":[
        "underwear",
        "nightwear"
    ],
    "wof:name":"White Apple Buying Service",
    "wof:placetype":"venue"
},
  "geometry": {"coordinates":[80.220467,13.026856],"type":"Point"}
}