{
  "type": "Feature",
  "properties": {
    "iso:country":"IN",
    "sg:address":"Manali Industrial Area, Manali,",
    "sg:city":"Chennai",
    "sg:classifiers":[
        {
            "category":"Home & Garden",
            "subcategory":"Garden Supply",
            "type":"Retail Goods"
        }
    ],
    "sg:phone":"+91 44 2594 1001",
    "sg:postcode":"600068",
    "sg:tags":[
        "fertilizer"
    ],
    "sg:website":"http://www.madrasfert.nic.in",
    "wof:name":"Madras Fertilizers Ltd.",
    "wof:placetype":"venue"
},
  "geometry": {"coordinates":[77.188499,32.240002],"type":"Point"}
}