{
  "type": "Feature",
  "properties": {
    "iso:country":"IN",
    "sg:address":"Kalol",
    "sg:city":"Panchmahals",
    "sg:phone":"+91 267635312",
    "sg:postcode":"389330",
    "sg:province":"Gujarat",
    "sg:website":"http://www.bohmisindustries.cjb.net",
    "wof:name":"Bohmis Industries Ltd",
    "wof:placetype":"venue"
},
  "geometry": {"coordinates":[72.498177,23.244471],"type":"Point"}
}