{
  "type": "Feature",
  "properties": {
    "iso:country":"IN",
    "sg:address":"V.p. Road, No.361,",
    "sg:city":"Mumbai",
    "sg:classifiers":[
        {
            "category":"Autos & Motor Vehicles",
            "subcategory":"Auto Supplies",
            "type":"Retail Goods"
        }
    ],
    "sg:phone":"+91 22 2388 3832",
    "sg:postcode":"400004",
    "sg:tags":[
        "automobile",
        "accessory"
    ],
    "sg:website":"http://www.crankshaftengine.com",
    "wof:name":"Styr Exports",
    "wof:placetype":"venue"
},
  "geometry": {"coordinates":[74.45098900000001,17.290974],"type":"Point"}
}