{
  "type": "Feature",
  "properties": {
    "iso:country":"IN",
    "sg:address":"Plot No. 6209, G.i.d.c. Industrial Estate,",
    "sg:city":"Ankleshwar",
    "sg:classifiers":[
        {
            "category":"Home & Garden",
            "subcategory":"Mobile Homes",
            "type":"Retail Goods"
        }
    ],
    "sg:phone":"+91 2646 226 578",
    "sg:postcode":"393002",
    "sg:tags":[
        "acid"
    ],
    "wof:name":"Prayosha Health Care Pvt. Ltd.",
    "wof:placetype":"venue"
},
  "geometry": {"coordinates":[80.306335,26.455313],"type":"Point"}
}