{
  "type": "Feature",
  "properties": {
    "iso:country":"IN",
    "sg:address":"A 30, 3rd Stage, Peenya Ind. Area,",
    "sg:city":"Bangalore",
    "sg:classifiers":[
        {
            "category":"Personal",
            "subcategory":"Shoe Repair & Shine",
            "type":"Services"
        }
    ],
    "sg:phone":"+91 80 2836 2741",
    "sg:postcode":"560058",
    "sg:tags":[
        "polishing",
        "polish",
        "material/machinery"
    ],
    "sg:website":"http://www.grantools.com",
    "wof:name":"Grantools Pvt. Ltd.",
    "wof:placetype":"venue"
},
  "geometry": {"coordinates":[77.52253,13.030821],"type":"Point"}
}