{
  "type": "Feature",
  "properties": {
    "iso:country":"IN",
    "sg:address":"59, Sakinaka, Andheri Kurla Road,",
    "sg:city":"Mumbai",
    "sg:classifiers":[
        {
            "category":"Shopping",
            "subcategory":"Crafts & Fabrics",
            "type":"Retail Goods"
        }
    ],
    "sg:phone":"+91 22 2851 1688",
    "sg:postcode":"400072",
    "wof:name":"Malhotra Silk Mills",
    "wof:placetype":"venue"
},
  "geometry": {"coordinates":[72.882103,19.090277],"type":"Point"}
}