{
  "type": "Feature",
  "properties": {
    "iso:country":"IN",
    "sg:address":"K-18, Udyog Nagar Ind. Area, Main Rohtak Road,",
    "sg:city":"Delhi",
    "sg:classifiers":[
        {
            "category":"Manufacturing",
            "subcategory":"Chemicals & Compounds",
            "type":"Manufacturing & Wholesale Goods"
        }
    ],
    "sg:phone":"+91 11 2547 7462",
    "sg:postcode":"110041",
    "sg:tags":[
        "supply"
    ],
    "sg:website":"http://www.orvin.com",
    "wof:name":"Organo Vinyl Private Limited",
    "wof:placetype":"venue"
},
  "geometry": {"coordinates":[77.16997499999999,28.669174],"type":"Point"}
}