{
  "type": "Feature",
  "properties": {
    "iso:country":"IN",
    "sg:address":"D-1, Unity Building, J.c. Road,",
    "sg:city":"Bangalore",
    "sg:classifiers":[
        {
            "category":"Manufacturing",
            "subcategory":"Printing",
            "type":"Manufacturing & Wholesale Goods"
        }
    ],
    "sg:phone":"+91 80 2222 3765",
    "sg:postcode":"560002",
    "sg:tags":[
        "machinery"
    ],
    "sg:website":"http://www.hmcvmt.com",
    "wof:name":"Hindustan Machinery Corporation",
    "wof:placetype":"venue"
},
  "geometry": {"coordinates":[77.581696,12.957047],"type":"Point"}
}