{
  "type": "Feature",
  "properties": {
    "iso:country":"IN",
    "sg:address":"47, Second Line Beach,",
    "sg:city":"Chennai",
    "sg:classifiers":[
        {
            "category":"Manufacturing",
            "subcategory":"Chemicals & Compounds",
            "type":"Manufacturing & Wholesale Goods"
        }
    ],
    "sg:phone":"+91 44 2534 0147",
    "sg:postcode":"600001",
    "sg:tags":[
        "supply"
    ],
    "wof:name":"Keystone Chemicals",
    "wof:placetype":"venue"
},
  "geometry": {"coordinates":[80.290863,13.09232],"type":"Point"}
}