{
  "type": "Feature",
  "properties": {
    "iso:country":"IN",
    "sg:address":"S.n. Banerjee Road",
    "sg:city":"Kolkata",
    "sg:phone":"+91 33 2216 6265",
    "sg:postcode":"700014",
    "sg:province":"West Bengal",
    "wof:name":"Doyen Micro Systems Pvt Ltd",
    "wof:placetype":"venue"
},
  "geometry": {"coordinates":[88.362617,22.560434],"type":"Point"}
}