{
  "type": "Feature",
  "properties": {
    "iso:country":"IN",
    "sg:address":"8, B.r.b. Basu Road,",
    "sg:city":"Kolkata",
    "sg:classifiers":[
        {
            "category":"Manufacturing",
            "subcategory":"Chemicals & Compounds",
            "type":"Manufacturing & Wholesale Goods"
        }
    ],
    "sg:phone":"+91 33 2242 0437",
    "sg:postcode":"700001",
    "sg:tags":[
        "supply"
    ],
    "wof:name":"Mansarovar Industrial Products Pvt. Ltd.",
    "wof:placetype":"venue"
},
  "geometry": {"coordinates":[88.33747099999999,22.587643],"type":"Point"}
}