{
  "type": "Feature",
  "properties": {
    "iso:country":"IN",
    "sg:address":"25, Bungalow Road, Odakkadu,",
    "sg:city":"Tirupur",
    "sg:classifiers":[
        {
            "category":"Shopping",
            "subcategory":"Clothing, Apparel, & Fashions",
            "type":"Retail Goods"
        }
    ],
    "sg:phone":"+91 421 224 9298",
    "sg:postcode":"641603",
    "sg:tags":[
        "menswear"
    ],
    "sg:website":"http://www.eastmanexports.com",
    "wof:name":"Eastman Exports",
    "wof:placetype":"venue"
},
  "geometry": {"coordinates":[77.335037,11.112531],"type":"Point"}
}