{
  "type": "Feature",
  "properties": {
    "iso:country":"IN",
    "sg:address":"78-a, Industrial Estate, Charkop Kandivli (w),",
    "sg:city":"Mumbai",
    "sg:classifiers":[
        {
            "category":"Retail",
            "subcategory":"Self-service Laundry",
            "type":"Services"
        }
    ],
    "sg:phone":"+91 22 2868 6116",
    "sg:postcode":"400067",
    "sg:tags":[
        "good",
        "consumer"
    ],
    "wof:name":"Vijay Bangle Works",
    "wof:placetype":"venue"
},
  "geometry": {"coordinates":[72.82643899999999,19.20808],"type":"Point"}
}