{
  "type": "Feature",
  "properties": {
    "iso:country":"IN",
    "sg:address":"B/h, Sion Fort, Sion (east)",
    "sg:city":"Mumbai",
    "sg:phone":"+91 22 2408 3334",
    "sg:postcode":"400022",
    "sg:province":"Maharashtra",
    "sg:website":"http://www.nitindye.com",
    "wof:name":"Nitin Dye-chem Pvt Ltd",
    "wof:placetype":"venue"
},
  "geometry": {"coordinates":[72.867683,19.046047],"type":"Point"}
}