{
  "type": "Feature",
  "properties": {
    "iso:country":"IN",
    "sg:address":"17, Bazaria Street,",
    "sg:city":"Firozabad",
    "sg:classifiers":[
        {
            "category":"Home & Garden",
            "subcategory":"Mobile Homes",
            "type":"Retail Goods"
        }
    ],
    "sg:phone":"+91 5612 241 082",
    "sg:postcode":"283203",
    "sg:tags":[
        "acid"
    ],
    "wof:name":"Nannumal Radhakishan",
    "wof:placetype":"venue"
},
  "geometry": {"coordinates":[79.451797,25.99074],"type":"Point"}
}