{
  "type": "Feature",
  "properties": {
    "iso:country":"IN",
    "sg:address":"3rd Floor, Zaveri Bazar",
    "sg:city":"Mumbai",
    "sg:phone":"+91 22 2345 3430",
    "sg:postcode":"400002",
    "sg:province":"Maharashtra",
    "wof:name":"Moda Meta Chem Pvt Ltd",
    "wof:placetype":"venue"
},
  "geometry": {"coordinates":[72.830498,18.949505],"type":"Point"}
}