{
  "type": "Feature",
  "properties": {
    "iso:country":"IN",
    "sg:address":"42/44, V.v. Chandan Street, 1st Floor, Room No.7, Vadgadi, Masjid,",
    "sg:city":"Mumbai",
    "sg:classifiers":[
        {
            "category":"Home & Garden",
            "subcategory":"Mobile Homes",
            "type":"Retail Goods"
        }
    ],
    "sg:phone":"+91 22 2343 9866",
    "sg:postcode":"400003",
    "sg:tags":[
        "acid"
    ],
    "wof:name":"Sagar Corporation",
    "wof:placetype":"venue"
},
  "geometry": {"coordinates":[72.835594,18.951937],"type":"Point"}
}