{
  "type": "Feature",
  "properties": {
    "iso:country":"IN",
    "sg:address":"Dadi Seth Agiary Lane",
    "sg:city":"Mumbai",
    "sg:phone":"+91 22 2201 3089",
    "sg:postcode":"400002",
    "sg:province":"Maharashtra",
    "sg:website":"http://www.rolexaluminium.com",
    "wof:name":"Rolex Aluminium Pvt Ltd",
    "wof:placetype":"venue"
},
  "geometry": {"coordinates":[72.827141,18.950607],"type":"Point"}
}