{
  "type": "Feature",
  "properties": {
    "iso:country":"IN",
    "sg:address":"No.4, Epip, Whitefield,",
    "sg:city":"Bangalore",
    "sg:classifiers":[
        {
            "category":"Building & Trades",
            "subcategory":"Construction",
            "type":"Services"
        }
    ],
    "sg:phone":"+91 80 2841 2865",
    "sg:postcode":"560066",
    "sg:tags":[
        "valve"
    ],
    "sg:website":"http://www.flowserve.com",
    "wof:name":"Flowserve Controls India Ltd.",
    "wof:placetype":"venue"
},
  "geometry": {"coordinates":[77.72648599999999,12.989101],"type":"Point"}
}