{
  "type": "Feature",
  "properties": {
    "iso:country":"IN",
    "sg:address":"G-84, Sector-9,",
    "sg:city":"Noida",
    "sg:classifiers":[
        {
            "category":"Manufacturing",
            "subcategory":"Chemicals & Compounds",
            "type":"Manufacturing & Wholesale Goods"
        }
    ],
    "sg:phone":"+91 120 308 4470",
    "sg:postcode":"201301",
    "sg:tags":[
        "paint",
        "product",
        "allied"
    ],
    "wof:name":"Larson Paints",
    "wof:placetype":"venue"
},
  "geometry": {"coordinates":[77.001747,28.46213],"type":"Point"}
}