{
  "type": "Feature",
  "properties": {
    "iso:country":"IN",
    "sg:address":"C2, Sector 2 2nd FLoor",
    "sg:city":"Noida",
    "sg:classifiers":[
        {
            "category":"Professional",
            "subcategory":"Computer Services",
            "type":"Services"
        }
    ],
    "sg:postcode":"201301",
    "sg:tags":[
        "career",
        "jobs",
        "job-search",
        "company-reviews",
        "company-ratings",
        "salary-search",
        "salary-comparison",
        "salary-benchmarking"
    ],
    "sg:website":"http://www.talentequity.in",
    "wof:name":"TalentEquity Solutions",
    "wof:placetype":"venue"
},
  "geometry": {"coordinates":[77.31593,28.584688],"type":"Point"}
}