{
  "type": "Feature",
  "properties": {
    "iso:country":"IN",
    "sg:address":"4-1-165, Patnool Street,",
    "sg:city":"Tirupati",
    "sg:classifiers":[
        {
            "category":"Banks & Credit Unions",
            "subcategory":"Investment Brokerage",
            "type":"Services"
        }
    ],
    "sg:phone":"+91 877 228 6398",
    "sg:postcode":"517507",
    "sg:tags":[
        "thread"
    ],
    "wof:name":"S. S. Kasi Thread Makers",
    "wof:placetype":"venue"
},
  "geometry": {"coordinates":[80.206711,13.039026],"type":"Point"}
}