{
  "type": "Feature",
  "properties": {
    "iso:country":"IN",
    "sg:address":"E-1161, Phase-iv, Industrial Area,",
    "sg:city":"Bhiwadi",
    "sg:classifiers":[
        {
            "category":"Manufacturing",
            "subcategory":"Rubber & Plastics",
            "type":"Manufacturing & Wholesale Goods"
        }
    ],
    "sg:phone":"+91 1493 222 924",
    "sg:postcode":"301019",
    "sg:tags":[
        "product"
    ],
    "sg:website":"http://www.paragonauto.com",
    "wof:name":"Paragon Autotech Products Pvt. Ltd.",
    "wof:placetype":"venue"
},
  "geometry": {"coordinates":[77.17235599999999,28.699236],"type":"Point"}
}