{
  "type": "Feature",
  "properties": {
    "iso:country":"IN",
    "sg:address":"No. 70, 5th Cross, S.s.i. Area, Rajajinagar,",
    "sg:city":"Bangalore",
    "sg:classifiers":[
        {
            "category":"Bus Station",
            "type":"Transportation"
        }
    ],
    "sg:phone":"+91 80 2297 0010",
    "sg:postcode":"560010",
    "sg:tags":[
        "switch"
    ],
    "wof:name":"Paramount Industries",
    "wof:placetype":"venue"
},
  "geometry": {"coordinates":[77.540031,13.0098],"type":"Point"}
}