{
  "type": "Feature",
  "properties": {
    "iso:country":"IN",
    "sg:address":"A/26, Giriraj Indl. Estate, Mahakali Caves Road, Andheri East,",
    "sg:city":"Mumbai",
    "sg:classifiers":[
        {
            "category":"Manufacturing",
            "subcategory":"Chemicals & Compounds",
            "type":"Manufacturing & Wholesale Goods"
        }
    ],
    "sg:phone":"+91 22 2687 0260",
    "sg:postcode":"400093",
    "sg:tags":[
        "coatings-powder",
        "coating"
    ],
    "wof:name":"Shah Polymer Coats",
    "wof:placetype":"venue"
},
  "geometry": {"coordinates":[72.86294599999999,19.118551],"type":"Point"}
}