{
  "type": "Feature",
  "properties": {
    "iso:country":"IN",
    "sg:address":"B-50/15, Site Iv, Sahibabad Industrial Area,",
    "sg:city":"Ghaziabad",
    "sg:classifiers":[
        {
            "category":"Manufacturing",
            "subcategory":"Rubber & Plastics",
            "type":"Manufacturing & Wholesale Goods"
        }
    ],
    "sg:phone":"+91 11 2397 2614",
    "sg:postcode":"201010",
    "sg:tags":[
        "product"
    ],
    "sg:website":"http://www.autotractorparts.com",
    "wof:name":"India Automotives",
    "wof:placetype":"venue"
},
  "geometry": {"coordinates":[77.34105700000001,28.660917],"type":"Point"}
}