{
  "type": "Feature",
  "properties": {
    "iso:country":"IN",
    "sg:address":"350/1, Nayandahalli, Mysore Road,",
    "sg:city":"Bangalore",
    "sg:classifiers":[
        {
            "category":"Manufacturing",
            "subcategory":"Wood Products",
            "type":"Manufacturing & Wholesale Goods"
        }
    ],
    "sg:phone":"+91 80 2860 0696",
    "sg:postcode":"560039",
    "sg:tags":[
        "plank",
        "timber"
    ],
    "wof:name":"Poonam Timbers",
    "wof:placetype":"venue"
},
  "geometry": {"coordinates":[77.532799,12.947309],"type":"Point"}
}