{
  "type": "Feature",
  "properties": {
    "iso:country":"IN",
    "sg:address":"District Centre, Janakpuri",
    "sg:city":"New Delhi",
    "sg:phone":"+91 11 2555 6944",
    "sg:postcode":"110058",
    "sg:province":"Delhi",
    "sg:website":"http://www.muvtons.com",
    "wof:name":"Castor Corp",
    "wof:placetype":"venue"
},
  "geometry": {"coordinates":[77.080849,28.629389],"type":"Point"}
}