{
  "type": "Feature",
  "properties": {
    "iso:country":"IN",
    "sg:address":"Plot No.g-20/5, M.i.d.c.,",
    "sg:city":"Ahmednagar",
    "sg:classifiers":[
        {
            "category":"Home & Garden",
            "subcategory":"Mobile Homes",
            "type":"Retail Goods"
        }
    ],
    "sg:phone":"+91 241 277 9199",
    "sg:postcode":"414111",
    "sg:tags":[
        "acid"
    ],
    "sg:website":"http://www.estellechem.com",
    "wof:name":"Estelle Chemicals Pvt. Ltd.",
    "wof:placetype":"venue"
},
  "geometry": {"coordinates":[76.536209,9.057627],"type":"Point"}
}