{
  "type": "Feature",
  "properties": {
    "iso:country":"IN",
    "sg:address":"Kumara Prak East",
    "sg:city":"Bangalore",
    "sg:phone":"+91 802288210",
    "sg:postcode":"560001",
    "sg:province":"Karnataka",
    "sg:website":"http://www.deduco.com",
    "wof:name":"Deduco Software Systems (i) Pvt Ltd",
    "wof:placetype":"venue"
},
  "geometry": {"coordinates":[77.578423,12.99255],"type":"Point"}
}