{
  "type": "Feature",
  "properties": {
    "iso:country":"IN",
    "sg:address":"25, Mittal Chambers, Nariman Point,",
    "sg:city":"Mumbai",
    "sg:classifiers":[
        {
            "category":"Manufacturing",
            "subcategory":"Chemicals & Compounds",
            "type":"Manufacturing & Wholesale Goods"
        }
    ],
    "sg:phone":"+91 22 6752 5552",
    "sg:postcode":"400021",
    "sg:tags":[
        "supply"
    ],
    "sg:website":"http://www.marubeni.com",
    "wof:name":"Marubeni India Private Limited",
    "wof:placetype":"venue"
},
  "geometry": {"coordinates":[72.821991,18.926422],"type":"Point"}
}