{
  "type": "Feature",
  "properties": {
    "iso:country":"IN",
    "sg:address":"Plot No:444/2, Phase-4,",
    "sg:city":"V.u. Nagar",
    "sg:classifiers":[
        {
            "category":"Food & Beverages",
            "subcategory":"Liquor & Beverages",
            "type":"Retail Goods"
        }
    ],
    "sg:phone":"+91 26922236160",
    "sg:postcode":"388121",
    "wof:name":"Jal Beverates Pvt. Ltd.",
    "wof:placetype":"venue"
},
  "geometry": {"coordinates":[73.876091,18.477884],"type":"Point"}
}