{
  "type": "Feature",
  "properties": {
    "iso:country":"IN",
    "sg:address":"Lokhandwala Complex, Kandivali (east),",
    "sg:city":"Mumbai",
    "sg:classifiers":[
        {
            "category":"Real Estate",
            "subcategory":"Surveying",
            "type":"Services"
        }
    ],
    "sg:phone":"+91 22 2846 6185",
    "sg:postcode":"400101",
    "sg:tags":[
        "pharmaceutical",
        "material",
        "raw"
    ],
    "wof:name":"Krish Pharma",
    "wof:placetype":"venue"
},
  "geometry": {"coordinates":[72.87370300000001,19.198238],"type":"Point"}
}