{
  "type": "Feature",
  "properties": {
    "iso:country":"IN",
    "sg:address":"97g/5a, Teachers Colony,",
    "sg:city":"Tuticorin",
    "sg:classifiers":[
        {
            "category":"Transit Center",
            "subcategory":"Freight",
            "type":"Transportation"
        }
    ],
    "sg:phone":"+91 461 239 2084",
    "sg:postcode":"628008",
    "sg:tags":[
        "agent",
        "shipping"
    ],
    "wof:name":"K. S. Murugan Shipping",
    "wof:placetype":"venue"
},
  "geometry": {"coordinates":[81.08461,20.587545],"type":"Point"}
}