{
  "type": "Feature",
  "properties": {
    "iso:country":"IN",
    "sg:address":"266-b, Patel Road, Ramnagar,",
    "sg:city":"Coimbatore",
    "sg:classifiers":[
        {
            "category":"Manufacturing",
            "subcategory":"Chemicals & Compounds",
            "type":"Manufacturing & Wholesale Goods"
        }
    ],
    "sg:phone":"+91 422 537 8928",
    "sg:postcode":"641009",
    "sg:tags":[
        "coatings-powder",
        "coating"
    ],
    "sg:website":"http://www.finecoatsindia.com",
    "wof:name":"Fine Coats",
    "wof:placetype":"venue"
},
  "geometry": {"coordinates":[76.961136,11.009016],"type":"Point"}
}