{
  "type": "Feature",
  "properties": {
    "iso:country":"IN",
    "sg:address":"Plot No.c1/248/2, G.i.d.c.industrial Area,",
    "sg:city":"Umbergaon",
    "sg:orig_category":"Filters-air, Gas, Liquid",
    "sg:phone":"+91 260 256 5082",
    "sg:postcode":"396171",
    "sg:website":"http://www.pharmatekindia.com",
    "wof:name":"Pharmatek Filtration Systems Pvt. Ltd.",
    "wof:placetype":"venue"
},
  "geometry": {"coordinates":[77.336746,28.68775],"type":"Point"}
}