{
  "type": "Feature",
  "properties": {
    "iso:country":"IN",
    "sg:address":"117/603, Pandu Nagar,",
    "sg:city":"Kanpur",
    "sg:classifiers":[
        {
            "category":"Shopping",
            "subcategory":"Crafts & Fabrics",
            "type":"Retail Goods"
        }
    ],
    "sg:phone":"+91 512 269 1634",
    "sg:postcode":"208005",
    "sg:tags":[
        "pigment"
    ],
    "wof:name":"Sriyam Pigments (p) Ltd.",
    "wof:placetype":"venue"
},
  "geometry": {"coordinates":[77.151749,28.651129],"type":"Point"}
}