{
  "type": "Feature",
  "properties": {
    "iso:country":"IN",
    "sg:address":"23 Sripuram,",
    "sg:city":"Tirunelveli",
    "sg:classifiers":[
        {
            "category":"Food & Beverages",
            "subcategory":"Fruits & Vegetables",
            "type":"Retail Goods"
        }
    ],
    "sg:phone":"+91 462 233 5503",
    "sg:postcode":"627001",
    "sg:tags":[
        "dried"
    ],
    "sg:website":"http://www.indiamart.com/tristarr/",
    "wof:name":"Tristarr Hortitech",
    "wof:placetype":"venue"
},
  "geometry": {"coordinates":[79.08841700000001,12.873267],"type":"Point"}
}