{
  "type": "Feature",
  "properties": {
    "iso:country":"IN",
    "sg:address":"65/73, C.p. Tank Road,",
    "sg:city":"Mumbai",
    "sg:classifiers":[
        {
            "category":"Real Estate",
            "subcategory":"Real Estate Agent",
            "type":"Services"
        }
    ],
    "sg:phone":"+91 22 2242 1388",
    "sg:postcode":"400004",
    "sg:tags":[
        "distributor"
    ],
    "wof:name":"Ramani Steel House",
    "wof:placetype":"venue"
},
  "geometry": {"coordinates":[72.827209,18.955893],"type":"Point"}
}