{
  "type": "Feature",
  "properties": {
    "iso:country":"IN",
    "sg:address":"C-5-8, Sector-57,",
    "sg:city":"Noida",
    "sg:classifiers":[
        {
            "category":"Home & Garden",
            "subcategory":"Building Materials",
            "type":"Retail Goods"
        }
    ],
    "sg:phone":"+91 120 258 1230",
    "sg:postcode":"201301",
    "sg:tags":[
        "sealant",
        "adhesive"
    ],
    "wof:name":"Fcl Technologies And Products Ltd.",
    "wof:placetype":"venue"
},
  "geometry": {"coordinates":[76.71489,30.73423],"type":"Point"}
}