{
  "type": "Feature",
  "properties": {
    "iso:country":"IN",
    "sg:address":"1652, 16 A Main, 8th Cross, Jp Nagar, 2nd Phase,",
    "sg:city":"Bangalore",
    "sg:classifiers":[
        {
            "category":"Manufacturing",
            "subcategory":"Rubber & Plastics",
            "type":"Manufacturing & Wholesale Goods"
        }
    ],
    "sg:phone":"+91 80 2658 8881",
    "sg:postcode":"560078",
    "sg:tags":[
        "product"
    ],
    "wof:name":"Omega Exim",
    "wof:placetype":"venue"
},
  "geometry": {"coordinates":[77.607758,12.913362],"type":"Point"}
}