{
  "type": "Feature",
  "properties": {
    "iso:country":"IN",
    "sg:address":"43, Ramaiah Colony,",
    "sg:city":"Tirupur",
    "sg:classifiers":[
        {
            "category":"Shopping",
            "subcategory":"Clothing, Apparel, & Fashions",
            "type":"Retail Goods"
        }
    ],
    "sg:phone":"+91 421 242 0442",
    "sg:postcode":"641602",
    "sg:tags":[
        "menswear"
    ],
    "wof:name":"Pandit Hosiery Mills",
    "wof:placetype":"venue"
},
  "geometry": {"coordinates":[77.336945,11.116403],"type":"Point"}
}