{
  "type": "Feature",
  "properties": {
    "iso:country":"IN",
    "sg:address":"R.t.nagar, 2nd Block",
    "sg:city":"Bangalore",
    "sg:phone":"+91 803533974",
    "sg:postcode":"560032",
    "sg:province":"Karnataka",
    "wof:name":"Triumph Research & Holdings Pvt Ltd",
    "wof:placetype":"venue"
},
  "geometry": {"coordinates":[77.640007,13.023782],"type":"Point"}
}