{
  "type": "Feature",
  "properties": {
    "iso:country":"IN",
    "sg:address":"322, T.v. Industrial Estate, S.k. Ahire Marg, Worli,",
    "sg:city":"Mumbai",
    "sg:classifiers":[
        {
            "category":"Manufacturing",
            "subcategory":"Chemicals & Compounds",
            "type":"Manufacturing & Wholesale Goods"
        }
    ],
    "sg:phone":"+91 22 2493 4855",
    "sg:postcode":"400025",
    "sg:tags":[
        "paint",
        "product",
        "allied"
    ],
    "sg:website":"http://www.morsum.net",
    "wof:name":"Morsun Coating Systems",
    "wof:placetype":"venue"
},
  "geometry": {"coordinates":[72.82079299999999,19.008354],"type":"Point"}
}