{
  "type": "Feature",
  "properties": {
    "iso:country":"IN",
    "sg:address":"Shop No. 1, Raj Lok, Ovari Pada, Dahisar (e),",
    "sg:city":"Mumbai",
    "sg:classifiers":[
        {
            "category":"Professional",
            "subcategory":"Detective & Security Services",
            "type":"Services"
        }
    ],
    "sg:phone":"+91 22 5602 9955",
    "sg:tags":[
        "alarm"
    ],
    "wof:name":"Fire Protection Systems",
    "wof:placetype":"venue"
},
  "geometry": {"coordinates":[72.848595,19.257641],"type":"Point"}
}