{
  "type": "Feature",
  "properties": {
    "iso:country":"IN",
    "sg:address":"D-430, 2nd Stage, 1 Peenya Industrial Estate,",
    "sg:city":"Bangalore",
    "sg:classifiers":[
        {
            "category":"Wholesale",
            "subcategory":"Electrical",
            "type":"Manufacturing & Wholesale Goods"
        }
    ],
    "sg:phone":"+91 80 2836 0760",
    "sg:postcode":"560058",
    "sg:tags":[
        "voltage",
        "stabilizer"
    ],
    "wof:name":"Aarpee Electronics",
    "wof:placetype":"venue"
},
  "geometry": {"coordinates":[77.539055,13.01035],"type":"Point"}
}