{
  "type": "Feature",
  "properties": {
    "iso:country":"IN",
    "sg:address":"Plot No. 47, Sector 27a,",
    "sg:city":"Faridabad",
    "sg:classifiers":[
        {
            "category":"Food & Beverages",
            "subcategory":"Specialty",
            "type":"Retail Goods"
        }
    ],
    "sg:phone":"+91 129 227 7877",
    "sg:postcode":"121003",
    "sg:tags":[
        "solvent"
    ],
    "wof:name":"Plaza Paints (p) Ltd.",
    "wof:placetype":"venue"
},
  "geometry": {"coordinates":[77.091698,28.465778],"type":"Point"}
}