{
  "type": "Feature",
  "properties": {
    "iso:country":"IN",
    "sg:address":"Plot No. 83 & 84, Road # 2 Banjara Hills",
    "sg:city":"Hyderabad",
    "sg:classifiers":[
        {
            "category":"Professional",
            "subcategory":"Computer Services",
            "type":"Services"
        }
    ],
    "sg:postcode":"500034",
    "sg:tags":[
        "software-testing",
        "quality-management",
        "quailty-assurance",
        "third-party-validation",
        "independent-testing-services",
        "software-testing-services"
    ],
    "sg:website":"http://www.applabs.com/",
    "wof:name":"AppLabs",
    "wof:placetype":"venue"
},
  "geometry": {"coordinates":[4.769483,44.667237],"type":"Point"}
}