{
  "type": "Feature",
  "properties": {
    "iso:country":"IN",
    "sg:address":"46, Veer Nariman Road,",
    "sg:city":"Mumbai",
    "sg:classifiers":[
        {
            "category":"Transit Center",
            "subcategory":"Freight",
            "type":"Transportation"
        }
    ],
    "sg:phone":"+91 22 6617 1819",
    "sg:postcode":"400001",
    "sg:tags":[
        "clearing",
        "forwarding",
        "agent"
    ],
    "sg:website":"http://www.tkpl.in",
    "wof:name":"Tulsidas Khimji Pvt. Ltd.",
    "wof:placetype":"venue"
},
  "geometry": {"coordinates":[72.827652,18.933075],"type":"Point"}
}