{
  "type": "Feature",
  "properties": {
    "iso:country":"IN",
    "sg:address":"Kirti Nagar",
    "sg:city":"New Delhi",
    "sg:phone":"+91 11 2545 8918",
    "sg:postcode":"110015",
    "sg:province":"Delhi",
    "wof:name":"Gaurav Impex",
    "wof:placetype":"venue"
},
  "geometry": {"coordinates":[77.145638,28.653767],"type":"Point"}
}