{
  "type": "Feature",
  "properties": {
    "iso:country":"IN",
    "sg:address":"1402/03, Raheja Centre, Nariman Point,",
    "sg:city":"Mumbai",
    "sg:classifiers":[
        {
            "category":"Utilities",
            "subcategory":"Cable",
            "type":"Services"
        }
    ],
    "sg:phone":"+91 22 2282 0240",
    "sg:postcode":"400021",
    "sg:tags":[
        "cables/cable",
        "conductor",
        "accessory"
    ],
    "sg:website":"http://www.smitaconductors.com",
    "wof:name":"Smita Conductors Limited",
    "wof:placetype":"venue"
},
  "geometry": {"coordinates":[72.823425,18.923597],"type":"Point"}
}