{
  "type": "Feature",
  "properties": {
    "iso:country":"IN",
    "sg:address":"365, 15th Cross, Mahalakshmipuram,",
    "sg:city":"Bangalore",
    "sg:classifiers":[
        {
            "category":"Personal",
            "subcategory":"Skin Care",
            "type":"Services"
        }
    ],
    "sg:phone":"+91 80 56 982417",
    "sg:postcode":"560086",
    "wof:name":"Arun Kannur",
    "wof:placetype":"venue"
},
  "geometry": {"coordinates":[77.571251,13.005418],"type":"Point"}
}