{
  "type": "Feature",
  "properties": {
    "iso:country":"IN",
    "sg:address":"203, M.b.c., 2nd Floor, 134, Infantry Road,",
    "sg:city":"Bangalore",
    "sg:classifiers":[
        {
            "category":"Banks & Credit Unions",
            "subcategory":"Atm",
            "type":"Services"
        }
    ],
    "sg:phone":"+91 80 2286 4956",
    "sg:postcode":"560001",
    "sg:tags":[
        "product",
        "allied",
        "switchgear"
    ],
    "sg:website":"http://www.cecoelectronics.co.in",
    "wof:name":"Ceco Electronics Pvt. Ltd.",
    "wof:placetype":"venue"
},
  "geometry": {"coordinates":[77.602112,12.980972],"type":"Point"}
}