{
  "type": "Feature",
  "properties": {
    "iso:country":"IN",
    "sg:address":"336, V.p. Road, Near Imperial Cenima,",
    "sg:city":"Mumbai",
    "sg:classifiers":[
        {
            "category":"Manufacturing",
            "subcategory":"Motor Vehicles & Parts",
            "type":"Manufacturing & Wholesale Goods"
        }
    ],
    "sg:phone":"+91 22 2382 1955",
    "sg:postcode":"400004",
    "sg:tags":[
        "auto"
    ],
    "wof:name":"Standard Inc. Exports",
    "wof:placetype":"venue"
},
  "geometry": {"coordinates":[77.210854,28.641275],"type":"Point"}
}