{
  "type": "Feature",
  "properties": {
    "iso:country":"IN",
    "sg:address":"5, Yusuf Bldg., 9, Abdul Rehman Street,",
    "sg:city":"Mumbai",
    "sg:classifiers":[
        {
            "category":"Shopping",
            "subcategory":"Crafts & Fabrics",
            "type":"Retail Goods"
        }
    ],
    "sg:phone":"+91 22 2343 3165",
    "sg:postcode":"400003",
    "wof:name":"Manco Wire Products",
    "wof:placetype":"venue"
},
  "geometry": {"coordinates":[72.832268,18.952494],"type":"Point"}
}