{
  "type": "Feature",
  "properties": {
    "iso:country":"IN",
    "sg:address":"Mithakhali Six Roads, Navrangpura",
    "sg:city":"Ahmedabad",
    "sg:phone":"+91 796421205",
    "sg:postcode":"380009",
    "sg:province":"Gujarat",
    "wof:name":"Charms Industries Ltd",
    "wof:placetype":"venue"
},
  "geometry": {"coordinates":[72.563896,23.039509],"type":"Point"}
}