{
  "type": "Feature",
  "properties": {
    "iso:country":"IN",
    "sg:address":"KPHB",
    "sg:city":"Hyderabad",
    "sg:classifiers":[
        {
            "category":"Professional",
            "subcategory":"Advertising",
            "type":"Services"
        }
    ],
    "sg:postcode":"500072",
    "sg:tags":[
        "trizeon",
        "seo",
        "search-engine-optimization",
        "search-engine-optimisation",
        "seo-services",
        "organic-seo",
        "top-seo-sites",
        "seo-experts",
        "seo-tips",
        "seo-company",
        "business-consulting-services",
        "outsourcing-in-india",
        "business-consulting",
        "it-consulting",
        "bpo",
        "software-servi"
    ],
    "sg:website":"http://www.trizeon.com",
    "wof:name":"Trizeon",
    "wof:placetype":"venue"
},
  "geometry": {"coordinates":[78.389911,17.498081],"type":"Point"}
}