{
  "type": "Feature",
  "properties": {
    "iso:country":"IN",
    "sg:address":"Monteth Road, 1st Floor, Egmore",
    "sg:city":"Chennai",
    "sg:phone":"+91 44 2855 3656",
    "sg:postcode":"600008",
    "sg:province":"Tamil Nadu",
    "wof:name":"Air Travel Enterprises India Ltd",
    "wof:placetype":"venue"
},
  "geometry": {"coordinates":[80.25939200000001,13.068261],"type":"Point"}
}