{
  "type": "Feature",
  "properties": {
    "iso:country":"IN",
    "sg:address":"C-385, Industrial Estate, Gokul Road,",
    "sg:city":"Hubli",
    "sg:classifiers":[
        {
            "category":"Manufacturing",
            "subcategory":"Rubber & Plastics",
            "type":"Manufacturing & Wholesale Goods"
        }
    ],
    "sg:phone":"+91 836 233 0072",
    "sg:postcode":"580030",
    "sg:tags":[
        "product"
    ],
    "wof:name":"Sona Industrial Elastomers",
    "wof:placetype":"venue"
},
  "geometry": {"coordinates":[75.116394,15.350564],"type":"Point"}
}