{
  "type": "Feature",
  "properties": {
    "iso:country":"IN",
    "sg:address":"D/220, Ansa Industrial Estate, Sakinaka,",
    "sg:city":"Mumbai",
    "sg:classifiers":[
        {
            "category":"Shopping",
            "subcategory":"Computers & Home Electronics",
            "type":"Retail Goods"
        }
    ],
    "sg:phone":"+91 22 2852 4847",
    "sg:postcode":"400072",
    "sg:tags":[
        "electronic",
        "consumer"
    ],
    "sg:website":"http://www.deurobroadcast.com",
    "wof:name":"Deuro Electronic System Pvt. Ltd.",
    "wof:placetype":"venue"
},
  "geometry": {"coordinates":[72.88884,19.109495],"type":"Point"}
}