{
  "type": "Feature",
  "properties": {
    "iso:country":"IN",
    "sg:address":"3, C.r. Avenue, 3rd Floor,",
    "sg:city":"Kolkata",
    "sg:classifiers":[
        {
            "category":"Manufacturing",
            "subcategory":"Chemicals & Compounds",
            "type":"Manufacturing & Wholesale Goods"
        }
    ],
    "sg:phone":"+91 33 2234 8170",
    "sg:postcode":"700072",
    "sg:tags":[
        "supply"
    ],
    "sg:website":"http://www.olivetreetrading.org",
    "wof:name":"Olive Tree Trading Pvt. Ltd.",
    "wof:placetype":"venue"
},
  "geometry": {"coordinates":[80.218277,13.090413],"type":"Point"}
}