{
  "type": "Feature",
  "properties": {
    "iso:country":"IN",
    "sg:address":"Opp D57 South Ext Part 1",
    "sg:city":"New Delhi",
    "sg:phone":"+91 11 5164 6101",
    "sg:postcode":"110003",
    "sg:province":"Delhi",
    "sg:website":"http://www.indiamart.com/activecontrols",
    "wof:name":"Active Controls",
    "wof:placetype":"venue"
},
  "geometry": {"coordinates":[77.221832,28.573606],"type":"Point"}
}