{
  "type": "Feature",
  "properties": {
    "iso:country":"IN",
    "sg:address":"A-39, Sector-10,",
    "sg:city":"Noida",
    "sg:classifiers":[
        {
            "category":"Manufacturing",
            "subcategory":"Rubber & Plastics",
            "type":"Manufacturing & Wholesale Goods"
        }
    ],
    "sg:phone":"+91 120 252 5990",
    "sg:postcode":"201301",
    "sg:tags":[
        "product"
    ],
    "wof:name":"Knietic Rolls Private Limited",
    "wof:placetype":"venue"
},
  "geometry": {"coordinates":[81.331688,21.183992],"type":"Point"}
}