{
  "type": "Feature",
  "properties": {
    "iso:country":"IN",
    "sg:address":"64, Chruch Street, Camp,",
    "sg:city":"Belgaum",
    "sg:classifiers":[
        {
            "category":"Manufacturing",
            "subcategory":"Rubber & Plastics",
            "type":"Manufacturing & Wholesale Goods"
        }
    ],
    "sg:phone":"+91 831 553 1685",
    "sg:postcode":"590001",
    "sg:tags":[
        "product"
    ],
    "wof:name":"Maashu Enterprises",
    "wof:placetype":"venue"
},
  "geometry": {"coordinates":[74.504387,15.856154],"type":"Point"}
}