{
  "type": "Feature",
  "properties": {
    "iso:country":"IN",
    "sg:address":"51, New Marketyard,",
    "sg:city":"Unjha",
    "sg:classifiers":[
        {
            "category":"Professional",
            "subcategory":"Credit Reporting & Collection",
            "type":"Services"
        }
    ],
    "sg:phone":"+91 2767 252 452",
    "sg:postcode":"384170",
    "sg:tags":[
        "seasoning",
        "spice"
    ],
    "sg:website":"http://www.bg.com",
    "wof:name":"Babulal Govindbhai Patel",
    "wof:placetype":"venue"
},
  "geometry": {"coordinates":[73.857254,18.480635],"type":"Point"}
}