{
  "type": "Feature",
  "properties": {
    "iso:country":"IN",
    "sg:address":"221 Nariman Point",
    "sg:city":"Mumbai",
    "sg:phone":"+91 22 2202 4818",
    "sg:postcode":"400021",
    "sg:province":"Maharashtra",
    "wof:name":"Air France",
    "wof:placetype":"venue"
},
  "geometry": {"coordinates":[72.824219,18.925573],"type":"Point"}
}