{
  "type": "Feature",
  "properties": {
    "iso:country":"IN",
    "sg:address":"Maker Chambers No. V/711, Nariman Point,",
    "sg:city":"Mumbai",
    "sg:classifiers":[
        {
            "category":"Professional",
            "subcategory":"Engineering",
            "type":"Services"
        }
    ],
    "sg:phone":"+91 22 2284 1773",
    "sg:postcode":"400021",
    "sg:tags":[
        "equipment",
        "good"
    ],
    "wof:name":"Sherman Intl.",
    "wof:placetype":"venue"
},
  "geometry": {"coordinates":[72.822289,18.923733],"type":"Point"}
}