{
  "type": "Feature",
  "properties": {
    "iso:country":"IN",
    "sg:address":"No.18 Uma Nagar,",
    "sg:city":"Thanjavur",
    "sg:orig_category":"Grain",
    "sg:phone":"+91 4362 233 324",
    "sg:postcode":"613007",
    "wof:name":"Indswami",
    "wof:placetype":"venue"
},
  "geometry": {"coordinates":[80.239784,13.032598],"type":"Point"}
}