{
  "type": "Feature",
  "properties": {
    "iso:country":"IN",
    "sg:address":"21, 2nd Bhatwadi, Girgaum Road,",
    "sg:city":"Mumbai",
    "sg:classifiers":[
        {
            "category":"Manufacturing",
            "subcategory":"Rubber & Plastics",
            "type":"Manufacturing & Wholesale Goods"
        }
    ],
    "sg:phone":"+91 22 6504 7817",
    "sg:postcode":"400004",
    "sg:tags":[
        "product"
    ],
    "sg:website":"http://www.dhwani-impex.com",
    "wof:name":"Dhwani Impex",
    "wof:placetype":"venue"
},
  "geometry": {"coordinates":[72.817665,18.956108],"type":"Point"}
}