{
  "type": "Feature",
  "properties": {
    "iso:country":"IN",
    "sg:address":"63, K. H. Road, B-27,",
    "sg:city":"Bangalore",
    "sg:classifiers":[
        {
            "category":"Government",
            "subcategory":"Fire Station",
            "type":"Public Place"
        }
    ],
    "sg:phone":"+91 80 4114 2666",
    "sg:postcode":"560027",
    "sg:tags":[
        "steel",
        "stainless",
        "product",
        "component"
    ],
    "sg:website":"http://www.stainlesstyle.com",
    "wof:name":"Stainless Style",
    "wof:placetype":"venue"
},
  "geometry": {"coordinates":[72.641022,23.245497],"type":"Point"}
}