{
  "type": "Feature",
  "properties": {
    "iso:country":"IN",
    "sg:address":"Banjarahills Road No 3",
    "sg:city":"Hyderabad",
    "sg:classifiers":[
        {
            "category":"Professional",
            "subcategory":"Computer Services",
            "type":"Services"
        }
    ],
    "sg:postcode":"500034",
    "sg:tags":[
        "yupptv",
        "live-tv",
        "online-tv",
        "internet-television"
    ],
    "sg:website":"http://www.yupptv.com",
    "wof:name":"YUPPTV",
    "wof:placetype":"venue"
},
  "geometry": {"coordinates":[78.434422,17.415429],"type":"Point"}
}