{
  "type": "Feature",
  "properties": {
    "iso:country":"IN",
    "sg:address":"Opp. G.e.b. Office, Bunder Road,",
    "sg:city":"Mandvi",
    "sg:classifiers":[
        {
            "category":"Manufacturing",
            "subcategory":"Chemicals & Compounds",
            "type":"Manufacturing & Wholesale Goods"
        }
    ],
    "sg:postcode":"370465",
    "sg:tags":[
        "salt"
    ],
    "sg:website":"http://www.siddharthminerals.com",
    "wof:name":"Siddharth Minerals",
    "wof:placetype":"venue"
},
  "geometry": {"coordinates":[70.92411,20.711803],"type":"Point"}
}