{
  "type": "Feature",
  "properties": {
    "iso:country":"IN",
    "sg:address":"Rajouri Garden",
    "sg:city":"New Delhi",
    "sg:phone":"+91 11 2512 2200",
    "sg:postcode":"110058",
    "sg:province":"Delhi",
    "sg:website":"http://www.rdoverseas.com",
    "wof:name":"Rajatdeep Overseas Pvt Ltd",
    "wof:placetype":"venue"
},
  "geometry": {"coordinates":[77.12119300000001,28.641386],"type":"Point"}
}