{
  "type": "Feature",
  "properties": {
    "iso:country":"IN",
    "sg:address":"N-37, Greater Kailash, Part-1,",
    "sg:city":"New Delhi",
    "sg:classifiers":[
        {
            "category":"Manufacturing",
            "subcategory":"Chemicals & Compounds",
            "type":"Manufacturing & Wholesale Goods"
        }
    ],
    "sg:phone":"+91 11 2923 2907",
    "sg:postcode":"110048",
    "sg:tags":[
        "resin"
    ],
    "sg:website":"http://www.victoragencies.com",
    "wof:name":"Victor Agencies Limited",
    "wof:placetype":"venue"
},
  "geometry": {"coordinates":[77.23764,28.547859],"type":"Point"}
}