{
  "type": "Feature",
  "properties": {
    "iso:country":"IN",
    "sg:address":"D-397, Midc, Ttc Area, Village Kukshet, Dist. Thane,",
    "sg:city":"Navi Mumbai",
    "sg:classifiers":[
        {
            "category":"Utilities",
            "subcategory":"Natural Gas",
            "type":"Services"
        }
    ],
    "sg:phone":"+91 22 3008 6937",
    "sg:tags":[
        "industrial"
    ],
    "sg:website":"http://www.vadilalgases.com",
    "wof:name":"Vadilal Chemicals Ltd.",
    "wof:placetype":"venue"
},
  "geometry": {"coordinates":[72.967178,19.23184],"type":"Point"}
}