{
  "type": "Feature",
  "properties": {
    "iso:country":"IN",
    "sg:address":"Park Street, Appejay House",
    "sg:city":"Kolkata",
    "sg:phone":"+91 3322295455014",
    "sg:postcode":"700016",
    "sg:province":"West Bengal",
    "wof:name":"Aft Industries Ltd",
    "wof:placetype":"venue"
},
  "geometry": {"coordinates":[88.351753,22.554607],"type":"Point"}
}