{
  "type": "Feature",
  "properties": {
    "iso:country":"IN",
    "sg:address":"17, Manindra Mitra Row, 2nd Floor,",
    "sg:city":"Kolkata",
    "sg:classifiers":[
        {
            "category":"Manufacturing",
            "subcategory":"Chemicals & Compounds",
            "type":"Manufacturing & Wholesale Goods"
        }
    ],
    "sg:phone":"+91 33 2351 7508",
    "sg:postcode":"700009",
    "sg:tags":[
        "supply"
    ],
    "wof:name":"S. R. International",
    "wof:placetype":"venue"
},
  "geometry": {"coordinates":[88.390274,22.608673],"type":"Point"}
}