{
  "type": "Feature",
  "properties": {
    "iso:country":"IN",
    "sg:address":"901, Maker Chambers 5, Nariman Point,",
    "sg:city":"Mumbai",
    "sg:classifiers":[
        {
            "category":"Wholesale",
            "subcategory":"Machinery & Supplies",
            "type":"Manufacturing & Wholesale Goods"
        }
    ],
    "sg:phone":"+91 22 2204 1183",
    "sg:postcode":"400021",
    "sg:tags":[
        "equipment",
        "goods",
        "electrical"
    ],
    "sg:website":"http://www.trafo.com",
    "wof:name":"General Data P. Ltd.",
    "wof:placetype":"venue"
},
  "geometry": {"coordinates":[72.822777,18.92416],"type":"Point"}
}