{
  "type": "Feature",
  "properties": {
    "iso:country":"IN",
    "sg:address":"2n-72, Bunglow, Plot , N.i.t.,",
    "sg:city":"Faridabad",
    "sg:classifiers":[
        {
            "category":"Manufacturing",
            "subcategory":"Rubber & Plastics",
            "type":"Manufacturing & Wholesale Goods"
        }
    ],
    "sg:phone":"+91 129 242 4385",
    "sg:postcode":"121001",
    "sg:tags":[
        "product"
    ],
    "wof:name":"Durga Enterprises",
    "wof:placetype":"venue"
},
  "geometry": {"coordinates":[74.461838,16.686392],"type":"Point"}
}