{
  "type": "Feature",
  "properties": {
    "iso:country":"IN",
    "sg:address":"A-18, G.t. Karnal Road, Industrial Area,",
    "sg:city":"Delhi",
    "sg:classifiers":[
        {
            "category":"Manufacturing",
            "subcategory":"Rubber & Plastics",
            "type":"Manufacturing & Wholesale Goods"
        }
    ],
    "sg:phone":"+91 11 2712 7238",
    "sg:postcode":"110033",
    "sg:tags":[
        "product"
    ],
    "sg:website":"http://www.famcom-india.com",
    "wof:name":"Farm Manufacturing Company",
    "wof:placetype":"venue"
},
  "geometry": {"coordinates":[77.181641,28.707069],"type":"Point"}
}