{
  "type": "Feature",
  "properties": {
    "iso:country":"IN",
    "sg:address":"1st Floor, 12, Richmond Road",
    "sg:city":"Bangalore",
    "sg:phone":"+91 802121710",
    "sg:postcode":"560025",
    "sg:province":"Karnataka",
    "sg:website":"http://www.hiscoindia.com",
    "wof:name":"Hisco Ltd",
    "wof:placetype":"venue"
},
  "geometry": {"coordinates":[77.605919,12.966026],"type":"Point"}
}