{
  "type": "Feature",
  "properties": {
    "iso:country":"IN",
    "sg:address":"25, Sindhi Colony, 3rd Floor, J.c. Road,",
    "sg:city":"Bangalore",
    "sg:classifiers":[
        {
            "category":"Manufacturing",
            "subcategory":"Chemicals & Compounds",
            "type":"Manufacturing & Wholesale Goods"
        }
    ],
    "sg:phone":"+91 80 2224 1994",
    "sg:postcode":"560002",
    "sg:tags":[
        "industrial"
    ],
    "wof:name":"Karavali Build-chem Pvt. Ltd.",
    "wof:placetype":"venue"
},
  "geometry": {"coordinates":[78.483009,17.440193],"type":"Point"}
}