{
  "type": "Feature",
  "properties": {
    "iso:country":"IN",
    "sg:address":"A-48, Sector-10,",
    "sg:city":"Noida",
    "sg:classifiers":[
        {
            "category":"Manufacturing",
            "subcategory":"Chemicals & Compounds",
            "type":"Manufacturing & Wholesale Goods"
        }
    ],
    "sg:phone":"+91 120 252 3005",
    "sg:postcode":"201301",
    "sg:tags":[
        "paint",
        "product",
        "allied"
    ],
    "sg:website":"http://www.opalpaints.com",
    "wof:name":"Opal Paints Products Pvt. Ltd.",
    "wof:placetype":"venue"
},
  "geometry": {"coordinates":[81.331688,21.183992],"type":"Point"}
}