{
  "type": "Feature",
  "properties": {
    "iso:country":"IN",
    "sg:address":"340/42, Samuel Street, 4th Floor,",
    "sg:city":"Mumbai",
    "sg:classifiers":[
        {
            "category":"Manufacturing",
            "subcategory":"Chemicals & Compounds",
            "type":"Manufacturing & Wholesale Goods"
        }
    ],
    "sg:phone":"+91 22 5631 2644",
    "sg:postcode":"400003",
    "sg:tags":[
        "industrial"
    ],
    "wof:name":"Trichem Laboratories (bombay) Pvt. Ltd.",
    "wof:placetype":"venue"
},
  "geometry": {"coordinates":[72.836662,18.951439],"type":"Point"}
}