{
  "type": "Feature",
  "properties": {
    "iso:country":"IN",
    "sg:address":"8, Harber View, 3rd Floor, 22, Colaba,",
    "sg:city":"Mumbai",
    "sg:orig_category":"Carpets - Hand Tufted",
    "sg:phone":"+91 22 2283 2410",
    "sg:postcode":"400001",
    "sg:website":"http://www.carpetsindia.net",
    "wof:name":"I. H. C. Overseas",
    "wof:placetype":"venue"
},
  "geometry": {"coordinates":[72.831902,18.918819],"type":"Point"}
}