{
  "type": "Feature",
  "properties": {
    "iso:country":"IN",
    "sg:address":"8, Civic Centre,",
    "sg:city":"Bhilai",
    "sg:classifiers":[
        {
            "category":"Manufacturing",
            "subcategory":"Chemicals & Compounds",
            "type":"Manufacturing & Wholesale Goods"
        }
    ],
    "sg:phone":"+91 788 226 1503",
    "sg:postcode":"490006",
    "sg:tags":[
        "supply"
    ],
    "wof:name":"Bhilai Cement",
    "wof:placetype":"venue"
},
  "geometry": {"coordinates":[81.343719,21.186457],"type":"Point"}
}