{
  "type": "Feature",
  "properties": {
    "iso:country":"IN",
    "sg:address":"43, 2nd Floor, Unity House, Abids,",
    "sg:city":"Hyderabad",
    "sg:classifiers":[
        {
            "category":"Manufacturing",
            "subcategory":"Chemicals & Compounds",
            "type":"Manufacturing & Wholesale Goods"
        }
    ],
    "sg:phone":"+91 40 2320 4887",
    "sg:postcode":"500001",
    "sg:tags":[
        "pharmaceutical"
    ],
    "wof:name":"Enal Drugs Pvt. Ltd.",
    "wof:placetype":"venue"
},
  "geometry": {"coordinates":[78.477318,17.393213],"type":"Point"}
}