{
  "type": "Feature",
  "properties": {
    "iso:country":"IN",
    "sg:address":"42, Gujar Street,",
    "sg:city":"Mumbai",
    "sg:classifiers":[
        {
            "category":"Shopping",
            "subcategory":"Luggage & Leather Goods",
            "type":"Retail Goods"
        }
    ],
    "sg:phone":"+91 22 2346 6633",
    "sg:postcode":"400001",
    "sg:tags":[
        "bag",
        "-"
    ],
    "sg:website":"http://www.rasulbhaiadamji.com",
    "wof:name":"Rasulbhai Adamji & Sons",
    "wof:placetype":"venue"
},
  "geometry": {"coordinates":[72.830208,18.959145],"type":"Point"}
}