{
  "type": "Feature",
  "properties": {
    "iso:country":"IN",
    "sg:address":"S.v. Road, Goregoan (w)",
    "sg:city":"Mumbai",
    "sg:phone":"+91 22 2871 1541",
    "sg:postcode":"400062",
    "sg:province":"Maharashtra",
    "wof:name":"Paras Chemplast Pvt Ltd",
    "wof:placetype":"venue"
},
  "geometry": {"coordinates":[72.843536,19.150368],"type":"Point"}
}