{
  "type": "Feature",
  "properties": {
    "iso:country":"IN",
    "sg:address":"C-1, Udyog Vihar, Vithalwadi (w),",
    "sg:city":"Ulhasnagar",
    "sg:classifiers":[
        {
            "category":"Manufacturing",
            "subcategory":"Metals",
            "type":"Manufacturing & Wholesale Goods"
        }
    ],
    "sg:phone":"+91 251 254 1684",
    "sg:postcode":"421003",
    "sg:tags":[
        "fabricator"
    ],
    "wof:name":"Marc Constructions",
    "wof:placetype":"venue"
},
  "geometry": {"coordinates":[73.148422,19.230255],"type":"Point"}
}