{
  "type": "Feature",
  "properties": {
    "iso:country":"IN",
    "sg:address":"184/87, Swami Vivekanand Road, Jogeshwari (w),",
    "sg:city":"Mumbai",
    "sg:classifiers":[
        {
            "category":"Manufacturing",
            "subcategory":"Chemicals & Compounds",
            "type":"Manufacturing & Wholesale Goods"
        }
    ],
    "sg:phone":"+91 22 2678 8258",
    "sg:postcode":"400102",
    "sg:tags":[
        "industrial"
    ],
    "sg:website":"http://www.excelind.com",
    "wof:name":"Excel Industries Ltd.",
    "wof:placetype":"venue"
},
  "geometry": {"coordinates":[72.84324599999999,19.149593],"type":"Point"}
}