{
  "type": "Feature",
  "properties": {
    "iso:country":"IN",
    "sg:address":"No. 30, F. Kamaraj Nagar, 2nd Street, P.n. Road,",
    "sg:city":"Tirupur",
    "sg:classifiers":[
        {
            "category":"Shopping",
            "subcategory":"Crafts & Fabrics",
            "type":"Retail Goods"
        }
    ],
    "sg:phone":"+91 421 248 0237",
    "sg:postcode":"641602",
    "sg:tags":[
        "knitted",
        "knitwear"
    ],
    "wof:name":"Flora International (india)",
    "wof:placetype":"venue"
},
  "geometry": {"coordinates":[80.256577,13.094447],"type":"Point"}
}