{
  "type": "Feature",
  "properties": {
    "iso:country":"IN",
    "sg:address":"50, Proctor Road, B-8, Janardan Bldg.,",
    "sg:city":"Mumbai",
    "sg:classifiers":[
        {
            "category":"Manufacturing",
            "subcategory":"Motor Vehicles & Parts",
            "type":"Manufacturing & Wholesale Goods"
        }
    ],
    "sg:phone":"+91 22 2388 6082",
    "sg:postcode":"400007",
    "sg:tags":[
        "component",
        "product",
        "electronic"
    ],
    "sg:website":"http://www.microchip.com",
    "wof:name":"Micro-chip Technologies",
    "wof:placetype":"venue"
},
  "geometry": {"coordinates":[72.815704,18.961235],"type":"Point"}
}