{
  "type": "Feature",
  "properties": {
    "iso:country":"IN",
    "sg:address":"205, Solucky Corner, Chakala, Andheri(e),",
    "sg:city":"Mumbai",
    "sg:classifiers":[
        {
            "category":"Manufacturing",
            "subcategory":"Motor Vehicles & Parts",
            "type":"Manufacturing & Wholesale Goods"
        }
    ],
    "sg:phone":"+91 22 2823 6239",
    "sg:postcode":"400099",
    "sg:tags":[
        "bearing"
    ],
    "sg:website":"http://www.swiftbearings.com",
    "wof:name":"Swift Bearings",
    "wof:placetype":"venue"
},
  "geometry": {"coordinates":[72.859184,19.114714],"type":"Point"}
}