{
  "type": "Feature",
  "properties": {
    "iso:country":"IN",
    "sg:address":"H-117, Behind New Power House, Industrial Area,",
    "sg:city":"Jodhpur",
    "sg:classifiers":[
        {
            "category":"Manufacturing",
            "subcategory":"Chemicals & Compounds",
            "type":"Manufacturing & Wholesale Goods"
        }
    ],
    "sg:phone":"+91 291 274 1674",
    "sg:postcode":"342003",
    "sg:tags":[
        "supply"
    ],
    "wof:name":"Ganga Jamuna Chemicals",
    "wof:placetype":"venue"
},
  "geometry": {"coordinates":[77.51815000000001,13.039126],"type":"Point"}
}