{
  "type": "Feature",
  "properties": {
    "iso:country":"IN",
    "sg:address":"Mehta Road",
    "sg:city":"Amritsar",
    "sg:phone":"+91 183586728",
    "sg:postcode":"143001",
    "sg:province":"Punjab",
    "sg:website":"http://www.rajcycleindia.com",
    "wof:name":"Raj Cycles India Pvt Ltd",
    "wof:placetype":"venue"
},
  "geometry": {"coordinates":[77.188377,28.652294],"type":"Point"}
}