{
  "type": "Feature",
  "properties": {
    "iso:country":"IN",
    "sg:address":"35/a, First Floor, 3rd C Cross, 2nd Block, 3rd Stage, Basaveshwaranagar,",
    "sg:city":"Bangalore",
    "sg:orig_category":"Veterinary Medicine",
    "sg:phone":"+91 80 2232 3336",
    "sg:postcode":"560079",
    "wof:name":"Glotech International",
    "wof:placetype":"venue"
},
  "geometry": {"coordinates":[77.536613,12.998101],"type":"Point"}
}