{
  "type": "Feature",
  "properties": {
    "iso:country":"IN",
    "sg:address":"171, Samuel Street, Masjid Bunder,",
    "sg:city":"Mumbai",
    "sg:classifiers":[
        {
            "category":"Food & Beverages",
            "subcategory":"Fruits & Vegetables",
            "type":"Retail Goods"
        }
    ],
    "sg:phone":"+91 22 2347 3121",
    "sg:postcode":"400009",
    "sg:tags":[
        "dried"
    ],
    "wof:name":"Harumal Gangaram & Co.",
    "wof:placetype":"venue"
},
  "geometry": {"coordinates":[72.836662,18.951439],"type":"Point"}
}