{
  "type": "Feature",
  "properties": {
    "iso:country":"IN",
    "sg:address":"Lbs Marg, Bhandup (w)",
    "sg:city":"Mumbai",
    "sg:phone":"+91 22 2591 6159",
    "sg:postcode":"400078",
    "sg:province":"Maharashtra",
    "wof:name":"M P Engineering Constructions (i) Pvt Ltd",
    "wof:placetype":"venue"
},
  "geometry": {"coordinates":[72.928932,19.135406],"type":"Point"}
}