{
  "type": "Feature",
  "properties": {
    "iso:country":"IN",
    "sg:address":"Khaderbagh",
    "sg:city":"Hyderabad",
    "sg:phone":"+91 40 2351 3613",
    "sg:postcode":"500002",
    "sg:province":"Andhra Pradesh",
    "sg:website":"http://www.vetrotex.co.in",
    "wof:name":"Saint Gobain India Ltd",
    "wof:placetype":"venue"
},
  "geometry": {"coordinates":[78.459503,17.423752],"type":"Point"}
}