{
  "type": "Feature",
  "properties": {
    "iso:country":"IN",
    "sg:address":"15b, Kasi Industrial Estate, Jafferkhanpet,",
    "sg:city":"Chennai",
    "sg:classifiers":[
        {
            "category":"Wholesale",
            "subcategory":"Chemicals & Plastics",
            "type":"Manufacturing & Wholesale Goods"
        }
    ],
    "sg:phone":"+91 44 2470 0248",
    "sg:postcode":"600083",
    "sg:tags":[
        "lab",
        "supply"
    ],
    "wof:name":"Paxmy Fine Chemicals",
    "wof:placetype":"venue"
},
  "geometry": {"coordinates":[80.206337,13.030587],"type":"Point"}
}