{
  "type": "Feature",
  "properties": {
    "iso:country":"IN",
    "sg:address":"No. A-9, Street No. 5, Cross Road 'b', M.i.d.c., Andheri,",
    "sg:city":"Mumbai",
    "sg:classifiers":[
        {
            "category":"Manufacturing",
            "subcategory":"Chemicals & Compounds",
            "type":"Manufacturing & Wholesale Goods"
        }
    ],
    "sg:phone":"+91 22 2820 2847",
    "sg:postcode":"400093",
    "sg:tags":[
        "supply"
    ],
    "wof:name":"Frezco Corpn.",
    "wof:placetype":"venue"
},
  "geometry": {"coordinates":[72.86829400000001,19.116081],"type":"Point"}
}