{
  "type": "Feature",
  "properties": {
    "iso:country":"IN",
    "sg:address":"Patliputra Colony",
    "sg:city":"Patna",
    "sg:phone":"+91 612266826",
    "sg:postcode":"800013",
    "sg:province":"Bihar",
    "wof:name":"Natraj Iron & Castings Ltd",
    "wof:placetype":"venue"
},
  "geometry": {"coordinates":[85.11422,25.625797],"type":"Point"}
}