{
  "type": "Feature",
  "properties": {
    "iso:country":"IN",
    "sg:address":"2nd Floor, Commerce House, Town Hall Road,",
    "sg:city":"Udaipur",
    "sg:classifiers":[
        {
            "category":"Organizations",
            "subcategory":"Labor Organization",
            "type":"Services"
        }
    ],
    "sg:phone":"+91 294 329 0784",
    "sg:postcode":"313001",
    "sg:tags":[
        "sandstone"
    ],
    "wof:name":"Fortune Stones Ltd.",
    "wof:placetype":"venue"
},
  "geometry": {"coordinates":[76.950203,11.00662],"type":"Point"}
}