{
  "type": "Feature",
  "properties": {
    "iso:country":"IN",
    "sg:address":"B-91, Phase I, Mayapuri Industrial Area,",
    "sg:city":"New Delhi",
    "sg:classifiers":[
        {
            "category":"Manufacturing",
            "subcategory":"Chemicals & Compounds",
            "type":"Manufacturing & Wholesale Goods"
        }
    ],
    "sg:phone":"+91 11 2811 5346",
    "sg:postcode":"110064",
    "sg:tags":[
        "paint",
        "product",
        "allied"
    ],
    "sg:website":"http://www.orientalcolours.com",
    "wof:name":"Oriental Colour & Paint Industries (p) Ltd.",
    "wof:placetype":"venue"
},
  "geometry": {"coordinates":[77.126945,28.630474],"type":"Point"}
}