{
  "type": "Feature",
  "properties": {
    "iso:country":"IN",
    "sg:address":"Irinjalakuda,",
    "sg:city":"Thrissur",
    "sg:orig_category":"Soap/detergents",
    "sg:phone":"+91 4882 826 218",
    "sg:postcode":"680121",
    "wof:name":"S. V. Products",
    "wof:placetype":"venue"
},
  "geometry": {"coordinates":[76.216309,10.343597],"type":"Point"}
}