{
  "type": "Feature",
  "properties": {
    "iso:country":"IN",
    "sg:address":"A. S. Char Street",
    "sg:city":"Bangalore",
    "sg:phone":"+91 802879704",
    "sg:postcode":"560053",
    "sg:province":"Karnataka",
    "wof:name":"Karnataka Chemical Industries",
    "wof:placetype":"venue"
},
  "geometry": {"coordinates":[77.57435599999999,12.967414],"type":"Point"}
}