{
  "type": "Feature",
  "properties": {
    "iso:country":"IN",
    "sg:address":"39/a, S.m. Road, T. Dasarahalli P.o.,",
    "sg:city":"Bangalore",
    "sg:classifiers":[
        {
            "category":"Wholesale",
            "subcategory":"Vending Machines",
            "type":"Manufacturing & Wholesale Goods"
        }
    ],
    "sg:phone":"+91 80 2839 4693",
    "sg:postcode":"560057",
    "sg:tags":[
        "weighing"
    ],
    "wof:name":"Pentonic Systems",
    "wof:placetype":"venue"
},
  "geometry": {"coordinates":[77.607216,12.972761],"type":"Point"}
}