{
  "type": "Feature",
  "properties": {
    "iso:country":"IN",
    "sg:address":"Race Course Road",
    "sg:city":"Bangalore",
    "sg:phone":"+91 802263202",
    "sg:postcode":"560001",
    "sg:province":"Karnataka",
    "wof:name":"Alupro Building Systems Pvt Ltd",
    "wof:placetype":"venue"
},
  "geometry": {"coordinates":[76.10303500000001,13.009877],"type":"Point"}
}