{
  "type": "Feature",
  "properties": {
    "iso:country":"IN",
    "sg:address":"5,4, 11th Cross, Maruthi Nagar, Madiwala,",
    "sg:city":"Bangalore",
    "sg:classifiers":[
        {
            "category":"Banks & Credit Unions",
            "subcategory":"Bank",
            "type":"Services"
        }
    ],
    "sg:postcode":"560068",
    "sg:tags":[
        "sweet",
        "namkeen"
    ],
    "wof:name":"Best Mummy Cake&sweets",
    "wof:placetype":"venue"
},
  "geometry": {"coordinates":[77.607727,12.912158],"type":"Point"}
}