{
  "type": "Feature",
  "properties": {
    "iso:country":"IN",
    "sg:address":"Industrial Town, Rajaji Nagar",
    "sg:city":"Bangalore",
    "sg:phone":"+91 803306819",
    "sg:postcode":"560044",
    "sg:province":"Karnataka",
    "wof:name":"Techtools",
    "wof:placetype":"venue"
},
  "geometry": {"coordinates":[77.543312,12.983084],"type":"Point"}
}