{
  "type": "Feature",
  "properties": {
    "iso:country":"IN",
    "sg:address":"Plot No. 430, Sector-8,",
    "sg:city":"Faridabad",
    "sg:classifiers":[
        {
            "category":"Manufacturing",
            "subcategory":"Chemicals & Compounds",
            "type":"Manufacturing & Wholesale Goods"
        }
    ],
    "sg:phone":"+91 129 221 1796",
    "sg:postcode":"121006",
    "sg:tags":[
        "supply"
    ],
    "sg:website":"quantumtech.co.in",
    "wof:name":"Quantum Technologies",
    "wof:placetype":"venue"
},
  "geometry": {"coordinates":[77.12406900000001,28.704706],"type":"Point"}
}