{
  "type": "Feature",
  "properties": {
    "iso:country":"IN",
    "sg:address":"51, Karattankadu, 6th, Street, K.n.p. Colony,",
    "sg:city":"Tiruppur",
    "sg:classifiers":[
        {
            "category":"Shopping",
            "subcategory":"Clothing, Apparel, & Fashions",
            "type":"Retail Goods"
        }
    ],
    "sg:phone":"+91 421 242 4750",
    "sg:postcode":"641608",
    "sg:tags":[
        "garment",
        "accessory"
    ],
    "sg:website":"http://www.prakav.com",
    "wof:name":"Sri Vasagam Imptex",
    "wof:placetype":"venue"
},
  "geometry": {"coordinates":[76.767952,15.790452],"type":"Point"}
}