{
  "type": "Feature",
  "properties": {
    "iso:country":"IN",
    "sg:address":"Resham Bhavan, 4th Floor, 78, Veer Nariman Road,",
    "sg:city":"Mumbai",
    "sg:classifiers":[
        {
            "category":"Banks & Credit Unions",
            "subcategory":"Investment Brokerage",
            "type":"Services"
        }
    ],
    "sg:phone":"+91 22 3027 3025",
    "sg:postcode":"400020",
    "sg:tags":[
        "agro",
        "product",
        "based",
        "commodity"
    ],
    "sg:website":"http://www.mahyco.com",
    "wof:name":"Mahyco Seeds Ltd.",
    "wof:placetype":"venue"
},
  "geometry": {"coordinates":[72.826706,18.933573],"type":"Point"}
}