{
  "type": "Feature",
  "properties": {
    "iso:country":"IN",
    "sg:address":"89, Mohamedali Road,",
    "sg:city":"Mumbai",
    "sg:classifiers":[
        {
            "category":"Manufacturing",
            "subcategory":"Tools & Machinery",
            "type":"Manufacturing & Wholesale Goods"
        }
    ],
    "sg:phone":"+91 22 2340 1840",
    "sg:postcode":"400003",
    "sg:tags":[
        "cutter",
        "cutting",
        "tools",
        "broach"
    ],
    "sg:website":"http://www.sanghvibrothers.com",
    "wof:name":"Sanghvi Brothers Trading Pvt. Ltd.",
    "wof:placetype":"venue"
},
  "geometry": {"coordinates":[72.83272599999999,18.955664],"type":"Point"}
}