{
  "type": "Feature",
  "properties": {
    "iso:country":"IN",
    "sg:address":"303, South Ex Tower,",
    "sg:city":"New Delhi",
    "sg:classifiers":[
        {
            "category":"Manufacturing",
            "subcategory":"Chemicals & Compounds",
            "type":"Manufacturing & Wholesale Goods"
        }
    ],
    "sg:phone":"+91 11 4134 5332",
    "sg:postcode":"110049",
    "sg:tags":[
        "resin"
    ],
    "sg:website":"http://www.progresic.com",
    "wof:name":"Progesic International",
    "wof:placetype":"venue"
},
  "geometry": {"coordinates":[80.859596,24.573036],"type":"Point"}
}