{
  "type": "Feature",
  "properties": {
    "iso:country":"IN",
    "sg:address":"Rajajinagar",
    "sg:city":"Bangalore",
    "sg:phone":"+91 803303103",
    "sg:postcode":"560044",
    "sg:province":"Karnataka",
    "sg:website":"http://www.kalpaelectrikals.com",
    "wof:name":"Kalpa Electrikal Pvt Ltd",
    "wof:placetype":"venue"
},
  "geometry": {"coordinates":[77.553345,12.990632],"type":"Point"}
}