{
  "type": "Feature",
  "properties": {
    "iso:country":"IN",
    "sg:address":"No. 6, Rajan Village.off Carter Road, Bandra,",
    "sg:city":"Mumbai",
    "sg:classifiers":[
        {
            "category":"Home & Garden",
            "subcategory":"Garden Supply",
            "type":"Retail Goods"
        }
    ],
    "sg:phone":"+91 22 2649 5589",
    "sg:postcode":"400050",
    "sg:tags":[
        "fertilizer"
    ],
    "wof:name":"Marian Maritime Private Limited",
    "wof:placetype":"venue"
},
  "geometry": {"coordinates":[72.823196,19.065874],"type":"Point"}
}