{
  "type": "Feature",
  "properties": {
    "iso:country":"IN",
    "sg:address":"A-11/1, Site-4, Link Road, Industrial Area,",
    "sg:city":"Sahibabad",
    "sg:classifiers":[
        {
            "category":"Manufacturing",
            "subcategory":"Chemicals & Compounds",
            "type":"Manufacturing & Wholesale Goods"
        }
    ],
    "sg:phone":"+91 120 289 6651",
    "sg:postcode":"201010",
    "sg:tags":[
        "coatings-powder",
        "coating"
    ],
    "sg:website":"http://www.rapidcoat.com",
    "wof:name":"Rapid Coat Division",
    "wof:placetype":"venue"
},
  "geometry": {"coordinates":[77.327522,28.654827],"type":"Point"}
}