{
  "type": "Feature",
  "properties": {
    "iso:country":"IN",
    "sg:address":"4 `t' Block, Jayanagar",
    "sg:city":"Bangalore",
    "sg:phone":"+91 806638755",
    "sg:postcode":"560041",
    "sg:province":"Karnataka",
    "sg:website":"http://www.tovya-india.com",
    "wof:name":"Tovya Automation Pvt Ltd",
    "wof:placetype":"venue"
},
  "geometry": {"coordinates":[77.584511,12.927514],"type":"Point"}
}