{
  "type": "Feature",
  "properties": {
    "iso:country":"IN",
    "sg:address":"201, Churchgate Chambers, N. M. L,",
    "sg:city":"Mumbai",
    "sg:classifiers":[
        {
            "category":"Shopping",
            "subcategory":"Crafts & Fabrics",
            "type":"Retail Goods"
        }
    ],
    "sg:phone":"+91 22 2262 4609",
    "sg:postcode":"400020",
    "sg:website":"http://www.gulfexports.com",
    "wof:name":"Gulf Enterprises Experts",
    "wof:placetype":"venue"
},
  "geometry": {"coordinates":[72.82428,18.930777],"type":"Point"}
}