{
  "type": "Feature",
  "properties": {
    "iso:country":"IN",
    "sg:address":"Plot No. 70133, 441st Phase, G.i.d.c,",
    "sg:city":"Vapi",
    "sg:classifiers":[
        {
            "category":"Manufacturing",
            "subcategory":"Chemicals & Compounds",
            "type":"Manufacturing & Wholesale Goods"
        }
    ],
    "sg:phone":"+91 260 654 3630",
    "sg:postcode":"396195",
    "sg:tags":[
        "supply"
    ],
    "sg:website":"http://www.varshchemicals.com",
    "wof:name":"Varsh Chemical",
    "wof:placetype":"venue"
},
  "geometry": {"coordinates":[75.839546,30.875616],"type":"Point"}
}