{
  "type": "Feature",
  "properties": {
    "iso:country":"IN",
    "sg:address":"209 Arun Chambers, Tardeo,",
    "sg:city":"Mumbai",
    "sg:classifiers":[
        {
            "category":"Wholesale",
            "subcategory":"Drugs",
            "type":"Manufacturing & Wholesale Goods"
        }
    ],
    "sg:phone":"+91 22 2352 1312",
    "sg:postcode":"400034",
    "sg:tags":[
        "bulk"
    ],
    "wof:name":"Vignesh Pharma Impex Pvt. Ltd.",
    "wof:placetype":"venue"
},
  "geometry": {"coordinates":[72.81379699999999,18.973169],"type":"Point"}
}