{
  "type": "Feature",
  "properties": {
    "iso:country":"IN",
    "sg:address":"Ram Baug, S.v. Road, Malad-west,",
    "sg:city":"Mumbai",
    "sg:classifiers":[
        {
            "category":"Farming",
            "subcategory":"Crops",
            "type":"Manufacturing & Wholesale Goods"
        }
    ],
    "sg:phone":"+91 22 2888 7372",
    "sg:postcode":"400064",
    "sg:tags":[
        "cereal"
    ],
    "wof:name":"Madam Agro Food Industries Pvt. Ltd.",
    "wof:placetype":"venue"
},
  "geometry": {"coordinates":[72.837997,19.084724],"type":"Point"}
}