{
  "type": "Feature",
  "properties": {
    "iso:country":"IN",
    "sg:address":"1h-26, Arya Samaj Road, Nit,",
    "sg:city":"Faridabad",
    "sg:classifiers":[
        {
            "category":"Manufacturing",
            "subcategory":"Rubber & Plastics",
            "type":"Manufacturing & Wholesale Goods"
        }
    ],
    "sg:phone":"+91 951294004422",
    "sg:postcode":"121001",
    "sg:tags":[
        "chemical",
        "-"
    ],
    "wof:name":"Unichem Impex Pvt. Ltd.",
    "wof:placetype":"venue"
},
  "geometry": {"coordinates":[77.058746,28.444416],"type":"Point"}
}