{
  "type": "Feature",
  "properties": {
    "iso:country":"IN",
    "sg:address":"2nd Street",
    "sg:city":"Tirupur",
    "sg:phone":"+91 421213165",
    "sg:postcode":"641604",
    "sg:province":"Tamil Nadu",
    "wof:name":"Sentinel Clothing Company",
    "wof:placetype":"venue"
},
  "geometry": {"coordinates":[80.185608,13.103618],"type":"Point"}
}