{
  "type": "Feature",
  "properties": {
    "iso:country":"IN",
    "sg:address":"Yes Kamal Building, Plot No.636, G.i.d.c.,",
    "sg:city":"Vapi",
    "sg:classifiers":[
        {
            "category":"Manufacturing",
            "subcategory":"Chemicals & Compounds",
            "type":"Manufacturing & Wholesale Goods"
        }
    ],
    "sg:phone":"+91 260 245 3504",
    "sg:postcode":"396195",
    "sg:tags":[
        "resin"
    ],
    "sg:website":"http://www.uniformsynthetics.com",
    "wof:name":"Uniform Synthetics",
    "wof:placetype":"venue"
},
  "geometry": {"coordinates":[80.231201,13.030189],"type":"Point"}
}