{
  "type": "Feature",
  "properties": {
    "iso:country":"IN",
    "sg:address":"Plot No. 604, Gidc, P. B. No. 37,",
    "sg:city":"Ankleshwar",
    "sg:classifiers":[
        {
            "category":"Manufacturing",
            "subcategory":"Chemicals & Compounds",
            "type":"Manufacturing & Wholesale Goods"
        }
    ],
    "sg:phone":"+91 2646 222 033",
    "sg:postcode":"393002",
    "sg:tags":[
        "plant",
        "processing"
    ],
    "wof:name":"Dyke Engineering Services",
    "wof:placetype":"venue"
},
  "geometry": {"coordinates":[70.826859,22.280378],"type":"Point"}
}