{
  "type": "Feature",
  "properties": {
    "iso:country":"IN",
    "sg:address":"Smith Road",
    "sg:city":"Chennai",
    "sg:phone":"+91 44 2852 2462",
    "sg:postcode":"600002",
    "sg:province":"Tamil Nadu",
    "wof:name":"Jai Motors Ltd",
    "wof:placetype":"venue"
},
  "geometry": {"coordinates":[80.260925,13.058558],"type":"Point"}
}