{
  "type": "Feature",
  "properties": {
    "iso:country":"IN",
    "sg:address":"Embassy Centre, No. 903, Nariman Point,",
    "sg:city":"Mumbai",
    "sg:classifiers":[
        {
            "category":"Manufacturing",
            "subcategory":"Rubber & Plastics",
            "type":"Manufacturing & Wholesale Goods"
        }
    ],
    "sg:phone":"+91 22 2283 0072",
    "sg:postcode":"400021",
    "sg:tags":[
        "product"
    ],
    "wof:name":"Span Rubber Products Pvt. Ltd.",
    "wof:placetype":"venue"
},
  "geometry": {"coordinates":[72.82118199999999,18.924328],"type":"Point"}
}