{
  "type": "Feature",
  "properties": {
    "iso:country":"IN",
    "sg:address":"75-b, Mittal Court, Nariman Point,",
    "sg:city":"Mumbai",
    "sg:classifiers":[
        {
            "category":"Home & Garden",
            "subcategory":"Garden Supply",
            "type":"Retail Goods"
        }
    ],
    "sg:phone":"+91 22 2284 6183",
    "sg:postcode":"400021",
    "sg:tags":[
        "fertilizer"
    ],
    "wof:name":"Mincore Resources Pvt. Ltd.",
    "wof:placetype":"venue"
},
  "geometry": {"coordinates":[72.822639,18.925814],"type":"Point"}
}