{
  "type": "Feature",
  "properties": {
    "iso:country":"IN",
    "sg:address":"Cannought Circus",
    "sg:city":"New Delhi",
    "sg:postcode":"110001",
    "sg:province":"Delhi",
    "sg:website":"www.abrobalancing.com",
    "wof:name":"Abro Balancing Machines Pvt Ltd",
    "wof:placetype":"venue"
},
  "geometry": {"coordinates":[77.21895600000001,28.633551],"type":"Point"}
}