{
  "type": "Feature",
  "properties": {
    "iso:country":"IN",
    "sg:address":"# 2, Venkateshapuram, 4th Street, P.n. Road,",
    "sg:city":"Tiruppur",
    "sg:classifiers":[
        {
            "category":"Shopping",
            "subcategory":"Crafts & Fabrics",
            "type":"Retail Goods"
        }
    ],
    "sg:phone":"+91 421 224 2296",
    "sg:postcode":"641602",
    "sg:tags":[
        "knitted",
        "knitwear"
    ],
    "wof:name":"Divya Impexs",
    "wof:placetype":"venue"
},
  "geometry": {"coordinates":[77.624222,13.019795],"type":"Point"}
}