{
  "type": "Feature",
  "properties": {
    "iso:country":"IN",
    "sg:address":"Jogani Industrial Estate, Chunabhatti (e)",
    "sg:city":"Mumbai",
    "sg:phone":"+91 22 2529 4667",
    "sg:postcode":"400022",
    "sg:province":"Maharashtra",
    "wof:name":"Time International",
    "wof:placetype":"venue"
},
  "geometry": {"coordinates":[72.87752500000001,19.057535],"type":"Point"}
}