{
  "type": "Feature",
  "properties": {
    "iso:country":"IN",
    "sg:address":"64, B.b.ganguly Street,",
    "sg:city":"Kolkata",
    "sg:classifiers":[
        {
            "category":"Manufacturing",
            "subcategory":"Chemicals & Compounds",
            "type":"Manufacturing & Wholesale Goods"
        }
    ],
    "sg:phone":"+91 33 2212 2222",
    "sg:postcode":"700012",
    "sg:tags":[
        "supply"
    ],
    "wof:name":"P. M. S. Enterprises",
    "wof:placetype":"venue"
},
  "geometry": {"coordinates":[88.356621,22.570993],"type":"Point"}
}