{
  "type": "Feature",
  "properties": {
    "iso:country":"IN",
    "sg:address":"#3, 3rd Cross Road, Ra Puram,",
    "sg:city":"Chennai",
    "sg:classifiers":[
        {
            "category":"Manufacturing",
            "subcategory":"Chemicals & Compounds",
            "type":"Manufacturing & Wholesale Goods"
        }
    ],
    "sg:phone":"+91 44 2432 6062",
    "sg:postcode":"600028",
    "sg:tags":[
        "supply"
    ],
    "wof:name":"Shaashwat Consultants",
    "wof:placetype":"venue"
},
  "geometry": {"coordinates":[80.25638600000001,13.028029],"type":"Point"}
}