{
  "type": "Feature",
  "properties": {
    "iso:country":"IN",
    "sg:address":"Dhiraj Apartments, Poddar Rd, Malad ( East)",
    "sg:city":"Mumbai",
    "sg:classifiers":[
        {
            "category":"Home & Garden",
            "subcategory":"Carpets & Floor Coverings",
            "type":"Retail Goods"
        }
    ],
    "sg:phone":"+91 22 2883 9061",
    "sg:postcode":"400097",
    "sg:tags":[
        "bedspread"
    ],
    "wof:name":"Poddar International",
    "wof:placetype":"venue"
},
  "geometry": {"coordinates":[72.83886,19.085688],"type":"Point"}
}