{
  "type": "Feature",
  "properties": {
    "iso:country":"IN",
    "sg:address":"144, 2nd Main, Kasturinagar",
    "sg:city":"Bangalore",
    "sg:classifiers":[
        {
            "category":"Professional",
            "subcategory":"Computer Services",
            "type":"Services"
        }
    ],
    "sg:postcode":"560043",
    "sg:tags":[
        "advanced-millennium-technologies",
        "amt",
        "bangalore",
        "taroby",
        "software-development",
        "programmers",
        "outsourcing",
        "crm",
        "erp",
        "cms-systems"
    ],
    "sg:website":"http://www.amt.in",
    "wof:name":"Advanced Millennium Technologies",
    "wof:placetype":"venue"
},
  "geometry": {"coordinates":[77.52114,12.968308],"type":"Point"}
}