{
  "type": "Feature",
  "properties": {
    "iso:country":"IN",
    "sg:address":"2nd Floor, 218, Saffron Complex, Fatehgunj,",
    "sg:city":"Vadodara",
    "sg:classifiers":[
        {
            "category":"Manufacturing",
            "subcategory":"Petroleum Products",
            "type":"Manufacturing & Wholesale Goods"
        }
    ],
    "sg:phone":"+91 265 278 0351",
    "sg:postcode":"390002",
    "sg:tags":[
        "oil",
        "castor"
    ],
    "wof:name":"Sharda Oilmills & Trading Company",
    "wof:placetype":"venue"
},
  "geometry": {"coordinates":[73.187622,22.318846],"type":"Point"}
}