{
  "type": "Feature",
  "properties": {
    "iso:country":"IN",
    "sg:address":"16 Kasturba Gandhi Marg",
    "sg:city":"New Delhi",
    "sg:phone":"+91 11 2331 1923",
    "sg:postcode":"110001",
    "sg:province":"Delhi",
    "wof:name":"Perfectpac Ltd",
    "wof:placetype":"venue"
},
  "geometry": {"coordinates":[77.225845,28.62215],"type":"Point"}
}