{
  "type": "Feature",
  "properties": {
    "iso:country":"IN",
    "sg:address":"2006, 100 Ft. Road, Hal 2nd Stage, Indiranagar,",
    "sg:city":"Bangalore",
    "sg:classifiers":[
        {
            "category":"Manufacturing",
            "subcategory":"Musical Instruments",
            "type":"Manufacturing & Wholesale Goods"
        }
    ],
    "sg:phone":"+91 80 2528 5296",
    "sg:postcode":"560008",
    "sg:tags":[
        "process",
        "control",
        "equipment"
    ],
    "sg:website":"http://www.onlineinstrumentsindia.com",
    "wof:name":"Online Instruments",
    "wof:placetype":"venue"
},
  "geometry": {"coordinates":[77.641121,12.973673],"type":"Point"}
}