{
  "type": "Feature",
  "properties": {
    "iso:country":"IN",
    "sg:address":"Vaishali, 2165, Sadashiv Peth,",
    "sg:city":"Pune",
    "sg:classifiers":[
        {
            "category":"Manufacturing",
            "subcategory":"Chemicals & Compounds",
            "type":"Manufacturing & Wholesale Goods"
        }
    ],
    "sg:phone":"+91 20 2433 0538",
    "sg:postcode":"411030",
    "sg:tags":[
        "supply"
    ],
    "wof:name":"Yuvraj Chemicals Pvt. Ltd.",
    "wof:placetype":"venue"
},
  "geometry": {"coordinates":[73.84122499999999,18.520874],"type":"Point"}
}