{
  "type": "Feature",
  "properties": {
    "iso:country":"IN",
    "sg:address":"K-2a, Hauz Khas Enclave,",
    "sg:city":"New Delhi",
    "sg:classifiers":[
        {
            "category":"Shopping",
            "subcategory":"Stationery & Office Supplies",
            "type":"Retail Goods"
        }
    ],
    "sg:phone":"+91 11 2696 2737",
    "sg:postcode":"110016",
    "sg:tags":[
        "paper"
    ],
    "wof:name":"Sundstrand Forms Pvt. Ltd.",
    "wof:placetype":"venue"
},
  "geometry": {"coordinates":[77.200996,28.546522],"type":"Point"}
}