{
  "type": "Feature",
  "properties": {
    "iso:country":"IN",
    "sg:address":"B-306 (b), Road No. 16, V.k.i. Area,",
    "sg:city":"Jaipur",
    "sg:classifiers":[
        {
            "category":"Manufacturing",
            "subcategory":"Rubber & Plastics",
            "type":"Manufacturing & Wholesale Goods"
        }
    ],
    "sg:phone":"+91 141 246 0903",
    "sg:postcode":"302013",
    "sg:tags":[
        "synthetic"
    ],
    "sg:website":"http://www.brsrubbers.com",
    "wof:name":"Brs Rubbers",
    "wof:placetype":"venue"
},
  "geometry": {"coordinates":[72.840874,19.160154],"type":"Point"}
}