{
  "type": "Feature",
  "properties": {
    "iso:country":"IN",
    "sg:address":"43, Nehru Place",
    "sg:city":"New Delhi",
    "sg:phone":"+91 11 2642 2294",
    "sg:postcode":"110019",
    "sg:province":"Delhi",
    "wof:name":"Electrorama",
    "wof:placetype":"venue"
},
  "geometry": {"coordinates":[77.25344800000001,28.550797],"type":"Point"}
}