{
  "type": "Feature",
  "properties": {
    "iso:country":"IN",
    "sg:address":"14/2, Old China Bazar Street, 2nd Floor,",
    "sg:city":"Kolkata",
    "sg:classifiers":[
        {
            "category":"Manufacturing",
            "subcategory":"Chemicals & Compounds",
            "type":"Manufacturing & Wholesale Goods"
        }
    ],
    "sg:phone":"+91 33 2210 3425",
    "sg:postcode":"700001",
    "sg:tags":[
        "supply"
    ],
    "wof:name":"Paras Dyes & Chemicals",
    "wof:placetype":"venue"
},
  "geometry": {"coordinates":[88.351212,22.579153],"type":"Point"}
}