{
  "type": "Feature",
  "properties": {
    "iso:country":"IN",
    "sg:address":"8426, Roshanara Road,",
    "sg:city":"Delhi",
    "sg:classifiers":[
        {
            "category":"Military Area",
            "subcategory":"Air Force Base",
            "type":"Public Place"
        }
    ],
    "sg:phone":"+91 11 2527 1874",
    "sg:postcode":"110007",
    "sg:tags":[
        "silica",
        "gel"
    ],
    "wof:name":"Star Traders",
    "wof:placetype":"venue"
},
  "geometry": {"coordinates":[77.20470400000001,28.669033],"type":"Point"}
}