{
  "type": "Feature",
  "properties": {
    "iso:country":"IN",
    "sg:address":"B-52, Prashant Vihar,",
    "sg:city":"Delhi",
    "sg:classifiers":[
        {
            "category":"Manufacturing",
            "subcategory":"Petroleum Products",
            "type":"Manufacturing & Wholesale Goods"
        }
    ],
    "sg:phone":"+91 11 2756 6054",
    "sg:postcode":"110085",
    "sg:tags":[
        "wax"
    ],
    "sg:website":"http://www.opgbeads.com",
    "wof:name":"Opg-india",
    "wof:placetype":"venue"
},
  "geometry": {"coordinates":[77.13557400000001,28.714409],"type":"Point"}
}