{
  "type": "Feature",
  "properties": {
    "iso:country":"IN",
    "sg:address":"No. A-345, 9th Main Road, Peenya, 2nd Stage,",
    "sg:city":"Bangalore",
    "sg:classifiers":[
        {
            "category":"Manufacturing",
            "subcategory":"Pet Food",
            "type":"Manufacturing & Wholesale Goods"
        }
    ],
    "sg:phone":"+91 80 2836 0448",
    "sg:postcode":"560058",
    "sg:tags":[
        "additive",
        "flavour"
    ],
    "wof:name":"H & R Flavours & Fragrances Pvt. Ltd.",
    "wof:placetype":"venue"
},
  "geometry": {"coordinates":[77.540352,13.011638],"type":"Point"}
}