{
  "type": "Feature",
  "properties": {
    "iso:country":"IN",
    "sg:address":"Nehru Road, Vile Parle (e)",
    "sg:city":"Mumbai",
    "sg:phone":"+91 226185293",
    "sg:postcode":"400057",
    "sg:province":"Maharashtra",
    "sg:website":"http://www.bellobell.com",
    "wof:name":"Bell-o-bell Impex Pvt Ltd",
    "wof:placetype":"venue"
},
  "geometry": {"coordinates":[72.846771,19.098246],"type":"Point"}
}