{
  "type": "Feature",
  "properties": {
    "iso:country":"IN",
    "sg:address":"77, Netaji Subhash Road, 2nd Flr, Room - 207,",
    "sg:city":"Kolkata",
    "sg:classifiers":[
        {
            "category":"Manufacturing",
            "subcategory":"Chemicals & Compounds",
            "type":"Manufacturing & Wholesale Goods"
        }
    ],
    "sg:phone":"+91 33 2243 2396",
    "sg:postcode":"700001",
    "sg:tags":[
        "industrial"
    ],
    "wof:name":"Bharatkumar Brothers",
    "wof:placetype":"venue"
},
  "geometry": {"coordinates":[77.23672500000001,28.655243],"type":"Point"}
}