{
  "type": "Feature",
  "properties": {
    "iso:country":"IN",
    "sg:address":"Plot No. C-1/4763/64, Gidc,",
    "sg:city":"Ankleshwar",
    "sg:classifiers":[
        {
            "category":"Shopping",
            "subcategory":"Crafts & Fabrics",
            "type":"Retail Goods"
        }
    ],
    "sg:phone":"+91 2646 251 423",
    "sg:postcode":"393002",
    "sg:tags":[
        "pigment"
    ],
    "wof:name":"Nepal Chemicals",
    "wof:placetype":"venue"
},
  "geometry": {"coordinates":[70.826859,22.280378],"type":"Point"}
}