{
  "type": "Feature",
  "properties": {
    "iso:country":"IN",
    "sg:address":"154, Mittal Towers 'b', 210, Nariman Point,",
    "sg:city":"Mumbai",
    "sg:classifiers":[
        {
            "category":"Manufacturing",
            "subcategory":"Chemicals & Compounds",
            "type":"Manufacturing & Wholesale Goods"
        }
    ],
    "sg:phone":"+91 22 2282 3680",
    "sg:postcode":"400021",
    "sg:tags":[
        "resin"
    ],
    "wof:name":"Pine Chemical Suppliers",
    "wof:placetype":"venue"
},
  "geometry": {"coordinates":[72.824631,18.924906],"type":"Point"}
}