{
  "type": "Feature",
  "properties": {
    "iso:country":"IN",
    "sg:address":"866/4/b, Gidc, Makarpura,",
    "sg:city":"Vadodara",
    "sg:classifiers":[
        {
            "category":"Professional",
            "subcategory":"Testing Lab",
            "type":"Services"
        }
    ],
    "sg:phone":"+91 265 263 8587",
    "sg:postcode":"390010",
    "sg:tags":[
        "measuring",
        "equipment",
        "electrical"
    ],
    "sg:website":"http://www.com-power.com",
    "wof:name":"Compatible Power Pvt. Ltd.",
    "wof:placetype":"venue"
},
  "geometry": {"coordinates":[72.65799,23.076591],"type":"Point"}
}