{
  "type": "Feature",
  "properties": {
    "iso:country":"IN",
    "sg:address":"25, Camac Street",
    "sg:city":"Kolkata",
    "sg:phone":"+91 33 2247 2189",
    "sg:postcode":"700016",
    "sg:province":"West Bengal",
    "wof:name":"Gbm Manufacturing Pvt Ltd",
    "wof:placetype":"venue"
},
  "geometry": {"coordinates":[88.353065,22.546921],"type":"Point"}
}