{
  "type": "Feature",
  "properties": {
    "iso:country":"IN",
    "sg:address":"27 Barakhamba Road",
    "sg:city":"New Delhi",
    "sg:phone":"+91 11 2373 9861",
    "sg:postcode":"110001",
    "sg:province":"Delhi",
    "sg:website":"http://www.textilesmarket.com",
    "wof:name":"Veena Enterprises Ltd",
    "wof:placetype":"venue"
},
  "geometry": {"coordinates":[77.226662,28.628914],"type":"Point"}
}