{
  "type": "Feature",
  "properties": {
    "iso:country":"IN",
    "sg:address":"Z-8, Street No.-4, Anand Parbat Industrial Area,",
    "sg:city":"New Delhi",
    "sg:classifiers":[
        {
            "category":"Manufacturing",
            "subcategory":"Rubber & Plastics",
            "type":"Manufacturing & Wholesale Goods"
        }
    ],
    "sg:phone":"+91 11 6637 1464",
    "sg:postcode":"110005",
    "sg:tags":[
        "product"
    ],
    "wof:name":"S. G. Prodcuts",
    "wof:placetype":"venue"
},
  "geometry": {"coordinates":[77.17755099999999,28.661634],"type":"Point"}
}