{
  "type": "Feature",
  "properties": {
    "iso:country":"IN",
    "sg:address":"49, Audiappa Naicken Street, 2nd Floor, Sowcarpet,",
    "sg:city":"Chennai",
    "sg:classifiers":[
        {
            "category":"Home & Garden",
            "subcategory":"Mobile Homes",
            "type":"Retail Goods"
        }
    ],
    "sg:phone":"+91 44 2529 7044",
    "sg:postcode":"600079",
    "sg:tags":[
        "acid"
    ],
    "wof:name":"Reliable Petro Chemicals",
    "wof:placetype":"venue"
},
  "geometry": {"coordinates":[80.282372,13.092222],"type":"Point"}
}