{
  "type": "Feature",
  "properties": {
    "iso:country":"IN",
    "sg:address":"P.o. Velliparamba, Calicut,",
    "sg:city":"Kozhikode",
    "sg:classifiers":[
        {
            "category":"Home & Garden",
            "subcategory":"Mobile Homes",
            "type":"Retail Goods"
        }
    ],
    "sg:phone":"+91 495 235 6009",
    "sg:postcode":"673008",
    "sg:tags":[
        "acid"
    ],
    "sg:website":"http://www.indiamart.com/victorysoaps",
    "wof:name":"Victory Soap Company",
    "wof:placetype":"venue"
},
  "geometry": {"coordinates":[75.85067,11.269944],"type":"Point"}
}