{
  "type": "Feature",
  "properties": {
    "iso:country":"IN",
    "sg:address":"No. 44, Nagdevi Cross Lane, 1st Floor,",
    "sg:city":"Mumbai",
    "sg:classifiers":[
        {
            "category":"Wholesale",
            "subcategory":"Machinery & Supplies",
            "type":"Manufacturing & Wholesale Goods"
        }
    ],
    "sg:phone":"+91 22 2342 9977",
    "sg:postcode":"400003",
    "sg:tags":[
        "equipment",
        "goods",
        "electrical"
    ],
    "sg:website":"http://www.solar-sale.com",
    "wof:name":"Solar Sales Syndicate",
    "wof:placetype":"venue"
},
  "geometry": {"coordinates":[72.83399199999999,18.950926],"type":"Point"}
}