{
  "type": "Feature",
  "properties": {
    "iso:country":"IN",
    "sg:address":"W/114(a), Midc, Badlapur(e),",
    "sg:city":"Badlapur",
    "sg:classifiers":[
        {
            "category":"Manufacturing",
            "subcategory":"Chemicals & Compounds",
            "type":"Manufacturing & Wholesale Goods"
        }
    ],
    "sg:phone":"+91 251 269 0692",
    "sg:postcode":"421503",
    "sg:tags":[
        "fine"
    ],
    "sg:website":"www.virginchemicals.com",
    "wof:name":"Rajesh Enterprises",
    "wof:placetype":"venue"
},
  "geometry": {"coordinates":[73.244102,19.151255],"type":"Point"}
}