{
  "type": "Feature",
  "properties": {
    "iso:country":"IN",
    "sg:address":"The Millenia Tower B, 4th Floor, Murphy Road, Ulsoor,",
    "sg:city":"Bangalore",
    "sg:classifiers":[
        {
            "category":"Home & Garden",
            "subcategory":"Building Materials",
            "type":"Retail Goods"
        }
    ],
    "sg:phone":"+91 80 4122 8893",
    "sg:tags":[
        "sealant",
        "adhesive"
    ],
    "sg:website":"http://www.momentive.com",
    "wof:name":"Momentive Performance Materials",
    "wof:placetype":"venue"
},
  "geometry": {"coordinates":[77.621414,12.978995],"type":"Point"}
}