{
  "type": "Feature",
  "properties": {
    "iso:country":"IN",
    "sg:address":"A-21, W.h.s., Kirti Nagar,",
    "sg:city":"New Delhi",
    "sg:orig_category":"Foam,rexine & P.u.products",
    "sg:phone":"+91 11 2367 7757",
    "sg:postcode":"110015",
    "wof:name":"Jain & Jayna Foams Pvt. Ltd.",
    "wof:placetype":"venue"
},
  "geometry": {"coordinates":[75.037018,29.52393],"type":"Point"}
}