{
  "type": "Feature",
  "properties": {
    "iso:country":"IN",
    "sg:address":"# 3049/15, Mahakavi Kuvempu Road, Malleswaram,",
    "sg:city":"Bangalore",
    "sg:classifiers":[
        {
            "category":"Utilities",
            "subcategory":"Natural Gas",
            "type":"Services"
        }
    ],
    "sg:phone":"+91 80 2332 9840",
    "sg:postcode":"560021",
    "sg:tags":[
        "thermocouple"
    ],
    "sg:website":"http://www.indfurnace.com",
    "wof:name":"Industrial Furnace & Controls",
    "wof:placetype":"venue"
},
  "geometry": {"coordinates":[77.55783099999999,12.998224],"type":"Point"}
}