{
  "type": "Feature",
  "properties": {
    "iso:country":"IN",
    "sg:address":"Punjabi Bagh",
    "sg:city":"New Delhi",
    "sg:phone":"+91 112541532",
    "sg:postcode":"110035",
    "sg:province":"Delhi",
    "sg:website":"http://www.jaganlamp.com",
    "wof:name":"Jagan Lamps Ltd",
    "wof:placetype":"venue"
},
  "geometry": {"coordinates":[77.116875,28.668196],"type":"Point"}
}