{
  "type": "Feature",
  "properties": {
    "iso:country":"IN",
    "sg:address":"B-7, Synthofine Industrial Estate, Off Aarey Road, Goregaon (e),",
    "sg:city":"Mumbai",
    "sg:classifiers":[
        {
            "category":"Train Station",
            "subcategory":"Light Rail",
            "type":"Transportation"
        }
    ],
    "sg:phone":"+91 22 2874 7809",
    "sg:postcode":"400063",
    "sg:tags":[
        "control",
        "board",
        "panel"
    ],
    "wof:name":"Suri Engineering",
    "wof:placetype":"venue"
},
  "geometry": {"coordinates":[72.855598,19.172028],"type":"Point"}
}