{
  "type": "Feature",
  "properties": {
    "iso:country":"IN",
    "sg:address":"4/1, Kempanna Street, Doddamavalli,",
    "sg:city":"Bangalore",
    "sg:classifiers":[
        {
            "category":"Manufacturing",
            "subcategory":"Pet Food",
            "type":"Manufacturing & Wholesale Goods"
        }
    ],
    "sg:phone":"+91 80 2657 3191",
    "sg:postcode":"560004",
    "sg:tags":[
        "additive",
        "flavour"
    ],
    "wof:name":"The Chemical Engineering Corporation Pvt. Ltd.",
    "wof:placetype":"venue"
},
  "geometry": {"coordinates":[77.582146,12.953601],"type":"Point"}
}