{
  "type": "Feature",
  "properties": {
    "iso:country":"IN",
    "sg:address":"No.44, Fee Channapa Indl. Estate, Kamakshipalya, Magadi Main Road,",
    "sg:city":"Bangalore",
    "sg:classifiers":[
        {
            "category":"Manufacturing",
            "subcategory":"Rubber & Plastics",
            "type":"Manufacturing & Wholesale Goods"
        }
    ],
    "sg:phone":"+91 80 3061 6909",
    "sg:tags":[
        "product"
    ],
    "wof:name":"Shreematha Precision Components",
    "wof:placetype":"venue"
},
  "geometry": {"coordinates":[77.525352,12.985409],"type":"Point"}
}