{
  "type": "Feature",
  "properties": {
    "iso:country":"IN",
    "sg:address":"Gammon House, Veer Savarker Marg, Prabha Devi,",
    "sg:city":"Mumbai",
    "sg:classifiers":[
        {
            "category":"Manufacturing",
            "subcategory":"Chemicals & Compounds",
            "type":"Manufacturing & Wholesale Goods"
        }
    ],
    "sg:phone":"+91 22 6661 4000",
    "sg:postcode":"400025",
    "sg:tags":[
        "sulphur"
    ],
    "sg:website":"http://www.gammonindia.com",
    "wof:name":"Gammon Nirman Limited",
    "wof:placetype":"venue"
},
  "geometry": {"coordinates":[72.826141,19.014938],"type":"Point"}
}