{
  "type": "Feature",
  "properties": {
    "iso:country":"IN",
    "sg:address":"70, Najafgarh Road Indl. Area, (rama Road),",
    "sg:city":"New Delhi",
    "sg:classifiers":[
        {
            "category":"Manufacturing",
            "subcategory":"Chemicals & Compounds",
            "type":"Manufacturing & Wholesale Goods"
        }
    ],
    "sg:phone":"+91 11 2593 4095",
    "sg:postcode":"110015",
    "sg:tags":[
        "resin"
    ],
    "wof:name":"K. V. Paints & Chemical Co.",
    "wof:placetype":"venue"
},
  "geometry": {"coordinates":[77.15503699999999,28.661768],"type":"Point"}
}