{
  "type": "Feature",
  "properties": {
    "iso:country":"IN",
    "sg:address":"Prospect Chambers, 317/21, Dr. D.n. Road, Fort,",
    "sg:city":"Mumbai",
    "sg:classifiers":[
        {
            "category":"Home & Garden",
            "subcategory":"Mobile Homes",
            "type":"Retail Goods"
        }
    ],
    "sg:phone":"+91 22 2204 8881",
    "sg:postcode":"400001",
    "sg:tags":[
        "acid"
    ],
    "sg:website":"http://www.dmcc.com",
    "wof:name":"Dharamji Morarji Chemicals Co. Ltd.",
    "wof:placetype":"venue"
},
  "geometry": {"coordinates":[72.832695,18.933973],"type":"Point"}
}