{
  "type": "Feature",
  "properties": {
    "iso:country":"IN",
    "sg:address":"Lamington Rd, Grant Road",
    "sg:city":"Mumbai",
    "sg:phone":"+91 22 5660 6474",
    "sg:postcode":"400007",
    "sg:province":"Maharashtra",
    "wof:name":"Procal Electronics India Ltd",
    "wof:placetype":"venue"
},
  "geometry": {"coordinates":[72.817627,18.961979],"type":"Point"}
}