{
  "type": "Feature",
  "properties": {
    "iso:country":"IN",
    "sg:address":"Office No. 20/21, 178 Sant Tukaram Road, Masjid Bunder (east),",
    "sg:city":"Mumbai",
    "sg:classifiers":[
        {
            "category":"Manufacturing",
            "subcategory":"Textiles",
            "type":"Manufacturing & Wholesale Goods"
        }
    ],
    "sg:phone":"+91 22 3633 6636",
    "sg:postcode":"400009",
    "sg:tags":[
        "cotton"
    ],
    "wof:name":"D. P. Cotton Co.",
    "wof:placetype":"venue"
},
  "geometry": {"coordinates":[72.83902,18.951038],"type":"Point"}
}