{
  "type": "Feature",
  "properties": {
    "iso:country":"IN",
    "sg:address":"E Moses Road, Worli, Mumbai",
    "sg:city":"Mumbai",
    "sg:classifiers":[
        {
            "category":"Wholesale",
            "subcategory":"Drugs",
            "type":"Manufacturing & Wholesale Goods"
        }
    ],
    "sg:phone":"+91 22 6662 7000",
    "sg:postcode":"400018",
    "sg:tags":[
        "bulk"
    ],
    "wof:name":"Kopran Limited",
    "wof:placetype":"venue"
},
  "geometry": {"coordinates":[72.82653000000001,18.983915],"type":"Point"}
}