{
  "type": "Feature",
  "properties": {
    "iso:country":"IN",
    "sg:address":"No.2, Rayapuram First Street,",
    "sg:city":"Tiruppur",
    "sg:classifiers":[
        {
            "category":"Landmark",
            "subcategory":"City Walls",
            "type":"Public Place"
        }
    ],
    "sg:phone":"+91 421 223 5241",
    "sg:postcode":"641601",
    "sg:tags":[
        "woven"
    ],
    "wof:name":"Balu Expoters",
    "wof:placetype":"venue"
},
  "geometry": {"coordinates":[80.296127,13.120965],"type":"Point"}
}