{
  "type": "Feature",
  "properties": {
    "iso:country":"IN",
    "sg:address":"C-1/72, Phase-ii, Ashok Vihar,",
    "sg:city":"Delhi",
    "sg:classifiers":[
        {
            "category":"Home & Garden",
            "subcategory":"Building Materials",
            "type":"Retail Goods"
        }
    ],
    "sg:postcode":"110052",
    "sg:tags":[
        "sealant",
        "adhesive"
    ],
    "wof:name":"Paras Chemicals",
    "wof:placetype":"venue"
},
  "geometry": {"coordinates":[77.020462,28.488319],"type":"Point"}
}