{
  "type": "Feature",
  "properties": {
    "iso:country":"IN",
    "sg:address":"Bhagirath Palace",
    "sg:city":"Delhi",
    "sg:phone":"+91 11 2386 5069",
    "sg:postcode":"110006",
    "sg:province":"Delhi",
    "sg:website":"http://www.wonderlites.com",
    "wof:name":"Electromech Sales",
    "wof:placetype":"venue"
},
  "geometry": {"coordinates":[77.233307,28.657848],"type":"Point"}
}