{
  "type": "Feature",
  "properties": {
    "iso:country":"IN",
    "sg:address":"7/12, Industrial Suburb 2nd Stage, Yashwantpur,",
    "sg:city":"Bangalore",
    "sg:classifiers":[
        {
            "category":"Shopping",
            "subcategory":"Clothing, Apparel, & Fashions",
            "type":"Retail Goods"
        }
    ],
    "sg:phone":"+91 80 2357 3101",
    "sg:postcode":"560094",
    "sg:tags":[
        "undergarment"
    ],
    "sg:website":"http://www.enamor.co.in",
    "wof:name":"Gokuldas Intimate Pvt. Ltd.",
    "wof:placetype":"venue"
},
  "geometry": {"coordinates":[77.541702,13.015496],"type":"Point"}
}