{
  "type": "Feature",
  "properties": {
    "iso:country":"IN",
    "sg:address":"1417, Prasad Chambers, Opera House,",
    "sg:city":"Mumbai",
    "sg:classifiers":[
        {
            "category":"Shopping",
            "subcategory":"Jewelry",
            "type":"Retail Goods"
        }
    ],
    "sg:phone":"+91 22 2362 6221",
    "sg:postcode":"400004",
    "sg:tags":[
        "diamond"
    ],
    "wof:name":"Janupam Brothers",
    "wof:placetype":"venue"
},
  "geometry": {"coordinates":[72.817444,18.954645],"type":"Point"}
}