{
  "type": "Feature",
  "properties": {
    "iso:country":"IN",
    "sg:address":"Lbs Marg, Bhandup West,",
    "sg:city":"Mumbai",
    "sg:classifiers":[
        {
            "category":"Professional",
            "subcategory":"Engineering",
            "type":"Services"
        }
    ],
    "sg:phone":"+91 22 2594 7689",
    "sg:postcode":"400078",
    "sg:tags":[
        "equipment",
        "good"
    ],
    "sg:website":"http://www.gkwltd.com",
    "wof:name":"Gkw Limited",
    "wof:placetype":"venue"
},
  "geometry": {"coordinates":[72.928932,19.135406],"type":"Point"}
}