{
  "type": "Feature",
  "properties": {
    "iso:country":"IN",
    "sg:address":"#2628, 8th A Main, Bsk Ii Stage,",
    "sg:city":"Bangalore",
    "sg:classifiers":[
        {
            "category":"Professional",
            "subcategory":"Computer Services",
            "type":"Services"
        }
    ],
    "sg:phone":"+91 80 2676 4094",
    "sg:postcode":"560070",
    "sg:tags":[
        "software"
    ],
    "wof:name":"Sresta Business Management Solutions",
    "wof:placetype":"venue"
},
  "geometry": {"coordinates":[77.570976,12.92539],"type":"Point"}
}