{
  "type": "Feature",
  "properties": {
    "iso:country":"IN",
    "sg:address":"109, Housing Board Colony, Near Patel Nagar, Jharsa Road,",
    "sg:city":"Gurgaon",
    "sg:classifiers":[
        {
            "category":"Manufacturing",
            "subcategory":"Chemicals & Compounds",
            "type":"Manufacturing & Wholesale Goods"
        }
    ],
    "sg:phone":"+91 124 232 8794",
    "sg:postcode":"122001",
    "sg:tags":[
        "supply"
    ],
    "wof:name":"D. D. Metals",
    "wof:placetype":"venue"
},
  "geometry": {"coordinates":[77.039902,28.453859],"type":"Point"}
}