{
  "type": "Feature",
  "properties": {
    "iso:country":"IN",
    "sg:address":"W-37/a, Midc, Shirgaon, Badlapur",
    "sg:city":"Thane",
    "sg:classifiers":[
        {
            "category":"Manufacturing",
            "subcategory":"Chemicals & Compounds",
            "type":"Manufacturing & Wholesale Goods"
        }
    ],
    "sg:phone":"+91 251 269 1522",
    "sg:postcode":"421503",
    "sg:tags":[
        "supply"
    ],
    "sg:website":"http://www.twinklechemilab.com",
    "wof:name":"Twinkle Chemi Lab Pvt. Ltd.",
    "wof:placetype":"venue"
},
  "geometry": {"coordinates":[73.24597199999999,19.152477],"type":"Point"}
}