{
  "type": "Feature",
  "properties": {
    "iso:country":"IN",
    "sg:address":"5328/67, Hardyan Singh Road, Karol Bagh,",
    "sg:city":"New Delhi",
    "sg:classifiers":[
        {
            "category":"Shopping",
            "subcategory":"Luggage & Leather Goods",
            "type":"Retail Goods"
        }
    ],
    "sg:phone":"+91 11 2573 3717",
    "sg:postcode":"110005",
    "sg:tags":[
        "synthetic",
        "pu/pvc"
    ],
    "sg:website":"http://www.babaleather.com",
    "wof:name":"Baba Leather Impex Private Limited",
    "wof:placetype":"venue"
},
  "geometry": {"coordinates":[77.190765,28.650675],"type":"Point"}
}