{
  "type": "Feature",
  "properties": {
    "iso:country":"IN",
    "sg:address":"Western Express Highway, Mira",
    "sg:city":"Thane",
    "sg:phone":"+91 228458193",
    "sg:postcode":"401104",
    "sg:province":"Maharashtra",
    "wof:name":"Zenna Plastics Ltd",
    "wof:placetype":"venue"
},
  "geometry": {"coordinates":[72.871223,19.256865],"type":"Point"}
}