{
  "type": "Feature",
  "properties": {
    "iso:country":"IN",
    "sg:address":"Plot No. 152, Sector-25,",
    "sg:city":"Faridabad",
    "sg:classifiers":[
        {
            "category":"Manufacturing",
            "subcategory":"Rubber & Plastics",
            "type":"Manufacturing & Wholesale Goods"
        }
    ],
    "sg:phone":"+91 129 406 3345",
    "sg:postcode":"121006",
    "sg:tags":[
        "chemical",
        "-"
    ],
    "wof:name":"Stikon India",
    "wof:placetype":"venue"
},
  "geometry": {"coordinates":[77.306595,28.336205],"type":"Point"}
}