{
  "type": "Feature",
  "properties": {
    "iso:country":"IN",
    "sg:address":"No. 30, Raja Market,",
    "sg:city":"Bangalore",
    "sg:classifiers":[
        {
            "category":"Banks & Credit Unions",
            "subcategory":"Investment Brokerage",
            "type":"Services"
        }
    ],
    "sg:phone":"+91 80 2222 4054",
    "sg:postcode":"560002",
    "sg:tags":[
        "precious",
        "stone",
        "semi"
    ],
    "wof:name":"Original Baby Prakash Diamonds",
    "wof:placetype":"venue"
},
  "geometry": {"coordinates":[77.578705,12.967613],"type":"Point"}
}