{
  "type": "Feature",
  "properties": {
    "iso:country":"IN",
    "sg:address":"Sun Mill Road, Lower Parel",
    "sg:city":"Mumbai",
    "sg:phone":"+91 22 2496 4122",
    "sg:postcode":"400013",
    "sg:province":"Maharashtra",
    "wof:name":"Finix Rubber Works",
    "wof:placetype":"venue"
},
  "geometry": {"coordinates":[72.829086,18.996618],"type":"Point"}
}