{
  "type": "Feature",
  "properties": {
    "iso:country":"IN",
    "sg:address":"100/107, Sampige Road, 7th Cross, Malleswaram,",
    "sg:city":"Bangalore",
    "sg:classifiers":[
        {
            "category":"Retail",
            "subcategory":"Emissions Testing",
            "type":"Services"
        }
    ],
    "sg:phone":"+91 80 2334 1355",
    "sg:postcode":"560003",
    "sg:tags":[
        "measuring",
        "instrument"
    ],
    "sg:website":"http://www.elico-india.com",
    "wof:name":"Elico Limited",
    "wof:placetype":"venue"
},
  "geometry": {"coordinates":[77.571388,12.998337],"type":"Point"}
}