{
  "type": "Feature",
  "properties": {
    "iso:country":"IN",
    "sg:address":"No.6, Railway Station Road,",
    "sg:city":"Tuticorin",
    "sg:classifiers":[
        {
            "category":"Home & Garden",
            "subcategory":"Building Materials",
            "type":"Retail Goods"
        }
    ],
    "sg:phone":"+91 44612300007",
    "sg:postcode":"628001",
    "sg:tags":[
        "granite"
    ],
    "wof:name":"Bagavathi Shipping Services",
    "wof:placetype":"venue"
},
  "geometry": {"coordinates":[76.35672,10.107749],"type":"Point"}
}