{
  "type": "Feature",
  "properties": {
    "iso:country":"IN",
    "sg:address":"390, 13th Cross Sadashiva Nagar,",
    "sg:city":"Bangalore",
    "sg:orig_category":"Pvc & Hdpe Pipes",
    "sg:phone":"+91 80 4124 7970",
    "sg:postcode":"560080",
    "wof:name":"Lektreka Corporation",
    "wof:placetype":"venue"
},
  "geometry": {"coordinates":[77.579643,13.007655],"type":"Point"}
}