{
  "type": "Feature",
  "properties": {
    "iso:country":"IN",
    "sg:address":"31, Bommasandra Industrial Area,",
    "sg:city":"Bangalore",
    "sg:classifiers":[
        {
            "category":"Wholesale",
            "subcategory":"Electrical",
            "type":"Manufacturing & Wholesale Goods"
        }
    ],
    "sg:phone":"+91 80 2783 4978",
    "sg:postcode":"560099",
    "sg:tags":[
        "voltage",
        "stabilizer"
    ],
    "sg:website":"http://www.intravidyut.trade-india.com",
    "wof:name":"Intra Vidyut Limited",
    "wof:placetype":"venue"
},
  "geometry": {"coordinates":[77.685104,12.816192],"type":"Point"}
}