{
  "type": "Feature",
  "properties": {
    "iso:country":"IN",
    "sg:address":"83, Narayan Dhuru Street, 2nd Floor,",
    "sg:city":"Mumbai",
    "sg:classifiers":[
        {
            "category":"Military Area",
            "subcategory":"Air Force Base",
            "type":"Public Place"
        }
    ],
    "sg:phone":"+91 22 2343 7539",
    "sg:postcode":"400003",
    "sg:tags":[
        "indicator",
        "electronic",
        "controller",
        "liquid",
        "level"
    ],
    "wof:name":"Mahavir Thermo Equipment",
    "wof:placetype":"venue"
},
  "geometry": {"coordinates":[72.833771,18.949526],"type":"Point"}
}