{
  "type": "Feature",
  "properties": {
    "iso:country":"IN",
    "sg:address":"Birhana Road",
    "sg:city":"Kanpur",
    "sg:phone":"+91 512363491",
    "sg:postcode":"208001",
    "sg:province":"Uttar Pradesh",
    "sg:website":"http://www.arthermoset.com",
    "wof:name":"A R Thermosets Pvt Ltd",
    "wof:placetype":"venue"
},
  "geometry": {"coordinates":[80.35453,26.462782],"type":"Point"}
}