{
  "type": "Feature",
  "properties": {
    "iso:country":"IN",
    "sg:address":"230, Industrial Area-a,",
    "sg:city":"Ludhiana",
    "sg:classifiers":[
        {
            "category":"Manufacturing",
            "subcategory":"Chemicals & Compounds",
            "type":"Manufacturing & Wholesale Goods"
        }
    ],
    "sg:phone":"+91 161 283 8311",
    "sg:postcode":"141003",
    "sg:tags":[
        "supply"
    ],
    "sg:website":"http://www.vsogroup.com/denim",
    "wof:name":"Malwa Industries Limited",
    "wof:placetype":"venue"
},
  "geometry": {"coordinates":[74.787102,13.334578],"type":"Point"}
}