{
  "type": "Feature",
  "properties": {
    "iso:country":"IN",
    "sg:address":"B-60, Pushpanjali Enclave, Pitampura,",
    "sg:city":"Delhi",
    "sg:classifiers":[
        {
            "category":"Manufacturing",
            "subcategory":"Rubber & Plastics",
            "type":"Manufacturing & Wholesale Goods"
        }
    ],
    "sg:phone":"+91 11 2703 0492",
    "sg:postcode":"110035",
    "sg:tags":[
        "product"
    ],
    "sg:website":"http://www.cemcongroup.net",
    "wof:name":"Cemcon Engineering Co. Pvt. Ltd.",
    "wof:placetype":"venue"
},
  "geometry": {"coordinates":[77.111839,28.694216],"type":"Point"}
}