{
  "type": "Feature",
  "properties": {
    "iso:country":"IN",
    "sg:address":"Court Chambers, No 4-b-1, New Marine Lines, No 35,",
    "sg:city":"Mumbai",
    "sg:classifiers":[
        {
            "category":"Manufacturing",
            "subcategory":"Motor Vehicles & Parts",
            "type":"Manufacturing & Wholesale Goods"
        }
    ],
    "sg:phone":"+91 22 2200 3791",
    "sg:postcode":"400020",
    "sg:tags":[
        "component",
        "product",
        "electronic"
    ],
    "wof:name":"Triveenus Impex & Trading Pvt. Ltd.",
    "wof:placetype":"venue"
},
  "geometry": {"coordinates":[72.828903,18.938452],"type":"Point"}
}