{
  "type": "Feature",
  "properties": {
    "iso:country":"IN",
    "sg:address":"A-14, Midc, Street No. 5, Cross Road 'b', Andheri (e),",
    "sg:city":"Mumbai",
    "sg:classifiers":[
        {
            "category":"Wholesale",
            "subcategory":"Drugs",
            "type":"Manufacturing & Wholesale Goods"
        }
    ],
    "sg:phone":"+91 22 2832 7321",
    "sg:postcode":"400093",
    "sg:tags":[
        "bulk"
    ],
    "sg:website":"http://www.niveditanet.com",
    "wof:name":"Nivedita Chemicals Pvt. Ltd.",
    "wof:placetype":"venue"
},
  "geometry": {"coordinates":[72.868431,19.11796],"type":"Point"}
}