{
  "type": "Feature",
  "properties": {
    "iso:country":"IN",
    "sg:address":"F-5, Midc, Ambad,",
    "sg:city":"Nashik",
    "sg:classifiers":[
        {
            "category":"Manufacturing",
            "subcategory":"Chemicals & Compounds",
            "type":"Manufacturing & Wholesale Goods"
        }
    ],
    "sg:phone":"+91 253 654 2027",
    "sg:postcode":"422010",
    "sg:tags":[
        "resin"
    ],
    "wof:name":"Imperial & Osaka Medical Co. (i) Pvt. Ltd.",
    "wof:placetype":"venue"
},
  "geometry": {"coordinates":[73.737488,19.960199],"type":"Point"}
}