{
  "type": "Feature",
  "properties": {
    "iso:country":"IN",
    "sg:address":"Bhat Bazar",
    "sg:city":"Mumbai",
    "sg:phone":"+91 22 2371 5095",
    "sg:postcode":"400009",
    "sg:province":"Maharashtra",
    "wof:name":"Unique Impex",
    "wof:placetype":"venue"
},
  "geometry": {"coordinates":[72.835854,18.954861],"type":"Point"}
}