{
  "type": "Feature",
  "properties": {
    "iso:country":"IN",
    "sg:address":"340, New Cloth Market, Raipur,",
    "sg:city":"Ahmedabad",
    "sg:classifiers":[
        {
            "category":"Manufacturing",
            "subcategory":"Chemicals & Compounds",
            "type":"Manufacturing & Wholesale Goods"
        }
    ],
    "sg:phone":"+91 79 2216 5280",
    "sg:postcode":"380002",
    "sg:tags":[
        "dye",
        "intermediate"
    ],
    "wof:name":"Juhi Impex",
    "wof:placetype":"venue"
},
  "geometry": {"coordinates":[72.59996,23.017845],"type":"Point"}
}