{
  "type": "Feature",
  "properties": {
    "iso:country":"IN",
    "sg:address":"506, Arun Chambers, Tardeo Road, Tardeo,",
    "sg:city":"Mumbai",
    "sg:classifiers":[
        {
            "category":"Utilities",
            "subcategory":"Natural Gas",
            "type":"Services"
        }
    ],
    "sg:phone":"+91 22 2496 4148",
    "sg:postcode":"400034",
    "sg:tags":[
        "industrial"
    ],
    "wof:name":"Srf Limited",
    "wof:placetype":"venue"
},
  "geometry": {"coordinates":[72.81379699999999,18.973169],"type":"Point"}
}