{
  "type": "Feature",
  "properties": {
    "iso:country":"IN",
    "sg:address":"Swamy Sivananda Salai",
    "sg:city":"Chennai",
    "sg:phone":"+91 44 2536 5636",
    "sg:postcode":"600007",
    "sg:province":"Tamil Nadu",
    "wof:name":"Marine Container Services (south) Pvt Ltd",
    "wof:placetype":"venue"
},
  "geometry": {"coordinates":[80.278366,13.069211],"type":"Point"}
}