{
  "type": "Feature",
  "properties": {
    "iso:country":"IN",
    "sg:address":"P.o. Box 10-3-193/13, Humayun Nagar,",
    "sg:city":"Hyderabad",
    "sg:classifiers":[
        {
            "category":"Manufacturing",
            "subcategory":"Rubber & Plastics",
            "type":"Manufacturing & Wholesale Goods"
        }
    ],
    "sg:phone":"+91 40 2353 6151",
    "sg:postcode":"500028",
    "sg:tags":[
        "product"
    ],
    "sg:website":"http://www.maasimpex.com",
    "wof:name":"Maas Impex",
    "wof:placetype":"venue"
},
  "geometry": {"coordinates":[78.444641,17.397192],"type":"Point"}
}