{
  "type": "Feature",
  "properties": {
    "iso:country":"IN",
    "sg:address":"R.n.t.marg",
    "sg:city":"Indore",
    "sg:phone":"+91 731514081",
    "sg:postcode":"452001",
    "sg:province":"Madhya Pradesh",
    "sg:website":"http://www.shreemaya.com",
    "wof:name":"Hotel Shreemaya",
    "wof:placetype":"venue"
},
  "geometry": {"coordinates":[75.873611,22.716345],"type":"Point"}
}