{
  "type": "Feature",
  "properties": {
    "iso:country":"IN",
    "sg:address":"408, Apeejay Bldg., 4th Floor, Fort,",
    "sg:city":"Mumbai",
    "sg:classifiers":[
        {
            "category":"Manufacturing",
            "subcategory":"Chemicals & Compounds",
            "type":"Manufacturing & Wholesale Goods"
        }
    ],
    "sg:phone":"+91 22 2282 4084",
    "sg:postcode":"400001",
    "sg:tags":[
        "dye",
        "intermediate"
    ],
    "wof:name":"Sumeeka Exports & Imports (p) Ltd.",
    "wof:placetype":"venue"
},
  "geometry": {"coordinates":[72.833763,18.928326],"type":"Point"}
}