{
  "type": "Feature",
  "properties": {
    "iso:country":"IN",
    "sg:address":"D-98, M.i.d.c.,",
    "sg:city":"Ahmednagar",
    "sg:classifiers":[
        {
            "category":"Utilities",
            "subcategory":"Natural Gas",
            "type":"Services"
        }
    ],
    "sg:phone":"+91 241 277 8142",
    "sg:postcode":"414111",
    "sg:tags":[
        "industrial"
    ],
    "wof:name":"Bnl Ammonia Pvt. Ltd.",
    "wof:placetype":"venue"
},
  "geometry": {"coordinates":[76.536209,9.057627],"type":"Point"}
}