{
  "type": "Feature",
  "properties": {
    "iso:country":"IN",
    "sg:address":"Western Express Highway, Goregaon (e),",
    "sg:city":"Mumbai",
    "sg:classifiers":[
        {
            "category":"Food & Beverages",
            "subcategory":"Dairy",
            "type":"Retail Goods"
        }
    ],
    "sg:phone":"+91 22 2685 6071",
    "sg:postcode":"400065",
    "sg:tags":[
        "product"
    ],
    "sg:website":"http://www.mahanand.in",
    "wof:name":"Mahanand Dairy",
    "wof:placetype":"venue"
},
  "geometry": {"coordinates":[72.858315,19.163736],"type":"Point"}
}