{
  "type": "Feature",
  "properties": {
    "iso:country":"IN",
    "sg:address":"131, Keshab Chandra Sen Street,",
    "sg:city":"Kolkata",
    "sg:classifiers":[
        {
            "category":"Manufacturing",
            "subcategory":"Rubber & Plastics",
            "type":"Manufacturing & Wholesale Goods"
        }
    ],
    "sg:phone":"+91 33 2354 3043",
    "sg:postcode":"700009",
    "sg:tags":[
        "product"
    ],
    "wof:name":"New India Rubber Works (p) Ltd.",
    "wof:placetype":"venue"
},
  "geometry": {"coordinates":[88.369225,22.577822],"type":"Point"}
}