{
  "type": "Feature",
  "properties": {
    "iso:country":"IN",
    "sg:address":"A-102a, 3rd Main Road, 2nd Stage, Peenya Industrial Estate,",
    "sg:city":"Bangalore",
    "sg:classifiers":[
        {
            "category":"Manufacturing",
            "subcategory":"Rubber & Plastics",
            "type":"Manufacturing & Wholesale Goods"
        }
    ],
    "sg:phone":"+91 80 6558 4696",
    "sg:postcode":"560058",
    "sg:tags":[
        "product"
    ],
    "sg:website":"http://www.brahad.com",
    "wof:name":"Brahad Elastomers (p) Ltd.",
    "wof:placetype":"venue"
},
  "geometry": {"coordinates":[77.547676,13.009836],"type":"Point"}
}