{
  "type": "Feature",
  "properties": {
    "iso:country":"IN",
    "sg:address":"No.v-31, 10th Main, 2nd Stage, Peenya Industrial Area,",
    "sg:city":"Bangalore",
    "sg:classifiers":[
        {
            "category":"Wholesale",
            "subcategory":"Chemicals & Plastics",
            "type":"Manufacturing & Wholesale Goods"
        }
    ],
    "sg:phone":"+91 80 2836 4585",
    "sg:postcode":"560058",
    "sg:tags":[
        "lab",
        "supply"
    ],
    "sg:website":"http://www.leonidchemicals.com",
    "wof:name":"Leonid Chemicals Pvt. Ltd.",
    "wof:placetype":"venue"
},
  "geometry": {"coordinates":[77.547539,13.014249],"type":"Point"}
}