{
  "type": "Feature",
  "properties": {
    "iso:country":"IN",
    "sg:address":"Kottigepalya Magadi Main Road",
    "sg:city":"Bangalore",
    "sg:phone":"+91 8022213872272",
    "sg:postcode":"560091",
    "sg:province":"Karnataka",
    "sg:website":"http://www.holosecurity.com",
    "wof:name":"Paras Poly Pack",
    "wof:placetype":"venue"
},
  "geometry": {"coordinates":[77.513618,12.987549],"type":"Point"}
}