{
  "type": "Feature",
  "properties": {
    "iso:country":"IN",
    "sg:address":"Shivajinagar",
    "sg:city":"Pune",
    "sg:phone":"+91 20 2553 4988",
    "sg:postcode":"411005",
    "sg:province":"Maharashtra",
    "wof:name":"Kirloskar Copeland Ltd",
    "wof:placetype":"venue"
},
  "geometry": {"coordinates":[77.305161,19.164877],"type":"Point"}
}