{
  "type": "Feature",
  "properties": {
    "iso:country":"IN",
    "sg:address":"Electric Mansion, 6th Floor, A.m. Marg, Prabhadevi,",
    "sg:city":"Mumbai",
    "sg:classifiers":[
        {
            "category":"Wholesale",
            "subcategory":"Vending Machines",
            "type":"Manufacturing & Wholesale Goods"
        }
    ],
    "sg:phone":"+91 22 2430 6237",
    "sg:postcode":"400025",
    "sg:tags":[
        "funicular",
        "car",
        "elevator"
    ],
    "sg:website":"http://www.bharatbijlee.com",
    "wof:name":"Bharat Bijlee Limited",
    "wof:placetype":"venue"
},
  "geometry": {"coordinates":[72.828781,19.01132],"type":"Point"}
}