{
  "type": "Feature",
  "properties": {
    "iso:country":"IN",
    "sg:address":"367, Farsh Bazar, Shahdara,",
    "sg:city":"Delhi",
    "sg:classifiers":[
        {
            "category":"Manufacturing",
            "subcategory":"Chemicals & Compounds",
            "type":"Manufacturing & Wholesale Goods"
        }
    ],
    "sg:phone":"+91 11 2386 1034",
    "sg:postcode":"110032",
    "sg:tags":[
        "supply"
    ],
    "wof:name":"Shree Gobind Pharmaceuticlas Pvt. Ltd.",
    "wof:placetype":"venue"
},
  "geometry": {"coordinates":[77.290436,28.669384],"type":"Point"}
}