{
  "type": "Feature",
  "properties": {
    "iso:country":"IN",
    "sg:address":"II Floor, Balammal Building No 33, Burkit Road, T Nagar",
    "sg:city":"Chennai",
    "sg:classifiers":[
        {
            "category":"Professional",
            "subcategory":"Computer Services",
            "type":"Services"
        }
    ],
    "sg:postcode":"600017",
    "sg:tags":[
        "telecom-opportunities",
        "robust-platforms",
        "telecom-media"
    ],
    "sg:website":"http://www.one97world.com",
    "wof:name":"One97 Communications",
    "wof:placetype":"venue"
},
  "geometry": {"coordinates":[80.229215,13.036476],"type":"Point"}
}