{
  "type": "Feature",
  "properties": {
    "iso:country":"IN",
    "sg:address":"No-28, 1st Floor, G.p.s. Complex, J.m. Road,",
    "sg:city":"Bangalore",
    "sg:classifiers":[
        {
            "category":"Shopping",
            "subcategory":"Crafts & Fabrics",
            "type":"Retail Goods"
        }
    ],
    "sg:phone":"+91 80 2224 2218",
    "sg:postcode":"560002",
    "sg:tags":[
        "silk"
    ],
    "wof:name":"C. M. Silks",
    "wof:placetype":"venue"
},
  "geometry": {"coordinates":[72.667412,23.212027],"type":"Point"}
}