{
  "type": "Feature",
  "properties": {
    "iso:country":"IN",
    "sg:address":"G.t.road",
    "sg:city":"Panipat",
    "sg:phone":"+91 174267997",
    "sg:postcode":"132103",
    "sg:province":"Haryana",
    "sg:website":"http://www.poojaexports.com",
    "wof:name":"Pooja Exports",
    "wof:placetype":"venue"
},
  "geometry": {"coordinates":[76.96347799999999,29.768011],"type":"Point"}
}