{
  "type": "Feature",
  "properties": {
    "iso:country":"IN",
    "sg:address":"No. B-229, 5th Main, 2nd Stage, Peenya Industrial Estate, Peenya,",
    "sg:city":"Bangalore",
    "sg:orig_category":"Foam,rexine & P.u.products",
    "sg:phone":"+91 80 2836 0042",
    "sg:postcode":"560058",
    "wof:name":"Premier Packaging",
    "wof:placetype":"venue"
},
  "geometry": {"coordinates":[77.516006,13.023997],"type":"Point"}
}