{
  "type": "Feature",
  "properties": {
    "iso:country":"IN",
    "sg:address":"Building 'c', Satam Industrial Estate, Chakala, Andheri (e),",
    "sg:city":"Mumbai",
    "sg:classifiers":[
        {
            "category":"Wholesale",
            "subcategory":"Machinery & Supplies",
            "type":"Manufacturing & Wholesale Goods"
        }
    ],
    "sg:phone":"+91 22 5692 3237",
    "sg:postcode":"400099",
    "sg:tags":[
        "equipment",
        "goods",
        "electrical"
    ],
    "wof:name":"Unicon Connectors Pvt. Ltd.",
    "wof:placetype":"venue"
},
  "geometry": {"coordinates":[72.859482,19.11231],"type":"Point"}
}