{
  "type": "Feature",
  "properties": {
    "iso:country":"IN",
    "sg:address":"73, Solomon, Sherly Rajan Road, Bandra (w),",
    "sg:city":"Mumbai",
    "sg:classifiers":[
        {
            "category":"Personal",
            "subcategory":"Hair Removal",
            "type":"Services"
        }
    ],
    "sg:phone":"+91 22 2648 0730",
    "sg:tags":[
        "cosmetic",
        "accessory"
    ],
    "wof:name":"Ashford Labs. Pvt. Ltd.",
    "wof:placetype":"venue"
},
  "geometry": {"coordinates":[72.830872,19.054758],"type":"Point"}
}