{
  "type": "Feature",
  "properties": {
    "iso:country":"IN",
    "sg:address":"W-70-b, M.i.d.c., Tarapur,",
    "sg:city":"Boisar",
    "sg:classifiers":[
        {
            "category":"Real Estate",
            "subcategory":"Surveying",
            "type":"Services"
        }
    ],
    "sg:phone":"+91 22 2766 2804",
    "sg:postcode":"401504",
    "sg:tags":[
        "pharmaceutical",
        "material",
        "raw"
    ],
    "wof:name":"Raj Lalita Chemicals Private Limited",
    "wof:placetype":"venue"
},
  "geometry": {"coordinates":[72.714149,19.872936],"type":"Point"}
}