{
  "type": "Feature",
  "properties": {
    "iso:country":"IN",
    "sg:address":"1020, Bootee Street, Camp,",
    "sg:city":"Pune",
    "sg:classifiers":[
        {
            "category":"Manufacturing",
            "subcategory":"Rubber & Plastics",
            "type":"Manufacturing & Wholesale Goods"
        }
    ],
    "sg:phone":"+91 20 2611 4602",
    "sg:postcode":"411001",
    "sg:tags":[
        "product"
    ],
    "wof:name":"Frank International",
    "wof:placetype":"venue"
},
  "geometry": {"coordinates":[73.877106,18.517031],"type":"Point"}
}