{
  "type": "Feature",
  "properties": {
    "iso:country":"IN",
    "sg:address":"1/4, Abdul Halim Lane,",
    "sg:city":"Kolkata",
    "sg:classifiers":[
        {
            "category":"Manufacturing",
            "subcategory":"Chemicals & Compounds",
            "type":"Manufacturing & Wholesale Goods"
        }
    ],
    "sg:phone":"+91 33 2244 1680",
    "sg:postcode":"700016",
    "sg:tags":[
        "supply"
    ],
    "wof:name":"Uni Print-o-chem Pvt. Ltd.",
    "wof:placetype":"venue"
},
  "geometry": {"coordinates":[88.36225899999999,22.556757],"type":"Point"}
}