{
  "type": "Feature",
  "properties": {
    "iso:country":"IN",
    "sg:address":"35-a, Udyog Nagaer,",
    "sg:city":"Kanpur",
    "sg:classifiers":[
        {
            "category":"Manufacturing",
            "subcategory":"Rubber & Plastics",
            "type":"Manufacturing & Wholesale Goods"
        }
    ],
    "sg:postcode":"208022",
    "sg:tags":[
        "product"
    ],
    "wof:name":"Time Rubber Factory",
    "wof:placetype":"venue"
},
  "geometry": {"coordinates":[72.846382,19.171909],"type":"Point"}
}