{
  "type": "Feature",
  "properties": {
    "iso:country":"IN",
    "sg:address":"Plot No. 127, Gidc,",
    "sg:city":"Umbergaon",
    "sg:classifiers":[
        {
            "category":"Manufacturing",
            "subcategory":"Tools & Machinery",
            "type":"Manufacturing & Wholesale Goods"
        }
    ],
    "sg:phone":"+91 260 256 3391",
    "sg:postcode":"396171",
    "sg:tags":[
        "processing",
        "plastic"
    ],
    "sg:website":"http://www.panchal-plastic.com",
    "wof:name":"Panchal Plastic Machinery Pvt. Ltd.",
    "wof:placetype":"venue"
},
  "geometry": {"coordinates":[70.826859,22.280378],"type":"Point"}
}