{
  "type": "Feature",
  "properties": {
    "iso:country":"IN",
    "sg:address":"Basti Bawa Khel,",
    "sg:city":"Jalandhar",
    "sg:classifiers":[
        {
            "category":"Manufacturing",
            "subcategory":"Rubber & Plastics",
            "type":"Manufacturing & Wholesale Goods"
        }
    ],
    "sg:phone":"+91 181 225 7898",
    "sg:postcode":"144021",
    "sg:tags":[
        "product"
    ],
    "wof:name":"Rubber Wing",
    "wof:placetype":"venue"
},
  "geometry": {"coordinates":[75.540222,31.335741],"type":"Point"}
}