{
  "type": "Feature",
  "properties": {
    "iso:country":"IN",
    "sg:address":"Jubilee Hills",
    "sg:city":"Hyderabad",
    "sg:phone":"+91 4023352130235",
    "sg:postcode":"500033",
    "sg:province":"Andhra Pradesh",
    "sg:website":"http://www.macinfo.net",
    "wof:name":"Mac Info (p) Ltd",
    "wof:placetype":"venue"
},
  "geometry": {"coordinates":[78.412659,17.429531],"type":"Point"}
}