{
  "type": "Feature",
  "properties": {
    "iso:country":"IN",
    "sg:address":"Netaji Subhash Marg, Daryaganj",
    "sg:city":"New Delhi",
    "sg:phone":"+91 11 2327 1898",
    "sg:postcode":"110002",
    "sg:province":"Delhi",
    "wof:name":"Hindustan Refrigeration Stores",
    "wof:placetype":"venue"
},
  "geometry": {"coordinates":[77.236633,28.654295],"type":"Point"}
}