{
  "type": "Feature",
  "properties": {
    "iso:country":"IN",
    "sg:address":"2, Railway Station Road,",
    "sg:city":"Mettupalayam",
    "sg:classifiers":[
        {
            "category":"Home & Garden",
            "subcategory":"Garden Supply",
            "type":"Retail Goods"
        }
    ],
    "sg:phone":"+91 4254 223 074",
    "sg:postcode":"641301",
    "sg:tags":[
        "fertilizer"
    ],
    "wof:name":"Mettupalayam Mills And General Trades P Ltd.",
    "wof:placetype":"venue"
},
  "geometry": {"coordinates":[76.35672,10.107749],"type":"Point"}
}