{
  "type": "Feature",
  "properties": {
    "iso:country":"IN",
    "sg:address":"B-17, B.s. Road, Ndustrial Area,",
    "sg:city":"Ghaziabad",
    "sg:classifiers":[
        {
            "category":"Manufacturing",
            "subcategory":"Chemicals & Compounds",
            "type":"Manufacturing & Wholesale Goods"
        }
    ],
    "sg:phone":"+91 120 656 1471",
    "sg:postcode":"201009",
    "sg:tags":[
        "plant",
        "processing"
    ],
    "wof:name":"Mag-tech Engineers",
    "wof:placetype":"venue"
},
  "geometry": {"coordinates":[76.230438,21.325993],"type":"Point"}
}