{
  "type": "Feature",
  "properties": {
    "iso:country":"IN",
    "sg:address":"611/b , Silverlin, Sayajiganj,",
    "sg:city":"Vadodara",
    "sg:classifiers":[
        {
            "category":"Home & Garden",
            "subcategory":"Garden Supply",
            "type":"Retail Goods"
        }
    ],
    "sg:phone":"+91 265 329 0337",
    "sg:postcode":"390005",
    "sg:tags":[
        "fertilizer"
    ],
    "wof:name":"Rem Organics",
    "wof:placetype":"venue"
},
  "geometry": {"coordinates":[73.183594,22.307827],"type":"Point"}
}