{
  "type": "Feature",
  "properties": {
    "iso:country":"IN",
    "sg:address":"C1/b, 2513/c, G.i.d.c. Estate,",
    "sg:city":"Ankleshwar",
    "sg:classifiers":[
        {
            "category":"Manufacturing",
            "subcategory":"Chemicals & Compounds",
            "type":"Manufacturing & Wholesale Goods"
        }
    ],
    "sg:phone":"+91 26462203132515",
    "sg:tags":[
        "dye",
        "intermediate"
    ],
    "wof:name":"Jay Khodiyar Chemicals",
    "wof:placetype":"venue"
},
  "geometry": {"coordinates":[77.61428100000001,12.97456],"type":"Point"}
}