{
  "type": "Feature",
  "properties": {
    "iso:country":"IN",
    "sg:address":"C-418, 4th Floor, Kailas Esplanade, Ghatkapar,",
    "sg:city":"Mumbai",
    "sg:classifiers":[
        {
            "category":"Shopping",
            "subcategory":"Crafts & Fabrics",
            "type":"Retail Goods"
        }
    ],
    "sg:phone":"+91 22 2500 3720",
    "sg:postcode":"400086",
    "wof:name":"Xena Trading Corporation",
    "wof:placetype":"venue"
},
  "geometry": {"coordinates":[72.913483,19.093426],"type":"Point"}
}