{
  "type": "Feature",
  "properties": {
    "iso:country":"IN",
    "sg:address":"Andheri (e)",
    "sg:city":"Mumbai",
    "sg:phone":"+91 22 2850 4499",
    "sg:postcode":"400059",
    "sg:province":"Maharashtra",
    "wof:name":"Bombay Carbon & Metcaps Pvt Ltd",
    "wof:placetype":"venue"
},
  "geometry": {"coordinates":[72.86927,19.11302],"type":"Point"}
}