{
  "type": "Feature",
  "properties": {
    "iso:country":"IN",
    "sg:address":"521, Lahori Gate, Naya Bazaar,",
    "sg:city":"Delhi",
    "sg:classifiers":[
        {
            "category":"Home & Garden",
            "subcategory":"Mobile Homes",
            "type":"Retail Goods"
        }
    ],
    "sg:phone":"+91 11 2396 6241",
    "sg:postcode":"110006",
    "sg:tags":[
        "acid"
    ],
    "wof:name":"Kedar Nath & Co.",
    "wof:placetype":"venue"
},
  "geometry": {"coordinates":[77.21363100000001,28.658339],"type":"Point"}
}