{
  "type": "Feature",
  "properties": {
    "iso:country":"IN",
    "sg:address":"161/1, Mahatma Gandhi Road, (3rd Floor, Room No: 77),",
    "sg:city":"Kolkata",
    "sg:classifiers":[
        {
            "category":"Manufacturing",
            "subcategory":"Chemicals & Compounds",
            "type":"Manufacturing & Wholesale Goods"
        }
    ],
    "sg:phone":"+91 33 2270 8999",
    "sg:postcode":"700007",
    "sg:tags":[
        "supply"
    ],
    "wof:name":"Vinayak Sales Corporation",
    "wof:placetype":"venue"
},
  "geometry": {"coordinates":[80.52063,16.589197],"type":"Point"}
}