{
  "type": "Feature",
  "properties": {
    "iso:country":"IN",
    "sg:address":"8/10, Mettupalayam Road, Gn Mills Post,",
    "sg:city":"Coimbatore",
    "sg:classifiers":[
        {
            "category":"Manufacturing",
            "subcategory":"Rubber & Plastics",
            "type":"Manufacturing & Wholesale Goods"
        }
    ],
    "sg:phone":"+91 422 264 2909",
    "sg:postcode":"641029",
    "sg:tags":[
        "product"
    ],
    "sg:website":"http://www.chandysons.net",
    "wof:name":"Chandy Sons Industrial Mouldings",
    "wof:placetype":"venue"
},
  "geometry": {"coordinates":[76.944641,11.059973],"type":"Point"}
}