{
  "type": "Feature",
  "properties": {
    "iso:country":"IN",
    "sg:address":"Camac Street",
    "sg:city":"Kolkata",
    "sg:phone":"+91 33 2282 7531",
    "sg:postcode":"700017",
    "sg:province":"West Bengal",
    "wof:name":"Jayshree Tea & Industry",
    "wof:placetype":"venue"
},
  "geometry": {"coordinates":[88.353065,22.546921],"type":"Point"}
}