{
  "type": "Feature",
  "properties": {
    "iso:country":"IN",
    "sg:address":"658, Basettypet Chickpet Cross,",
    "sg:city":"Bangalore",
    "sg:classifiers":[
        {
            "category":"Shopping",
            "subcategory":"Crafts & Fabrics",
            "type":"Retail Goods"
        }
    ],
    "sg:phone":"+91 80 2228 0854",
    "sg:postcode":"560053",
    "sg:tags":[
        "silk"
    ],
    "wof:name":"Sri Kirshna Silk Fabrics",
    "wof:placetype":"venue"
},
  "geometry": {"coordinates":[77.575935,12.970312],"type":"Point"}
}