{
  "type": "Feature",
  "properties": {
    "iso:country":"IN",
    "sg:address":"23, K.p.n. Colony, 1st Street,",
    "sg:city":"Tirupur",
    "sg:classifiers":[
        {
            "category":"Utilities",
            "subcategory":"Mobile Phone",
            "type":"Services"
        }
    ],
    "sg:phone":"+91 421 224 2904",
    "sg:postcode":"641601",
    "sg:tags":[
        "outerwear"
    ],
    "wof:name":"East West Agencies",
    "wof:placetype":"venue"
},
  "geometry": {"coordinates":[80.21781900000001,13.061496],"type":"Point"}
}