{
  "type": "Feature",
  "properties": {
    "iso:country":"IN",
    "sg:address":"126/a, Bepin Behari, Ganguly Street,",
    "sg:city":"Kolkata",
    "sg:classifiers":[
        {
            "category":"Manufacturing",
            "subcategory":"Pet Food",
            "type":"Manufacturing & Wholesale Goods"
        }
    ],
    "sg:phone":"+91 33 2227 2625",
    "sg:postcode":"700012",
    "sg:tags":[
        "additive",
        "flavour"
    ],
    "sg:website":"http://www.aksorganich.com",
    "wof:name":"Calcutta Chemical Corporation",
    "wof:placetype":"venue"
},
  "geometry": {"coordinates":[88.366592,22.567659],"type":"Point"}
}