{
  "type": "Feature",
  "properties": {
    "iso:country":"IN",
    "sg:address":"Ghatkopar Industrial Estate, C-230, L.b.s. Marg, Ghatkopar (w),",
    "sg:city":"Mumbai",
    "sg:classifiers":[
        {
            "category":"Shopping",
            "subcategory":"Party Supplies",
            "type":"Retail Goods"
        }
    ],
    "sg:phone":"+91 22 2500 8616",
    "sg:postcode":"400086",
    "sg:tags":[
        "equipment",
        "baker"
    ],
    "wof:name":"Dairy Udyog",
    "wof:placetype":"venue"
},
  "geometry": {"coordinates":[72.913574,19.097116],"type":"Point"}
}