{
  "type": "Feature",
  "properties": {
    "iso:country":"IN",
    "sg:address":"Bakaram",
    "sg:city":"Hyderabad",
    "sg:phone":"+91 40 5652 9501",
    "sg:postcode":"560048",
    "sg:province":"Andhra Pradesh",
    "wof:name":"South India Prime Tannery Pvt Ltd",
    "wof:placetype":"venue"
},
  "geometry": {"coordinates":[78.496506,17.418409],"type":"Point"}
}