{
  "type": "Feature",
  "properties": {
    "iso:country":"IN",
    "sg:address":"100, Market Yard, N.g.,",
    "sg:city":"Unjha",
    "sg:classifiers":[
        {
            "category":"Home & Garden",
            "subcategory":"Garden Supply",
            "type":"Retail Goods"
        }
    ],
    "sg:phone":"+91 2767 252 694",
    "sg:postcode":"384170",
    "sg:tags":[
        "seed"
    ],
    "wof:name":"Guru Sons.",
    "wof:placetype":"venue"
},
  "geometry": {"coordinates":[73.867638,18.48687],"type":"Point"}
}