{
  "type": "Feature",
  "properties": {
    "iso:country":"IN",
    "sg:address":"113-114, Sharma Industrial Estate, Goregaon(e),",
    "sg:city":"Mumbai",
    "sg:classifiers":[
        {
            "category":"Shopping",
            "subcategory":"Baby Store",
            "type":"Retail Goods"
        }
    ],
    "sg:phone":"+91 22 5699 4721",
    "sg:postcode":"400063",
    "sg:tags":[
        "garment",
        "childrenwear"
    ],
    "wof:name":"Bonsai Apparels",
    "wof:placetype":"venue"
},
  "geometry": {"coordinates":[72.85713199999999,19.166401],"type":"Point"}
}