{
  "type": "Feature",
  "properties": {
    "iso:country":"IN",
    "sg:address":"86d-1, Industrial Suburb, \nIi Stage, Yeshwanthpur,",
    "sg:city":"Bangalore",
    "sg:orig_category":"Readymade Garments",
    "sg:phone":"+91 80 2337 1144",
    "sg:postcode":"560022",
    "sg:website":"http://www.texportoverseas.com",
    "wof:name":"Texport Overseas",
    "wof:placetype":"venue"
},
  "geometry": {"coordinates":[77.539055,13.01035],"type":"Point"}
}