{
  "type": "Feature",
  "properties": {
    "iso:country":"IN",
    "sg:address":"75-c, Mohd Ali Rd.,",
    "sg:city":"Mumbai",
    "sg:classifiers":[
        {
            "category":"Manufacturing",
            "subcategory":"Motor Vehicles & Parts",
            "type":"Manufacturing & Wholesale Goods"
        }
    ],
    "sg:phone":"+91 22 2342 9865",
    "sg:postcode":"400003",
    "sg:tags":[
        "component",
        "product",
        "electronic"
    ],
    "wof:name":"S. B. Dungarpurwala & Co.",
    "wof:placetype":"venue"
},
  "geometry": {"coordinates":[78.475182,17.36648],"type":"Point"}
}