{
  "type": "Feature",
  "properties": {
    "iso:country":"IN",
    "sg:address":"87 Kr Road",
    "sg:city":"Bangalore",
    "sg:classifiers":[
        {
            "category":"Professional",
            "subcategory":"Computer Services",
            "type":"Services"
        }
    ],
    "sg:phone":"+91 80 2650 0255",
    "sg:postcode":"560004",
    "sg:tags":[
        "software"
    ],
    "sg:website":"http://www.coreobjects.com",
    "wof:name":"Coreobjects India Pvt Ltd",
    "wof:placetype":"venue"
},
  "geometry": {"coordinates":[78.261475,12.927182],"type":"Point"}
}