{
  "type": "Feature",
  "properties": {
    "iso:country":"IN",
    "sg:address":"51, Mangaldas Rd., Lohar Chawl,",
    "sg:city":"Mumbai",
    "sg:classifiers":[
        {
            "category":"Banks & Credit Unions",
            "subcategory":"Investment Brokerage",
            "type":"Services"
        }
    ],
    "sg:phone":"+91 22 5633 7060",
    "sg:postcode":"400002",
    "sg:tags":[
        "energy",
        "conservation",
        "product"
    ],
    "sg:website":"http://www.cronyelectronics.com",
    "wof:name":"Crony Electronics Pvt. Ltd.",
    "wof:placetype":"venue"
},
  "geometry": {"coordinates":[72.831734,18.947433],"type":"Point"}
}