{
  "type": "Feature",
  "properties": {
    "iso:country":"IN",
    "sg:address":"G-5-6, B.i.d.c, Gorwa,",
    "sg:city":"Vadodara",
    "sg:classifiers":[
        {
            "category":"Health Services",
            "subcategory":"Medical Lab",
            "type":"Services"
        }
    ],
    "sg:phone":"+91 265 228 2061",
    "sg:postcode":"390016",
    "sg:tags":[
        "pharmaceutical",
        "formulation"
    ],
    "sg:website":"http://www.centurionlab.com",
    "wof:name":"Centurion Laboratories",
    "wof:placetype":"venue"
},
  "geometry": {"coordinates":[73.155609,22.32782],"type":"Point"}
}