{
  "type": "Feature",
  "properties": {
    "iso:country":"IN",
    "sg:address":"158, K.m. Sharma Marg, Lohar Chawl,",
    "sg:city":"Mumbai",
    "sg:classifiers":[
        {
            "category":"Train Station",
            "subcategory":"Light Rail",
            "type":"Transportation"
        }
    ],
    "sg:phone":"+91 22 2208 7249",
    "sg:postcode":"400002",
    "sg:tags":[
        "control",
        "board",
        "panel"
    ],
    "wof:name":"D. J. Enterprise",
    "wof:placetype":"venue"
},
  "geometry": {"coordinates":[72.83181,18.946951],"type":"Point"}
}