{
  "type": "Feature",
  "properties": {
    "iso:country":"IN",
    "sg:address":"F-2, Udyog Nagar",
    "sg:city":"New Delhi",
    "sg:classifiers":[
        {
            "category":"Professional",
            "subcategory":"Computer Services",
            "type":"Services"
        }
    ],
    "sg:postcode":"110041",
    "sg:tags":[
        "web-development-company",
        "offshore-software-development",
        "web-promotion",
        "internet-marketing",
        "web-design"
    ],
    "sg:website":"http://www.vinove.com/",
    "wof:name":"Vinove IT Software & Services",
    "wof:placetype":"venue"
},
  "geometry": {"coordinates":[77.087384,28.68183],"type":"Point"}
}