{
  "type": "Feature",
  "properties": {
    "iso:country":"IN",
    "sg:address":"32, East Second Street, Ramaiah Colony,",
    "sg:city":"Tirupur",
    "sg:classifiers":[
        {
            "category":"Shopping",
            "subcategory":"Clothing, Apparel, & Fashions",
            "type":"Retail Goods"
        }
    ],
    "sg:phone":"+91 421 433 4155",
    "sg:postcode":"641602",
    "sg:tags":[
        "shirt"
    ],
    "wof:name":"Vipro Garments Buying Agencies",
    "wof:placetype":"venue"
},
  "geometry": {"coordinates":[77.33625000000001,11.115479],"type":"Point"}
}