{
  "type": "Feature",
  "properties": {
    "iso:country":"IN",
    "sg:address":"Plot No. N-2, Baikampady Indl. Area,",
    "sg:city":"Mangalore",
    "sg:classifiers":[
        {
            "category":"Manufacturing",
            "subcategory":"Chemicals & Compounds",
            "type":"Manufacturing & Wholesale Goods"
        }
    ],
    "sg:phone":"+91 824 240 7570",
    "sg:postcode":"575011",
    "sg:tags":[
        "resin"
    ],
    "wof:name":"Organo Sublimo Extracts",
    "wof:placetype":"venue"
},
  "geometry": {"coordinates":[74.806847,12.949685],"type":"Point"}
}