{
  "type": "Feature",
  "properties": {
    "iso:country":"IN",
    "sg:address":"55/57, Mirza Street, Zaveri Bazar,",
    "sg:city":"Mumbai",
    "sg:classifiers":[
        {
            "category":"Landmark",
            "subcategory":"City Walls",
            "type":"Public Place"
        }
    ],
    "sg:phone":"+91 22 2343 7518",
    "sg:postcode":"400003",
    "sg:tags":[
        "velvet",
        "fabric",
        "corduroy"
    ],
    "sg:website":"http://www.arrkayvelvets.com",
    "wof:name":"Shree Radhavallabh Textiles (bombay)",
    "wof:placetype":"venue"
},
  "geometry": {"coordinates":[72.83223700000001,18.950575],"type":"Point"}
}