{
  "type": "Feature",
  "properties": {
    "iso:country":"IN",
    "sg:address":"7-b, Pritoria Street,",
    "sg:city":"Kolkata",
    "sg:classifiers":[
        {
            "category":"Manufacturing",
            "subcategory":"Chemicals & Compounds",
            "type":"Manufacturing & Wholesale Goods"
        }
    ],
    "sg:phone":"+91 33 2282 2181",
    "sg:postcode":"700071",
    "sg:tags":[
        "supply"
    ],
    "sg:website":"http://www.quakerchem.com",
    "wof:name":"Quaker Chemical India Ltd.",
    "wof:placetype":"venue"
},
  "geometry": {"coordinates":[88.35114299999999,22.543427],"type":"Point"}
}