{
  "type": "Feature",
  "properties": {
    "iso:country":"IN",
    "sg:address":"C-86, Iti Industrial Estate, Whitefield Road, Mahadevapura,",
    "sg:city":"Bangalore",
    "sg:orig_category":"Telescope",
    "sg:phone":"+91 80 2851 1329",
    "sg:postcode":"560048",
    "sg:website":"http://www.opticsindia.com / www.binocularsindia.com",
    "wof:name":"Optics & Allied Engg. Pvt. Ltd.",
    "wof:placetype":"venue"
},
  "geometry": {"coordinates":[77.698364,12.997111],"type":"Point"}
}