{
  "type": "Feature",
  "properties": {
    "iso:country":"IN",
    "sg:address":"24, N. S. Road, 1st Floor,",
    "sg:city":"Kolkata",
    "sg:classifiers":[
        {
            "category":"Manufacturing",
            "subcategory":"Chemicals & Compounds",
            "type":"Manufacturing & Wholesale Goods"
        }
    ],
    "sg:phone":"+91 33 2220 2532",
    "sg:postcode":"700001",
    "sg:tags":[
        "supply"
    ],
    "wof:name":"Khaitan Borthers Pvt. Ltd.",
    "wof:placetype":"venue"
},
  "geometry": {"coordinates":[72.836777,19.107164],"type":"Point"}
}