{
  "type": "Feature",
  "properties": {
    "iso:country":"IN",
    "sg:address":"415, Apollo Tower, 2, M.g.road,",
    "sg:city":"Indore",
    "sg:classifiers":[
        {
            "category":"Home & Garden",
            "subcategory":"Mobile Homes",
            "type":"Retail Goods"
        }
    ],
    "sg:phone":"+91 731407588123",
    "sg:postcode":"452001",
    "sg:tags":[
        "acid"
    ],
    "wof:name":"Dhanraj Organic P. Ltd.",
    "wof:placetype":"venue"
},
  "geometry": {"coordinates":[75.884712,22.722963],"type":"Point"}
}