{
  "type": "Feature",
  "properties": {
    "iso:country":"IN",
    "sg:address":"31/10, R.s. Pillai Street,",
    "sg:city":"Tindivanam",
    "sg:orig_category":"Henna & Henna Products",
    "sg:phone":"+91 4147 227 634",
    "wof:name":"K. S. G. Enterprises",
    "wof:placetype":"venue"
},
  "geometry": {"coordinates":[79.695351,12.84042],"type":"Point"}
}