{
  "type": "Feature",
  "properties": {
    "iso:country":"IN",
    "sg:address":"H.d. Bldg. 21/4, Kennedy Bridge,",
    "sg:city":"Mumbai",
    "sg:classifiers":[
        {
            "category":"Shopping",
            "subcategory":"Luggage & Leather Goods",
            "type":"Retail Goods"
        }
    ],
    "sg:phone":"+91 22 2388 2167",
    "sg:postcode":"400004",
    "sg:tags":[
        "bag",
        "-",
        "cotton/canvas/synthetic"
    ],
    "wof:name":"Rathi Exports Pvt. Ltd.",
    "wof:placetype":"venue"
},
  "geometry": {"coordinates":[72.814705,18.958914],"type":"Point"}
}