{
  "type": "Feature",
  "properties": {
    "iso:country":"IN",
    "sg:address":"143, B-8, Bommasandra Industrial Area,",
    "sg:city":"Bangalore",
    "sg:classifiers":[
        {
            "category":"Bars & Pubs",
            "subcategory":"Dive Bar",
            "type":"Food & Drink"
        }
    ],
    "sg:phone":"+91 80 2783 1720",
    "sg:postcode":"560099",
    "sg:tags":[
        "shaft",
        "bright",
        "collar"
    ],
    "sg:website":"http://www.gearock.com",
    "wof:name":"Gearock Forge Pvt. Ltd.",
    "wof:placetype":"venue"
},
  "geometry": {"coordinates":[77.685104,12.816192],"type":"Point"}
}