{
  "type": "Feature",
  "properties": {
    "iso:country":"IN",
    "sg:address":"Uday Park",
    "sg:city":"New Delhi",
    "sg:phone":"+91 11 2651 3912",
    "sg:postcode":"110049",
    "sg:province":"Delhi",
    "sg:website":"http://www.scientech-india.com",
    "wof:name":"Scientific Mes-technik Pvt Ltd",
    "wof:placetype":"venue"
},
  "geometry": {"coordinates":[77.21932200000001,28.560101],"type":"Point"}
}