{
  "type": "Feature",
  "properties": {
    "iso:country":"IN",
    "sg:address":"Bela Court No.2, Colaba,",
    "sg:city":"Mumbai",
    "sg:classifiers":[
        {
            "category":"Shopping",
            "subcategory":"Crafts & Fabrics",
            "type":"Retail Goods"
        }
    ],
    "sg:phone":"+91 22 2283 0477",
    "sg:postcode":"400005",
    "sg:tags":[
        "pigment"
    ],
    "wof:name":"Golden Dyes Corpn. (india) Pvt. Ltd.",
    "wof:placetype":"venue"
},
  "geometry": {"coordinates":[72.826683,18.916138],"type":"Point"}
}