{
  "type": "Feature",
  "properties": {
    "iso:country":"IN",
    "sg:address":"3-b, Udyog Nagar, Swami Vivekanand Road, Goregaon(w),",
    "sg:city":"Mumbai",
    "sg:classifiers":[
        {
            "category":"Manufacturing",
            "subcategory":"Chemicals & Compounds",
            "type":"Manufacturing & Wholesale Goods"
        }
    ],
    "sg:phone":"+91 22 2874 1701",
    "sg:postcode":"400062",
    "sg:tags":[
        "coatings-powder",
        "coating"
    ],
    "sg:website":"http://www.progressivechemicals.net",
    "wof:name":"Progressive Electroplating Chemicals Pvt. Ltd.",
    "wof:placetype":"venue"
},
  "geometry": {"coordinates":[72.845352,19.171698],"type":"Point"}
}