{
  "type": "Feature",
  "properties": {
    "iso:country":"IN",
    "sg:address":"Mooker Nallamuthu Street",
    "sg:city":"Chennai",
    "sg:phone":"+91 44 2522 3754",
    "sg:postcode":"600001",
    "sg:province":"Tamil Nadu",
    "wof:name":"O P Steels Ltd",
    "wof:placetype":"venue"
},
  "geometry": {"coordinates":[80.290009,13.092497],"type":"Point"}
}