{
  "type": "Feature",
  "properties": {
    "iso:country":"IN",
    "sg:address":"21, Opp. M.i.d.c. Office,",
    "sg:city":"Badlapur",
    "sg:classifiers":[
        {
            "category":"Manufacturing",
            "subcategory":"Chemicals & Compounds",
            "type":"Manufacturing & Wholesale Goods"
        }
    ],
    "sg:phone":"+91 251 269 0380",
    "sg:postcode":"421503",
    "sg:tags":[
        "supply"
    ],
    "wof:name":"Venus Fluorides & Chemicals",
    "wof:placetype":"venue"
},
  "geometry": {"coordinates":[73.784363,18.651051],"type":"Point"}
}