{
  "type": "Feature",
  "properties": {
    "iso:country":"IN",
    "sg:address":"Chambaghat",
    "sg:city":"Solan",
    "sg:phone":"+91 179230578",
    "sg:postcode":"173212",
    "sg:province":"Himachal Pradesh",
    "sg:website":"http://www.shivalikbimetals.com",
    "wof:name":"Shivalik Bimetal Controls Ltd",
    "wof:placetype":"venue"
},
  "geometry": {"coordinates":[77.09877,30.923506],"type":"Point"}
}