{
  "type": "Feature",
  "properties": {
    "iso:country":"IN",
    "sg:address":"707, J.k. Chambers, Sector-17, Vashi,",
    "sg:city":"Navi Mumbai",
    "sg:classifiers":[
        {
            "category":"Manufacturing",
            "subcategory":"Chemicals & Compounds",
            "type":"Manufacturing & Wholesale Goods"
        }
    ],
    "sg:phone":"+91 22 2789 4245",
    "sg:postcode":"400705",
    "sg:tags":[
        "supply"
    ],
    "wof:name":"Hi-q-chemique",
    "wof:placetype":"venue"
},
  "geometry": {"coordinates":[72.999619,19.069084],"type":"Point"}
}