{
  "type": "Feature",
  "properties": {
    "iso:country":"IN",
    "sg:address":"1007, Chowk Dholewal, G.t. Road,",
    "sg:city":"Ludhiana",
    "sg:classifiers":[
        {
            "category":"Manufacturing",
            "subcategory":"Chemicals & Compounds",
            "type":"Manufacturing & Wholesale Goods"
        }
    ],
    "sg:phone":"+91 161 254 2449",
    "sg:postcode":"141003",
    "sg:tags":[
        "paint",
        "product",
        "allied"
    ],
    "wof:name":"Imperial Coating International Co. India",
    "wof:placetype":"venue"
},
  "geometry": {"coordinates":[75.872452,30.892729],"type":"Point"}
}