{
  "type": "Feature",
  "properties": {
    "iso:country":"IN",
    "sg:address":"15, Fancy Chambers, 94 Surat St., Masjid,",
    "sg:city":"Mumbai",
    "sg:classifiers":[
        {
            "category":"Communications",
            "subcategory":"Film & Video Production",
            "type":"Services"
        }
    ],
    "sg:phone":"+91 22 2379 1412",
    "sg:postcode":"400009",
    "sg:tags":[
        "container"
    ],
    "wof:name":"M.p.bombay Transport Carriers",
    "wof:placetype":"venue"
},
  "geometry": {"coordinates":[72.839005,18.953011],"type":"Point"}
}