{
  "type": "Feature",
  "properties": {
    "iso:country":"IN",
    "sg:address":"415, City Centre, 570, M.g.road,",
    "sg:city":"Indore",
    "sg:classifiers":[
        {
            "category":"Manufacturing",
            "subcategory":"Chemicals & Compounds",
            "type":"Manufacturing & Wholesale Goods"
        }
    ],
    "sg:phone":"+91 731 502 6421",
    "sg:postcode":"452001",
    "sg:tags":[
        "supply"
    ],
    "wof:name":"Srm Impex Pvt. Ltd.",
    "wof:placetype":"venue"
},
  "geometry": {"coordinates":[77.158218,28.70295],"type":"Point"}
}