{
  "type": "Feature",
  "properties": {
    "iso:country":"IN",
    "sg:address":"V/69 Cherpunkal P.o",
    "sg:city":"Kottayam",
    "sg:classifiers":[
        {
            "category":"Manufacturing",
            "subcategory":"Rubber & Plastics",
            "type":"Manufacturing & Wholesale Goods"
        }
    ],
    "sg:phone":"+91 481 225 5473",
    "sg:postcode":"686584",
    "sg:tags":[
        "product"
    ],
    "wof:name":"Vembanad Rubbers",
    "wof:placetype":"venue"
},
  "geometry": {"coordinates":[76.641914,9.685056],"type":"Point"}
}