{
  "type": "Feature",
  "properties": {
    "iso:country":"IN",
    "sg:address":"2, Ho Chimin Sarani,",
    "sg:city":"Kolkata",
    "sg:classifiers":[
        {
            "category":"Manufacturing",
            "subcategory":"Chemicals & Compounds",
            "type":"Manufacturing & Wholesale Goods"
        }
    ],
    "sg:phone":"+91 33 2282 2976",
    "sg:postcode":"700071",
    "sg:tags":[
        "supply"
    ],
    "wof:name":"Skill Dye Chemical Pvt. Ltd.",
    "wof:placetype":"venue"
},
  "geometry": {"coordinates":[88.27092,22.489367],"type":"Point"}
}