{
  "type": "Feature",
  "properties": {
    "iso:country":"IN",
    "sg:address":"# 2 Rajaji St. West, Kamaraj Nager,",
    "sg:city":"Chennai",
    "sg:classifiers":[
        {
            "category":"Home & Garden",
            "subcategory":"Garden Supply",
            "type":"Retail Goods"
        }
    ],
    "sg:phone":"+91 44 2655 3743",
    "sg:postcode":"600054",
    "sg:tags":[
        "fertilizer"
    ],
    "wof:name":"Sams Trading",
    "wof:placetype":"venue"
},
  "geometry": {"coordinates":[80.292625,13.102119],"type":"Point"}
}