{
  "type": "Feature",
  "properties": {
    "iso:country":"IN",
    "sg:address":"547, K.r. Garden Koramangala Village,",
    "sg:city":"Bangalore",
    "sg:classifiers":[
        {
            "category":"Manufacturing",
            "subcategory":"Tools & Machinery",
            "type":"Manufacturing & Wholesale Goods"
        }
    ],
    "sg:phone":"+91 80 2571 1450",
    "sg:postcode":"560095",
    "sg:tags":[
        "component",
        "auto",
        "part",
        "turned",
        "precision"
    ],
    "wof:name":"Balaji Inds.",
    "wof:placetype":"venue"
},
  "geometry": {"coordinates":[77.615662,12.932185],"type":"Point"}
}