{
  "type": "Feature",
  "properties": {
    "iso:country":"IN",
    "sg:address":"2 A/3, Asaf Ali Road",
    "sg:city":"New Delhi",
    "sg:phone":"+91 11 2326 3672",
    "sg:postcode":"110002",
    "sg:province":"Delhi",
    "sg:website":"http://www.macoindia.com",
    "wof:name":"Maco Pvt Ltd",
    "wof:placetype":"venue"
},
  "geometry": {"coordinates":[77.233452,28.641699],"type":"Point"}
}