{
  "type": "Feature",
  "properties": {
    "iso:country":"IN",
    "sg:address":"Administrative Building,",
    "sg:city":"Nepa Nagar",
    "sg:classifiers":[
        {
            "category":"Shopping",
            "subcategory":"Stationery & Office Supplies",
            "type":"Retail Goods"
        }
    ],
    "sg:phone":"+91 7325 222 234",
    "sg:postcode":"450221",
    "sg:tags":[
        "paper"
    ],
    "wof:name":"Nepa Ltd",
    "wof:placetype":"venue"
},
  "geometry": {"coordinates":[81.050407,16.695715],"type":"Point"}
}