{
  "type": "Feature",
  "properties": {
    "iso:country":"IN",
    "sg:address":"A-1, New Shaktinagar,",
    "sg:city":"Udaipur",
    "sg:classifiers":[
        {
            "category":"Shopping",
            "subcategory":"Used Merchandise",
            "type":"Retail Goods"
        }
    ],
    "sg:phone":"+91 294 241 0686",
    "sg:postcode":"313001",
    "sg:tags":[
        "merchant",
        "exporter"
    ],
    "sg:website":"http://www.rubiconindia.com",
    "wof:name":"Rubicon International",
    "wof:placetype":"venue"
},
  "geometry": {"coordinates":[77.195061,28.676954],"type":"Point"}
}