{
  "type": "Feature",
  "properties": {
    "iso:country":"IN",
    "sg:address":"218, Kika Street,",
    "sg:city":"Mumbai",
    "sg:classifiers":[
        {
            "category":"Wholesale",
            "subcategory":"Hardware",
            "type":"Manufacturing & Wholesale Goods"
        }
    ],
    "sg:phone":"+91 22 2242 2939",
    "sg:postcode":"400002",
    "sg:tags":[
        "builder",
        "product",
        "brass"
    ],
    "wof:name":"Shah Sakalchand Chunilal & Co.",
    "wof:placetype":"venue"
},
  "geometry": {"coordinates":[72.82943,18.955406],"type":"Point"}
}