{
  "type": "Feature",
  "properties": {
    "iso:country":"IN",
    "sg:address":"Bellary Road, Venkatala, Yelahanka,",
    "sg:city":"Bangalore",
    "sg:classifiers":[
        {
            "category":"Banks & Credit Unions",
            "subcategory":"Investment Brokerage",
            "type":"Services"
        }
    ],
    "sg:phone":"+91 80 2846 0418",
    "sg:postcode":"560064",
    "sg:tags":[
        "stone"
    ],
    "wof:name":"Bangalore Ceramics",
    "wof:placetype":"venue"
},
  "geometry": {"coordinates":[76.918732,15.13854],"type":"Point"}
}