{
  "type": "Feature",
  "properties": {
    "iso:country":"IN",
    "sg:address":"207, Bhaveshwar Complex, Vidyavihar (w),",
    "sg:city":"Mumbai",
    "sg:classifiers":[
        {
            "category":"Banks & Credit Unions",
            "subcategory":"Investment Brokerage",
            "type":"Services"
        }
    ],
    "sg:phone":"+91 22 2514 9797",
    "sg:postcode":"400086",
    "sg:tags":[
        "energy",
        "management",
        "saving"
    ],
    "sg:website":"http://www.swatienergy.com",
    "wof:name":"Swati Energy & Projects Pvt. Ltd.",
    "wof:placetype":"venue"
},
  "geometry": {"coordinates":[72.912666,19.092699],"type":"Point"}
}