{
  "type": "Feature",
  "properties": {
    "iso:country":"IN",
    "sg:address":"K.k.nagar",
    "sg:city":"Madurai",
    "sg:phone":"+91 452587776",
    "sg:postcode":"625020",
    "sg:province":"Tamil Nadu",
    "sg:website":"http://www.indian-foods.com",
    "wof:name":"Indian Foods Pvt Ltd",
    "wof:placetype":"venue"
},
  "geometry": {"coordinates":[78.693764,10.758761],"type":"Point"}
}