{
  "type": "Feature",
  "properties": {
    "iso:country":"IN",
    "sg:address":"217, Samuel Street, Room No.10, 3rd Floor, Vadgadi,",
    "sg:city":"Mumbai",
    "sg:classifiers":[
        {
            "category":"Food & Beverages",
            "subcategory":"Specialty",
            "type":"Retail Goods"
        }
    ],
    "sg:phone":"+91 22 5699 3631",
    "sg:postcode":"400003",
    "sg:tags":[
        "solvent"
    ],
    "wof:name":"Karan Monomers Private Limited",
    "wof:placetype":"venue"
},
  "geometry": {"coordinates":[72.836662,18.951439],"type":"Point"}
}