{
  "type": "Feature",
  "properties": {
    "iso:country":"IN",
    "sg:address":"Lalita Park",
    "sg:city":"New Delhi",
    "sg:phone":"+91 11 2252 0088",
    "sg:postcode":"110048",
    "sg:province":"Delhi",
    "wof:name":"Inferno Pacifires Pvt Ltd",
    "wof:placetype":"venue"
},
  "geometry": {"coordinates":[77.274277,28.630932],"type":"Point"}
}