{
  "type": "Feature",
  "properties": {
    "iso:country":"IN",
    "sg:address":"217, Arun Chambers, Tardeo Road,",
    "sg:city":"Mumbai",
    "sg:classifiers":[
        {
            "category":"Professional",
            "subcategory":"Engineering",
            "type":"Services"
        }
    ],
    "sg:phone":"+91 22 2351 0121",
    "sg:postcode":"400034",
    "sg:tags":[
        "equipment",
        "good"
    ],
    "wof:name":"Spenta Sales",
    "wof:placetype":"venue"
},
  "geometry": {"coordinates":[72.81379699999999,18.973169],"type":"Point"}
}