{
  "type": "Feature",
  "properties": {
    "iso:country":"IN",
    "sg:address":"H.o. 33a J.l. Nehru Road, 12th Floor, Suite 13,",
    "sg:city":"Kolkata",
    "sg:classifiers":[
        {
            "category":"Manufacturing",
            "subcategory":"Chemicals & Compounds",
            "type":"Manufacturing & Wholesale Goods"
        }
    ],
    "sg:phone":"+91 33 2226 6728",
    "sg:postcode":"700071",
    "sg:tags":[
        "chemicals-additives"
    ],
    "sg:website":"http://www.prabhupolycolor.com",
    "wof:name":"Prabhu Polycolor Pvt. Ltd.",
    "wof:placetype":"venue"
},
  "geometry": {"coordinates":[75.572884,13.933999],"type":"Point"}
}