{
  "type": "Feature",
  "properties": {
    "iso:country":"IN",
    "sg:address":"# 20/1, 1st Floor, Mission Road,",
    "sg:city":"Bangalore",
    "sg:orig_category":"Sarees",
    "sg:postcode":"560027",
    "wof:name":"The House Of Weavers",
    "wof:placetype":"venue"
},
  "geometry": {"coordinates":[77.590965,12.962548],"type":"Point"}
}