{
  "type": "Feature",
  "properties": {
    "iso:country":"IN",
    "sg:address":"S. P. Road",
    "sg:city":"Secunderabad",
    "sg:phone":"+91 40 2784 2182",
    "sg:postcode":"500003",
    "sg:province":"Andhra Pradesh",
    "sg:website":"http://www.pokarna.com",
    "wof:name":"Pokarna Granites Ltd",
    "wof:placetype":"venue"
},
  "geometry": {"coordinates":[78.470978,17.347868],"type":"Point"}
}