{
  "type": "Feature",
  "properties": {
    "iso:country":"IN",
    "sg:address":"C-318, Vashi Plaza Sector-17, Vashi,",
    "sg:city":"Mumbai",
    "sg:classifiers":[
        {
            "category":"Communications",
            "subcategory":"Film & Video Production",
            "type":"Services"
        }
    ],
    "sg:phone":"+91 22 2780 1078",
    "sg:postcode":"400703",
    "sg:tags":[
        "container"
    ],
    "sg:website":"http://www.snsgroup.biz",
    "wof:name":"S. N. S. Marine, Inc.",
    "wof:placetype":"venue"
},
  "geometry": {"coordinates":[73.004158,19.101946],"type":"Point"}
}