{
  "type": "Feature",
  "properties": {
    "iso:country":"IN",
    "sg:address":"Prabhat Nagar No. 1, Jogeshwari (w),",
    "sg:city":"Mumbai",
    "sg:classifiers":[
        {
            "category":"Real Estate",
            "subcategory":"Surveying",
            "type":"Services"
        }
    ],
    "sg:phone":"+91 22 2678 6339",
    "sg:postcode":"400102",
    "sg:tags":[
        "pharmaceutical",
        "material",
        "raw"
    ],
    "wof:name":"Pharma Medico (i) Pvt. Ltd.",
    "wof:placetype":"venue"
},
  "geometry": {"coordinates":[72.847488,19.143631],"type":"Point"}
}