{
  "type": "Feature",
  "properties": {
    "iso:country":"IN",
    "sg:address":"Opp. Bandra Railway Station, Bandra (w)",
    "sg:city":"Mumbai",
    "sg:phone":"+91 22 2642 4956",
    "sg:postcode":"400050",
    "sg:province":"Maharashtra",
    "wof:name":"Shree Krishna Drilling Services Pvt Ltd",
    "wof:placetype":"venue"
},
  "geometry": {"coordinates":[72.840805,19.054825],"type":"Point"}
}