{
  "type": "Feature",
  "properties": {
    "iso:country":"IN",
    "sg:address":"Middleton Street, P B No 8242",
    "sg:city":"Kolkata",
    "sg:phone":"+91 33 2240 3903",
    "sg:postcode":"700071",
    "sg:province":"West Bengal",
    "wof:name":"Cycle Corporation Of India Ltd",
    "wof:placetype":"venue"
},
  "geometry": {"coordinates":[88.350761,22.54908],"type":"Point"}
}