{
  "type": "Feature",
  "properties": {
    "iso:country":"IN",
    "sg:address":"C-124, Ghatkopar Industrial Estate, Ghatkopar (w),",
    "sg:city":"Mumbai",
    "sg:orig_category":"Box Making Machinery",
    "sg:phone":"+91 22 2500 8732",
    "sg:postcode":"400077",
    "sg:website":"http://www.eaglestrapping.com",
    "wof:name":"Eagle Manufacturing Company",
    "wof:placetype":"venue"
},
  "geometry": {"coordinates":[72.914101,19.101273],"type":"Point"}
}