{
  "type": "Feature",
  "properties": {
    "iso:country":"IN",
    "sg:address":"# 202, Raheja Chambers, 12, Museum Road,",
    "sg:city":"Bangalore",
    "sg:classifiers":[
        {
            "category":"Professional",
            "subcategory":"Art Services",
            "type":"Services"
        }
    ],
    "sg:phone":"+91 80 2558 3440",
    "sg:postcode":"560001",
    "sg:tags":[
        "design",
        "software"
    ],
    "sg:website":"http://www.macmillanindia.com/ www.emacmillan.com",
    "wof:name":"Mac Millan India Ltd.",
    "wof:placetype":"venue"
},
  "geometry": {"coordinates":[77.603645,12.973545],"type":"Point"}
}