{
  "type": "Feature",
  "properties": {
    "iso:country":"IN",
    "sg:address":"No. 152, 1st Floor, Balepet,",
    "sg:city":"Bangalore",
    "sg:classifiers":[
        {
            "category":"Shopping",
            "subcategory":"Clothing, Apparel, & Fashions",
            "type":"Retail Goods"
        }
    ],
    "sg:phone":"+91 80 2225 2045",
    "sg:postcode":"560053",
    "sg:tags":[
        "t-shirt"
    ],
    "wof:name":"Venus Clothing Co.",
    "wof:placetype":"venue"
},
  "geometry": {"coordinates":[77.575912,12.972297],"type":"Point"}
}