{
  "type": "Feature",
  "properties": {
    "iso:country":"IN",
    "sg:address":"#251, N. S. Palya,",
    "sg:city":"Bangalore",
    "sg:classifiers":[
        {
            "category":"Manufacturing",
            "subcategory":"Metals",
            "type":"Manufacturing & Wholesale Goods"
        }
    ],
    "sg:phone":"+91 80 2668 1702",
    "sg:postcode":"560076",
    "sg:tags":[
        "sheet",
        "component"
    ],
    "wof:name":"Disha Precisions (p) Ltd.",
    "wof:placetype":"venue"
},
  "geometry": {"coordinates":[77.63858,13.009579],"type":"Point"}
}