{
  "type": "Feature",
  "properties": {
    "iso:country":"IN",
    "sg:address":"264, G.i.d.c., Phase-2, Dediyasan,",
    "sg:city":"Mehsana",
    "sg:classifiers":[
        {
            "category":"Manufacturing",
            "subcategory":"Chemicals & Compounds",
            "type":"Manufacturing & Wholesale Goods"
        }
    ],
    "sg:phone":"+91 2762 224 359",
    "sg:postcode":"384002",
    "sg:tags":[
        "industrial"
    ],
    "wof:name":"Laxmi Chemicals",
    "wof:placetype":"venue"
},
  "geometry": {"coordinates":[77.568298,12.923807],"type":"Point"}
}