{
  "type": "Feature",
  "properties": {
    "iso:country":"IN",
    "sg:address":"Surat \u2013 Hazira State Highway, Hazira, Engr ( Elect), Kribhco,",
    "sg:city":"Surat",
    "sg:classifiers":[
        {
            "category":"Home & Garden",
            "subcategory":"Garden Supply",
            "type":"Retail Goods"
        }
    ],
    "sg:phone":"+91 261 280 2164",
    "sg:postcode":"395007",
    "sg:tags":[
        "fertilizer"
    ],
    "sg:website":"http://www.kribhco.net",
    "wof:name":"Kribhco",
    "wof:placetype":"venue"
},
  "geometry": {"coordinates":[72.81952699999999,21.195009],"type":"Point"}
}