{
  "type": "Feature",
  "properties": {
    "iso:country":"IN",
    "sg:address":"Plot No. 49, Daultabad Road, Near Railway Crossing,",
    "sg:city":"Gurgaon",
    "sg:classifiers":[
        {
            "category":"Manufacturing",
            "subcategory":"Rubber & Plastics",
            "type":"Manufacturing & Wholesale Goods"
        }
    ],
    "sg:phone":"+91 124 324 7498",
    "sg:postcode":"122001",
    "sg:tags":[
        "product"
    ],
    "wof:name":"Shiv Industries",
    "wof:placetype":"venue"
},
  "geometry": {"coordinates":[77.012466,28.485056],"type":"Point"}
}