{
  "type": "Feature",
  "properties": {
    "iso:country":"IN",
    "sg:address":"Bangalore Hosiery Complex, # 107, Ist Floor, A.s. Char Street,",
    "sg:city":"Bangalore",
    "sg:classifiers":[
        {
            "category":"Shopping",
            "subcategory":"Clothing, Apparel, & Fashions",
            "type":"Retail Goods"
        }
    ],
    "sg:phone":"+91 80 4122 0654",
    "sg:postcode":"560053",
    "sg:tags":[
        "shirt"
    ],
    "wof:name":"Denim City",
    "wof:placetype":"venue"
},
  "geometry": {"coordinates":[77.594376,12.971606],"type":"Point"}
}