{
  "type": "Feature",
  "properties": {
    "iso:country":"IN",
    "sg:address":"123, New Sonal Industrial Estate No.2, Kanchpada, Link Road, Malad (w),",
    "sg:city":"Mumbai",
    "sg:classifiers":[
        {
            "category":"Structure",
            "subcategory":"Tower",
            "type":"Public Place"
        }
    ],
    "sg:phone":"+91 22 2880 5089",
    "sg:postcode":"400064",
    "sg:tags":[
        "plant",
        "cooling",
        "chilling"
    ],
    "wof:name":"Blue Chip Cooling Towers Pvt. Ltd.",
    "wof:placetype":"venue"
},
  "geometry": {"coordinates":[72.835846,19.189947],"type":"Point"}
}