{
  "type": "Feature",
  "properties": {
    "iso:country":"IN",
    "sg:address":"Sathy Road, Saravanampatti",
    "sg:city":"Coimbatore",
    "sg:phone":"+91 422866133",
    "sg:postcode":"641035",
    "sg:province":"Tamil Nadu",
    "wof:name":"Chola Pumps Pvt Ltd",
    "wof:placetype":"venue"
},
  "geometry": {"coordinates":[77.016899,11.073649],"type":"Point"}
}