{
  "type": "Feature",
  "properties": {
    "iso:country":"IN",
    "sg:address":"9c, Lord Sinha Road,",
    "sg:city":"Kolkata",
    "sg:classifiers":[
        {
            "category":"Home & Garden",
            "subcategory":"Building Materials",
            "type":"Retail Goods"
        }
    ],
    "sg:phone":"+91 33 2282 8144",
    "sg:postcode":"700071",
    "sg:tags":[
        "sealant",
        "adhesive"
    ],
    "wof:name":"Super Bond Mfg. Pvt. Ltd.",
    "wof:placetype":"venue"
},
  "geometry": {"coordinates":[88.348961,22.544367],"type":"Point"}
}