{
  "type": "Feature",
  "properties": {
    "iso:country":"IN",
    "sg:address":"E-69, Greater Kailash-i,",
    "sg:city":"New Delhi",
    "sg:classifiers":[
        {
            "category":"Manufacturing",
            "subcategory":"Rubber & Plastics",
            "type":"Manufacturing & Wholesale Goods"
        }
    ],
    "sg:phone":"+91 11 4254 2341",
    "sg:postcode":"110048",
    "sg:tags":[
        "product"
    ],
    "sg:website":"http://www.royalmotorcycle.com",
    "wof:name":"Royal Motor Cycles",
    "wof:placetype":"venue"
},
  "geometry": {"coordinates":[77.23764,28.547859],"type":"Point"}
}