{
  "type": "Feature",
  "properties": {
    "iso:country":"IN",
    "sg:address":"1-f, Industrial Area,",
    "sg:city":"Ujjain",
    "sg:classifiers":[
        {
            "category":"Wholesale",
            "subcategory":"Machinery & Supplies",
            "type":"Manufacturing & Wholesale Goods"
        }
    ],
    "sg:phone":"+91 734 251 6852",
    "sg:postcode":"456006",
    "sg:tags":[
        "equipment",
        "goods",
        "electrical"
    ],
    "wof:name":"Kohinoor Switchgears Pvt. Ltd.",
    "wof:placetype":"venue"
},
  "geometry": {"coordinates":[74.787102,13.334578],"type":"Point"}
}