{
  "type": "Feature",
  "properties": {
    "iso:country":"IN",
    "sg:address":"402, J.k. Chambers, Sector-17, Vashi,",
    "sg:city":"Mumbai",
    "sg:classifiers":[
        {
            "category":"Manufacturing",
            "subcategory":"Chemicals & Compounds",
            "type":"Manufacturing & Wholesale Goods"
        }
    ],
    "sg:phone":"+91 22 2789 3553",
    "sg:postcode":"400703",
    "sg:tags":[
        "paint",
        "product",
        "allied"
    ],
    "wof:name":"Surfa Coats",
    "wof:placetype":"venue"
},
  "geometry": {"coordinates":[72.999619,19.069084],"type":"Point"}
}