{
  "type": "Feature",
  "properties": {
    "iso:country":"IN",
    "sg:address":"Azamabad",
    "sg:city":"Hyderabad",
    "sg:phone":"+91 40 2763 1578",
    "sg:postcode":"500020",
    "sg:province":"Andhra Pradesh",
    "wof:name":"National Engg Service",
    "wof:placetype":"venue"
},
  "geometry": {"coordinates":[78.510712,17.410498],"type":"Point"}
}