{
  "type": "Feature",
  "properties": {
    "iso:country":"IN",
    "sg:address":"Princess Street",
    "sg:city":"Mumbai",
    "sg:phone":"+91 22 2205 5224",
    "sg:postcode":"400002",
    "sg:province":"Maharashtra",
    "sg:website":"http://www.eyewearindia.com",
    "wof:name":"Eternity Eyewear Pvt Ltd",
    "wof:placetype":"venue"
},
  "geometry": {"coordinates":[72.830635,18.947435],"type":"Point"}
}