{
  "type": "Feature",
  "properties": {
    "iso:country":"IN",
    "sg:address":"82, Epip, White Field,",
    "sg:city":"Bangalore",
    "sg:classifiers":[
        {
            "category":"Shopping",
            "subcategory":"Clothing, Apparel, & Fashions",
            "type":"Retail Goods"
        }
    ],
    "sg:phone":"+91 80 2841 6483",
    "sg:postcode":"560066",
    "sg:tags":[
        "shirt"
    ],
    "wof:name":"Mgk Impex P Ltd.",
    "wof:placetype":"venue"
},
  "geometry": {"coordinates":[77.710266,12.976968],"type":"Point"}
}