{
  "type": "Feature",
  "properties": {
    "iso:country":"IN",
    "sg:address":"2nd Floor, Press Club Building,",
    "sg:city":"Thiruvananthapuram",
    "sg:classifiers":[
        {
            "category":"Banks & Credit Unions",
            "subcategory":"Financial Services",
            "type":"Services"
        }
    ],
    "sg:phone":"+91 471 232 0844",
    "sg:postcode":"695001",
    "sg:tags":[
        "exchange",
        "finance",
        "foreign"
    ],
    "wof:name":"Kerala Artisans Development Corporation Ltd.",
    "wof:placetype":"venue"
},
  "geometry": {"coordinates":[78.046722,30.324162],"type":"Point"}
}