{
  "type": "Feature",
  "properties": {
    "iso:country":"IN",
    "sg:address":"# 67/3, Indl. Suburb, Yeshwanthpur,",
    "sg:city":"Bangalore",
    "sg:classifiers":[
        {
            "category":"Manufacturing",
            "subcategory":"Pet Food",
            "type":"Manufacturing & Wholesale Goods"
        }
    ],
    "sg:phone":"+91 80 2347 9296",
    "sg:postcode":"560022",
    "sg:tags":[
        "additive",
        "flavour"
    ],
    "wof:name":"Creative Aromatics (specialities) Pvt. Ltd.",
    "wof:placetype":"venue"
},
  "geometry": {"coordinates":[77.539726,13.021764],"type":"Point"}
}