{
  "type": "Feature",
  "properties": {
    "iso:country":"IN",
    "sg:address":"#1009e, 4th Main, R.p.c. Layout,",
    "sg:city":"Bangalore",
    "sg:classifiers":[
        {
            "category":"Manufacturing",
            "subcategory":"Tools & Machinery",
            "type":"Manufacturing & Wholesale Goods"
        }
    ],
    "sg:phone":"+91 80 3185 8199",
    "sg:postcode":"560040",
    "sg:tags":[
        "component",
        "auto",
        "part",
        "turned",
        "precision"
    ],
    "wof:name":"Ocean Enterprises",
    "wof:placetype":"venue"
},
  "geometry": {"coordinates":[77.542747,12.972351],"type":"Point"}
}