{
  "type": "Feature",
  "properties": {
    "iso:country":"IN",
    "sg:address":"32 Arunagiri Road,",
    "sg:city":"Arni",
    "sg:classifiers":[
        {
            "category":"Home & Garden",
            "subcategory":"Garden Supply",
            "type":"Retail Goods"
        }
    ],
    "sg:phone":"+91 4173 226 389",
    "sg:postcode":"632301",
    "sg:tags":[
        "fertilizer"
    ],
    "wof:name":"Sakthi Trading Co.",
    "wof:placetype":"venue"
},
  "geometry": {"coordinates":[80.171432,13.043974],"type":"Point"}
}