{
  "type": "Feature",
  "properties": {
    "iso:country":"IN",
    "sg:address":"# 56, Kamakshipalya, Magadi Main Road,",
    "sg:city":"Bangalore",
    "sg:classifiers":[
        {
            "category":"Retail",
            "subcategory":"Emissions Testing",
            "type":"Services"
        }
    ],
    "sg:phone":"+91 80 2348 4214",
    "sg:postcode":"560079",
    "sg:tags":[
        "pp",
        "hdpe",
        "sack"
    ],
    "wof:name":"Sheba Polysacks Pvt. Ltd.",
    "wof:placetype":"venue"
},
  "geometry": {"coordinates":[77.525352,12.985409],"type":"Point"}
}