{
  "type": "Feature",
  "properties": {
    "iso:country":"IN",
    "sg:address":"H-547, Riico Indl. Area-i,",
    "sg:city":"Bhiwadi",
    "sg:classifiers":[
        {
            "category":"Manufacturing",
            "subcategory":"Rubber & Plastics",
            "type":"Manufacturing & Wholesale Goods"
        }
    ],
    "sg:phone":"+91 1493 221 850",
    "sg:postcode":"301019",
    "sg:tags":[
        "polymer"
    ],
    "wof:name":"Sundeep Rubbers Pvt. Ltd.",
    "wof:placetype":"venue"
},
  "geometry": {"coordinates":[74.626869,24.913612],"type":"Point"}
}