{
  "type": "Feature",
  "properties": {
    "iso:country":"IN",
    "sg:address":"139s, Shah Complex,",
    "sg:city":"Tirunelveli",
    "sg:classifiers":[
        {
            "category":"Professional",
            "subcategory":"Engineering",
            "type":"Services"
        }
    ],
    "sg:phone":"+91 462 233 6712",
    "sg:postcode":"627006",
    "sg:tags":[
        "equipment",
        "good"
    ],
    "wof:name":"Asia Global Enterprises",
    "wof:placetype":"venue"
},
  "geometry": {"coordinates":[77.58607499999999,12.966959],"type":"Point"}
}