{
  "type": "Feature",
  "properties": {
    "iso:country":"IN",
    "sg:address":"Habibullah Road, T. Nagar",
    "sg:city":"Chennai",
    "sg:phone":"+91 44 2824 1923",
    "sg:postcode":"600017",
    "sg:province":"Tamil Nadu",
    "sg:website":"http://www.maars-soft.com",
    "wof:name":"Maars Software International Ltd",
    "wof:placetype":"venue"
},
  "geometry": {"coordinates":[80.239845,13.049805],"type":"Point"}
}