{
  "type": "Feature",
  "properties": {
    "iso:country":"IN",
    "sg:address":"280-a, N.g.g.o Colony, Thathampatty,",
    "sg:city":"Salem",
    "sg:classifiers":[
        {
            "category":"Manufacturing",
            "subcategory":"Chemicals & Compounds",
            "type":"Manufacturing & Wholesale Goods"
        }
    ],
    "sg:phone":"+91 427 224 2692",
    "sg:postcode":"636014",
    "sg:tags":[
        "supply"
    ],
    "wof:name":"Sree Manohari Chemicals",
    "wof:placetype":"venue"
},
  "geometry": {"coordinates":[78.201324,11.662389],"type":"Point"}
}