{
  "type": "Feature",
  "properties": {
    "iso:country":"IN",
    "sg:address":"Navghar, Vasai Road (e)",
    "sg:city":"Thane",
    "sg:phone":"+91 250331925",
    "sg:postcode":"401210",
    "sg:province":"Maharashtra",
    "sg:website":"http://www.maharashtradirectory.com/el2/panku/",
    "wof:name":"Vallabha Graphics Pvt Ltd",
    "wof:placetype":"venue"
},
  "geometry": {"coordinates":[72.96022000000001,19.285913],"type":"Point"}
}