{
  "type": "Feature",
  "properties": {
    "iso:country":"IN",
    "sg:address":"G-44, Seepz Andheri (e),",
    "sg:city":"Mumbai",
    "sg:classifiers":[
        {
            "category":"Shopping",
            "subcategory":"Jewelry",
            "type":"Retail Goods"
        }
    ],
    "sg:phone":"+91 22 2829 0726",
    "sg:postcode":"400096",
    "sg:tags":[
        "diamond"
    ],
    "wof:name":"Tara Jewels",
    "wof:placetype":"venue"
},
  "geometry": {"coordinates":[72.876656,19.123783],"type":"Point"}
}