{
  "type": "Feature",
  "properties": {
    "iso:country":"IN",
    "sg:address":"24-a,tawawala Bldg., 147, 1st Floor, Pathak Wadi, Lohar Chawl,",
    "sg:city":"Mumbai",
    "sg:classifiers":[
        {
            "category":"Utilities",
            "subcategory":"Cable",
            "type":"Services"
        }
    ],
    "sg:phone":"+91 22 2209 4504",
    "sg:postcode":"400002",
    "sg:tags":[
        "cables/cable",
        "conductor",
        "accessory"
    ],
    "wof:name":"S. Manoj & Company",
    "wof:placetype":"venue"
},
  "geometry": {"coordinates":[72.830765,18.946476],"type":"Point"}
}