{
  "type": "Feature",
  "properties": {
    "iso:country":"IN",
    "sg:address":"1096, EVR Periyar Road,",
    "sg:city":"Chennai",
    "sg:classifiers":[
        {
            "category":"Professional",
            "subcategory":"Computer Services",
            "type":"Services"
        }
    ],
    "sg:postcode":"600003",
    "sg:tags":[
        "e-learning",
        "learning-management-systems",
        "elearning-solutions",
        "elearning-products",
        "software",
        "lms",
        "lms-solutions",
        "school-management-systems"
    ],
    "sg:website":"http://www.whitehouseit.com",
    "wof:name":"White House Business Solutions ",
    "wof:placetype":"venue"
},
  "geometry": {"coordinates":[80.251922,13.080128],"type":"Point"}
}