{
  "type": "Feature",
  "properties": {
    "iso:country":"IN",
    "sg:address":"8-a, National Highway, Lalpar,",
    "sg:city":"Morbi",
    "sg:classifiers":[
        {
            "category":"Manufacturing",
            "subcategory":"Chemicals & Compounds",
            "type":"Manufacturing & Wholesale Goods"
        }
    ],
    "sg:phone":"+91 2822 240 405",
    "sg:postcode":"363641",
    "sg:tags":[
        "supply"
    ],
    "wof:name":"Bond Impex Pvt. Ltd.",
    "wof:placetype":"venue"
},
  "geometry": {"coordinates":[77.188957,28.607586],"type":"Point"}
}