{
  "type": "Feature",
  "properties": {
    "iso:country":"IN",
    "sg:address":"A/2081, Bhandup Industrial Estate, L.b.s. Marg, Bhandup (w),",
    "sg:city":"Mumbai",
    "sg:classifiers":[
        {
            "category":"Manufacturing",
            "subcategory":"Rubber & Plastics",
            "type":"Manufacturing & Wholesale Goods"
        }
    ],
    "sg:phone":"+91 22 2596 3258",
    "sg:postcode":"400078",
    "sg:tags":[
        "product"
    ],
    "sg:website":"http://www.rmapplied.com",
    "wof:name":"Rm Applied Engineers",
    "wof:placetype":"venue"
},
  "geometry": {"coordinates":[72.937935,19.154734],"type":"Point"}
}