{
  "type": "Feature",
  "properties": {
    "iso:country":"IN",
    "sg:address":"C-26 Sector- 59,",
    "sg:city":"Noida",
    "sg:classifiers":[
        {
            "category":"Manufacturing",
            "subcategory":"Rubber & Plastics",
            "type":"Manufacturing & Wholesale Goods"
        }
    ],
    "sg:phone":"+91 120 436 2413",
    "sg:postcode":"201301",
    "sg:tags":[
        "polymer"
    ],
    "wof:name":"Jubilant Organosys Ltd.",
    "wof:placetype":"venue"
},
  "geometry": {"coordinates":[77.31090500000001,28.309315],"type":"Point"}
}