{
  "type": "Feature",
  "properties": {
    "iso:country":"IN",
    "sg:address":"R-1/3, Sunder Nagar, Malad (west),",
    "sg:city":"Mumbai",
    "sg:classifiers":[
        {
            "category":"Shopping",
            "subcategory":"Baby Store",
            "type":"Retail Goods"
        }
    ],
    "sg:phone":"+91 22 2882 1369",
    "sg:postcode":"400064",
    "sg:tags":[
        "infant",
        "product"
    ],
    "wof:name":"Skb Elastomers",
    "wof:placetype":"venue"
},
  "geometry": {"coordinates":[72.87075,19.126095],"type":"Point"}
}