{
  "type": "Feature",
  "properties": {
    "iso:country":"IN",
    "sg:address":"129, Dispensary Road, N.c. Road,",
    "sg:city":"Bangalore",
    "sg:classifiers":[
        {
            "category":"Professional",
            "subcategory":"Credit Reporting & Collection",
            "type":"Services"
        }
    ],
    "sg:phone":"+91 80 2555 0263",
    "sg:postcode":"560001",
    "sg:tags":[
        "seasoning",
        "spice"
    ],
    "wof:name":"Vasantha Traders",
    "wof:placetype":"venue"
},
  "geometry": {"coordinates":[77.609077,12.981288],"type":"Point"}
}