{
  "type": "Feature",
  "properties": {
    "iso:country":"IN",
    "sg:address":"1007-a, Panchratna Building, Opera House,",
    "sg:city":"Mumbai",
    "sg:classifiers":[
        {
            "category":"Structure",
            "subcategory":"Warehouse",
            "type":"Public Place"
        }
    ],
    "sg:phone":"+91 22 2368 0942",
    "sg:postcode":"400004",
    "sg:tags":[
        "decorative",
        "item"
    ],
    "wof:name":"Chordia International",
    "wof:placetype":"venue"
},
  "geometry": {"coordinates":[72.816254,18.955734],"type":"Point"}
}