{
  "type": "Feature",
  "properties": {
    "iso:country":"IN",
    "sg:address":"B-8/1, Mayapuri Industrial Area, Phase - 1,",
    "sg:city":"New Delhi",
    "sg:classifiers":[
        {
            "category":"Manufacturing",
            "subcategory":"Chemicals & Compounds",
            "type":"Manufacturing & Wholesale Goods"
        }
    ],
    "sg:phone":"+91 11 2811 6772",
    "sg:postcode":"110064",
    "sg:tags":[
        "plant",
        "processing"
    ],
    "wof:name":"Singhson Engineers",
    "wof:placetype":"venue"
},
  "geometry": {"coordinates":[77.12694500000001,28.630474],"type":"Point"}
}