{
  "type": "Feature",
  "properties": {
    "iso:country":"IN",
    "sg:address":"W-35, M.i.d.c., Bhosari,",
    "sg:city":"Pune",
    "sg:classifiers":[
        {
            "category":"Manufacturing",
            "subcategory":"Chemicals & Compounds",
            "type":"Manufacturing & Wholesale Goods"
        }
    ],
    "sg:phone":"+91 20 2712 1043",
    "sg:postcode":"411026",
    "sg:tags":[
        "paint",
        "product",
        "allied"
    ],
    "wof:name":"Nasa Paints & Products",
    "wof:placetype":"venue"
},
  "geometry": {"coordinates":[73.83496100000001,18.630056],"type":"Point"}
}