{
  "type": "Feature",
  "properties": {
    "iso:country":"IN",
    "sg:address":"No.40, 5th Cross, Sriramapuram,",
    "sg:city":"Bangalore",
    "sg:classifiers":[
        {
            "category":"Retail",
            "subcategory":"Emissions Testing",
            "type":"Services"
        }
    ],
    "sg:phone":"+91 94 48 273856",
    "sg:postcode":"560021",
    "sg:tags":[
        "measuring",
        "instrument"
    ],
    "wof:name":"Vsn Enterprises",
    "wof:placetype":"venue"
},
  "geometry": {"coordinates":[77.566422,12.996853],"type":"Point"}
}