{
  "type": "Feature",
  "properties": {
    "iso:country":"IN",
    "sg:address":"16, K. K. Gupta Indl. Est., Mulund (w),",
    "sg:city":"Mumbai",
    "sg:classifiers":[
        {
            "category":"Manufacturing",
            "subcategory":"Chemicals & Compounds",
            "type":"Manufacturing & Wholesale Goods"
        }
    ],
    "sg:phone":"+91 22 2567 7581",
    "sg:postcode":"400080",
    "sg:tags":[
        "plant",
        "processing"
    ],
    "sg:website":"http://www.universalenggsys.com",
    "wof:name":"Universal Engineering Systems",
    "wof:placetype":"venue"
},
  "geometry": {"coordinates":[72.952789,19.181257],"type":"Point"}
}