{
  "type": "Feature",
  "properties": {
    "iso:country":"IN",
    "sg:address":"Plot No. A-54, Midc,",
    "sg:city":"Badlapur",
    "sg:classifiers":[
        {
            "category":"Manufacturing",
            "subcategory":"Chemicals & Compounds",
            "type":"Manufacturing & Wholesale Goods"
        }
    ],
    "sg:phone":"+91 251 269 0200",
    "sg:postcode":"421503",
    "sg:tags":[
        "industrial"
    ],
    "wof:name":"Himalaya Industries",
    "wof:placetype":"venue"
},
  "geometry": {"coordinates":[75.320808,19.855721],"type":"Point"}
}