{
  "type": "Feature",
  "properties": {
    "iso:country":"IN",
    "sg:address":"No. 11/2 B Opp Hennur Bande, Hennur Road,",
    "sg:city":"Bangalore",
    "sg:classifiers":[
        {
            "category":"Bus Station",
            "type":"Transportation"
        }
    ],
    "sg:phone":"+91 80 2544 0855",
    "sg:postcode":"560043",
    "sg:tags":[
        "switch"
    ],
    "wof:name":"Mani Enterprises",
    "wof:placetype":"venue"
},
  "geometry": {"coordinates":[77.641029,13.036842],"type":"Point"}
}