{
  "type": "Feature",
  "properties": {
    "iso:country":"IN",
    "sg:address":"79, Gandhi Nagar, 5th Fourth Cross,",
    "sg:city":"Dharmapuri",
    "sg:classifiers":[
        {
            "category":"Manufacturing",
            "subcategory":"Chemicals & Compounds",
            "type":"Manufacturing & Wholesale Goods"
        }
    ],
    "sg:phone":"+91 4342 262 130",
    "sg:postcode":"636701",
    "sg:tags":[
        "supply"
    ],
    "wof:name":"Bismiroma Aromatic Chemicals",
    "wof:placetype":"venue"
},
  "geometry": {"coordinates":[77.542618,12.971989],"type":"Point"}
}