{
  "type": "Feature",
  "properties": {
    "iso:country":"IN",
    "sg:address":"2/5, 6th Cross, Old Guddadahalli, Mysore Road,",
    "sg:city":"Bangalore",
    "sg:classifiers":[
        {
            "category":"Shopping",
            "subcategory":"Crafts & Fabrics",
            "type":"Retail Goods"
        }
    ],
    "sg:phone":"+91 80 2674 8559",
    "sg:postcode":"560026",
    "sg:tags":[
        "silk"
    ],
    "wof:name":"Vogosa Exports",
    "wof:placetype":"venue"
},
  "geometry": {"coordinates":[77.549522,12.956805],"type":"Point"}
}