{
  "type": "Feature",
  "properties": {
    "iso:country":"IN",
    "sg:address":"71, 4th Main Road, Gandhi Nagar, Adyar,",
    "sg:city":"Chennai",
    "sg:classifiers":[
        {
            "category":"Manufacturing",
            "subcategory":"Chemicals & Compounds",
            "type":"Manufacturing & Wholesale Goods"
        }
    ],
    "sg:phone":"+91 44 2442 6830",
    "sg:postcode":"600020",
    "sg:tags":[
        "supply"
    ],
    "wof:name":"Mfpl Fluorine Products Ltd.",
    "wof:placetype":"venue"
},
  "geometry": {"coordinates":[80.253761,13.009522],"type":"Point"}
}