{
  "type": "Feature",
  "properties": {
    "iso:country":"IN",
    "sg:address":"R N Mukherjee Road, 1st Floor",
    "sg:city":"Kolkata",
    "sg:phone":"+91 33 2248 7800",
    "sg:postcode":"700001",
    "sg:province":"West Bengal",
    "wof:name":"Seven Hills Opticommunication Pvt Ltd",
    "wof:placetype":"venue"
},
  "geometry": {"coordinates":[88.351257,22.570007],"type":"Point"}
}