{
  "type": "Feature",
  "properties": {
    "iso:country":"IN",
    "sg:address":"Prasad Chmbers, 917, Opera House,",
    "sg:city":"Mumbai",
    "sg:classifiers":[
        {
            "category":"Shopping",
            "subcategory":"Jewelry",
            "type":"Retail Goods"
        }
    ],
    "sg:phone":"+91 22 2368 2266",
    "sg:postcode":"400004",
    "sg:tags":[
        "diamond"
    ],
    "wof:name":"Lotus Gem",
    "wof:placetype":"venue"
},
  "geometry": {"coordinates":[72.81744399999999,18.954645],"type":"Point"}
}