{
  "type": "Feature",
  "properties": {
    "iso:country":"IN",
    "sg:address":"W-198 (a), Midc Phase-ii,",
    "sg:city":"Dombivili",
    "sg:classifiers":[
        {
            "category":"Manufacturing",
            "subcategory":"Chemicals & Compounds",
            "type":"Manufacturing & Wholesale Goods"
        }
    ],
    "sg:phone":"+91 22 2676 1552",
    "sg:postcode":"421204",
    "sg:tags":[
        "dye",
        "intermediate"
    ],
    "wof:name":"Bhavani Chem Traders",
    "wof:placetype":"venue"
},
  "geometry": {"coordinates":[77.034859,20.684992],"type":"Point"}
}