{
  "type": "Feature",
  "properties": {
    "iso:country":"IN",
    "sg:address":"A-90, Naraina Industrial Area, Phase-i,",
    "sg:city":"New Delhi",
    "sg:orig_category":"Pvc Resins",
    "sg:phone":"+91 11 4141 1132",
    "sg:postcode":"110028",
    "wof:name":"Incom Cables (p) Ltd.",
    "wof:placetype":"venue"
},
  "geometry": {"coordinates":[77.135574,28.631302],"type":"Point"}
}