{
  "type": "Feature",
  "properties": {
    "iso:country":"IN",
    "sg:address":"Johari Bazar",
    "sg:city":"Jaipur",
    "sg:phone":"+91 141 256 3189",
    "sg:postcode":"302003",
    "sg:province":"Rajasthan",
    "wof:name":"Mohan Exports",
    "wof:placetype":"venue"
},
  "geometry": {"coordinates":[75.825729,26.918915],"type":"Point"}
}