{
  "type": "Feature",
  "properties": {
    "iso:country":"IN",
    "sg:address":"1, Jalaram Commercial Centre, Saki Vihar Road, Sakinaka,",
    "sg:city":"Mumbai",
    "sg:orig_category":"Fan",
    "sg:phone":"+91 22 2852 5522",
    "sg:postcode":"400072",
    "wof:name":"Universal Pollution Control (i) Pvt. Ltd.",
    "wof:placetype":"venue"
},
  "geometry": {"coordinates":[72.887947,19.107935],"type":"Point"}
}