{
  "type": "Feature",
  "properties": {
    "iso:country":"IN",
    "sg:address":"#2326, 3rd Main, Rpc Layout,",
    "sg:city":"Bangalore",
    "sg:classifiers":[
        {
            "category":"Organizations",
            "subcategory":"Labor Organization",
            "type":"Services"
        }
    ],
    "sg:phone":"+91 80 2338 9399",
    "sg:postcode":"560040",
    "sg:tags":[
        "sandstone"
    ],
    "sg:website":"http://www.bilwaexports.com",
    "wof:name":"Sri Bilwa Exports Pvt. Ltd.",
    "wof:placetype":"venue"
},
  "geometry": {"coordinates":[77.544128,12.97228],"type":"Point"}
}