{
  "type": "Feature",
  "properties": {
    "iso:country":"IN",
    "sg:address":"Devkaran Mansion, 46, Vithaldas Road, Lohar Chawl,",
    "sg:city":"Mumbai",
    "sg:classifiers":[
        {
            "category":"Banks & Credit Unions",
            "subcategory":"Investment Brokerage",
            "type":"Services"
        }
    ],
    "sg:phone":"+91 22 2205 8547",
    "sg:postcode":"400002",
    "sg:tags":[
        "transmission",
        "line",
        "good",
        "electrical"
    ],
    "sg:website":"http://www.camaxindia.com",
    "wof:name":"Camax (india)",
    "wof:placetype":"venue"
},
  "geometry": {"coordinates":[72.831146,18.947405],"type":"Point"}
}