{
  "type": "Feature",
  "properties": {
    "iso:country":"IN",
    "sg:address":"326, Maulala Azad Road, Duncan Road,",
    "sg:city":"Mumbai",
    "sg:classifiers":[
        {
            "category":"Structure",
            "subcategory":"Warehouse",
            "type":"Public Place"
        }
    ],
    "sg:phone":"+91 22 5605 3934",
    "sg:postcode":"400028",
    "sg:tags":[
        "decorative",
        "item"
    ],
    "wof:name":"Shreeji Stones",
    "wof:placetype":"venue"
},
  "geometry": {"coordinates":[72.82873499999999,18.966997],"type":"Point"}
}