{
  "type": "Feature",
  "properties": {
    "iso:country":"IN",
    "sg:address":"D/203, Shreeram Apt., S.v.road, Kandivli (w),",
    "sg:city":"Mumbai",
    "sg:classifiers":[
        {
            "category":"Manufacturing",
            "subcategory":"Chemicals & Compounds",
            "type":"Manufacturing & Wholesale Goods"
        }
    ],
    "sg:phone":"+91 22 2861 2768",
    "sg:postcode":"400067",
    "sg:tags":[
        "supply"
    ],
    "wof:name":"Jamunesh Imex",
    "wof:placetype":"venue"
},
  "geometry": {"coordinates":[72.80740400000001,19.197575],"type":"Point"}
}