{
  "type": "Feature",
  "properties": {
    "iso:country":"IN",
    "sg:address":"136, East  Ponnurangam Road, R.s. Puram,",
    "sg:city":"Coimbatore",
    "sg:classifiers":[
        {
            "category":"Manufacturing",
            "subcategory":"Rubber & Plastics",
            "type":"Manufacturing & Wholesale Goods"
        }
    ],
    "sg:phone":"+91 422 436 7075",
    "sg:postcode":"641002",
    "sg:tags":[
        "synthetic"
    ],
    "wof:name":"Sri Ganessh Enterprises",
    "wof:placetype":"venue"
},
  "geometry": {"coordinates":[76.94901299999999,11.011093],"type":"Point"}
}