{
  "type": "Feature",
  "properties": {
    "iso:country":"IN",
    "sg:address":"3, Anand Indl. Estate, Mohan Nagar,",
    "sg:city":"Ghaziabad",
    "sg:classifiers":[
        {
            "category":"Manufacturing",
            "subcategory":"Chemicals & Compounds",
            "type":"Manufacturing & Wholesale Goods"
        }
    ],
    "sg:phone":"+91 120 325 2790",
    "sg:tags":[
        "supply"
    ],
    "wof:name":"Manish Bio-chem Products Pvt. Ltd.",
    "wof:placetype":"venue"
},
  "geometry": {"coordinates":[77.376945,28.680077],"type":"Point"}
}