{
  "type": "Feature",
  "properties": {
    "iso:country":"IN",
    "sg:address":"5, Sati Industrial Estate, I.b. Patel Road, Goregaon (e),",
    "sg:city":"Mumbai",
    "sg:classifiers":[
        {
            "category":"Wholesale",
            "subcategory":"Machinery & Supplies",
            "type":"Manufacturing & Wholesale Goods"
        }
    ],
    "sg:phone":"+91 22 2686 3884",
    "sg:postcode":"400063",
    "sg:tags":[
        "equipment",
        "goods",
        "electrical"
    ],
    "wof:name":"Aerolite Industries",
    "wof:placetype":"venue"
},
  "geometry": {"coordinates":[72.8545,19.161535],"type":"Point"}
}