{
  "type": "Feature",
  "properties": {
    "iso:country":"IN",
    "sg:address":"No 53, Begur Road,",
    "sg:city":"Bangalore",
    "sg:orig_category":"Readymade Garments",
    "sg:phone":"+91 80 2573 2373",
    "sg:postcode":"560068",
    "wof:name":"Jockey",
    "wof:placetype":"venue"
},
  "geometry": {"coordinates":[77.62603799999999,12.89476],"type":"Point"}
}