{
  "type": "Feature",
  "properties": {
    "iso:country":"IN",
    "sg:address":"S-418a, Manipal Centre 47, Dickenson Road,",
    "sg:city":"Bangalore",
    "sg:classifiers":[
        {
            "category":"Manufacturing",
            "subcategory":"Chemicals & Compounds",
            "type":"Manufacturing & Wholesale Goods"
        }
    ],
    "sg:phone":"+91 80 2532 1274",
    "sg:postcode":"560042",
    "sg:tags":[
        "supply"
    ],
    "wof:name":"Gulshan Sugars & Chemicals Ltd.",
    "wof:placetype":"venue"
},
  "geometry": {"coordinates":[77.61444899999999,12.974972],"type":"Point"}
}