{
  "type": "Feature",
  "properties": {
    "iso:country":"IN",
    "sg:address":"10/850, Malviya Nagar,",
    "sg:city":"Jaipur",
    "sg:classifiers":[
        {
            "category":"Manufacturing",
            "subcategory":"Chemicals & Compounds",
            "type":"Manufacturing & Wholesale Goods"
        }
    ],
    "sg:phone":"+91 141 255 2182",
    "sg:postcode":"302017",
    "sg:tags":[
        "supply"
    ],
    "wof:name":"Psb Udyog",
    "wof:placetype":"venue"
},
  "geometry": {"coordinates":[77.214645,28.534197],"type":"Point"}
}