{
  "type": "Feature",
  "properties": {
    "iso:country":"IN",
    "sg:address":"A38-h, Sector-64,",
    "sg:city":"Noida",
    "sg:classifiers":[
        {
            "category":"Manufacturing",
            "subcategory":"Chemicals & Compounds",
            "type":"Manufacturing & Wholesale Goods"
        }
    ],
    "sg:phone":"+91 120 240 3101",
    "sg:postcode":"201301",
    "sg:tags":[
        "plant",
        "processing"
    ],
    "wof:name":"Nunerg Engineering Pvt. Ltd.",
    "wof:placetype":"venue"
},
  "geometry": {"coordinates":[76.74086800000001,30.686123],"type":"Point"}
}