{
  "type": "Feature",
  "properties": {
    "iso:country":"IN",
    "sg:address":"802, Shilp, C.g. Road,",
    "sg:city":"Ahmedabad",
    "sg:classifiers":[
        {
            "category":"Wholesale",
            "subcategory":"Chemicals & Plastics",
            "type":"Manufacturing & Wholesale Goods"
        }
    ],
    "sg:phone":"+91 79 6661 0793",
    "sg:postcode":"380002",
    "sg:tags":[
        "dye"
    ],
    "wof:name":"Loxim Ind. Pvt. Ltd.",
    "wof:placetype":"venue"
},
  "geometry": {"coordinates":[72.561378,23.061472],"type":"Point"}
}