{
  "type": "Feature",
  "properties": {
    "iso:country":"IN",
    "sg:address":"Nagar Road",
    "sg:city":"Pune",
    "sg:phone":"+91 206684708",
    "sg:postcode":"411006",
    "sg:province":"Maharashtra",
    "sg:website":"http://www.ancent.com",
    "wof:name":"Ancent Software International Ltd",
    "wof:placetype":"venue"
},
  "geometry": {"coordinates":[73.90123699999999,18.553646],"type":"Point"}
}