{
  "type": "Feature",
  "properties": {
    "iso:country":"IN",
    "sg:address":"28/2, Ii Main Road, Seshadripuram,",
    "sg:city":"Bangalore",
    "sg:classifiers":[
        {
            "category":"Wholesale",
            "subcategory":"Auto Parts",
            "type":"Manufacturing & Wholesale Goods"
        }
    ],
    "sg:phone":"+91 80 2356 1391",
    "sg:postcode":"560020",
    "sg:tags":[
        "component",
        "pressed"
    ],
    "sg:website":"http://www.centurysystech.com",
    "wof:name":"Century Controls",
    "wof:placetype":"venue"
},
  "geometry": {"coordinates":[77.574005,12.991027],"type":"Point"}
}