{
  "type": "Feature",
  "properties": {
    "iso:country":"IN",
    "sg:address":"139, Kohinoor Indl., Western Express Highway, Goregaon (e),",
    "sg:city":"Mumbai",
    "sg:classifiers":[
        {
            "category":"Communications",
            "subcategory":"Film & Video Production",
            "type":"Services"
        }
    ],
    "sg:phone":"+91 22 6702 2804",
    "sg:postcode":"400063",
    "sg:tags":[
        "lighting",
        "product",
        "electrical",
        "component",
        "/"
    ],
    "wof:name":"Lumens Group Of Companies",
    "wof:placetype":"venue"
},
  "geometry": {"coordinates":[72.858429,19.170286],"type":"Point"}
}