{
  "type": "Feature",
  "properties": {
    "iso:country":"IN",
    "sg:address":"2/12 Amar Niketan, J B Nagar, Andheri (e),",
    "sg:city":"Mumbai",
    "sg:classifiers":[
        {
            "category":"Manufacturing",
            "subcategory":"Chemicals & Compounds",
            "type":"Manufacturing & Wholesale Goods"
        }
    ],
    "sg:phone":"+91 22 2836 1166",
    "sg:postcode":"400059",
    "sg:tags":[
        "supply"
    ],
    "wof:name":"Amus Corpn.",
    "wof:placetype":"venue"
},
  "geometry": {"coordinates":[72.86919399999999,19.111139],"type":"Point"}
}