{
  "type": "Feature",
  "properties": {
    "iso:country":"IN",
    "sg:address":"A-13/52, Siddharth Nagar, Goregaon-west,",
    "sg:city":"Mumbai",
    "sg:classifiers":[
        {
            "category":"Food & Beverages",
            "subcategory":"Bakery",
            "type":"Retail Goods"
        }
    ],
    "sg:phone":"+91 251 248 9754",
    "sg:postcode":"400062",
    "sg:tags":[
        "biscuit"
    ],
    "wof:name":"Saijee Impex",
    "wof:placetype":"venue"
},
  "geometry": {"coordinates":[72.904549,19.09861],"type":"Point"}
}