{
  "type": "Feature",
  "properties": {
    "iso:country":"IN",
    "sg:address":"8, Hill Crest , North South Road No 10, Juhu Scheme,",
    "sg:city":"Mumbai",
    "sg:classifiers":[
        {
            "category":"Professional",
            "subcategory":"Engineering",
            "type":"Services"
        }
    ],
    "sg:phone":"+91 22 2620 0407",
    "sg:postcode":"400049",
    "sg:tags":[
        "equipment",
        "good"
    ],
    "wof:name":"Chemotech India",
    "wof:placetype":"venue"
},
  "geometry": {"coordinates":[72.830254,19.11364],"type":"Point"}
}