{
  "type": "Feature",
  "properties": {
    "iso:country":"IN",
    "sg:address":"Egmore",
    "sg:city":"Chennai",
    "sg:phone":"+91 44 2855 4770",
    "sg:postcode":"600008",
    "sg:province":"Tamil Nadu",
    "wof:name":"Zip Industries Ltd",
    "wof:placetype":"venue"
},
  "geometry": {"coordinates":[80.257225,13.073093],"type":"Point"}
}