{
  "type": "Feature",
  "properties": {
    "iso:country":"IN",
    "sg:address":"1-b, Ssja,",
    "sg:city":"Kota",
    "sg:classifiers":[
        {
            "category":"Manufacturing",
            "subcategory":"Chemicals & Compounds",
            "type":"Manufacturing & Wholesale Goods"
        }
    ],
    "sg:phone":"+91 744 236 0136",
    "sg:tags":[
        "supply"
    ],
    "wof:name":"Gulzag Industries Ltd.",
    "wof:placetype":"venue"
},
  "geometry": {"coordinates":[74.795692,13.008674],"type":"Point"}
}