{
  "type": "Feature",
  "properties": {
    "iso:country":"IN",
    "sg:address":"Coats Road, T.nagar",
    "sg:city":"Chennai",
    "sg:phone":"+91 44 2823 3949",
    "sg:postcode":"600017",
    "sg:province":"Tamil Nadu",
    "wof:name":"King Chemicals",
    "wof:placetype":"venue"
},
  "geometry": {"coordinates":[80.233276,13.043861],"type":"Point"}
}