{
  "type": "Feature",
  "properties": {
    "iso:country":"IN",
    "sg:address":"36/37, Mittal Towers, Nariman Point,",
    "sg:city":"Mumbai",
    "sg:classifiers":[
        {
            "category":"Manufacturing",
            "subcategory":"Metals",
            "type":"Manufacturing & Wholesale Goods"
        }
    ],
    "sg:phone":"+91 22 5630 6818",
    "sg:postcode":"400021",
    "sg:tags":[
        "copper",
        "product"
    ],
    "sg:website":"http://www.metacopper.com",
    "wof:name":"Meta Copper And Alloys Ltd.",
    "wof:placetype":"venue"
},
  "geometry": {"coordinates":[72.824631,18.924906],"type":"Point"}
}