{
  "type": "Feature",
  "properties": {
    "iso:country":"IN",
    "sg:address":"7B, Third Street Balajinagar",
    "sg:city":"Chennai",
    "sg:classifiers":[
        {
            "category":"Professional",
            "subcategory":"Computer Services",
            "type":"Services"
        }
    ],
    "sg:postcode":"600 014",
    "sg:website":"http://www.realimage.com",
    "wof:name":"Real Image Media Technologies",
    "wof:placetype":"venue"
},
  "geometry": {"coordinates":[80.152961,13.037779],"type":"Point"}
}