{
  "type": "Feature",
  "properties": {
    "iso:country":"IN",
    "sg:address":"#750, Chickpet,",
    "sg:city":"Bangalore",
    "sg:classifiers":[
        {
            "category":"Shopping",
            "subcategory":"Clothing, Apparel, & Fashions",
            "type":"Retail Goods"
        }
    ],
    "sg:phone":"+91 80 2226 3404",
    "sg:postcode":"560053",
    "sg:tags":[
        "shirt"
    ],
    "sg:website":"http://www.colombostores.com",
    "wof:name":"Colombo Stores",
    "wof:placetype":"venue"
},
  "geometry": {"coordinates":[77.574837,12.970479],"type":"Point"}
}