{
  "type": "Feature",
  "properties": {
    "iso:country":"IN",
    "sg:address":"219, Maker Chamber V,  Nariman Point,",
    "sg:city":"Mumbai",
    "sg:classifiers":[
        {
            "category":"Manufacturing",
            "subcategory":"Chemicals & Compounds",
            "type":"Manufacturing & Wholesale Goods"
        }
    ],
    "sg:phone":"+91 22 2284 4823",
    "sg:postcode":"400021",
    "sg:tags":[
        "pharmaceutical"
    ],
    "wof:name":"Essem Exports And Marketing",
    "wof:placetype":"venue"
},
  "geometry": {"coordinates":[72.822159,18.923862],"type":"Point"}
}