{
  "type": "Feature",
  "properties": {
    "iso:country":"IN",
    "sg:address":"14/a, Maskati Market, Kalupur,",
    "sg:city":"Ahmedabad",
    "sg:classifiers":[
        {
            "category":"Manufacturing",
            "subcategory":"Chemicals & Compounds",
            "type":"Manufacturing & Wholesale Goods"
        }
    ],
    "sg:phone":"+91 79 2217 3788",
    "sg:postcode":"380002",
    "sg:tags":[
        "supply"
    ],
    "wof:name":"Tushar Enterprise",
    "wof:placetype":"venue"
},
  "geometry": {"coordinates":[72.598831,23.029278],"type":"Point"}
}