{
  "type": "Feature",
  "properties": {
    "iso:country":"IN",
    "sg:address":"231, 2nd Floor, Champaklal Industrial Estate, Sion - East,",
    "sg:city":"Mumbai",
    "sg:classifiers":[
        {
            "category":"Farming",
            "subcategory":"Crops",
            "type":"Manufacturing & Wholesale Goods"
        }
    ],
    "sg:phone":"+91 22 2409 0509",
    "sg:postcode":"400022",
    "sg:tags":[
        "cereal"
    ],
    "wof:name":"Aardee Globiz",
    "wof:placetype":"venue"
},
  "geometry": {"coordinates":[72.866837,19.042019],"type":"Point"}
}