{
  "type": "Feature",
  "properties": {
    "iso:country":"IN",
    "sg:address":"63, Jolly Maker Apt.2, Cuffe Parade,",
    "sg:city":"Mumbai",
    "sg:classifiers":[
        {
            "category":"Retail",
            "subcategory":"Self-service Laundry",
            "type":"Services"
        }
    ],
    "sg:phone":"+91 22 2218 7238",
    "sg:postcode":"400005",
    "sg:tags":[
        "good",
        "consumer"
    ],
    "wof:name":"Sheth Impex",
    "wof:placetype":"venue"
},
  "geometry": {"coordinates":[72.81905399999999,18.915291],"type":"Point"}
}