{
  "type": "Feature",
  "properties": {
    "iso:country":"IN",
    "sg:address":"121, Atlanta, Nariman Point,",
    "sg:city":"Mumbai",
    "sg:classifiers":[
        {
            "category":"Manufacturing",
            "subcategory":"Chemicals & Compounds",
            "type":"Manufacturing & Wholesale Goods"
        }
    ],
    "sg:phone":"+91 22 2285 1007",
    "sg:postcode":"400021",
    "sg:tags":[
        "dye",
        "intermediate"
    ],
    "sg:website":"http://www.ravidyeware.com",
    "wof:name":"Siddharth Colorchem. Ltd.",
    "wof:placetype":"venue"
},
  "geometry": {"coordinates":[72.82431,18.927296],"type":"Point"}
}