{
  "type": "Feature",
  "properties": {
    "iso:country":"IN",
    "sg:address":"Lower Parel",
    "sg:city":"Mumbai",
    "sg:phone":"+91 22 2497 4444",
    "sg:postcode":"400013",
    "sg:province":"Maharashtra",
    "sg:website":"http://www.globalsources.com/atit.co",
    "wof:name":"Atit Textile Industries Ltd",
    "wof:placetype":"venue"
},
  "geometry": {"coordinates":[72.824959,19.002481],"type":"Point"}
}