{
  "type": "Feature",
  "properties": {
    "iso:country":"IN",
    "sg:address":"#102 A ,santa clara,Intermediate Ring Road,Bangalore",
    "sg:city":"Bangalore",
    "sg:classifiers":[
        {
            "category":"Professional",
            "subcategory":"Computer Services",
            "type":"Services"
        }
    ],
    "sg:postcode":"560047",
    "sg:tags":[
        "gps-game",
        "gps-gaming",
        "location-based-gaming",
        "location-based-games",
        "location-based-services",
        "playing-outside",
        "geocaching"
    ],
    "sg:website":"http://www.orbster.com",
    "wof:name":"Orbster",
    "wof:placetype":"venue"
},
  "geometry": {"coordinates":[8.410278,49.009256],"type":"Point"}
}