{
  "type": "Feature",
  "properties": {
    "iso:country":"IN",
    "sg:address":"No. 1, M.s.r. Industrial Estate, Mathikere,",
    "sg:city":"Bangalore",
    "sg:classifiers":[
        {
            "category":"Professional",
            "subcategory":"Printing & Photocopies",
            "type":"Services"
        }
    ],
    "sg:phone":"+91 80 2360 8427",
    "sg:postcode":"560054",
    "sg:tags":[
        "material"
    ],
    "wof:name":"Ess Cee Enterprises",
    "wof:placetype":"venue"
},
  "geometry": {"coordinates":[77.561142,13.036857],"type":"Point"}
}