{
  "type": "Feature",
  "properties": {
    "iso:country":"IN",
    "sg:address":"26-a, Sarojini Nagar,",
    "sg:city":"Kanpur",
    "sg:classifiers":[
        {
            "category":"Home & Garden",
            "subcategory":"Building Materials",
            "type":"Retail Goods"
        }
    ],
    "sg:phone":"+91 512 223 0402",
    "sg:postcode":"208005",
    "sg:tags":[
        "sealant",
        "adhesive"
    ],
    "wof:name":"Ruchi Exports",
    "wof:placetype":"venue"
},
  "geometry": {"coordinates":[77.195961,28.576874],"type":"Point"}
}