{
  "type": "Feature",
  "properties": {
    "iso:country":"IN",
    "sg:address":"C-87, Woodland, Gandhi Bhawan, Kothrud,",
    "sg:city":"Pune",
    "sg:classifiers":[
        {
            "category":"Home & Garden",
            "subcategory":"Building Materials",
            "type":"Retail Goods"
        }
    ],
    "sg:phone":"+91 209881470889",
    "sg:postcode":"411038",
    "sg:tags":[
        "sealant",
        "adhesive"
    ],
    "wof:name":"Eoc Uk Limited",
    "wof:placetype":"venue"
},
  "geometry": {"coordinates":[73.804459,18.498739],"type":"Point"}
}