{
  "type": "Feature",
  "properties": {
    "iso:country":"IN",
    "sg:address":"145, Sdf-v, Seepz, Andheri (east),",
    "sg:city":"Mumbai",
    "sg:classifiers":[
        {
            "category":"Government",
            "subcategory":"Post Office",
            "type":"Public Place"
        }
    ],
    "sg:phone":"+91 22 2829 0244",
    "sg:postcode":"400096",
    "sg:tags":[
        "board",
        "circuit"
    ],
    "sg:website":"http://www.finelineindia.com",
    "wof:name":"Fine-line Circuits Limited",
    "wof:placetype":"venue"
},
  "geometry": {"coordinates":[72.875153,19.126781],"type":"Point"}
}