{
  "type": "Feature",
  "properties": {
    "iso:country":"IN",
    "sg:address":"14, Netaji Subhas Road, 1st Floor,",
    "sg:city":"Kolkata",
    "sg:classifiers":[
        {
            "category":"Manufacturing",
            "subcategory":"Chemicals & Compounds",
            "type":"Manufacturing & Wholesale Goods"
        }
    ],
    "sg:phone":"+91 33 2231 5360",
    "sg:postcode":"700001",
    "sg:tags":[
        "supply"
    ],
    "wof:name":"Sai Enterprises",
    "wof:placetype":"venue"
},
  "geometry": {"coordinates":[88.350288,22.580135],"type":"Point"}
}