{
  "type": "Feature",
  "properties": {
    "iso:country":"IN",
    "sg:address":"No. 38, 16th, 'c' Main, 4th Block Kormangala,",
    "sg:city":"Bangalore",
    "sg:classifiers":[
        {
            "category":"Manufacturing",
            "subcategory":"Rubber & Plastics",
            "type":"Manufacturing & Wholesale Goods"
        }
    ],
    "sg:phone":"+91 80 2553 1064",
    "sg:postcode":"560034",
    "sg:tags":[
        "product"
    ],
    "wof:name":"Kk Traders & Manufacturers",
    "wof:placetype":"venue"
},
  "geometry": {"coordinates":[77.626221,12.935612],"type":"Point"}
}