{
  "type": "Feature",
  "properties": {
    "iso:country":"IN",
    "sg:address":"54, 8th Cross, 4th Main Road, S.r. Nagar,",
    "sg:city":"Bangalore",
    "sg:orig_category":"Sarees",
    "sg:phone":"+91 80 2221 9973",
    "sg:postcode":"560027",
    "wof:name":"Adi  Silks",
    "wof:placetype":"venue"
},
  "geometry": {"coordinates":[77.592545,12.965964],"type":"Point"}
}