{
  "type": "Feature",
  "properties": {
    "iso:country":"IN",
    "sg:address":"14, Rani Jhanhsi Road,",
    "sg:city":"Delhi",
    "sg:classifiers":[
        {
            "category":"Manufacturing",
            "subcategory":"Rubber & Plastics",
            "type":"Manufacturing & Wholesale Goods"
        }
    ],
    "sg:phone":"+91 11 2351 6567",
    "sg:postcode":"110055",
    "sg:tags":[
        "synthetic"
    ],
    "sg:website":"http://www.cpil.com",
    "wof:name":"Chandra Prabhu International Limited",
    "wof:placetype":"venue"
},
  "geometry": {"coordinates":[77.203079,28.658995],"type":"Point"}
}