{
  "type": "Feature",
  "properties": {
    "iso:country":"IN",
    "sg:address":"17th Cross, Maleswaram,",
    "sg:city":"Bangalore",
    "sg:classifiers":[
        {
            "category":"Bus Station",
            "type":"Transportation"
        }
    ],
    "sg:phone":"+91 80 2344 5516",
    "sg:postcode":"560003",
    "sg:tags":[
        "switch"
    ],
    "sg:website":"http://www.dbups.com",
    "wof:name":"Db Power Electronics Pvt. Ltd.",
    "wof:placetype":"venue"
},
  "geometry": {"coordinates":[77.566315,13.007462],"type":"Point"}
}