{
  "type": "Feature",
  "properties": {
    "iso:country":"IN",
    "sg:address":"C-220a, Ghatkopar Indl. Estate, Ghatkopar(w),",
    "sg:city":"Mumbai",
    "sg:classifiers":[
        {
            "category":"Manufacturing",
            "subcategory":"Tools & Machinery",
            "type":"Manufacturing & Wholesale Goods"
        }
    ],
    "sg:phone":"+91 22 2500 8088",
    "sg:postcode":"400086",
    "sg:tags":[
        "die",
        "casting"
    ],
    "wof:name":"Patterns & Engineers",
    "wof:placetype":"venue"
},
  "geometry": {"coordinates":[72.914101,19.101273],"type":"Point"}
}