{
  "type": "Feature",
  "properties": {
    "iso:country":"IN",
    "sg:address":"148/8, Garodia Nagar,",
    "sg:city":"Mumbai",
    "sg:classifiers":[
        {
            "category":"Shopping",
            "subcategory":"Bicycles & Sporting Goods",
            "type":"Retail Goods"
        }
    ],
    "sg:phone":"+91 22 2506 0430",
    "sg:postcode":"400077",
    "sg:tags":[
        "spare",
        "bicycles",
        "component"
    ],
    "wof:name":"Mini Exports",
    "wof:placetype":"venue"
},
  "geometry": {"coordinates":[80.23129299999999,13.05995],"type":"Point"}
}