{
  "type": "Feature",
  "properties": {
    "iso:country":"IN",
    "sg:address":"C/264/1, Bapuji Nagar,",
    "sg:city":"Kolkata",
    "sg:orig_category":"Pvc Resins",
    "sg:phone":"+91 33 2413 3557",
    "sg:postcode":"700092",
    "sg:website":"http://www.srinjoyimpex.co.nr",
    "wof:name":"Srinjoy Impex",
    "wof:placetype":"venue"
},
  "geometry": {"coordinates":[85.83390799999999,20.255529],"type":"Point"}
}