{
  "type": "Feature",
  "properties": {
    "iso:country":"IN",
    "sg:address":"Ezra Street",
    "sg:city":"Kolkata",
    "sg:phone":"+91 33 2235 8211",
    "sg:postcode":"700001",
    "sg:province":"West Bengal",
    "wof:name":"Modern Fibotex India Ltd",
    "wof:placetype":"venue"
},
  "geometry": {"coordinates":[88.353035,22.57485],"type":"Point"}
}