{
  "type": "Feature",
  "properties": {
    "iso:country":"IN",
    "sg:address":"Village Kaka,",
    "sg:city":"Ludhiana",
    "sg:orig_category":"Foam,rexine & P.u.products",
    "sg:phone":"+91 161 270 4045",
    "sg:postcode":"141008",
    "wof:name":"Modern Foam Udyog",
    "wof:placetype":"venue"
},
  "geometry": {"coordinates":[72.843704,19.022301],"type":"Point"}
}