{
  "type": "Feature",
  "properties": {
    "iso:country":"IN",
    "sg:address":"D-23, Industrial Area, B.s. Road,",
    "sg:city":"Ghaziabad",
    "sg:classifiers":[
        {
            "category":"Home & Garden",
            "subcategory":"Building Materials",
            "type":"Retail Goods"
        }
    ],
    "sg:tags":[
        "sealant",
        "adhesive"
    ],
    "wof:name":"Global Adhesives",
    "wof:placetype":"venue"
},
  "geometry": {"coordinates":[76.23043800000001,21.325993],"type":"Point"}
}