{
  "type": "Feature",
  "properties": {
    "iso:country":"IN",
    "sg:address":"205, Princess Street,",
    "sg:city":"Mumbai",
    "sg:classifiers":[
        {
            "category":"Utilities",
            "subcategory":"Fuel Oil & Lpg",
            "type":"Services"
        }
    ],
    "sg:phone":"+91 22 2206 2626",
    "sg:postcode":"400002",
    "sg:tags":[
        "aromatics",
        "essential"
    ],
    "sg:website":"http://www.privi.com",
    "wof:name":"Privi Organics Limited",
    "wof:placetype":"venue"
},
  "geometry": {"coordinates":[72.830635,18.947435],"type":"Point"}
}