{
  "type": "Feature",
  "properties": {
    "iso:country":"IN",
    "sg:address":"B-39, 91st Floor, Sector 40,",
    "sg:city":"Noida",
    "sg:classifiers":[
        {
            "category":"Manufacturing",
            "subcategory":"Petroleum Products",
            "type":"Manufacturing & Wholesale Goods"
        }
    ],
    "sg:phone":"+91 120 433 1944",
    "sg:postcode":"201301",
    "sg:tags":[
        "wax"
    ],
    "sg:website":"http://www.dmgpolypack.com",
    "wof:name":"Dmg Polypack",
    "wof:placetype":"venue"
},
  "geometry": {"coordinates":[77.057884,28.4489],"type":"Point"}
}