{
  "type": "Feature",
  "properties": {
    "iso:country":"IN",
    "sg:address":"#41, 2nd Floor, 100 Feet Road, 4th Block, Koramangala,",
    "sg:city":"Bangalore",
    "sg:classifiers":[
        {
            "category":"Shopping",
            "subcategory":"Crafts & Fabrics",
            "type":"Retail Goods"
        }
    ],
    "sg:phone":"+91 80 4131 7558",
    "sg:postcode":"560034",
    "sg:tags":[
        "silk"
    ],
    "wof:name":"Madhu Silk Emporium",
    "wof:placetype":"venue"
},
  "geometry": {"coordinates":[77.62318399999999,12.932578],"type":"Point"}
}