{
  "type": "Feature",
  "properties": {
    "iso:country":"IN",
    "sg:address":"89, Avanti G Road, 5th Floor #3,",
    "sg:city":"Mumbai",
    "sg:classifiers":[
        {
            "category":"Shopping",
            "subcategory":"Jewelry",
            "type":"Retail Goods"
        }
    ],
    "sg:phone":"+91 22 2281 5722",
    "sg:postcode":"400002",
    "sg:tags":[
        "diamond"
    ],
    "wof:name":"Srimal International",
    "wof:placetype":"venue"
},
  "geometry": {"coordinates":[72.824821,18.942928],"type":"Point"}
}