{
  "type": "Feature",
  "properties": {
    "iso:country":"IN",
    "sg:address":"C-29, 2nd Stage, Peenya Ind. Estate,",
    "sg:city":"Bangalore",
    "sg:classifiers":[
        {
            "category":"Manufacturing",
            "subcategory":"Rubber & Plastics",
            "type":"Manufacturing & Wholesale Goods"
        }
    ],
    "sg:phone":"+91 80 2836 0622",
    "sg:postcode":"560058",
    "sg:tags":[
        "polymer"
    ],
    "wof:name":"Shree Polypacks",
    "wof:placetype":"venue"
},
  "geometry": {"coordinates":[77.515373,13.030847],"type":"Point"}
}