{
  "type": "Feature",
  "properties": {
    "iso:country":"IN",
    "sg:address":"Jodhpur Village Road, Satellite",
    "sg:city":"Ahmedabad",
    "sg:phone":"+91 79400677",
    "sg:postcode":"380015",
    "sg:province":"Gujarat",
    "wof:name":"Maruti Infrastructure Ltd",
    "wof:placetype":"venue"
},
  "geometry": {"coordinates":[72.52879299999999,23.024292],"type":"Point"}
}