{
  "type": "Feature",
  "properties": {
    "iso:country":"IN",
    "sg:address":"Mount Road",
    "sg:city":"Chennai",
    "sg:phone":"+91 44 2846 0283",
    "sg:postcode":"600002",
    "sg:province":"Tamil Nadu",
    "wof:name":"Neptune Refrigeration Co Pvt Ltd",
    "wof:placetype":"venue"
},
  "geometry": {"coordinates":[80.249786,13.048869],"type":"Point"}
}