{
  "type": "Feature",
  "properties": {
    "iso:country":"IN",
    "sg:address":"Nugambakkam High Road",
    "sg:city":"Chennai",
    "sg:phone":"+91 44 2827 5327",
    "sg:postcode":"600034",
    "sg:province":"Tamil Nadu",
    "wof:name":"Famtex Exports Pvt Ltd",
    "wof:placetype":"venue"
},
  "geometry": {"coordinates":[80.24820699999999,13.058237],"type":"Point"}
}