{
  "type": "Feature",
  "properties": {
    "iso:country":"IN",
    "sg:address":"G-5/6, Sangeet Plaza, Marol Maroshi Road, Andheri (east),",
    "sg:city":"Mumbai",
    "sg:classifiers":[
        {
            "category":"Manufacturing",
            "subcategory":"Tools & Machinery",
            "type":"Manufacturing & Wholesale Goods"
        }
    ],
    "sg:phone":"+91 22 2856 0852",
    "sg:postcode":"400059",
    "sg:tags":[
        "farm",
        "machine",
        "agriculture"
    ],
    "sg:website":"http://www.villa-mode.com",
    "wof:name":"Villa-mode Export (india) Pvt. Ltd.",
    "wof:placetype":"venue"
},
  "geometry": {"coordinates":[72.878899,19.1106],"type":"Point"}
}