{
  "type": "Feature",
  "properties": {
    "iso:country":"IN",
    "sg:address":"Plot No. 54-b, Sector-18,",
    "sg:city":"Gurgaon",
    "sg:classifiers":[
        {
            "category":"Manufacturing",
            "subcategory":"Chemicals & Compounds",
            "type":"Manufacturing & Wholesale Goods"
        }
    ],
    "sg:phone":"+91 124 400 7222",
    "sg:postcode":"122001",
    "sg:tags":[
        "paint",
        "product",
        "allied"
    ],
    "wof:name":"Asian Ppg Industries Limited",
    "wof:placetype":"venue"
},
  "geometry": {"coordinates":[76.83606,30.704401],"type":"Point"}
}