{
  "type": "Feature",
  "properties": {
    "iso:country":"IN",
    "sg:address":"L B S Marg",
    "sg:city":"Thane",
    "sg:phone":"+91 22 2541 6036",
    "sg:postcode":"400601",
    "sg:province":"Maharashtra",
    "sg:website":"http://www.aireff.com",
    "wof:name":"Aireff Detox Incineration Ltd",
    "wof:placetype":"venue"
},
  "geometry": {"coordinates":[72.925827,19.119278],"type":"Point"}
}