{
  "type": "Feature",
  "properties": {
    "iso:country":"IN",
    "sg:address":"U-1 Plot, Cama Industrial Estate, Goregaon (east),",
    "sg:city":"Mumbai",
    "sg:classifiers":[
        {
            "category":"Manufacturing",
            "subcategory":"Rubber & Plastics",
            "type":"Manufacturing & Wholesale Goods"
        }
    ],
    "sg:phone":"+91 22 2673 0748",
    "sg:postcode":"400063",
    "sg:tags":[
        "product"
    ],
    "wof:name":"Sathi Industries",
    "wof:placetype":"venue"
},
  "geometry": {"coordinates":[72.85375999999999,19.158243],"type":"Point"}
}