{
  "type": "Feature",
  "properties": {
    "iso:country":"IN",
    "sg:address":"314, Hill View Industrial Estate, Amrut Nagar, Ghatkopar West,",
    "sg:city":"Mumbai",
    "sg:classifiers":[
        {
            "category":"Manufacturing",
            "subcategory":"Musical Instruments",
            "type":"Manufacturing & Wholesale Goods"
        }
    ],
    "sg:phone":"+91 22 2500 8604",
    "sg:postcode":"400086",
    "sg:tags":[
        "electronic"
    ],
    "sg:website":"http://www.mecord.com",
    "wof:name":"Mecord Systems And Services Pvt. Ltd.",
    "wof:placetype":"venue"
},
  "geometry": {"coordinates":[72.913071,19.101727],"type":"Point"}
}