{
  "type": "Feature",
  "properties": {
    "iso:country":"IN",
    "sg:address":"# 48, 1st Floor, A.s.char Street, B.v.k.iyengar Road,",
    "sg:city":"Bangalore",
    "sg:classifiers":[
        {
            "category":"Manufacturing",
            "subcategory":"Chemicals & Compounds",
            "type":"Manufacturing & Wholesale Goods"
        }
    ],
    "sg:phone":"+91 80 3061 2264",
    "sg:postcode":"560053",
    "sg:tags":[
        "supply"
    ],
    "wof:name":"Pure Trading Asia Limited",
    "wof:placetype":"venue"
},
  "geometry": {"coordinates":[77.575668,12.96982],"type":"Point"}
}