{
  "type": "Feature",
  "properties": {
    "iso:country":"IN",
    "sg:address":"91, Govt. Industrial Estate,",
    "sg:city":"Kanpur",
    "sg:classifiers":[
        {
            "category":"Manufacturing",
            "subcategory":"Chemicals & Compounds",
            "type":"Manufacturing & Wholesale Goods"
        }
    ],
    "sg:phone":"+91 512 222 4720",
    "sg:tags":[
        "supply"
    ],
    "wof:name":"Shri Gopal Engg. & Chemicals Works Ltd.",
    "wof:placetype":"venue"
},
  "geometry": {"coordinates":[80.185654,13.083773],"type":"Point"}
}