{
  "type": "Feature",
  "properties": {
    "iso:country":"IN",
    "sg:address":"Fatehabad Road, Near Hotel Taj View Crossing",
    "sg:city":"Agra",
    "sg:phone":"+91 56233229",
    "sg:postcode":"282001",
    "sg:province":"Uttar Pradesh",
    "wof:name":"Joint Venture Tours & Travels",
    "wof:placetype":"venue"
},
  "geometry": {"coordinates":[78.040993,27.161156],"type":"Point"}
}