{
  "type": "Feature",
  "properties": {
    "iso:country":"IN",
    "sg:address":"Saidabad",
    "sg:city":"Hyderabad",
    "sg:phone":"+91 40 2453 4526",
    "sg:postcode":"500059",
    "sg:province":"Andhra Pradesh",
    "sg:website":"http://www.nath.trade-india.com",
    "wof:name":"Enzed Chloro Products Pvt Ltd",
    "wof:placetype":"venue"
},
  "geometry": {"coordinates":[78.50644699999999,17.356382],"type":"Point"}
}