{
  "type": "Feature",
  "properties": {
    "iso:country":"IN",
    "sg:address":"1186, 12th B Main, I Cross, Hal 2nd Stage, Indiranagar,",
    "sg:city":"Bangalore",
    "sg:classifiers":[
        {
            "category":"Manufacturing",
            "subcategory":"Electronics",
            "type":"Manufacturing & Wholesale Goods"
        }
    ],
    "sg:phone":"+91 80 2521 9387",
    "sg:postcode":"560008",
    "sg:tags":[
        "semiconductor"
    ],
    "wof:name":"Wpi International (i) Pvt. Ltd.",
    "wof:placetype":"venue"
},
  "geometry": {"coordinates":[77.64196,12.970206],"type":"Point"}
}