{
  "type": "Feature",
  "properties": {
    "iso:country":"IN",
    "sg:address":"509, Topaz Building, Panjagutta,",
    "sg:city":"Hyderabad",
    "sg:classifiers":[
        {
            "category":"Real Estate",
            "subcategory":"Surveying",
            "type":"Services"
        }
    ],
    "sg:phone":"+91 40 2341 6036",
    "sg:postcode":"500082",
    "sg:tags":[
        "pharmaceutical",
        "material",
        "raw"
    ],
    "sg:website":"http://www.liquorsindia.com",
    "wof:name":"Liquors India Limited",
    "wof:placetype":"venue"
},
  "geometry": {"coordinates":[78.45414700000001,17.429024],"type":"Point"}
}