{
  "type": "Feature",
  "properties": {
    "iso:country":"IN",
    "sg:address":"C62 Nizamuddin East",
    "sg:city":"New Delhi",
    "sg:classifiers":[
        {
            "category":"Professional",
            "subcategory":"Computer Services",
            "type":"Services"
        }
    ],
    "sg:postcode":"110013",
    "sg:tags":[
        "online-shopping",
        "etailing",
        "ecommerce"
    ],
    "sg:website":"http://www.autsun.com",
    "wof:name":"AUTSUN.COM",
    "wof:placetype":"venue"
},
  "geometry": {"coordinates":[77.249855,28.589896],"type":"Point"}
}