{
  "type": "Feature",
  "properties": {
    "iso:country":"IN",
    "sg:address":"B-21, Harmony Blgd., Ram Ngr, Borivali (w),",
    "sg:city":"Mumbai",
    "sg:classifiers":[
        {
            "category":"Shopping",
            "subcategory":"Baby Store",
            "type":"Retail Goods"
        }
    ],
    "sg:phone":"+91 22 2806 1160",
    "sg:postcode":"400092",
    "sg:tags":[
        "garment",
        "childrenwear"
    ],
    "sg:website":"http://www.pragatifashions.com",
    "wof:name":"Agent Amit",
    "wof:placetype":"venue"
},
  "geometry": {"coordinates":[72.867653,19.136621],"type":"Point"}
}