{
  "type": "Feature",
  "properties": {
    "iso:country":"IN",
    "sg:address":"E-10, Industrial Estate, Guindy,",
    "sg:city":"Chennai",
    "sg:classifiers":[
        {
            "category":"Wholesale",
            "subcategory":"Chemicals & Plastics",
            "type":"Manufacturing & Wholesale Goods"
        }
    ],
    "sg:phone":"+91 44 2232 1202",
    "sg:postcode":"600032",
    "sg:tags":[
        "lab",
        "supply"
    ],
    "wof:name":"Scientific Supply (p) Ltd.",
    "wof:placetype":"venue"
},
  "geometry": {"coordinates":[80.211105,13.009055],"type":"Point"}
}