{
  "type": "Feature",
  "properties": {
    "iso:country":"IN",
    "sg:address":"#2234, 23rd Crs, K.r. Road, Banashankari 2nd Stage,",
    "sg:city":"Bangalore",
    "sg:classifiers":[
        {
            "category":"Manufacturing",
            "subcategory":"Musical Instruments",
            "type":"Manufacturing & Wholesale Goods"
        }
    ],
    "sg:phone":"+91 80 6614 6565",
    "sg:tags":[
        "process",
        "control",
        "equipment"
    ],
    "wof:name":"Honeywell Automation India Ltd",
    "wof:placetype":"venue"
},
  "geometry": {"coordinates":[77.555511,12.932187],"type":"Point"}
}