{
  "type": "Feature",
  "properties": {
    "iso:country":"IN",
    "sg:address":"8/116, D.n. Nagar, No. 1, Versova Road, Andheri (w),",
    "sg:city":"Mumbai",
    "sg:classifiers":[
        {
            "category":"Wholesale",
            "subcategory":"Construction Materials",
            "type":"Manufacturing & Wholesale Goods"
        }
    ],
    "sg:phone":"+91 22 2062 8776",
    "sg:postcode":"400053",
    "sg:tags":[
        "building",
        "supply"
    ],
    "wof:name":"Tirupati Construction",
    "wof:placetype":"venue"
},
  "geometry": {"coordinates":[72.83017,19.128242],"type":"Point"}
}