{
  "type": "Feature",
  "properties": {
    "iso:country":"IN",
    "sg:address":"71, 1st Floor, Dr. Rajkumar Road, Prakashnagar,",
    "sg:city":"Bangalore",
    "sg:classifiers":[
        {
            "category":"Utilities",
            "subcategory":"Cable",
            "type":"Services"
        }
    ],
    "sg:phone":"+91 80 2312 4046",
    "sg:postcode":"560021",
    "sg:tags":[
        "rope",
        "wire"
    ],
    "sg:website":"http://www.seekandsource.com/dhoist",
    "wof:name":"D. C. Hoist & Instruments",
    "wof:placetype":"venue"
},
  "geometry": {"coordinates":[77.557899,12.99098],"type":"Point"}
}