{
  "type": "Feature",
  "properties": {
    "iso:country":"IN",
    "sg:address":"6, Datta Mandir Road, Bhandup (w),",
    "sg:city":"Mumbai",
    "sg:classifiers":[
        {
            "category":"Wholesale",
            "subcategory":"Books, Periodicals, & Newspapers",
            "type":"Manufacturing & Wholesale Goods"
        }
    ],
    "sg:phone":"+91 22 2565 2148",
    "sg:postcode":"400078",
    "sg:tags":[
        "publisher",
        "book"
    ],
    "sg:website":"http://www.printhouseindia.com",
    "wof:name":"Print House India Pvt. Ltd.",
    "wof:placetype":"venue"
},
  "geometry": {"coordinates":[72.94154399999999,19.153999],"type":"Point"}
}