{
  "type": "Feature",
  "properties": {
    "iso:country":"IN",
    "sg:address":"8, Canning Street,",
    "sg:city":"Kolkata",
    "sg:classifiers":[
        {
            "category":"Manufacturing",
            "subcategory":"Chemicals & Compounds",
            "type":"Manufacturing & Wholesale Goods"
        }
    ],
    "sg:phone":"+91 33 2210 4975",
    "sg:postcode":"700001",
    "sg:tags":[
        "supply"
    ],
    "wof:name":"Economics (india)",
    "wof:placetype":"venue"
},
  "geometry": {"coordinates":[77.223007,28.620871],"type":"Point"}
}