{
  "type": "Feature",
  "properties": {
    "iso:country":"IN",
    "sg:address":"Deonar Road",
    "sg:city":"Mumbai",
    "sg:phone":"+91 22 2551 1674",
    "sg:postcode":"400088",
    "sg:province":"Maharashtra",
    "sg:website":"http://www.esisaws.com",
    "wof:name":"Eastern Steel Industries",
    "wof:placetype":"venue"
},
  "geometry": {"coordinates":[72.920204,19.052849],"type":"Point"}
}