{
  "type": "Feature",
  "properties": {
    "iso:country":"IN",
    "sg:address":"42, G. Floor, World Trade Centre,",
    "sg:city":"New Delhi",
    "sg:classifiers":[
        {
            "category":"Manufacturing",
            "subcategory":"Chemicals & Compounds",
            "type":"Manufacturing & Wholesale Goods"
        }
    ],
    "sg:phone":"+91 11 2341 1200",
    "sg:postcode":"110001",
    "sg:tags":[
        "supply"
    ],
    "wof:name":"Deepak Micro Minerals",
    "wof:placetype":"venue"
},
  "geometry": {"coordinates":[72.818497,18.91408],"type":"Point"}
}