{
  "type": "Feature",
  "properties": {
    "iso:country":"IN",
    "sg:address":"C-7/5, B.s.r. Industrial Area,",
    "sg:city":"Ghaziabad",
    "sg:classifiers":[
        {
            "category":"Manufacturing",
            "subcategory":"Chemicals & Compounds",
            "type":"Manufacturing & Wholesale Goods"
        }
    ],
    "sg:phone":"+91 120 324 4611",
    "sg:tags":[
        "paint",
        "product",
        "allied"
    ],
    "wof:name":"Jay Pee Colour & Coating",
    "wof:placetype":"venue"
},
  "geometry": {"coordinates":[74.787102,13.334578],"type":"Point"}
}