{
  "type": "Feature",
  "properties": {
    "iso:country":"IN",
    "sg:address":"Basti Shiekh,",
    "sg:city":"Jalandhar",
    "sg:classifiers":[
        {
            "category":"Manufacturing",
            "subcategory":"Leather Goods",
            "type":"Manufacturing & Wholesale Goods"
        }
    ],
    "sg:phone":"+91 181 500 7487",
    "sg:postcode":"144001",
    "wof:name":"Mohinder Jit Chemicals",
    "wof:placetype":"venue"
},
  "geometry": {"coordinates":[75.534218,31.314241],"type":"Point"}
}