{
  "type": "Feature",
  "properties": {
    "iso:country":"IN",
    "sg:address":"105, Nirmal Industrial Estate, Road No.29, Sion East,",
    "sg:city":"Mumbai",
    "sg:classifiers":[
        {
            "category":"Shopping",
            "subcategory":"Luggage & Leather Goods",
            "type":"Retail Goods"
        }
    ],
    "sg:phone":"+91 22 2407 7634",
    "sg:postcode":"400022",
    "sg:tags":[
        "bag",
        "-"
    ],
    "wof:name":"Indian Art Industries",
    "wof:placetype":"venue"
},
  "geometry": {"coordinates":[72.868813,19.046179],"type":"Point"}
}