{
  "type": "Feature",
  "properties": {
    "iso:country":"IN",
    "sg:address":"201/b, Senate, Lokhandwala Complex, Kandivli (e),",
    "sg:city":"Mumbai",
    "sg:classifiers":[
        {
            "category":"Military Area",
            "subcategory":"Air Force Base",
            "type":"Public Place"
        }
    ],
    "sg:phone":"+91 22 6598 5114",
    "sg:postcode":"400101",
    "sg:tags":[
        "spare",
        "component",
        "boilers"
    ],
    "wof:name":"R. P. Enterprises",
    "wof:placetype":"venue"
},
  "geometry": {"coordinates":[72.874779,19.199841],"type":"Point"}
}