{
  "type": "Feature",
  "properties": {
    "iso:country":"IN",
    "sg:address":"Sarojini Devi Road,",
    "sg:city":"Secunderabad",
    "sg:phone":"+91 4027896348784",
    "sg:postcode":"500003",
    "sg:province":"Andhra Pradesh",
    "wof:name":"Coromandel Stampings & Stones Ltd",
    "wof:placetype":"venue"
},
  "geometry": {"coordinates":[78.491577,17.441364],"type":"Point"}
}