{
  "type": "Feature",
  "properties": {
    "iso:country":"IN",
    "sg:address":"B.i.a.",
    "sg:city":"Bangalore",
    "sg:phone":"+91 807832313",
    "sg:postcode":"562158",
    "sg:province":"Karnataka",
    "sg:website":"http://www.vinirforge.com",
    "wof:name":"Vinir Forge",
    "wof:placetype":"venue"
},
  "geometry": {"coordinates":[77.656998,12.968318],"type":"Point"}
}