{
  "type": "Feature",
  "properties": {
    "iso:country":"IN",
    "sg:address":"10, Community Centre, Mayapuri Phase-1,",
    "sg:city":"New Delhi",
    "sg:classifiers":[
        {
            "category":"Manufacturing",
            "subcategory":"Chemicals & Compounds",
            "type":"Manufacturing & Wholesale Goods"
        }
    ],
    "sg:phone":"+91 11 2638 9968",
    "sg:postcode":"110064",
    "sg:tags":[
        "paint",
        "product",
        "allied"
    ],
    "sg:website":"http://www.howardindia.com",
    "wof:name":"Howard",
    "wof:placetype":"venue"
},
  "geometry": {"coordinates":[77.103325,28.626047],"type":"Point"}
}