{
  "type": "Feature",
  "properties": {
    "iso:country":"IN",
    "sg:address":"Sion",
    "sg:city":"Mumbai",
    "sg:phone":"+91 22 2409 0124",
    "sg:postcode":"400022",
    "sg:province":"Maharashtra",
    "sg:website":"http://www.chokseychem.com",
    "wof:name":"Choksey Chemicals Pvt Ltd",
    "wof:placetype":"venue"
},
  "geometry": {"coordinates":[72.872223,19.047201],"type":"Point"}
}