{
  "type": "Feature",
  "properties": {
    "iso:country":"IN",
    "sg:address":"79, Dr. Annie Besant Road, Worli,",
    "sg:city":"Mumbai",
    "sg:classifiers":[
        {
            "category":"Manufacturing",
            "subcategory":"Tools & Machinery",
            "type":"Manufacturing & Wholesale Goods"
        }
    ],
    "sg:phone":"+91 22 2493 2071",
    "sg:postcode":"400018",
    "sg:tags":[
        "electric",
        "power"
    ],
    "sg:website":"http://www.boschindia.com",
    "wof:name":"Motor Industries Co. Ltd.",
    "wof:placetype":"venue"
},
  "geometry": {"coordinates":[72.818054,19.00559],"type":"Point"}
}