{
  "type": "Feature",
  "properties": {
    "iso:country":"IN",
    "sg:address":"220, Unnati Tower, Central Spine Vidyadhar Nagar,",
    "sg:city":"Jaipur",
    "sg:classifiers":[
        {
            "category":"Manufacturing",
            "subcategory":"Chemicals & Compounds",
            "type":"Manufacturing & Wholesale Goods"
        }
    ],
    "sg:phone":"+91 141 286 4121",
    "sg:tags":[
        "supply"
    ],
    "wof:name":"Krishi Chemicals",
    "wof:placetype":"venue"
},
  "geometry": {"coordinates":[75.780029,26.962561],"type":"Point"}
}