{
  "type": "Feature",
  "properties": {
    "iso:country":"IN",
    "sg:address":"10/2, 14th 'b' Cross, Agrahara Dasarahalli,",
    "sg:city":"Bangalore",
    "sg:classifiers":[
        {
            "category":"Manufacturing",
            "subcategory":"Tools & Machinery",
            "type":"Manufacturing & Wholesale Goods"
        }
    ],
    "sg:phone":"+91 80 2311 3156",
    "sg:postcode":"560079",
    "sg:tags":[
        "component",
        "auto",
        "part",
        "turned",
        "precision"
    ],
    "wof:name":"J. K. Precision Industries",
    "wof:placetype":"venue"
},
  "geometry": {"coordinates":[77.539658,12.976842],"type":"Point"}
}