{
  "type": "Feature",
  "properties": {
    "iso:country":"IN",
    "sg:address":"7/23, Grants Building, Arthur Bunder Road, Colaba,",
    "sg:city":"Mumbai",
    "sg:classifiers":[
        {
            "category":"Shopping",
            "subcategory":"Crafts & Fabrics",
            "type":"Retail Goods"
        }
    ],
    "sg:phone":"+91 22 2283 7215",
    "sg:postcode":"400005",
    "sg:website":"http://www.vijaysilk.com",
    "wof:name":"Vijay Silk House Group",
    "wof:placetype":"venue"
},
  "geometry": {"coordinates":[72.83002500000001,18.918604],"type":"Point"}
}