{
  "type": "Feature",
  "properties": {
    "iso:country":"IN",
    "sg:address":"18, Community Centre, New Friends Colony,",
    "sg:city":"New Delhi",
    "sg:classifiers":[
        {
            "category":"Manufacturing",
            "subcategory":"Chemicals & Compounds",
            "type":"Manufacturing & Wholesale Goods"
        }
    ],
    "sg:phone":"+91 11 4167 2760",
    "sg:postcode":"110025",
    "sg:tags":[
        "supply"
    ],
    "sg:website":"http://www.proecenergy.com",
    "wof:name":"Proec Energy Ltd.",
    "wof:placetype":"venue"
},
  "geometry": {"coordinates":[77.270569,28.572609],"type":"Point"}
}