{
  "type": "Feature",
  "properties": {
    "iso:country":"IN",
    "sg:address":"163-b, Mittal Indl. Est., Bldg. No. 5, Andheri (e),",
    "sg:city":"Mumbai",
    "sg:classifiers":[
        {
            "category":"Shopping",
            "subcategory":"Crafts & Fabrics",
            "type":"Retail Goods"
        }
    ],
    "sg:phone":"+91 22 2850 8054",
    "sg:postcode":"400059",
    "sg:tags":[
        "export"
    ],
    "sg:website":"http://www.yuvahome.com",
    "wof:name":"Yuva Textile Industries Ltd.",
    "wof:placetype":"venue"
},
  "geometry": {"coordinates":[72.882591,19.107027],"type":"Point"}
}