{
  "type": "Feature",
  "properties": {
    "iso:country":"IN",
    "sg:address":"Unit No. 2, Navghar Road, Bhayander(e),",
    "sg:city":"Thane",
    "sg:classifiers":[
        {
            "category":"Manufacturing",
            "subcategory":"Rubber & Plastics",
            "type":"Manufacturing & Wholesale Goods"
        }
    ],
    "sg:phone":"+91 22 2816 8473",
    "sg:postcode":"401105",
    "sg:tags":[
        "product"
    ],
    "wof:name":"Rashmi Rubber & Plastic Industries",
    "wof:placetype":"venue"
},
  "geometry": {"coordinates":[72.862259,19.307472],"type":"Point"}
}