{
  "type": "Feature",
  "properties": {
    "iso:country":"IN",
    "sg:address":"52, Sakhar Bhavan, Nariman Point,",
    "sg:city":"Mumbai",
    "sg:classifiers":[
        {
            "category":"Shopping",
            "subcategory":"Crafts & Fabrics",
            "type":"Retail Goods"
        }
    ],
    "sg:phone":"+91 22 4095 6800",
    "sg:postcode":"400021",
    "sg:tags":[
        "cotton"
    ],
    "wof:name":"Arunoday Mills Ltd.",
    "wof:placetype":"venue"
},
  "geometry": {"coordinates":[72.821381,18.92671],"type":"Point"}
}