{
  "type": "Feature",
  "properties": {
    "iso:country":"IN",
    "sg:address":"J-453, Midc, Bhosari,",
    "sg:city":"Pune",
    "sg:classifiers":[
        {
            "category":"Manufacturing",
            "subcategory":"Rubber & Plastics",
            "type":"Manufacturing & Wholesale Goods"
        }
    ],
    "sg:phone":"+91 20 2712 2185",
    "sg:postcode":"411026",
    "sg:tags":[
        "product"
    ],
    "wof:name":"Nss Polymers",
    "wof:placetype":"venue"
},
  "geometry": {"coordinates":[73.778671,18.639656],"type":"Point"}
}