{
  "type": "Feature",
  "properties": {
    "iso:country":"IN",
    "sg:address":"A-18/2, Bhel Colony, Old Alwal,",
    "sg:city":"Hyderabad",
    "sg:classifiers":[
        {
            "category":"Manufacturing",
            "subcategory":"Chemicals & Compounds",
            "type":"Manufacturing & Wholesale Goods"
        }
    ],
    "sg:phone":"+91 40 2786 5393",
    "sg:postcode":"500010",
    "sg:tags":[
        "supply"
    ],
    "wof:name":"Avishi Multiple Udyog",
    "wof:placetype":"venue"
},
  "geometry": {"coordinates":[78.489555,17.504961],"type":"Point"}
}