{
  "type": "Feature",
  "properties": {
    "iso:country":"IN",
    "sg:address":"79, Vasant Engg. Compd., O/o. Yamuna Mill, Dabhoi Road, Pratap Nagar",
    "sg:city":"Vadodara",
    "sg:classifiers":[
        {
            "category":"Health Services",
            "subcategory":"Nursing And Care Facility",
            "type":"Services"
        }
    ],
    "sg:phone":"+91 265 258 0144",
    "sg:tags":[
        "personal",
        "equipment",
        "safety"
    ],
    "wof:name":"Rinaro Safety Products",
    "wof:placetype":"venue"
},
  "geometry": {"coordinates":[73.232666,22.284618],"type":"Point"}
}