{
  "type": "Feature",
  "properties": {
    "iso:country":"IN",
    "sg:address":"6-d1, Court Chambers, 35, New Marine Lines,",
    "sg:city":"Mumbai",
    "sg:classifiers":[
        {
            "category":"Manufacturing",
            "subcategory":"Chemicals & Compounds",
            "type":"Manufacturing & Wholesale Goods"
        }
    ],
    "sg:phone":"+91 22 2200 0588",
    "sg:postcode":"400020",
    "sg:tags":[
        "pharmaceutical"
    ],
    "wof:name":"Vianco Pharma Private Ltd.",
    "wof:placetype":"venue"
},
  "geometry": {"coordinates":[72.828903,18.938452],"type":"Point"}
}