{
  "type": "Feature",
  "properties": {
    "iso:country":"IN",
    "sg:address":"601, Silverline, Sayajigunj,",
    "sg:city":"Vadodara",
    "sg:classifiers":[
        {
            "category":"Shopping",
            "subcategory":"Crafts & Fabrics",
            "type":"Retail Goods"
        }
    ],
    "sg:phone":"+91 265 222 5905",
    "sg:postcode":"390018",
    "sg:tags":[
        "pigment"
    ],
    "sg:website":"http://www.ritvi.com",
    "wof:name":"Ritvi Group Of Companies",
    "wof:placetype":"venue"
},
  "geometry": {"coordinates":[73.183594,22.307827],"type":"Point"}
}