{
  "type": "Feature",
  "properties": {
    "iso:country":"IN",
    "sg:address":"15-b, Hemanta Basu Sarani,",
    "sg:city":"Kolkata",
    "sg:classifiers":[
        {
            "category":"Home & Garden",
            "subcategory":"Mobile Homes",
            "type":"Retail Goods"
        }
    ],
    "sg:phone":"+91 33 2248 8581",
    "sg:postcode":"700001",
    "sg:tags":[
        "acid"
    ],
    "wof:name":"Murlidhar Ratanlal Exports Ltd.",
    "wof:placetype":"venue"
},
  "geometry": {"coordinates":[88.349396,22.569002],"type":"Point"}
}