{
  "type": "Feature",
  "properties": {
    "iso:country":"IN",
    "sg:address":"Anand",
    "sg:city":"Vithal Udyognagar",
    "sg:phone":"+91 269235125",
    "sg:postcode":"388121",
    "sg:province":"Gujarat",
    "wof:name":"Vidhya Wires Pvt Ltd",
    "wof:placetype":"venue"
},
  "geometry": {"coordinates":[72.973091,20.768162],"type":"Point"}
}