{
  "type": "Feature",
  "properties": {
    "iso:country":"IN",
    "sg:address":"No. 23 & 24, 2nd Floor, AMR Tech Park, Hosur Road, Bangalore - 560 068, Karnataka, India.",
    "sg:city":"Banglore",
    "sg:classifiers":[
        {
            "category":"Professional",
            "subcategory":"Computer Services",
            "type":"Services"
        }
    ],
    "sg:postcode":"560 068",
    "sg:tags":[
        "mobile-data-vas-technology",
        "vas-infrastructure-products",
        "smsc",
        "mmsc",
        "cbc",
        "sdp",
        "mobile--vas"
    ],
    "sg:website":"http://www.teledna.com/",
    "wof:name":"TeleDNA",
    "wof:placetype":"venue"
},
  "geometry": {"coordinates":[77.641655,12.961868],"type":"Point"}
}