{
  "type": "Feature",
  "properties": {
    "iso:country":"IN",
    "sg:address":"R.b. Mehta Marg, Ghatkopar (e)",
    "sg:city":"Mumbai",
    "sg:phone":"+91 22 2852 0116",
    "sg:postcode":"400077",
    "sg:province":"Maharashtra",
    "sg:website":"http://www.business.vsnl.com/aamulya",
    "wof:name":"Amulya Industries",
    "wof:placetype":"venue"
},
  "geometry": {"coordinates":[72.904137,19.089104],"type":"Point"}
}