{
  "type": "Feature",
  "properties": {
    "iso:country":"IN",
    "sg:address":"First Stage, B.t.m. Layout",
    "sg:city":"Bangalore",
    "sg:phone":"+91 806783137",
    "sg:postcode":"560029",
    "sg:province":"Karnataka",
    "sg:website":"http://www.dlink.com",
    "wof:name":"D-link (india) Ltd",
    "wof:placetype":"venue"
},
  "geometry": {"coordinates":[77.612083,12.918597],"type":"Point"}
}