{
  "type": "Feature",
  "properties": {
    "iso:country":"IN",
    "sg:address":"54/a/1, Salt Lake, Sector V,",
    "sg:city":"Kolkata",
    "sg:classifiers":[
        {
            "category":"Manufacturing",
            "subcategory":"Chemicals & Compounds",
            "type":"Manufacturing & Wholesale Goods"
        }
    ],
    "sg:phone":"+91 33 2367 3496",
    "sg:postcode":"700091",
    "sg:tags":[
        "supply"
    ],
    "sg:website":"http://www.haldiapetrochemicals.com",
    "wof:name":"Haldia Petrolium Ltd.",
    "wof:placetype":"venue"
},
  "geometry": {"coordinates":[88.431297,22.573305],"type":"Point"}
}