{
  "type": "Feature",
  "properties": {
    "iso:country":"IN",
    "sg:address":"431, Lamington Road, 1st Floor,",
    "sg:city":"Mumbai",
    "sg:classifiers":[
        {
            "category":"Manufacturing",
            "subcategory":"Motor Vehicles & Parts",
            "type":"Manufacturing & Wholesale Goods"
        }
    ],
    "sg:phone":"+91 22 2389 2195",
    "sg:postcode":"400004",
    "sg:tags":[
        "bearing"
    ],
    "wof:name":"Galaxy Exports",
    "wof:placetype":"venue"
},
  "geometry": {"coordinates":[72.818321,18.963913],"type":"Point"}
}