{
  "type": "Feature",
  "properties": {
    "iso:country":"IN",
    "sg:address":"4576, Main Bazar, Pahar Ganj,",
    "sg:city":"New Delhi",
    "sg:classifiers":[
        {
            "category":"Manufacturing",
            "subcategory":"Chemicals & Compounds",
            "type":"Manufacturing & Wholesale Goods"
        }
    ],
    "sg:phone":"+91 11 6549 6964",
    "sg:postcode":"110055",
    "sg:tags":[
        "paint",
        "product",
        "allied"
    ],
    "wof:name":"Meenakshi Art & Crafts",
    "wof:placetype":"venue"
},
  "geometry": {"coordinates":[77.213211,28.64109],"type":"Point"}
}