{
  "type": "Feature",
  "properties": {
    "iso:country":"IN",
    "sg:address":"23/10-b, West 2nd Street, Ramaiah Colony,",
    "sg:city":"Tirupur",
    "sg:orig_category":"Non-woven Fabrics",
    "sg:phone":"+91 421 657 1318",
    "sg:postcode":"641602",
    "sg:website":"http://www.apparelstocklots.net",
    "wof:name":"G. V. Creations",
    "wof:placetype":"venue"
},
  "geometry": {"coordinates":[77.33625,11.115479],"type":"Point"}
}