{
  "type": "Feature",
  "properties": {
    "iso:country":"IN",
    "sg:address":"317, 8th Cross, Peenya Indl. Estate,",
    "sg:city":"Bangalore",
    "sg:classifiers":[
        {
            "category":"Real Estate",
            "subcategory":"Surveying",
            "type":"Services"
        }
    ],
    "sg:phone":"+91 80 2836 5884",
    "sg:postcode":"560058",
    "sg:tags":[
        "pharmaceutical",
        "material",
        "raw"
    ],
    "wof:name":"Naturae Homoeomed",
    "wof:placetype":"venue"
},
  "geometry": {"coordinates":[77.51393899999999,13.022583],"type":"Point"}
}