{
  "type": "Feature",
  "properties": {
    "iso:country":"IN",
    "sg:address":"8, Bhatta Gali, G.i.d.c.,",
    "sg:city":"Pandesara",
    "sg:classifiers":[
        {
            "category":"Manufacturing",
            "subcategory":"Rubber & Plastics",
            "type":"Manufacturing & Wholesale Goods"
        }
    ],
    "sg:phone":"+91 261 869 0419",
    "sg:tags":[
        "polymer"
    ],
    "wof:name":"Sona Chemicals",
    "wof:placetype":"venue"
},
  "geometry": {"coordinates":[70.826859,22.280378],"type":"Point"}
}