{
  "type": "Feature",
  "properties": {
    "iso:country":"IN",
    "sg:address":"C/214 Manchestor Tower, Avinashi Road,",
    "sg:city":"Tirupur",
    "sg:orig_category":"Readymade Garments",
    "sg:phone":"+91 422 221 1316",
    "sg:postcode":"641602",
    "sg:website":"http://www.enjoytex.com",
    "wof:name":"Enjoy Textile India (p) Ltd.",
    "wof:placetype":"venue"
},
  "geometry": {"coordinates":[76.987129,11.013837],"type":"Point"}
}