{
  "type": "Feature",
  "properties": {
    "iso:country":"IN",
    "sg:address":"5th Main, Prashanth Nagar",
    "sg:city":"Bangalore",
    "sg:phone":"+91 803283819",
    "sg:postcode":"560079",
    "sg:province":"Karnataka",
    "wof:name":"Shriraj Engineers Pvt Ltd",
    "wof:placetype":"venue"
},
  "geometry": {"coordinates":[77.5327,12.976123],"type":"Point"}
}