{
  "type": "Feature",
  "properties": {
    "iso:country":"IN",
    "sg:address":"64, Oil Mill Road, Lingrapuram,",
    "sg:city":"Bangalore",
    "sg:orig_category":"Soap/detergents",
    "sg:phone":"+91 80 2559 3738",
    "sg:postcode":"560084",
    "wof:name":"J.f.soap  Industriess",
    "wof:placetype":"venue"
},
  "geometry": {"coordinates":[77.630692,13.012966],"type":"Point"}
}