{
  "type": "Feature",
  "properties": {
    "iso:country":"IN",
    "sg:address":"125, G.i.d.c., Waghodia,",
    "sg:city":"Vadodara",
    "sg:classifiers":[
        {
            "category":"Bars & Pubs",
            "subcategory":"Gay Bar",
            "type":"Food & Drink"
        }
    ],
    "sg:phone":"+91 265 343 3879",
    "sg:postcode":"391760",
    "sg:tags":[
        "nut",
        "bolt"
    ],
    "wof:name":"Pioneer Industries",
    "wof:placetype":"venue"
},
  "geometry": {"coordinates":[73.233536,22.286194],"type":"Point"}
}