{
  "type": "Feature",
  "properties": {
    "iso:country":"IN",
    "sg:address":"1619, 2nd Main Road, 3rd Block, Hrbr Layout, Kalyan Nagar P.o.,",
    "sg:city":"Bangalore",
    "sg:classifiers":[
        {
            "category":"Utilities",
            "subcategory":"Natural Gas",
            "type":"Services"
        }
    ],
    "sg:phone":"+91 80 2544 5418",
    "sg:postcode":"560043",
    "sg:tags":[
        "solder",
        "welding"
    ],
    "sg:website":"http://www.hybridmetals.com",
    "wof:name":"Hybrid Metals Pvt. Ltd.",
    "wof:placetype":"venue"
},
  "geometry": {"coordinates":[77.625366,13.031104],"type":"Point"}
}