{
  "type": "Feature",
  "properties": {
    "iso:country":"IN",
    "sg:address":"467-a, Indutrial Area-b, Gill Road,",
    "sg:city":"Ludhiana",
    "sg:classifiers":[
        {
            "category":"Manufacturing",
            "subcategory":"Rubber & Plastics",
            "type":"Manufacturing & Wholesale Goods"
        }
    ],
    "sg:phone":"+91 161 253 0543",
    "sg:tags":[
        "product"
    ],
    "wof:name":"Metalife Auto Rubber Parts",
    "wof:placetype":"venue"
},
  "geometry": {"coordinates":[75.858467,30.887638],"type":"Point"}
}