{
  "type": "Feature",
  "properties": {
    "iso:country":"IN",
    "sg:address":"P V R Road, Ranasinghpet",
    "sg:city":"Bangalore",
    "sg:phone":"+91 802877181",
    "sg:postcode":"560053",
    "sg:province":"Karnataka",
    "wof:name":"Laxmi Enterprises",
    "wof:placetype":"venue"
},
  "geometry": {"coordinates":[77.569321,12.957183],"type":"Point"}
}