{
  "type": "Feature",
  "properties": {
    "iso:country":"IN",
    "sg:address":"1st Floor, New Link Road",
    "sg:city":"Mumbai",
    "sg:phone":"+91 22 2823 1872",
    "sg:postcode":"400069",
    "sg:province":"Maharashtra",
    "sg:website":"http://www.atc.co.in",
    "wof:name":"A T C (clearing & Shipping) Pvt Ltd",
    "wof:placetype":"venue"
},
  "geometry": {"coordinates":[72.831917,19.136951],"type":"Point"}
}