{
  "type": "Feature",
  "properties": {
    "iso:country":"IN",
    "sg:address":"B-7, Patparganj Industrial Area,",
    "sg:city":"New Delhi",
    "sg:classifiers":[
        {
            "category":"Real Estate",
            "subcategory":"Surveying",
            "type":"Services"
        }
    ],
    "sg:phone":"+91 112214111115",
    "sg:postcode":"110092",
    "sg:tags":[
        "pharmaceutical",
        "material",
        "raw"
    ],
    "sg:website":"http://www.reddylimited.com",
    "wof:name":"Reddy Pharmaceutical Limited",
    "wof:placetype":"venue"
},
  "geometry": {"coordinates":[77.310905,28.639425],"type":"Point"}
}