{
  "type": "Feature",
  "properties": {
    "iso:country":"IN",
    "sg:address":"232, 3rd Phase, Peenya Indl. Area,",
    "sg:city":"Bangalore",
    "sg:orig_category":"Foam,rexine & P.u.products",
    "sg:phone":"+91 80 2839 5788",
    "sg:postcode":"560058",
    "wof:name":"Foam Products Polyurethane",
    "wof:placetype":"venue"
},
  "geometry": {"coordinates":[77.52253,13.030821],"type":"Point"}
}