{
  "type": "Feature",
  "properties": {
    "iso:country":"IN",
    "sg:address":"240/c, Bombay Talkies Compound, Malad,",
    "sg:city":"Mumbai",
    "sg:classifiers":[
        {
            "category":"Utilities",
            "subcategory":"Natural Gas",
            "type":"Services"
        }
    ],
    "sg:phone":"+91 22 2882 0503",
    "sg:postcode":"400064",
    "sg:tags":[
        "chemical",
        "equipment",
        "metal",
        "electroplating"
    ],
    "wof:name":"Combine Engineering Works",
    "wof:placetype":"venue"
},
  "geometry": {"coordinates":[72.843079,19.179806],"type":"Point"}
}