{
  "type": "Feature",
  "properties": {
    "iso:country":"IN",
    "sg:address":"#30, 12th Cross, Andrahalli Main Road, Peenya 2nd Stage,",
    "sg:city":"Bangalore",
    "sg:classifiers":[
        {
            "category":"Utilities",
            "subcategory":"Cable",
            "type":"Services"
        }
    ],
    "sg:phone":"+91 80 4117 2744",
    "sg:postcode":"560091",
    "sg:tags":[
        "equipment",
        "telecommunication"
    ],
    "wof:name":"Krupanjali Tool Tech",
    "wof:placetype":"venue"
},
  "geometry": {"coordinates":[77.509438,13.019554],"type":"Point"}
}