{
  "type": "Feature",
  "properties": {
    "iso:country":"IN",
    "sg:address":"39, Chokkasandra, T-dasarahalli P.o,",
    "sg:city":"Bangalore",
    "sg:classifiers":[
        {
            "category":"Food & Beverages",
            "subcategory":"Bakery",
            "type":"Retail Goods"
        }
    ],
    "sg:phone":"+91 80 2837 1610",
    "sg:postcode":"560057",
    "sg:tags":[
        "x-ray"
    ],
    "wof:name":"R. B. X-ray Systems",
    "wof:placetype":"venue"
},
  "geometry": {"coordinates":[77.515366,13.038951],"type":"Point"}
}