{
  "type": "Feature",
  "properties": {
    "iso:country":"IN",
    "sg:address":"525/22, Khera, G.t. Road,",
    "sg:city":"Delhi",
    "sg:classifiers":[
        {
            "category":"Manufacturing",
            "subcategory":"Chemicals & Compounds",
            "type":"Manufacturing & Wholesale Goods"
        }
    ],
    "sg:phone":"+91 11 3256 9352",
    "sg:postcode":"110095",
    "sg:tags":[
        "industrial"
    ],
    "wof:name":"Kandpal Rasayan (p) Ltd.",
    "wof:placetype":"venue"
},
  "geometry": {"coordinates":[75.782242,31.064575],"type":"Point"}
}