{
  "type": "Feature",
  "properties": {
    "iso:country":"IN",
    "sg:address":"Plot No. 11, Sector-5, Vaishali,",
    "sg:city":"Ghaziabad",
    "sg:classifiers":[
        {
            "category":"Manufacturing",
            "subcategory":"Chemicals & Compounds",
            "type":"Manufacturing & Wholesale Goods"
        }
    ],
    "sg:phone":"+91 120 437 0555",
    "sg:postcode":"201010",
    "sg:tags":[
        "paint",
        "product",
        "allied"
    ],
    "wof:name":"Sohan Lal Gupta",
    "wof:placetype":"venue"
},
  "geometry": {"coordinates":[77.344437,28.641636],"type":"Point"}
}