{
  "type": "Feature",
  "properties": {
    "iso:country":"IN",
    "sg:address":"C G Road, Panchwati",
    "sg:city":"Ahmedabad",
    "sg:phone":"+91 796423532",
    "sg:postcode":"380006",
    "sg:province":"Gujarat",
    "wof:name":"Merge Systems Pvt Ltd",
    "wof:placetype":"venue"
},
  "geometry": {"coordinates":[72.557739,23.028051],"type":"Point"}
}