{
  "type": "Feature",
  "properties": {
    "iso:country":"IN",
    "sg:address":"Datta Pada Road, Borivili (e),",
    "sg:city":"Mumbai",
    "sg:classifiers":[
        {
            "category":"Shopping",
            "subcategory":"Jewelry",
            "type":"Retail Goods"
        }
    ],
    "sg:phone":"+91 22 2870 3012",
    "sg:postcode":"400066",
    "sg:tags":[
        "diamond"
    ],
    "wof:name":"Suashish Jewellery Ltd.",
    "wof:placetype":"venue"
},
  "geometry": {"coordinates":[72.858559,19.223827],"type":"Point"}
}