{
  "type": "Feature",
  "properties": {
    "iso:country":"IN",
    "sg:address":"25 Kasturba Gandhi Marg",
    "sg:city":"New Delhi",
    "sg:phone":"+91 11 2331 6831",
    "sg:postcode":"110001",
    "sg:province":"Delhi",
    "sg:website":"http://www.marutiudyog.com",
    "wof:name":"Maruti Udyog Ltd",
    "wof:placetype":"venue"
},
  "geometry": {"coordinates":[77.22584500000001,28.62215],"type":"Point"}
}