{
  "type": "Feature",
  "properties": {
    "iso:country":"IN",
    "sg:address":"227-b, South Marret Street,",
    "sg:city":"Madurai",
    "sg:classifiers":[
        {
            "category":"Manufacturing",
            "subcategory":"Chemicals & Compounds",
            "type":"Manufacturing & Wholesale Goods"
        }
    ],
    "sg:phone":"+91 452 233 2223",
    "sg:postcode":"625001",
    "sg:tags":[
        "supply"
    ],
    "wof:name":"Jayanthi Trading Company",
    "wof:placetype":"venue"
},
  "geometry": {"coordinates":[78.124657,9.921018],"type":"Point"}
}