{
  "type": "Feature",
  "properties": {
    "iso:country":"IN",
    "sg:address":"Madh Marve Road, Malad (w)",
    "sg:city":"Mumbai",
    "sg:phone":"+91 22 2882 3331",
    "sg:postcode":"400095",
    "sg:province":"Maharashtra",
    "wof:name":"Resort, The",
    "wof:placetype":"venue"
},
  "geometry": {"coordinates":[72.81564299999999,19.19673],"type":"Point"}
}