{
  "type": "Feature",
  "properties": {
    "iso:country":"IN",
    "sg:address":"Plot No. S-183, M.i.d.c., Bhosari,",
    "sg:city":"Pune",
    "sg:classifiers":[
        {
            "category":"Manufacturing",
            "subcategory":"Rubber & Plastics",
            "type":"Manufacturing & Wholesale Goods"
        }
    ],
    "sg:phone":"+91 20 2712 1821",
    "sg:postcode":"411026",
    "sg:tags":[
        "chemical",
        "-"
    ],
    "wof:name":"Kirti Chemicals",
    "wof:placetype":"venue"
},
  "geometry": {"coordinates":[73.834961,18.630056],"type":"Point"}
}