{
  "type": "Feature",
  "properties": {
    "iso:country":"IN",
    "sg:address":"Jalaram Park, L.b.s. Marg, Near Bhandup Sonapur, Bhandup (west),",
    "sg:city":"Mumbai",
    "sg:classifiers":[
        {
            "category":"Wholesale",
            "subcategory":"Construction Materials",
            "type":"Manufacturing & Wholesale Goods"
        }
    ],
    "sg:phone":"+91 22 2591 1142",
    "sg:postcode":"400078",
    "sg:tags":[
        "building",
        "supply"
    ],
    "wof:name":"Jalaram Jagruti",
    "wof:placetype":"venue"
},
  "geometry": {"coordinates":[72.938057,19.163015],"type":"Point"}
}