{
  "type": "Feature",
  "properties": {
    "iso:country":"IN",
    "sg:address":"S. No. 5, M. I. D. C, Badlapur,",
    "sg:city":"Thane",
    "sg:classifiers":[
        {
            "category":"Manufacturing",
            "subcategory":"Chemicals & Compounds",
            "type":"Manufacturing & Wholesale Goods"
        }
    ],
    "sg:phone":"+91 251 269 0256",
    "sg:postcode":"421503",
    "sg:tags":[
        "paint",
        "product",
        "allied"
    ],
    "wof:name":"Coral Paints Pvt. Ltd.",
    "wof:placetype":"venue"
},
  "geometry": {"coordinates":[73.24597199999999,19.152477],"type":"Point"}
}