{
  "type": "Feature",
  "properties": {
    "iso:country":"IN",
    "sg:address":"56-57, Sir P. M. Road, Fort,",
    "sg:city":"Mumbai",
    "sg:classifiers":[
        {
            "category":"Transit Center",
            "subcategory":"Freight",
            "type":"Transportation"
        }
    ],
    "sg:phone":"+91 91222663805",
    "sg:postcode":"400001",
    "sg:tags":[
        "clearing",
        "forwarding",
        "agent"
    ],
    "wof:name":"Keshavlal Kalyanji & Co.",
    "wof:placetype":"venue"
},
  "geometry": {"coordinates":[72.835007,18.933912],"type":"Point"}
}