{
  "type": "Feature",
  "properties": {
    "iso:country":"IN",
    "sg:address":"No. 28, Stanes Road, 4th Street,",
    "sg:city":"Tirupur",
    "sg:classifiers":[
        {
            "category":"Shopping",
            "subcategory":"Crafts & Fabrics",
            "type":"Retail Goods"
        }
    ],
    "sg:phone":"+91 421 224 7500",
    "sg:postcode":"641602",
    "sg:tags":[
        "knitted",
        "knitwear"
    ],
    "wof:name":"Canimaara Garments",
    "wof:placetype":"venue"
},
  "geometry": {"coordinates":[77.33674600000001,11.110574],"type":"Point"}
}