{
  "type": "Feature",
  "properties": {
    "iso:country":"IN",
    "sg:address":"Bn 41 (east), Shalimar Bagh,",
    "sg:city":"Delhi",
    "sg:classifiers":[
        {
            "category":"Manufacturing",
            "subcategory":"Chemicals & Compounds",
            "type":"Manufacturing & Wholesale Goods"
        }
    ],
    "sg:phone":"+91 11 2749 4894",
    "sg:postcode":"110088",
    "sg:tags":[
        "industrial"
    ],
    "sg:website":"http://www.pulsarechem.com",
    "wof:name":"Focus Combine Marketing (p) Ltd",
    "wof:placetype":"venue"
},
  "geometry": {"coordinates":[77.21225699999999,28.658819],"type":"Point"}
}