{
  "type": "Feature",
  "properties": {
    "iso:country":"IN",
    "sg:address":"D/8, Triveni, 66, Walkeshwar Road,",
    "sg:city":"Mumbai",
    "sg:classifiers":[
        {
            "category":"Manufacturing",
            "subcategory":"Chemicals & Compounds",
            "type":"Manufacturing & Wholesale Goods"
        }
    ],
    "sg:phone":"+91 22 3097 5823",
    "sg:postcode":"400006",
    "sg:tags":[
        "supply"
    ],
    "sg:website":"artindia.net/anup",
    "wof:name":"Frosty",
    "wof:placetype":"venue"
},
  "geometry": {"coordinates":[72.803696,18.952219],"type":"Point"}
}