{
  "type": "Feature",
  "properties": {
    "iso:country":"IN",
    "sg:address":"5/5777, Dev Nagar, Karol Bagh,",
    "sg:city":"New Delhi",
    "sg:orig_category":"Foam,rexine & P.u.products",
    "sg:phone":"+91 11 2586 4564",
    "sg:postcode":"110005",
    "wof:name":"Enkay Foam Private Limited",
    "wof:placetype":"venue"
},
  "geometry": {"coordinates":[77.184822,28.654299],"type":"Point"}
}