{
  "type": "Feature",
  "properties": {
    "iso:country":"IN",
    "sg:address":"#29/16, 2nd Street  Shakthi Nagar, Kodambakkam,",
    "sg:city":"Chennai (Tamilnadu)",
    "sg:classifiers":[
        {
            "category":"Professional",
            "subcategory":"Computer Services",
            "type":"Services"
        }
    ],
    "sg:postcode":"24",
    "sg:website":"http://www.webmindtree.com",
    "wof:name":"WebMindtree",
    "wof:placetype":"venue"
},
  "geometry": {"coordinates":[80.228556,13.065093],"type":"Point"}
}