{
  "type": "Feature",
  "properties": {
    "iso:country":"IN",
    "sg:address":"2/51, Tardeo A/c Market, Tardeo Road,",
    "sg:city":"Mumbai",
    "sg:classifiers":[
        {
            "category":"Manufacturing",
            "subcategory":"Chemicals & Compounds",
            "type":"Manufacturing & Wholesale Goods"
        }
    ],
    "sg:phone":"+91 22 2351 4340",
    "sg:postcode":"400034",
    "sg:tags":[
        "fine"
    ],
    "wof:name":"Rishi Enterprises",
    "wof:placetype":"venue"
},
  "geometry": {"coordinates":[72.813889,18.973789],"type":"Point"}
}