{
  "type": "Feature",
  "properties": {
    "iso:country":"IN",
    "sg:address":"Ttk Road, Alwarpet",
    "sg:city":"Chennai",
    "sg:phone":"+91 44 2466 0122",
    "sg:postcode":"600018",
    "sg:province":"Tamil Nadu",
    "wof:name":"Aqs Systems Pvt Ltd",
    "wof:placetype":"venue"
},
  "geometry": {"coordinates":[80.250076,13.029187],"type":"Point"}
}