{
  "type": "Feature",
  "properties": {
    "iso:country":"IN",
    "sg:address":"48/1/10-11, Site Iv, Industrial Area, Sahibabad,",
    "sg:city":"Ghaziabad",
    "sg:classifiers":[
        {
            "category":"Shopping",
            "subcategory":"Stationery & Office Supplies",
            "type":"Retail Goods"
        }
    ],
    "sg:phone":"+91 120 320 9707",
    "sg:tags":[
        "paper"
    ],
    "wof:name":"Germane Teknologies India (p) Ltd.",
    "wof:placetype":"venue"
},
  "geometry": {"coordinates":[77.34105700000001,28.660917],"type":"Point"}
}