{
  "type": "Feature",
  "properties": {
    "iso:country":"IN",
    "sg:address":"Hydernagar, Kukatpally",
    "sg:city":"Hyderabad",
    "sg:phone":"+91 40 2305 8351",
    "sg:postcode":"500072",
    "sg:province":"Andhra Pradesh",
    "sg:website":"http://www.samrakshana.com",
    "wof:name":"Samrakshana Electricals Ltd",
    "wof:placetype":"venue"
},
  "geometry": {"coordinates":[78.382797,17.502029],"type":"Point"}
}