{
  "type": "Feature",
  "properties": {
    "iso:country":"IN",
    "sg:address":"B-23, Lawrence Road, Industrial Area,",
    "sg:city":"Delhi",
    "sg:classifiers":[
        {
            "category":"Manufacturing",
            "subcategory":"Petroleum Products",
            "type":"Manufacturing & Wholesale Goods"
        }
    ],
    "sg:phone":"+91 11 2718 5602",
    "sg:postcode":"110035",
    "sg:tags":[
        "wax"
    ],
    "sg:website":"http://www.hanumanagro.com, http://www.indiacocopeat.com",
    "wof:name":"Hanuman Agro Industries Pvt. Ltd.",
    "wof:placetype":"venue"
},
  "geometry": {"coordinates":[77.14868199999999,28.68149],"type":"Point"}
}