{
  "type": "Feature",
  "properties": {
    "iso:country":"IN",
    "sg:address":"90-93, Udyog Vihar,",
    "sg:city":"Udaipur",
    "sg:classifiers":[
        {
            "category":"Manufacturing",
            "subcategory":"Chemicals & Compounds",
            "type":"Manufacturing & Wholesale Goods"
        }
    ],
    "sg:phone":"+91 294 244 0307",
    "sg:postcode":"313001",
    "sg:tags":[
        "paint",
        "product",
        "allied"
    ],
    "sg:website":"http://www.naharcolours.com",
    "wof:name":"Nahar Colours & Coating Ltd.",
    "wof:placetype":"venue"
},
  "geometry": {"coordinates":[77.07659099999999,28.503771],"type":"Point"}
}