{
  "type": "Feature",
  "properties": {
    "iso:country":"IN",
    "sg:address":"Rajinder Nagar",
    "sg:city":"New Delhi",
    "sg:phone":"+91 11 2571 6504",
    "sg:postcode":"110060",
    "sg:province":"Delhi",
    "sg:website":"http://www.envirotech-hygiene.com",
    "wof:name":"Envirotech Hygiene Systems India Pvt Ltd",
    "wof:placetype":"venue"
},
  "geometry": {"coordinates":[77.18589799999999,28.640427],"type":"Point"}
}