{
  "type": "Feature",
  "properties": {
    "iso:country":"IN",
    "sg:address":"E-1/14, Bharat Nagar, 342, Grant Road,",
    "sg:city":"Mumbai",
    "sg:classifiers":[
        {
            "category":"Utilities",
            "subcategory":"Water",
            "type":"Services"
        }
    ],
    "sg:phone":"+91 22 2389 8582",
    "sg:postcode":"400007",
    "sg:tags":[
        "pulley",
        "coupling"
    ],
    "wof:name":"Metalinox India",
    "wof:placetype":"venue"
},
  "geometry": {"coordinates":[72.819939,18.96188],"type":"Point"}
}