{
  "type": "Feature",
  "properties": {
    "iso:country":"IN",
    "sg:address":"52, Jawahar Marg,",
    "sg:city":"Indore",
    "sg:classifiers":[
        {
            "category":"Manufacturing",
            "subcategory":"Chemicals & Compounds",
            "type":"Manufacturing & Wholesale Goods"
        }
    ],
    "sg:phone":"+91 731 236 7253",
    "sg:postcode":"452007",
    "sg:tags":[
        "supply"
    ],
    "wof:name":"Hakimuddin Haiderali",
    "wof:placetype":"venue"
},
  "geometry": {"coordinates":[75.85417200000001,22.716246],"type":"Point"}
}