{
  "type": "Feature",
  "properties": {
    "iso:country":"IN",
    "sg:address":"S. V. Road, Malad (west)",
    "sg:city":"Mumbai",
    "sg:phone":"+91 22 2880 2522",
    "sg:postcode":"400064",
    "sg:province":"Maharashtra",
    "wof:name":"Taj Chains",
    "wof:placetype":"venue"
},
  "geometry": {"coordinates":[72.843788,19.116213],"type":"Point"}
}