{
  "type": "Feature",
  "properties": {
    "iso:country":"IN",
    "sg:address":"H-2, 405, Misquitta Nagar, Vidya Mandir, Dahisar (east),",
    "sg:city":"Mumbai",
    "sg:classifiers":[
        {
            "category":"Wholesale",
            "subcategory":"Construction Materials",
            "type":"Manufacturing & Wholesale Goods"
        }
    ],
    "sg:phone":"+91 22 2848 5278",
    "sg:tags":[
        "building",
        "supply"
    ],
    "wof:name":"Armour Surface Coatings",
    "wof:placetype":"venue"
},
  "geometry": {"coordinates":[72.848595,19.257641],"type":"Point"}
}