{
  "type": "Feature",
  "properties": {
    "iso:country":"IN",
    "sg:address":"79/51, P. N. Road, Weavers Colony,",
    "sg:city":"Tirupur",
    "sg:classifiers":[
        {
            "category":"Shopping",
            "subcategory":"Clothing, Apparel, & Fashions",
            "type":"Retail Goods"
        }
    ],
    "sg:phone":"+91 421 247 5577",
    "sg:postcode":"641606",
    "sg:tags":[
        "t-shirt"
    ],
    "sg:website":"http://www.arunaapparels.com",
    "wof:name":"Aruna Apparels",
    "wof:placetype":"venue"
},
  "geometry": {"coordinates":[76.946663,11.025138],"type":"Point"}
}