{
  "type": "Feature",
  "properties": {
    "iso:country":"IN",
    "sg:address":"307, Mandvi Navjivan, 121/127, Kazi Sayed Street,",
    "sg:city":"Mumbai",
    "sg:classifiers":[
        {
            "category":"Manufacturing",
            "subcategory":"Chemicals & Compounds",
            "type":"Manufacturing & Wholesale Goods"
        }
    ],
    "sg:phone":"+91 22 2341 5656",
    "sg:postcode":"400003",
    "sg:tags":[
        "supply"
    ],
    "wof:name":"Thakker Chemicals Pvt. Ltd.",
    "wof:placetype":"venue"
},
  "geometry": {"coordinates":[72.837029,18.950844],"type":"Point"}
}