{
  "type": "Feature",
  "properties": {
    "iso:country":"IN",
    "sg:address":"9 K C Ind Estate, Subhash Road, Jogeshwari (e),",
    "sg:city":"Mumbai",
    "sg:classifiers":[
        {
            "category":"Manufacturing",
            "subcategory":"Rubber & Plastics",
            "type":"Manufacturing & Wholesale Goods"
        }
    ],
    "sg:phone":"+91 22 2832 5874",
    "sg:postcode":"400060",
    "sg:tags":[
        "product"
    ],
    "wof:name":"I P Group",
    "wof:placetype":"venue"
},
  "geometry": {"coordinates":[72.851112,19.137617],"type":"Point"}
}