{
  "type": "Feature",
  "properties": {
    "iso:country":"IN",
    "sg:address":"54, Ezra Street,",
    "sg:city":"Kolkata",
    "sg:classifiers":[
        {
            "category":"Shopping",
            "subcategory":"Stationery & Office Supplies",
            "type":"Retail Goods"
        }
    ],
    "sg:phone":"+91 33 2215 4245",
    "sg:postcode":"700001",
    "sg:tags":[
        "paper"
    ],
    "wof:name":"Tripura Coke Co. Pvt. Ltd.",
    "wof:placetype":"venue"
},
  "geometry": {"coordinates":[88.353035,22.57485],"type":"Point"}
}