{
  "type": "Feature",
  "properties": {
    "iso:country":"IN",
    "sg:address":"Gaytri Bhwwan,",
    "sg:city":"Yavatmal",
    "sg:classifiers":[
        {
            "category":"Home & Garden",
            "subcategory":"Garden Supply",
            "type":"Retail Goods"
        }
    ],
    "sg:phone":"+91 7232 244 219",
    "sg:postcode":"445001",
    "sg:tags":[
        "fertilizer"
    ],
    "wof:name":"Gayatri Micro Elements & Chemicals",
    "wof:placetype":"venue"
},
  "geometry": {"coordinates":[78.487038,17.401066],"type":"Point"}
}