{
  "type": "Feature",
  "properties": {
    "iso:country":"IN",
    "sg:address":"Off. Veera Desai Road, Andheri (w)",
    "sg:city":"Mumbai",
    "sg:phone":"+91 22 5693 1344",
    "sg:postcode":"400053",
    "sg:province":"Maharashtra",
    "sg:website":"http://www.beechins.com",
    "wof:name":"Beechin's Creations Pvt Ltd",
    "wof:placetype":"venue"
},
  "geometry": {"coordinates":[72.83725,19.132605],"type":"Point"}
}