{
  "type": "Feature",
  "properties": {
    "iso:country":"IN",
    "sg:address":"605, Dalamal Chambers, 29, New Marine Lines,",
    "sg:city":"Mumbai",
    "sg:classifiers":[
        {
            "category":"Manufacturing",
            "subcategory":"Chemicals & Compounds",
            "type":"Manufacturing & Wholesale Goods"
        }
    ],
    "sg:phone":"+91 22 5633 3562",
    "sg:postcode":"400020",
    "sg:tags":[
        "supply"
    ],
    "wof:name":"Tarunkumar Chemicals Pvt. Ltd.",
    "wof:placetype":"venue"
},
  "geometry": {"coordinates":[72.828629,18.939135],"type":"Point"}
}